Workbook

Sheet FT-GEI-SO-016 Informe 2023
A1: INFORME DE AUSENTISMO POR INCAPACIDAD 2023
A2: DESCRIPCIÓN | B2: ENERO | C2: FEBRERO | D2: MARZO | E2: ABRIL | F2: MAYO | G2: JUNIO | H2: JULIO | I2: AGOSTO | J2: SEPTIEMBRE | K2: OCTUBRE | L2: NOVIEMBRE | M2: DICIEMBRE | N2: TOTAL
A3: No. de Empleados | B3: 966 | C3: 984 | D3: 959 | E3: 815 | F3: 815 | G3: 829 | H3: 831 | I3: 842 | J3: 847 | K3: 844 | L3: 843 | M3: 843 | N3: =SUM(B3:M3) -> 10418
A4: Horas Hombre Trabajadas Totales - HHTT | B4: 241301 | C4: 254274 | D4: 250972 | E4: 215081 | F4: 220213 | G4: 224539 | H4: 234920 | I4: 224539 | J4: 243827 | K4: 215592 | L4: 240139 | M4: 240139 | N4: =+SUM(B4:M4) -> 2805536
A5: No. De días progamados de trabajo (No. Empleados * días mes laborados base) | B5: =+B3*20 -> 19320 | C5: =+C3*20 -> 19680 | D5: =+D3*20 -> 19180 | E5: =+E3*20 -> 16300 | F5: =+F3*20 -> 16300 | G5: =+G3*20 -> 16580 | H5: =+H3*20 -> 16620 | I5: =+I3*20 -> 16840 | ... N5: =+N3*20 -> 208360
A6: Total de días de Incapacidad EG - AC | B6: =278+30+3+14+2+37+10 -> 374 | C6: =229+3+30+9+20 -> 291 | D6: =177+15+30 -> 222 | E6: =191+4+15+30 -> 240 | F6: =174+10+2+15 -> 201 | G6: 255 | H6: 234 | I6: 182 | J6: 330 | K6: 152 | L6: 175 | M6: 71 | N6: =+SUM(B6:M6) -> 2727
A7: Número de Personal Incapacitado en el periodo por Incapacidad Común (EG -AC) | B7: =16+1+1+1+1+1 -> 21 | C7: =19+1+1+1+1 -> 23 | D7: =16+1+1 -> 18 | E7: =17+1+1+1 -> 20 | F7: =16+1+1+1 -> 19 | G7: 20 | H7: 21 | I7: 19 | J7: 17 | K7: 18 | L7: 19 | M7: 8 | N7: =+SUM(B7:M7) -> 223
A8: Total de días de Incapacidad AT | B8: 19 | C8: 0 | D8: 22 | E8: 0 | F8: 3 | G8: 0 | H8: 0 | I8: 0 | J8: 41 | K8: 0 | L8: 1 | M8: 0 | N8: =+SUM(B8:M8) -> 86
A9: Número de Personal Incapacitado en el periodo por Incapacidad laboral (AT) | B9: 1 | C9: 0 | D9: 2 | E9: 0 | F9: 1 | G9: 0 | H9: 0 | I9: 0 | J9: 1 | K9: 0 | L9: 20 | M9: 0 | N9: =+SUM(B9:M9) -> 25
A10: No. de Personas Fallecidas por EG - AC | B10: 0 | C10: 0 | D10: 0 | E10: 0 | F10: 0 | G10: 0 | H10: 0 | I10: 0 | J10: 0 | K10: 0 | L10: 0 | M10: 0 | N10: =+SUM(B10:M10) -> 0
A11: Número de casos reportados de Enfermedad Laboral | B11: 0 | C11: 0 | D11: 0 | E11: 0 | F11: 0 | G11: 0 | H11: 0 | I11: 0 | J11: 0 | K11: 0 | L11: 0 | M11: 0 | N11: 0
A12: Número de casos aprobados por la ARL como Enfermedad Laboral | B12: 0 | C12: 0 | D12: 0 | E12: 0 | F12: 0 | G12: 0 | H12: 0 | I12: 0 | J12: 0 | K12: 0 | L12: 0 | M12: 0 | N12: 0
A13: Número de casos existentes (antiguios) de Enfermedad Laboral | B13: 0 | C13: 0 | D13: 0 | E13: 0 | F13: 0 | G13: 0 | H13: 0 | I13: 0 | J13: 0 | K13: 0 | L13: 0 | M13: 0 | N13: 0
A14: Total de días de incapacidad de Enfermedad Laboral | B14: 0 | C14: 0 | D14: 0 | E14: 0 | F14: 0 | G14: 0 | H14: 0 | I14: 0 | J14: 0 | K14: 0 | L14: 0 | M14: 0 | N14: 0
A15: Tasa Global de ausentismo (EG+AC+AT+EL) | B15: =IFERROR(((B6+B8+B14)/B5),0) -> 0.020341615 | C15: =IFERROR(((C6+C8+C14)/C5),0) -> 0.014786585 | D15: =IFERROR(((D6+D8+D14)/D5),0) -> 0.012721585 | E15: =IFERROR(((E6+E8+E14)/E5),0) -> 0.014723926 | F15: =IFERROR(((F6+F8+F14)/F5),0) -> 0.012515337 | G15: =IFERROR(((G6+G8+G14)/G5),0) -> 0.015379976 | H15: =IFERROR(((H6+H8+H14)/H5),0) -> 0.014079422 | I15: =IFERROR(((I6+I8+I14)/I5),0) -> 0.010807601 | ... N15: =IFERROR(((N6+N8+N14)/N5),0) -> 0.013500672 | O15: 1072
A16: Tasa Global de ausentismo Enfermedad General o Accidente Común | B16: =IFERROR((B6/B5),0) -> 0.019358178 | C16: =IFERROR((C6/C5),0) -> 0.014786585 | D16: =IFERROR((D6/D5),0) -> 0.011574557 | E16: =IFERROR((E6/E5),0) -> 0.014723926 | F16: =IFERROR((F6/F5),0) -> 0.012331288 | G16: =IFERROR((G6/G5),0) -> 0.015379976 | H16: =IFERROR((H6/H5),0) -> 0.014079422 | I16: =IFERROR((I6/I5),0) -> 0.010807601 | ... N16: =IFERROR((N6/N5),0) -> 0.013087925
A17: Indice de Frecuencia Ausentismo | B17: =IFERROR(((B7/B4)*20000),0) -> 1.7405647 | C17: =IFERROR(((C7/C4)*20000),0) -> 1.8090721 | D17: =IFERROR(((D7/D4)*20000),0) -> 1.434423 | E17: =IFERROR(((E7/E4)*20000),0) -> 1.8597645 | F17: =IFERROR(((F7/F4)*20000),0) -> 1.725602 | G17: =IFERROR(((G7/G4)*20000),0) -> 1.7814277 | H17: =IFERROR(((H7/H4)*20000),0) -> 1.7878427 | I17: =IFERROR(((I7/I4)*20000),0) -> 1.6923563 | ... M17: =IFERROR(((M7/M4)*20000),0) -> 0.66628078 | N17: =IFERROR(((N7/N4)*240000),0) -> 19.076569
A18: Indice de Severidad Ausentismo | B18: =IFERROR(((B6/B4)*20000),0) -> 30.998628 | C18: =IFERROR(((C6/C4)*20000),0) -> 22.888695 | D18: =IFERROR(((D6/D4)*20000),0) -> 17.691217 | E18: =IFERROR(((E6/E4)*20000),0) -> 22.317174 | F18: =IFERROR(((F6/F4)*20000),0) -> 18.255053 | G18: =IFERROR(((G6/G4)*20000),0) -> 22.713203 | H18: =IFERROR(((H6/H4)*20000),0) -> 19.921675 | I18: =IFERROR(((I6/I4)*20000),0) -> 16.210992 | ... M18: =IFERROR(((M6/M4)*20000),0) -> 5.9132419 | N18: =IFERROR(((N6/N4)*240000),0) -> 233.28163
A19: Indice de General de Ausentismo | B19: =IFERROR((B7/B3),0) -> 0.02173913 | C19: =IFERROR((C7/C3),0) -> 0.023373984 | D19: =IFERROR((D7/D3),0) -> 0.018769552 | E19: =IFERROR((E7/E3),0) -> 0.024539877 | F19: =IFERROR((F7/F3),0) -> 0.023312883 | G19: =IFERROR((G7/G3),0) -> 0.024125452 | H19: =IFERROR((H7/H3),0) -> 0.025270758 | I19: =IFERROR((I7/I3),0) -> 0.022565321 | ... N19: =IFERROR((N7/N3),0) -> 0.02140526
A20: Tasa de Mortalidad por EG - AC | B20: =IFERROR(((B10/B3)*1000),0) -> 0 | C20: =IFERROR(((C10/C3)*1000),0) -> 0 | D20: =IFERROR(((D10/D3)*1000),0) -> 0 | E20: =IFERROR(((E10/E3)*1000),0) -> 0 | F20: =IFERROR(((F10/F3)*1000),0) -> 0 | G20: =IFERROR(((G10/G3)*1000),0) -> 0 | H20: =IFERROR(((H10/H3)*1000),0) -> 0 | I20: =IFERROR(((I10/I3)*1000),0) -> 0 | ... N20: =IFERROR(((N10/N3)*1000),0) -> 0
A21: Ausentismo por Cauda medica | B21: =IFERROR((((B6+B8)/B5)),0) -> 0.020341615 | C21: =IFERROR((((C6+C8)/C5)),0) -> 0.014786585 | D21: =IFERROR((((D6+D8)/D5)),0) -> 0.012721585 | E21: =IFERROR((((E6+E8)/E5)),0) -> 0.014723926 | F21: =IFERROR((((F6+F8)/F5)),0) -> 0.012515337 | G21: =IFERROR((((G6+G8)/G5)),0) -> 0.015379976 | H21: =IFERROR((((H6+H8)/H5)),0) -> 0.014079422 | I21: =IFERROR((((I6+I8)/I5)),0) -> 0.010807601 | ... M21: =IFERROR((((M6+M8)/M5)),0) -> 0.0042111507 | N21: =IFERROR((((N7+N9)/N5)),0) -> 0.0011902476 | O21: 312
A22: Incidencia por Enfermedad Laboral | B22: =IFERROR((B12/B3)*100000,0) -> 0 | C22: =IFERROR((C12/C3)*100000,0) -> 0 | D22: =IFERROR((D12/D3)*100000,0) -> 0 | E22: =IFERROR((E12/E3)*100000,0) -> 0 | F22: =IFERROR((F12/F3)*100000,0) -> 0 | G22: =IFERROR((G12/G3)*100000,0) -> 0 | H22: =IFERROR((H12/H3)*100000,0) -> 0 | I22: =IFERROR((I12/I3)*100000,0) -> 0 | ... N22: =IFERROR((N12/N3)*100000,0) -> 0 | O22: 312
A23: Prevalencia por Enfermedad Laboral | B23: =IFERROR(((B12+B13)/B3)*100000,0) -> 0 | C23: =IFERROR(((C12+C13)/C3)*100000,0) -> 0 | D23: =IFERROR(((D12+D13)/D3)*100000,0) -> 0 | E23: =IFERROR(((E12+E13)/E3)*100000,0) -> 0 | F23: =IFERROR(((F12+F13)/F3)*100000,0) -> 0 | G23: =IFERROR(((G12+G13)/G3)*100000,0) -> 0 | H23: =IFERROR(((H12+H13)/H3)*100000,0) -> 0 | I23: =IFERROR(((I12+I13)/I3)*100000,0) -> 0 | ... N23: =IFERROR(((N12+N13)/N3)*100000,0) -> 0 | O23: 312
A24: Severidad por Enfermedad Laboral | B24: =IFERROR(#REF!(B19/#REF!),0) -> 0 | C24: =IFERROR((C19/#REF!),0) -> 0 | D24: =IFERROR((D19/#REF!),0) -> 0 | E24: =IFERROR((E19/#REF!),0) -> 0 | F24: =IFERROR((F19/#REF!),0) -> 0 | G24: =IFERROR((G19/#REF!),0) -> 0 | H24: =IFERROR((H19/#REF!),0) -> 0 | I24: =IFERROR((I19/#REF!),0) -> 0 | J24: =IFERROR((J19/#REF!),0) -> 0 | ... M24: =IFERROR((M19/#REF!),0) -> 0 | N24: 1 | O24: 1072
A25: Peligros asociados al ausentismo | B25: Virus | C25: Virus | D25: Virus | E25: Virus | F25: Virus | G25: Virus
A29: ANALISIS DE INDICADORES
A30: Enero: | B30: En el mes de enero de 2023 no se presentaron casos de mortalidad por enfermedad general, ni casos de enfermedad laboral, el ausentismo por causa medica esta en 2,03% en los 19320 dias de trabajo programados al personal de la empresa para este mes. De 21 personas se presentaron incapaciad se genera un total de 374 días de ausentismo por enfermedad general o accidente común
A31: Febrero: | B31: En el mes de febrero de 2023 no se presentaron casos de mortalidad por enfermedad general, ni casos de enfermedad laboral, el ausentismo por causa medica esta en 1,48% en los 19680 dias de trabajo programados al personal de la empresa para este mes. De 23 personas se presentaron incapaciad se genera un total de 291 días de ausentismo por enfermedad general o accidente común
A32: Marzo: | B32: En el mes de marzo de 2023 no se presentaron casos de mortalidad por enfermedad general, ni casos de enfermedad laboral, el ausentismo por causa medica esta en 1,27% en los 19180 dias de trabajo programados al personal de la empresa para este mes. De 18 personas se presentaron incapaciad se genera un total de 222 días de ausentismo por enfermedad general o accidente común
A33: Abril: | B33: En el mes de abril de 2023 no se presentaron casos de mortalidad por enfermedad general, ni casos de enfermedad laboral, el ausentismo por causa medica esta en 1,47% en los 16300 dias de trabajo programados al personal de la empresa para este mes. De 20 personas se presentaron incapaciad se genera un total de 240 días de ausentismo por enfermedad general o accidente común
A34: Mayo: | B34: En el mes de mayo de 2023 no se presentaron casos de mortalidad por enfermedad general, ni casos de enfermedad laboral, el ausentismo por causa medica esta en 1,25% en los 16300 dias de trabajo programados al personal de la empresa para este mes. De 19 personas se presentaron incapaciad se genera un total de 201 días de ausentismo por enfermedad general o accidente común
A35: Junio: | B35: En el mes de junio de 2023 no se presentaron casos de mortalidad por enfermedad general, ni casos de enfermedad laboral, el ausentismo por causa medica esta en 1,54% en los 16580 dias de trabajo programados al personal de la empresa para este mes. De 20 personas se presentaron incapaciad se genera un total de 255 días de ausentismo por enfermedad general o accidente común
A36: Julio: | B36: En el mes de julio de 2023 no se presentaron casos de mortalidad por enfermedad general, ni casos de enfermedad laboral, el ausentismo por causa medica esta en 1,41% en los 16620 dias de trabajo programados al personal de la empresa para este mes. De 21 personas se presentaron incapaciad se genera un total de 234 días de ausentismo por enfermedad general o accidente común
A37: Agosto: | B37: En el mes de agosto de 2023 no se presentaron casos de mortalidad por enfermedad general, ni casos de enfermedad laboral, el ausentismo por causa medica esta en 1,08% en los 16840 dias de trabajo programados al personal de la empresa para este mes. De 19 personas se presentaron incapaciad se genera un total de 182 días de ausentismo por enfermedad general o accidente común
A38: Septiembre: | B38: En el mes de septiembre de 2023 no se presentaron casos de mortalidad por enfermedad general, ni casos de enfermedad laboral, el ausentismo por causa medica esta en 2,19% en los 16940 dias de trabajo programados al personal de la empresa para este mes. De 17 personas se presentaron incapaciad se genera un total de 330 días de ausentismo por enfermedad general o accidente común
A39: Octubre: | B39: En el mes de ooctubre de 2023 no se presentaron casos de mortalidad por enfermedad general, ni casos de enfermedad laboral, el ausentismo por causa medica esta en 0,90% en los 16880 dias de trabajo programados al personal de la empresa para este mes. De 18 personas se presentaron incapaciad se genera un total de 152 días de ausentismo por enfermedad general o accidente común
A40: Noviembre: | B40: En el mes de noviembre de 2023 no se presentaron casos de mortalidad por enfermedad general, ni casos de enfermedad laboral, el ausentismo por causa medica esta en 1,04% en los 16860 dias de trabajo programados al personal de la empresa para este mes. De 19 personas se presentaron incapaciad se genera un total de 175 días de ausentismo por enfermedad general o accidente común
A41: Diciembre: | B41: En el mes de noviembre de 2023 no se presentaron casos de mortalidad por enfermedad general, ni casos de enfermedad laboral, el ausentismo por causa medica esta en 0,42% en los 16860 dias de trabajo programados al personal de la empresa para este mes. De 8 personas se presentaron incapaciad se genera un total de 71 días de ausentismo por enfermedad general o accidente común
B50: 2021 | C50: 2020 | D50: 2019 | E50: 2018 | F50: 2017
A51: Tasa Global de ausentismo | B51: =N15 -> 0.013500672 | C51: 0.0096270062 | D51: =+N15 -> 0.013500672 | E51: 0.38 | F51: 0.14
A52: Indice de Frecuencia Ausentismo | B52: =N17 -> 19.076569 | C52: 24.186053 | D52: =+N17 -> 19.076569 | E52: 2.31 | F52: 1.3
A53: Indice de Severidad Ausentismo | B53: =N18 -> 233.28163 | C53: 273.26956 | D53: =+N18 -> 233.28163 | E53: 29.01 | F53: 11.7
A54: Indice de General de Ausentismo | B54: =N19 -> 0.02140526 | C54: 0.026723096 | D54: =+N19 -> 0.02140526 | E54: 0.03 | F54: 0.0151
A55: Tasa de Mortalidad por EG - AC | B55: =N20 -> 0 | C55: 0.24183797 | D55: =+N20 -> 0 | E55: 1.26 | F55: 1.58
A56: Incidencia por Enfermedad Laboral | B56: =N22 -> 0 | C56: 0 | D56: =+N22 -> 0 | E56: 0 | F56: 0
A57: Prevalencia por Enfermedad Laboral | B57: =N23 -> 0 | C57: 0 | D57: =+N23 -> 0 | E57: 0 | F57: 0
A58: Severidad por Enfermedad Laboral | B58: =N24 -> 1 | C58: 1 | D58: =+#REF! -> #REF! | E58: 0 | F58: 0
A59: Ausentismo por causa medica | B59: =N21 -> 0.0011902476 | C59: 0.00084997819 | D59: =+N21 -> 0.0011902476
M81: 1.26
M82: 1.58
M83: =+M82-M81 -> 0.32

Sheet FT-GEI-SO-016 Informe 2024
A1: INFORME DE AUSENTISMO POR INCAPACIDAD 2024
A2: DESCRIPCIÓN | B2: ENERO | C2: FEBRERO | D2: MARZO | E2: ABRIL | F2: MAYO | G2: JUNIO | H2: JULIO | I2: AGOSTO | J2: SEPTIEMBRE | K2: OCTUBRE | L2: NOVIEMBRE | M2: DICIEMBRE | N2: TOTAL
A3: No. de Empleados | B3: 827 | C3: 817 | D3: 795 | E3: 794 | F3: 798 | G3: 774 | H3: 824 | I3: 782 | J3: 780 | K3: 785 | L3: 775 | M3: 734 | N3: =SUM(B3:M3) -> 9485
A4: Horas Hombre Trabajadas Totales - HHTT | B4: 195263 | C4: 203265 | D4: 194562 | E4: =20445+182590 -> 203035 | F4: 202195 | G4: 187853 | H4: 194571 | I4: 199736 | J4: 196502 | K4: 196699 | L4: 185922 | M4: 196300 | N4: =+SUM(B4:M4) -> 2355903
A5: No. De días progamados de trabajo (No. Empleados * días mes laborados base) | B5: =+B3*26 -> 21502 | C5: =+C3*26 -> 21242 | D5: =+D3*26 -> 20670 | E5: =+E3*26 -> 20644 | F5: =+F3*26 -> 20748 | G5: =+G3*26 -> 20124 | H5: =+H3*26 -> 21424 | I5: =+I3*26 -> 20332 | ... M5: =+M3*26 -> 19084 | N5: =+N3*20 -> 189700
A6: Total de días de Incapacidad EG - AC | B6: 201 | C6: 168 | D6: 251 | E6: 245 | F6: 315 | G6: 255 | H6: 130 | I6: 171 | J6: 175 | K6: 179 | L6: 178 | M6: 108 | N6: =+SUM(B6:M6) -> 2376
A7: Número de Personal Incapacitado en el periodo por Incapacidad Común (EG -AC) | B7: 22 | C7: 15 | D7: 14 | E7: 22 | F7: 28 | G7: 16 | H7: 16 | I7: 12 | J7: 20 | K7: 23 | L7: 21 | M7: 13 | N7: =+SUM(B7:M7) -> 222
A8: Total de días de Incapacidad AT | B8: 0 | C8: 0 | D8: 0 | E8: 30 | F8: 37 | G8: 78 | H8: 50 | I8: 10 | J8: 8 | K8: 6 | L8: 0 | M8: 6 | N8: =+SUM(B8:M8) -> 225
A9: Número de Personal Incapacitado en el periodo por Incapacidad laboral (AT) | B9: 0 | C9: 0 | D9: 0 | E9: 1 | F9: 2 | G9: 3 | H9: 2 | I9: 1 | J9: 1 | K9: 2 | L9: 0 | M9: 1 | N9: =+SUM(B9:M9) -> 13
A10: No. de Personas Fallecidas por EG - AC | B10: 0 | C10: 0 | D10: 0 | E10: 0 | F10: 0 | G10: 0 | H10: 0 | I10: 0 | J10: 0 | K10: 0 | L10: 0 | M10: 0 | N10: =+SUM(B10:M10) -> 0
A11: Número de casos reportados de Enfermedad Laboral | B11: 0 | C11: 0 | D11: 0 | E11: 0 | F11: 0 | G11: 0 | H11: 0 | I11: 0 | J11: 0 | K11: 0 | L11: 0 | M11: 0 | N11: 0
A12: Número de casos aprobados por la ARL como Enfermedad Laboral | B12: 0 | C12: 0 | D12: 0 | E12: 0 | F12: 0 | G12: 0 | H12: 0 | I12: 0 | J12: 0 | K12: 0 | L12: 0 | M12: 0 | N12: 0
A13: Número de casos existentes (antiguios) de Enfermedad Laboral | B13: 0 | C13: 0 | D13: 0 | E13: 0 | F13: 0 | G13: 0 | H13: 0 | I13: 0 | J13: 0 | K13: 0 | L13: 0 | M13: 0 | N13: 0
A14: Total de días de incapacidad de Enfermedad Laboral | B14: 0 | C14: 0 | D14: 0 | E14: 0 | F14: 0 | G14: 0 | H14: 0 | I14: 0 | J14: 0 | K14: 0 | L14: 0 | M14: 0 | N14: 0
A15: Tasa Global de ausentismo (EG+AC+AT+EL) | B15: =IFERROR(((B6+B8+B14)/B5),0) -> 0.0093479676 | C15: =IFERROR(((C6+C8+C14)/C5),0) -> 0.0079088598 | D15: =IFERROR(((D6+D8+D14)/D5),0) -> 0.012143203 | E15: =IFERROR(((E6+E8+E14)/E5),0) -> 0.013321062 | F15: =IFERROR(((F6+F8+F14)/F5),0) -> 0.016965491 | G15: =IFERROR(((G6+G8+G14)/G5),0) -> 0.016547406 | H15: =IFERROR(((H6+H8+H14)/H5),0) -> 0.0084017924 | I15: =IFERROR(((I6+I8+I14)/I5),0) -> 0.0089022231 | ... N15: =IFERROR(((N6+N8+N14)/N5),0) -> 0.013711123 | O15: 1072
A16: Tasa Global de ausentismo Enfermedad General o Accidente Común | B16: =IFERROR((B6/B5),0) -> 0.0093479676 | C16: =IFERROR((C6/C5),0) -> 0.0079088598 | D16: =IFERROR((D6/D5),0) -> 0.012143203 | E16: =IFERROR((E6/E5),0) -> 0.011867855 | F16: =IFERROR((F6/F5),0) -> 0.015182186 | G16: =IFERROR((G6/G5),0) -> 0.012671437 | H16: =IFERROR((H6/H5),0) -> 0.0060679612 | I16: =IFERROR((I6/I5),0) -> 0.0084103876 | ... N16: =IFERROR((N6/N5),0) -> 0.01252504
A17: Indice de Frecuencia Ausentismo | B17: =IFERROR(((B7/B4)*20000),0) -> 2.2533711 | C17: =IFERROR(((C7/C4)*20000),0) -> 1.4759058 | D17: =IFERROR(((D7/D4)*20000),0) -> 1.4391299 | E17: =IFERROR(((E7/E4)*20000),0) -> 2.167114 | F17: =IFERROR(((F7/F4)*20000),0) -> 2.7696036 | G17: =IFERROR(((G7/G4)*20000),0) -> 1.7034596 | H17: =IFERROR(((H7/H4)*20000),0) -> 1.6446439 | I17: =IFERROR(((I7/I4)*20000),0) -> 1.2015861 | ... M17: =IFERROR(((M7/M4)*20000),0) -> 1.3245033 | N17: =IFERROR(((N7/N4)*240000),0) -> 22.615532
A18: Indice de Severidad Ausentismo | B18: =IFERROR(((B6/B4)*20000),0) -> 20.587618 | C18: =IFERROR(((C6/C4)*20000),0) -> 16.530145 | D18: =IFERROR(((D6/D4)*20000),0) -> 25.801544 | E18: =IFERROR(((E6/E4)*20000),0) -> 24.13377 | F18: =IFERROR(((F6/F4)*20000),0) -> 31.158041 | G18: =IFERROR(((G6/G4)*20000),0) -> 27.148888 | H18: =IFERROR(((H6/H4)*20000),0) -> 13.362731 | I18: =IFERROR(((I6/I4)*20000),0) -> 17.122602 | ... M18: =IFERROR(((M6/M4)*20000),0) -> 11.003566 | N18: =IFERROR(((N6/N4)*240000),0) -> 242.04732
A19: Indice de General de Ausentismo | B19: =IFERROR((B7/B3),0) -> 0.026602177 | C19: =IFERROR((C7/C3),0) -> 0.018359853 | D19: =IFERROR((D7/D3),0) -> 0.017610063 | E19: =IFERROR((E7/E3),0) -> 0.027707809 | F19: =IFERROR((F7/F3),0) -> 0.035087719 | G19: =IFERROR((G7/G3),0) -> 0.020671835 | H19: =IFERROR((H7/H3),0) -> 0.019417476 | I19: =IFERROR((I7/I3),0) -> 0.015345269 | ... N19: =IFERROR((N7/N3),0) -> 0.023405377
A20: Tasa de Mortalidad por EG - AC | B20: =IFERROR(((B10/B3)*1000),0) -> 0 | C20: =IFERROR(((C10/C3)*1000),0) -> 0 | D20: =IFERROR(((D10/D3)*1000),0) -> 0 | E20: =IFERROR(((E10/E3)*1000),0) -> 0 | F20: =IFERROR(((F10/F3)*1000),0) -> 0 | G20: =IFERROR(((G10/G3)*1000),0) -> 0 | H20: =IFERROR(((H10/H3)*1000),0) -> 0 | I20: =IFERROR(((I10/I3)*1000),0) -> 0 | ... N20: =IFERROR(((N10/N3)*1000),0) -> 0
A21: Ausentismo por Cauda medica | B21: =IFERROR((((B6+B8)/B5)),0) -> 0.0093479676 | C21: =IFERROR((((C6+C8)/C5)),0) -> 0.0079088598 | D21: =IFERROR((((D6+D8)/D5)),0) -> 0.012143203 | E21: =IFERROR((((E6+E8)/E5)),0) -> 0.013321062 | F21: =IFERROR((((F6+F8)/F5)),0) -> 0.016965491 | G21: =IFERROR((((G6+G8)/G5)),0) -> 0.016547406 | H21: =IFERROR((((H6+H8)/H5)),0) -> 0.0084017924 | I21: =IFERROR((((I6+I8)/I5)),0) -> 0.0089022231 | ... M21: =IFERROR((((M6+M8)/M5)),0) -> 0.0059735904 | N21: =IFERROR((((N7+N9)/N5)),0) -> 0.0012387981 | O21: 312
A22: Incidencia por Enfermedad Laboral | B22: =IFERROR((B12/B3)*100000,0) -> 0 | C22: =IFERROR((C12/C3)*100000,0) -> 0 | D22: =IFERROR((D12/D3)*100000,0) -> 0 | E22: =IFERROR((E12/E3)*100000,0) -> 0 | F22: =IFERROR((F12/F3)*100000,0) -> 0 | G22: =IFERROR((G12/G3)*100000,0) -> 0 | H22: =IFERROR((H12/H3)*100000,0) -> 0 | I22: =IFERROR((I12/I3)*100000,0) -> 0 | ... N22: =IFERROR((N12/N3)*100000,0) -> 0 | O22: 312 | T22: 1.7405647 | U22: 1.8090721 | V22: 1.434423 | W22: 1.8597645 | X22: 1.725602 | Y22: 1.7814277 | Z22: 1.7878427 | AA22: 1.6923563 | AB22: 1.3944313 | AC22: 1.6698208 | AD22: 1.5824169 | AE22: 0.66628078
A23: Prevalencia por Enfermedad Laboral | B23: =IFERROR(((B12+B13)/B3)*100000,0) -> 0 | C23: =IFERROR(((C12+C13)/C3)*100000,0) -> 0 | D23: =IFERROR(((D12+D13)/D3)*100000,0) -> 0 | E23: =IFERROR(((E12+E13)/E3)*100000,0) -> 0 | F23: =IFERROR(((F12+F13)/F3)*100000,0) -> 0 | G23: =IFERROR(((G12+G13)/G3)*100000,0) -> 0 | H23: =IFERROR(((H12+H13)/H3)*100000,0) -> 0 | I23: =IFERROR(((I12+I13)/I3)*100000,0) -> 0 | ... N23: =IFERROR(((N12+N13)/N3)*100000,0) -> 0 | O23: 312
A24: Severidad por Enfermedad Laboral | B24: =IFERROR(#REF!(B19/#REF!),0) -> 0 | C24: =IFERROR((C19/#REF!),0) -> 0 | D24: =IFERROR((D19/#REF!),0) -> 0 | E24: =IFERROR((E19/#REF!),0) -> 0 | F24: =IFERROR((F19/#REF!),0) -> 0 | G24: =IFERROR((G19/#REF!),0) -> 0 | H24: =IFERROR((H19/#REF!),0) -> 0 | I24: =IFERROR((I19/#REF!),0) -> 0 | J24: =IFERROR((J19/#REF!),0) -> 0 | ... M24: =IFERROR((M19/#REF!),0) -> 0 | N24: =IFERROR(((N13+N14)/N4)*100000,0) -> 0 | O24: 1072
A25: Peligros asociados al ausentismo | B25: Virus | C25: Virus | D25: Virus | E25: Virus | F25: Virus | G25: Virus
A29: ANALISIS DE INDICADORES
A30: Enero: | B30: En el mes de enero de 2024 no se presentaron casos de mortalidad por enfermedad general, ni casos de enfermedad laboral, el ausentismo por causa medica esta en 0,935% en los 21502 dias de trabajo programados al personal de la empresa para este mes. De 22 personas se presentaron incapacidad se genera un total de 201días de ausentismo por enfermedad general o accidente común
A31: Febrero: | B31: En el mes de febrero de 2024 no se presentaron casos de mortalidad por enfermedad general, ni casos de enfermedad laboral, el ausentismo por causa medica esta en 0,791% en los 21242 dias de trabajo programados al personal de la empresa para este mes. De 15 personas se presentaron incapacidad se genera un total de 168 días de ausentismo por enfermedad general o accidente común
A32: Marzo: | B32: En el mes de marzo de 2024 no se presentaron casos de mortalidad por enfermedad general, ni casos de enfermedad laboral, el ausentismo por causa medica esta en 1,214% en los 20670 dias de trabajo programados al personal de la empresa para este mes. De 14 personas se presentaron incapacidad se genera un total de 251 días de ausentismo por enfermedad general o accidente común
A33: Abril: | B33: En el mes de abril de 2024 no se presentaron casos de mortalidad por enfermedad general, ni casos de enfermedad laboral, el ausentismo por causa medica esta en 1,332% en los 20644 dias de trabajo programados al personal de la empresa para este mes. De 22 personas se presentaron incapacidad se genera un total de 245 días de ausentismo por enfermedad general o accidente común
A34: Mayo: | B34: En el mes de mayo de 2024 no se presentaron casos de mortalidad por enfermedad general, ni casos de enfermedad laboral, el ausentismo por causa medica esta en 1,697% en los 20740 dias de trabajo programados al personal de la empresa para este mes. De 28 personas se presentaron incapacidad se genera un total de 315 días de ausentismo por enfermedad general o accidente común
A35: Junio: | B35: En el mes de junio de 2024 no se presentaron casos de mortalidad por enfermedad general, ni casos de enfermedad laboral, el ausentismo por causa medica esta en 1,655% en los 20124 dias de trabajo programados al personal de la empresa para este mes. De 16 personas se presentaron incapacidad se genera un total de 255 días de ausentismo por enfermedad general o accidente común
A36: Julio: | B36: En el mes de julio de 2024 no se presentaron casos de mortalidad por enfermedad general, ni casos de enfermedad laboral, el ausentismo por causa medica esta en 0,840% en los 21424 dias de trabajo programados al personal de la empresa para este mes. De 16 personas se presentaron incapacidad se genera un total de 130 días de ausentismo por enfermedad general o accidente común
A37: Agosto: | B37: En el mes de agosto de 2024 no se presentaron casos de mortalidad por enfermedad general, ni casos de enfermedad laboral, el ausentismo por causa medica esta en 0,890% en los 20332 dias de trabajo programados al personal de la empresa para este mes. De 12 personas se presentaron incapacidad se genera un total de 171 días de ausentismo por enfermedad general o accidente común
A38: Septiembre: | B38: En el mes de septiembre de 2024 no se presentaron casos de mortalidad por enfermedad general, ni casos de enfermedad laboral, el ausentismo por causa medica esta en 0,902% en los 20280 dias de trabajo programados al personal de la empresa para este mes. De 20 personas se presentaron incapacidad se genera un total de 175 días de ausentismo por enfermedad general o accidente común
A39: Octubre: | B39: En el mes de octubre de 2024 no se presentaron casos de mortalidad por enfermedad general, ni casos de enfermedad laboral, el ausentismo por causa medica esta en 0,906% en los 20410 dias de trabajo programados al personal de la empresa para este mes. De 23 personas se presentaron incapacidad se genera un total de 179 días de ausentismo por enfermedad general o accidente común
A40: Noviembre: | B40: En el mes de noviembre de 2024 no se presentaron casos de mortalidad por enfermedad general, ni casos de enfermedad laboral, el ausentismo por causa medica esta en 0,883% en los 20150 dias de trabajo programados al personal de la empresa para este mes. De 21 personas se presentaron incapacidad se genera un total de 178 días de ausentismo por enfermedad general o accidente común
A41: Diciembre: | B41: En el mes de diciembre de 2024 no se presentaron casos de mortalidad por enfermedad general, ni casos de enfermedad laboral, el ausentismo por causa medica esta en 0,597% en los 19084 dias de trabajo programados al personal de la empresa para este mes. De 13 personas se presentaron incapacidad se genera un total de 108 días de ausentismo por enfermedad general o accidente común
B50: 2021 | C50: 2020 | D50: 2019 | E50: 2018 | F50: 2017
A51: Tasa Global de ausentismo | B51: =N15 -> 0.013711123 | C51: 0.0096270062 | D51: =+N15 -> 0.013711123 | E51: 0.38 | F51: 0.14
A52: Indice de Frecuencia Ausentismo | B52: =N17 -> 22.615532 | C52: 24.186053 | D52: =+N17 -> 22.615532 | E52: 2.31 | F52: 1.3
A53: Indice de Severidad Ausentismo | B53: =N18 -> 242.04732 | C53: 273.26956 | D53: =+N18 -> 242.04732 | E53: 29.01 | F53: 11.7
A54: Indice de General de Ausentismo | B54: =N19 -> 0.023405377 | C54: 0.026723096 | D54: =+N19 -> 0.023405377 | E54: 0.03 | F54: 0.0151
A55: Tasa de Mortalidad por EG - AC | B55: =N20 -> 0 | C55: 0.24183797 | D55: =+N20 -> 0 | E55: 1.26 | F55: 1.58
A56: Incidencia por Enfermedad Laboral | B56: =N22 -> 0 | C56: 0 | D56: =+N22 -> 0 | E56: 0 | F56: 0
A57: Prevalencia por Enfermedad Laboral | B57: =N23 -> 0 | C57: 0 | D57: =+N23 -> 0 | E57: 0 | F57: 0
A58: Severidad por Enfermedad Laboral | B58: =N24 -> 0 | C58: 1 | D58: =+#REF! -> #REF! | E58: 0 | F58: 0
A59: Ausentismo por causa medica | B59: =N21 -> 0.0012387981 | C59: 0.00084997819 | D59: =+N21 -> 0.0012387981
M81: 1.26
M82: 1.58
M83: =+M82-M81 -> 0.32

Sheet FT-GEI-SO-016 Informe 2025
A1: INFORME DE AUSENTISMO POR INCAPACIDAD 2025
A2: DESCRIPCIÓN | B2: 45658 | C2: 45689 | D2: MARZO | E2: ABRIL | F2: MAYO | G2: JUNIO | H2: JULIO | I2: AGOSTO | J2: SEPTIEMBRE | K2: OCTUBRE | L2: NOVIEMBRE | M2: DICIEMBRE | N2: TOTAL
A3: No. de Empleados | B3: 748 | C3: 708 | D3: 736 | E3: 746 | F3: 750 | G3: 733 | H3: 709 | I3: 702 | J3: 703 | K3: 728 | L3: 743 | M3: 715 | N3: =SUM(B3:M3) -> 8721
A4: Horas Hombre Trabajadas Totales - HHTT | B4: 180888 | C4: =17932+40318+120618 -> 178868 | D4: =17403+41056+173988 -> 232447 | E4: 232803 | F4: 187499 | G4: 187499 | H4: 187499 | I4: 187499 | J4: 172688 | K4: 172894 | L4: 177040 | M4: 176488 | N4: =+SUM(B4:M4) -> 2274112
A5: No. De días progamados de trabajo (No. Empleados * días mes laborados base) | B5: =21*B3 -> 15708 | C5: =20*C3 -> 14160 | D5: =D3*24 -> 17664 | E5: =E3*20 -> 14920 | F5: =F3*26 -> 19500 | G5: =G3*22 -> 16126 | H5: =H3*27 -> 19143 | I5: =I3*24 -> 16848 | J5: =J3*24 -> 16872 | K5: =K3*26 -> 18928 | L5: =L3*23 -> 17089 | M5: =M3*25 -> 17875 | N5: =+N3*20 -> 174420
A6: Total de días de Incapacidad EG - AC | B6: 158 | C6: 93 | D6: 178 | E6: 136 | F6: 111 | G6: 106 | H6: 119 | I6: 54 | J6: 341 | K6: 190 | L6: 321 | M6: 130 | N6: =+SUM(B6:M6) -> 1937
A7: Número de Personal Incapacitado en el periodo por Incapacidad Común (EG -AC) | B7: 16 | C7: 12 | D7: 15 | E7: 11 | F7: 11 | G7: 12 | H7: 19 | I7: 7 | J7: 20 | K7: 20 | L7: 31 | M7: 19 | N7: =+SUM(B7:M7) -> 193
A8: Total de días de Incapacidad AT | B8: 0 | C8: 2 | D8: 3 | E8: 0 | F8: 14 | G8: 0 | H8: 0 | I8: 0 | J8: 5 | K8: 33 | L8: 30 | M8: 10 | N8: =+SUM(B8:M8) -> 97
A9: Número de Personal Incapacitado en el periodo por Incapacidad laboral (AT) | B9: 0 | C9: 1 | D9: 1 | E9: 0 | F9: 1 | G9: 0 | H9: 1 | I9: 0 | J9: 1 | K9: 2 | L9: 1 | M9: 1 | N9: =+SUM(B9:M9) -> 9
A10: No. de Personas Fallecidas por EG - AC | B10: 0 | C10: 0 | D10: 0 | E10: 0 | F10: 0 | G10: 0 | H10: 0 | I10: 0 | J10: 0 | K10: 0 | L10: 0 | M10: 0 | N10: =+SUM(B10:M10) -> 0
A11: Número de casos reportados de Enfermedad Laboral | B11: 0 | C11: 0 | D11: 0 | E11: 0 | F11: 0 | G11: 0 | H11: 0 | I11: 0 | J11: 0 | K11: 0 | L11: 0 | M11: 0 | N11: 0
A12: Número de casos aprobados por la ARL como Enfermedad Laboral | B12: 0 | C12: 0 | D12: 0 | E12: 0 | F12: 0 | G12: 0 | H12: 0 | I12: 0 | J12: 0 | K12: 0 | L12: 0 | M12: 0 | N12: 0
A13: Número de casos existentes (antiguios) de Enfermedad Laboral | B13: 0 | C13: 0 | D13: 0 | E13: 0 | F13: 0 | G13: 0 | H13: 0 | I13: 0 | J13: 0 | K13: 0 | L13: 0 | M13: 0 | N13: 0
A14: Total de días de incapacidad de Enfermedad Laboral | B14: 0 | C14: 0 | D14: 0 | E14: 0 | F14: 0 | G14: 0 | H14: 0 | I14: 0 | J14: 0 | K14: 0 | L14: 0 | M14: 0 | N14: 0
A15: Tasa Global de ausentismo (EG+AC+AT+EL) | B15: =IFERROR(((B6+B8+B14)/B5),0) -> 0.010058569 | C15: =IFERROR(((C6+C8+C14)/C5),0) -> 0.0067090395 | D15: =IFERROR(((D6+D8+D14)/D5),0) -> 0.01024683 | E15: =IFERROR(((E6+I14E8+E14)/E5),0) -> 0 | F15: =IFERROR(((F6+F8+F14)/F5),0) -> 0.0064102564 | G15: =IFERROR(((G6+G8+G14)/G5),0) -> 0.0065732358 | H15: =IFERROR(((H6+H8+H14)/H5),0) -> 0.0062163715 | I15: =IFERROR(((I6+I8+I14)/I5),0) -> 0.0032051282 | J15: =IFERROR(((J6+J8+J14)/J5),0) -> 0.020507349 | K15: =IFERROR(((K6+K8+K14)/K5),0) -> 0.011781488 | L15: =IFERROR(((L6+L8+L14)/L5),0) -> 0.020539528 | M15: =IFERROR(((M6+M8+M14)/M5),0) -> 0.0078321678 | N15: =IFERROR(((N6+N8+N14)/N5),0) -> 0.011661507
A16: Tasa Global de ausentismo Enfermedad General o Accidente Común | B16: =IFERROR((B6/B5),0) -> 0.010058569 | C16: =IFERROR((C6/C5),0) -> 0.0065677966 | D16: =IFERROR((D6/D5),0) -> 0.010076993 | E16: =IFERROR((E6/E5),0) -> 0.0091152815 | F16: =IFERROR((F6/F5),0) -> 0.0056923077 | G16: =IFERROR((G6/G5),0) -> 0.0065732358 | H16: =IFERROR((H6/H5),0) -> 0.0062163715 | I16: =IFERROR((I6/I5),0) -> 0.0032051282 | ... N16: =IFERROR((N6/N5),0) -> 0.011105378
A17: Indice de Frecuencia Ausentismo | B17: =IFERROR(((B7/B4)*20000),0) -> 1.7690505 | C17: =IFERROR(((C7/C4)*20000),0) -> 1.3417716 | D17: =IFERROR(((D7/D4)*20000),0) -> 1.2906168 | E17: =IFERROR(((E7/E4)*20000),0) -> 0.945005 | F17: =IFERROR(((F7/F4)*20000),0) -> 1.1733396 | G17: =IFERROR(((G7/G4)*20000),0) -> 1.2800068 | H17: =IFERROR(((H7/H4)*20000),0) -> 2.0266775 | I17: =IFERROR(((I7/I4)*20000),0) -> 0.74667065 | ... M17: =IFERROR(((M7/M4)*20000),0) -> 2.1531209 | N17: =IFERROR(((N7/N4)*240000),0) -> 20.36839
A18: Indice de Severidad Ausentismo | B18: =IFERROR(((B6/B4)*20000),0) -> 17.469373 | C18: =IFERROR(((C6/C4)*20000),0) -> 10.39873 | D18: =IFERROR(((D6/D4)*20000),0) -> 15.315319 | E18: =IFERROR(((E6/E4)*20000),0) -> 11.683698 | F18: =IFERROR(((F6/F4)*20000),0) -> 11.840063 | G18: =IFERROR(((G6/G4)*20000),0) -> 11.306727 | H18: =IFERROR(((H6/H4)*20000),0) -> 12.693401 | I18: =IFERROR(((I6/I4)*20000),0) -> 5.7600307 | ... M18: =IFERROR(((M6/M4)*20000),0) -> 14.73188 | N18: =IFERROR(((N6/N4)*240000),0) -> 204.42265
A19: Indice de General de Ausentismo | B19: =IFERROR((B7/B3),0) -> 0.021390374 | C19: =IFERROR((C7/C3),0) -> 0.016949153 | D19: =IFERROR((D7/D3),0) -> 0.020380435 | E19: =IFERROR((E7/E3),0) -> 0.014745308 | F19: =IFERROR((F7/F3),0) -> 0.014666667 | G19: =IFERROR((G7/G3),0) -> 0.016371078 | H19: =IFERROR((H7/H3),0) -> 0.026798307 | I19: =IFERROR((I7/I3),0) -> 0.00997151 | ... N19: =IFERROR((N7/N3),0) -> 0.02213049
A20: Tasa de Mortalidad por EG - AC | B20: =IFERROR(((B10/B3)*1000),0) -> 0 | C20: =IFERROR(((C10/C3)*1000),0) -> 0 | D20: =IFERROR(((D10/D3)*1000),0) -> 0 | E20: =IFERROR(((E10/E3)*1000),0) -> 0 | F20: =IFERROR(((F10/F3)*1000),0) -> 0 | G20: =IFERROR(((G10/G3)*1000),0) -> 0 | H20: =IFERROR(((H10/H3)*1000),0) -> 0 | I20: =IFERROR(((I10/I3)*1000),0) -> 0 | ... N20: =IFERROR(((N10/N3)*1000),0) -> 0
A21: Ausentismo por Cauda medica | B21: =IFERROR((((B6+B8)/B5)),0) -> 0.010058569 | C21: =IFERROR((((C6+C8)/C5)),0) -> 0.0067090395 | D21: =IFERROR((((D6+D8)/D5)),0) -> 0.01024683 | E21: =IFERROR((((E6+E8)/E5)),0) -> 0.0091152815 | F21: =IFERROR((((F6+F8)/F5)),0) -> 0.0064102564 | G21: =IFERROR((((G6+G8)/G5)),0) -> 0.0065732358 | H21: =IFERROR((((H6+H8)/H5)),0) -> 0.0062163715 | I21: =IFERROR((((I6+I8)/I5)),0) -> 0.0032051282 | ... M21: =IFERROR((((M6+M8)/M5)),0) -> 0.0078321678 | N21: =IFERROR((((N7+N9)/N5)),0) -> 0.0011581241
A22: Incidencia por Enfermedad Laboral | B22: =IFERROR((B12/B3)*100000,0) -> 0 | C22: =IFERROR((C12/C3)*100000,0) -> 0 | D22: =IFERROR((D12/D3)*100000,0) -> 0 | E22: =IFERROR((E12/E3)*100000,0) -> 0 | F22: =IFERROR((F12/F3)*100000,0) -> 0 | G22: =IFERROR((G12/G3)*100000,0) -> 0 | H22: =IFERROR((H12/H3)*100000,0) -> 0 | I22: =IFERROR((I12/I3)*100000,0) -> 0 | ... N22: =IFERROR((N12/N3)*100000,0) -> 0
A23: Prevalencia por Enfermedad Laboral | B23: =IFERROR(((B12+B13)/B3)*100000,0) -> 0 | C23: =IFERROR(((C12+C13)/C3)*100000,0) -> 0 | D23: =IFERROR(((D12+D13)/D3)*100000,0) -> 0 | E23: =IFERROR(((E12+E13)/E3)*100000,0) -> 0 | F23: =IFERROR(((F12+F13)/F3)*100000,0) -> 0 | G23: =IFERROR(((G12+G13)/G3)*100000,0) -> 0 | H23: =IFERROR(((H12+H13)/H3)*100000,0) -> 0 | I23: =IFERROR(((I12+I13)/I3)*100000,0) -> 0 | ... N23: =IFERROR(((N12+N13)/N3)*100000,0) -> 0
A24: Severidad por Enfermedad Laboral | B24: =IFERROR(#REF!(B19/#REF!),0) -> 0 | C24: =IFERROR((C19/#REF!),0) -> 0 | D24: =IFERROR((D19/#REF!),0) -> 0 | E24: =IFERROR((E19/#REF!),0) -> 0 | F24: =IFERROR((F19/#REF!),0) -> 0 | G24: =IFERROR((G19/#REF!),0) -> 0 | H24: =IFERROR((H19/#REF!),0) -> 0 | I24: =IFERROR((I19/#REF!),0) -> 0 | J24: =IFERROR((J19/#REF!),0) -> 0 | ... M24: =IFERROR((M19/#REF!),0) -> 0 | N24: =IFERROR(((N13+N14)/N4)*100000,0) -> 0
A25: Peligros asociados al ausentismo | B25: Virus | C25: Virus | D25: Virus | E25: Virus | F25: Virus | G25: Virus
A29: ANALISIS DE INDICADORES
A30: Enero: | B30: En el mes de enero de 2025 no se presentaron casos de mortalidad por enfermedad general, ni casos de enfermedad laboral, el ausentismo por causa medica esta en 1,024% en los 15435 dias de trabajo programados al personal de la empresa para este mes. De 16 personas se presentaron incapacidad se genera un total de 158 días de ausentismo por enfermedad general o accidente común
A31: Febrero: | B31: En el mes de febrero de 2025 no se presentaron casos de mortalidad por enfermedad general, ni casos de enfermedad laboral, el ausentismo por causa medica esta en 0,581% en los 16340 dias de trabajo programados al personal de la empresa para este mes. De 12 personas se presentaron incapacidad se genera un total de 93 días de ausentismo por enfermedad general o accidente común
A32: Marzo: | B32: En el mes de marzo de 2025 no se presentaron casos de mortalidad por enfermedad general, ni casos de enfermedad laboral, el ausentismo por causa medica esta en 1,025% en los 17664 dias de trabajo programados al personal de la empresa para este mes. De 15 personas se presentaron incapacidad se genera un total de 178 días de ausentismo por enfermedad general o accidente común
A33: Abril: | B33: En el mes de abril de 2025 no se presentaron casos de mortalidad por enfermedad general, ni casos de enfermedad laboral, el ausentismo por causa medica esta en 0,912% en los 14920 dias de trabajo programados al personal de la empresa para este mes. De 11 personas se presentaron incapacidad se genera un total de 136 días de ausentismo por enfermedad general o accidente común
A34: Mayo: | B34: En el mes de mayo de 2025 no se presentaron casos de mortalidad por enfermedad general, ni casos de enfermedad laboral, el ausentismo por causa medica esta en 0,694% en los 18000 dias de trabajo programados al personal de la empresa para este mes. De 11 personas se presentaron incapacidad se genera un total de 111 días de ausentismo por enfermedad general o accidente común
A35: Junio: | B35: En el mes de junio de 2025 no se presentaron casos de mortalidad por enfermedad general, ni casos de enfermedad laboral, el ausentismo por causa medica esta en 0,669% en los 15840 dias de trabajo programados al personal de la empresa para este mes. De 12 personas se presentaron incapacidad se genera un total de 106 días de ausentismo por enfermedad general o accidente común
A36: Julio: | B36: En el mes de julio de 2025 no se presentaron casos de mortalidad por enfermedad general, ni casos de enfermedad laboral, el ausentismo por causa medica esta en 0,632% en los 18819 dias de trabajo programados al personal de la empresa para este mes. De 19 personas se presentaron incapacidad se genera un total de 95 días de ausentismo por enfermedad general o accidente común.
A37: Agosto: | B37: En el mes de Agosto de 2025 no se presentaron casos de mortalidad por enfermedad general, ni casos de enfermedad laboral, el ausentismo por causa medica esta en 0,326% en los 16560 dias de trabajo programados al personal de la empresa para este mes. De 7 personas se presentaron incapacidad se genera un total de 54 días de ausentismo por enfermedad general o accidente común.
A38: Septiembre: | B38: En el mes de Septiembre de 2025 no se presentaron casos de mortalidad por enfermedad general, ni casos de enfermedad laboral, el ausentismo por causa medica esta en 2,051% en los 16872 dias de trabajo programados al personal de la empresa para este mes. De 20 personas se presentaron incapacidad se genera un total de 341 días de ausentismo por enfermedad general o accidente común.
A39: Octubre: | B39: En el mes de Octubre de 2025 no se presentaron casos de mortalidad por enfermedad general, ni casos de enfermedad laboral, el ausentismo por causa medica esta en 1,178% en los 18928 dias de trabajo programados al personal de la empresa para este mes. De 20 personas se presentaron incapacidad se genera un total de 190 días de ausentismo por enfermedad general o accidente común.
A40: Noviembre: | B40: En el mes de Noviembre de 2025 no se presentaron casos de mortalidad por enfermedad general, ni casos de enfermedad laboral, el ausentismo por causa medica esta en 2,054% en los 17089 dias de trabajo programados al personal de la empresa para este mes. De 31 personas se presentaron incapacidad se genera un total de 321 días de ausentismo por enfermedad general o accidente común.
A41: Diciembre: | B41: En el mes de Diciembre de 2025 no se presentaron casos de mortalidad por enfermedad general, ni casos de enfermedad laboral, el ausentismo por causa medica esta en 0,783% en los 17875 dias de trabajo programados al personal de la empresa para este mes. De 19 personas se presentaron incapacidad se genera un total de 130 días de ausentismo por enfermedad general o accidente común.
B50: 2021 | C50: 2020 | D50: 2019 | E50: 2018 | F50: 2017
A51: Tasa Global de ausentismo | B51: =N15 -> 0.011661507 | C51: 0.0096270062 | D51: =+N15 -> 0.011661507 | E51: 0.38 | F51: 0.14
A52: Indice de Frecuencia Ausentismo | B52: =N17 -> 20.36839 | C52: 24.186053 | D52: =+N17 -> 20.36839 | E52: 2.31 | F52: 1.3
A53: Indice de Severidad Ausentismo | B53: =N18 -> 204.42265 | C53: 273.26956 | D53: =+N18 -> 204.42265 | E53: 29.01 | F53: 11.7
A54: Indice de General de Ausentismo | B54: =N19 -> 0.02213049 | C54: 0.026723096 | D54: =+N19 -> 0.02213049 | E54: 0.03 | F54: 0.0151
A55: Tasa de Mortalidad por EG - AC | B55: =N20 -> 0 | C55: 0.24183797 | D55: =+N20 -> 0 | E55: 1.26 | F55: 1.58
A56: Incidencia por Enfermedad Laboral | B56: =N22 -> 0 | C56: 0 | D56: =+N22 -> 0 | E56: 0 | F56: 0
A57: Prevalencia por Enfermedad Laboral | B57: =N23 -> 0 | C57: 0 | D57: =+N23 -> 0 | E57: 0 | F57: 0
A58: Severidad por Enfermedad Laboral | B58: =N24 -> 0 | C58: 1 | D58: =+#REF! -> #REF! | E58: 0 | F58: 0
A59: Ausentismo por causa medica | B59: =N21 -> 0.0011581241 | C59: 0.00084997819 | D59: =+N21 -> 0.0011581241
M81: 1.26
M82: 1.58
M83: =+M82-M81 -> 0.32

Sheet FT-GEI-SO-016 Informe 2026
A1: INFORME DE AUSENTISMO POR INCAPACIDAD 2026
A2: DESCRIPCIÓN | B2: 45658 | C2: 45689 | D2: MARZO | E2: ABRIL | F2: MAYO | G2: JUNIO | H2: JULIO | I2: AGOSTO | J2: SEPTIEMBRE | K2: OCTUBRE | L2: NOVIEMBRE | M2: DICIEMBRE | N2: TOTAL
A3: No. de Empleados | B3: 714 | C3: 713 | D3: 698 | E3: 710 | F3: 688 | N3: =SUM(B3:M3) -> 3523
A4: Horas Hombre Trabajadas Totales - HHTT | B4: =17159+43383+101180 -> 161722 | C4: =17804+44116+107946 -> 169866 | D4: =17804+44116+107946 -> 169866 | E4: =17804+44116+107946 -> 169866 | F4: 166597 | N4: =+SUM(B4:M4) -> 837917
A5: No. De días progamados de trabajo (No. Empleados * días mes laborados base) | B5: =25*B3 -> 17850 | C5: =24*C3 -> 17112 | D5: =D3*25 -> 17450 | E5: =24*E3 -> 17040 | F5: =F3*23 -> 15824 | N5: =+N3*20 -> 70460
A6: Total de días de Incapacidad EG - AC | B6: 137 | C6: =195 + 69 -> 264 | D6: =178+80 -> 258 | E6: =134+95 -> 229 | F6: =92+86 -> 178 | N6: =+SUM(B6:M6) -> 1066 | Q6: ANALIZO COLUMNA N Incapacidad DEJANDO SOLO LOS QUE Inc. Enfermedad general, ANALIZO COLUMAN V Periodo inicial y COLUMNA Y Periodo final Y SUMO LOS DATOS NUMERICOS QUE ESTAN EN LA COLUMNA W Dias Y COLUMNA Z Dias
A7: Número de Personal Incapacitado en el periodo por Incapacidad Común (EG -AC) | B7: 19 | C7: 23 | D7: 20 | E7: 18 | F7: 20 | N7: =+SUM(B7:M7) -> 100 | Q7: ANALIZO COLUMNA N Incapacidad DEJANDO SOLO LOS QUE Inc. Enfermedad general Y VOY LA COLUMNA D Cedula PARA IDENTIFICAR LA REPETITIVIDAD EN CEDULAS Y SUPRIMIR LAS REPETIDAS PARA CONTAR EL NUMERO DE TRABAJADORES QUE REPORTARON INCAPACIDAD
A8: Total de días de Incapacidad AT | B8: 24 | C8: 27 | D8: =8+27 -> 35 | E8: 1 | F8: 4 | N8: =+SUM(B8:M8) -> 91 | Q8: ANALIZO COLUMNA N Incapacidad DEJANDO SOLO LOS QUE Inc. Accidente Trabajo, ANALIZO COLUMAN V Periodo inicial y COLUMNA Y Periodo final Y SUMO LOS DATOS NUMERICOS QUE ESTAN EN LA COLUMNA W Dias Y COLUMNA Z Dias
A9: Número de Personal Incapacitado en el periodo por Incapacidad laboral (AT) | B9: 3 | C9: 2 | D9: 3 | E9: 1 | F9: 1 | N9: =+SUM(B9:M9) -> 10 | Q9: ANALIZO COLUMNA N Incapacidad DEJANDO SOLO LOS QUE Inc. Accidente Trabajo Y VOY LA COLUMNA D Cedula PARA IDENTIFICAR LA REPETITIVIDAD EN CEDULAS Y SUPRIMIR LAS REPETIDAS PARA CONTAR EL NUMERO DE TRABAJADORES QUE REPORTARON INCAPACIDAD
A10: No. de Personas Fallecidas por EG - AC | B10: 0 | C10: 0 | D10: 0 | E10: 0 | F10: 0 | N10: =+SUM(B10:M10) -> 0 | Q10: COLUMAN T ( TIPO INCAPACIDAD) | R10: Agregar a item en web FALLECIDO
A11: Número de casos reportados de Enfermedad Laboral | B11: 0 | C11: 0 | D11: 0 | E11: 0 | F11: 0 | N11: 0 | Q11: COLUMAN N (INCAPACIDAD) | R11: Agregar a item en web Inc. Enfermedad Laboral
A12: Número de casos aprobados por la ARL como Enfermedad Laboral | B12: 0 | C12: 0 | D12: 0 | E12: 0 | F12: 0 | N12: 0 | Q12: EDITABLES
A13: Número de casos existentes (antiguios) de Enfermedad Laboral | B13: 0 | C13: 0 | D13: 0 | E13: 0 | F13: 0 | N13: 0 | Q13: EDITABLES
A14: Total de días de incapacidad de Enfermedad Laboral | B14: 0 | C14: 0 | D14: 0 | E14: 0 | F14: 0 | N14: 0 | Q14: COLUMAN N (INCAPACIDAD) SALE DE LA SUMATORIA DE Nro. Dias Incapacidad QUE ESTA EN LA COLUMNA O | R14: Agregar a item en web Inc. Enfermedad Laboral
A15: Tasa Global de ausentismo (EG+AC+AT+EL) | B15: =IFERROR(((B6+B8+B14)/B5),0) -> 0.0090196078 | C15: =IFERROR(((C6+C8+C14)/C5),0) -> 0.01700561 | D15: =IFERROR(((D6+D8+D14)/D5),0) -> 0.016790831 | E15: =IFERROR(((E6+I14E8+E14)/E5),0) -> 0 | F15: =IFERROR(((F6+F8+F14)/F5),0) -> 0.011501517 | G15: =IFERROR(((G6+G8+G14)/G5),0) -> 0 | H15: =IFERROR(((H6+H8+H14)/H5),0) -> 0 | I15: =IFERROR(((I6+I8+I14)/I5),0) -> 0 | J15: =IFERROR(((J6+J8+J14)/J5),0) -> 0 | K15: =IFERROR(((K6+K8+K14)/K5),0) -> 0 | L15: =IFERROR(((L6+L8+L14)/L5),0) -> 0 | M15: =IFERROR(((M6+M8+M14)/M5),0) -> 0 | N15: =IFERROR(((N6+N8+N14)/N5),0) -> 0.016420664
A16: Tasa Global de ausentismo Enfermedad General o Accidente Común | B16: =IFERROR((B6/B5),0) -> 0.00767507 | C16: =IFERROR((C6/C5),0) -> 0.01542777 | D16: =IFERROR((D6/D5),0) -> 0.0147851 | E16: =IFERROR((E6/E5),0) -> 0.013438967 | F16: =IFERROR((F6/F5),0) -> 0.011248736 | G16: =IFERROR((G6/G5),0) -> 0 | H16: =IFERROR((H6/H5),0) -> 0 | I16: =IFERROR((I6/I5),0) -> 0 | ... N16: =IFERROR((N6/N5),0) -> 0.015129151
A17: Indice de Frecuencia Ausentismo | B17: =IFERROR(((B7/B4)*20000),0) -> 2.3497112 | C17: =IFERROR(((C7/C4)*20000),0) -> 2.7080169 | D17: =IFERROR(((D7/D4)*20000),0) -> 2.3547973 | E17: =IFERROR(((E7/E4)*20000),0) -> 2.1193176 | F17: =IFERROR(((F7/F4)*20000),0) -> 2.4010036 | G17: =IFERROR(((G7/G4)*20000),0) -> 0 | H17: =IFERROR(((H7/H4)*20000),0) -> 0 | I17: =IFERROR(((I7/I4)*20000),0) -> 0 | ... M17: =IFERROR(((M7/M4)*20000),0) -> 0 | N17: =IFERROR(((N7/N4)*240000),0) -> 28.642455
A18: Indice de Severidad Ausentismo | B18: =IFERROR(((B6/B4)*20000),0) -> 16.942655 | C18: =IFERROR(((C6/C4)*20000),0) -> 31.083325 | D18: =IFERROR(((D6/D4)*20000),0) -> 30.376885 | E18: =IFERROR(((E6/E4)*20000),0) -> 26.962429 | F18: =IFERROR(((F6/F4)*20000),0) -> 21.368932 | G18: =IFERROR(((G6/G4)*20000),0) -> 0 | H18: =IFERROR(((H6/H4)*20000),0) -> 0 | I18: =IFERROR(((I6/I4)*20000),0) -> 0 | ... M18: =IFERROR(((M6/M4)*20000),0) -> 0 | N18: =IFERROR(((N6/N4)*240000),0) -> 305.32857
A19: Indice de General de Ausentismo | B19: =IFERROR((B7/B3),0) -> 0.026610644 | C19: =IFERROR((C7/C3),0) -> 0.032258065 | D19: =IFERROR((D7/D3),0) -> 0.028653295 | E19: =IFERROR((E7/E3),0) -> 0.025352113 | F19: =IFERROR((F7/F3),0) -> 0.029069767 | G19: =IFERROR((G7/G3),0) -> 0 | H19: =IFERROR((H7/H3),0) -> 0 | I19: =IFERROR((I7/I3),0) -> 0 | ... N19: =IFERROR((N7/N3),0) -> 0.028384899
A20: Tasa de Mortalidad por EG - AC | B20: =IFERROR(((B10/B3)*1000),0) -> 0 | C20: =IFERROR(((C10/C3)*1000),0) -> 0 | D20: =IFERROR(((D10/D3)*1000),0) -> 0 | E20: =IFERROR(((E10/E3)*1000),0) -> 0 | F20: =IFERROR(((F10/F3)*1000),0) -> 0 | G20: =IFERROR(((G10/G3)*1000),0) -> 0 | H20: =IFERROR(((H10/H3)*1000),0) -> 0 | I20: =IFERROR(((I10/I3)*1000),0) -> 0 | ... N20: =IFERROR(((N10/N3)*1000),0) -> 0
A21: Ausentismo por Cauda medica | B21: =IFERROR((((B6+B8)/B5)),0) -> 0.0090196078 | C21: =IFERROR((((C6+C8)/C5)),0) -> 0.01700561 | D21: =IFERROR((((D6+D8)/D5)),0) -> 0.016790831 | E21: =IFERROR((((E6+E8)/E5)),0) -> 0.013497653 | F21: =IFERROR((((F6+F8)/F5)),0) -> 0.011501517 | G21: =IFERROR((((G6+G8)/G5)),0) -> 0 | H21: =IFERROR((((H6+H8)/H5)),0) -> 0 | I21: =IFERROR((((I6+I8)/I5)),0) -> 0 | ... M21: =IFERROR((((M6+M8)/M5)),0) -> 0 | N21: =IFERROR((((N7+N9)/N5)),0) -> 0.0015611695
A22: Incidencia por Enfermedad Laboral | B22: =IFERROR((B12/B3)*100000,0) -> 0 | C22: =IFERROR((C12/C3)*100000,0) -> 0 | D22: =IFERROR((D12/D3)*100000,0) -> 0 | E22: =IFERROR((E12/E3)*100000,0) -> 0 | F22: =IFERROR((F12/F3)*100000,0) -> 0 | G22: =IFERROR((G12/G3)*100000,0) -> 0 | H22: =IFERROR((H12/H3)*100000,0) -> 0 | I22: =IFERROR((I12/I3)*100000,0) -> 0 | ... N22: =IFERROR((N12/N3)*100000,0) -> 0
A23: Prevalencia por Enfermedad Laboral | B23: =IFERROR(((B12+B13)/B3)*100000,0) -> 0 | C23: =IFERROR(((C12+C13)/C3)*100000,0) -> 0 | D23: =IFERROR(((D12+D13)/D3)*100000,0) -> 0 | E23: =IFERROR(((E12+E13)/E3)*100000,0) -> 0 | F23: =IFERROR(((F12+F13)/F3)*100000,0) -> 0 | G23: =IFERROR(((G12+G13)/G3)*100000,0) -> 0 | H23: =IFERROR(((H12+H13)/H3)*100000,0) -> 0 | I23: =IFERROR(((I12+I13)/I3)*100000,0) -> 0 | ... N23: =IFERROR(((N12+N13)/N3)*100000,0) -> 0
A24: Severidad por Enfermedad Laboral | B24: =IFERROR(#REF!(B19/#REF!),0) -> 0 | C24: =IFERROR((C19/#REF!),0) -> 0 | D24: =IFERROR((D19/#REF!),0) -> 0 | E24: =IFERROR((E19/#REF!),0) -> 0 | F24: =IFERROR((F19/#REF!),0) -> 0 | G24: =IFERROR((G19/#REF!),0) -> 0 | H24: =IFERROR((H19/#REF!),0) -> 0 | I24: =IFERROR((I19/#REF!),0) -> 0 | J24: =IFERROR((J19/#REF!),0) -> 0 | ... M24: =IFERROR((M19/#REF!),0) -> 0 | N24: =IFERROR(((N13+N14)/N4)*100000,0) -> 0
A25: Peligros asociados al ausentismo | B25: Virus | C25: Virus | D25: Virus | E25: Virus | F25: Virus | G25: Virus
A29: ANALISIS DE INDICADORES
A30: Enero: | B30: En el mes de enero de 2026 no se presentaron casos de mortalidad por enfermedad general, ni casos de enfermedad laboral, el ausentismo por causa medica esta en 1,434% en los 17850 dias de trabajo programados al personal de la empresa para este mes. De 26 personas se presentaron incapacidad se genera un total de 206 días de ausentismo por enfermedad general o accidente común
A31: Febrero: | B31: En el mes de febrero de 2026 no se presentaron casos de mortalidad por enfermedad general, ni casos de enfermedad laboral, el ausentismo por causa medica esta en 1,484% en los 17112 dias de trabajo programados al personal de la empresa para este mes. De 21 personas se presentaron incapacidad se genera un total de 207 días de ausentismo por enfermedad general o accidente común
A32: Marzo: | B32: En el mes de marzo de 2026 no se presentaron casos de mortalidad por enfermedad general, ni casos de enfermedad laboral, el ausentismo por causa medica esta en 1,885% en los 17450 dias de trabajo programados al personal de la empresa para este mes. De 26 personas se presentaron incapacidad se genera un total de 282 días de ausentismo por enfermedad general o accidente común
A33: Abril: | B33: En el mes de abril de 2026 no se presentaron casos de mortalidad por enfermedad general, ni casos de enfermedad laboral, el ausentismo por causa medica esta en 1,015% en los 17040 dias de trabajo programados al personal de la empresa para este mes. De 19 personas se presentaron incapacidad se genera un total de 172 días de ausentismo por enfermedad general o accidente común
A34: Mayo:
A35: Junio:
A36: Julio:
A37: Agosto:
A38: Septiembre:
A39: Octubre:
A40: Noviembre:
A41: Diciembre:
B50: 2021 | C50: 2020 | D50: 2019 | E50: 2018 | F50: 2017
A51: Tasa Global de ausentismo | B51: =N15 -> 0.016420664 | C51: 0.0096270062 | D51: =+N15 -> 0.016420664 | E51: 0.38 | F51: 0.14
A52: Indice de Frecuencia Ausentismo | B52: =N17 -> 28.642455 | C52: 24.186053 | D52: =+N17 -> 28.642455 | E52: 2.31 | F52: 1.3
A53: Indice de Severidad Ausentismo | B53: =N18 -> 305.32857 | C53: 273.26956 | D53: =+N18 -> 305.32857 | E53: 29.01 | F53: 11.7
A54: Indice de General de Ausentismo | B54: =N19 -> 0.028384899 | C54: 0.026723096 | D54: =+N19 -> 0.028384899 | E54: 0.03 | F54: 0.0151
A55: Tasa de Mortalidad por EG - AC | B55: =N20 -> 0 | C55: 0.24183797 | D55: =+N20 -> 0 | E55: 1.26 | F55: 1.58
A56: Incidencia por Enfermedad Laboral | B56: =N22 -> 0 | C56: 0 | D56: =+N22 -> 0 | E56: 0 | F56: 0
A57: Prevalencia por Enfermedad Laboral | B57: =N23 -> 0 | C57: 0 | D57: =+N23 -> 0 | E57: 0 | F57: 0
A58: Severidad por Enfermedad Laboral | B58: =N24 -> 0 | C58: 1 | D58: =+#REF! -> #REF! | E58: 0 | F58: 0
A59: Ausentismo por causa medica | B59: =N21 -> 0.0015611695 | C59: 0.00084997819 | D59: =+N21 -> 0.0015611695
M81: 1.26
M82: 1.58
M83: =+M82-M81 -> 0.32

Sheet BD Reporte Incapacidades
A1: Fecha de incapacidad | B1: Mes | C1: Año | D1: Cedula | E1: Nombre del Empleado | F1: Genero | G1: Entidad salud que cubre la atención | H1: ENTIDAD QUE PAGA LA INCAPACIDAD | I1: Tipo de Contrato | J1: Cargo | K1: fecha de ingreso a la empresa | L1: Contrato / Cliente | M1: Ciudad de Agencia | N1: Incapacidad | O1: Nro. Dias Incapacidad | P1: Fecha Inicio | Q1: Fecha Fin | R1: DX CIE10 | S1: Descripción DX | T1: Tipo incapacidad | U1: Periodo Efectivo | V1: Periodo inicial | W1: dias | X1: Periodo siguiente | Y1: Periodo final | Z1: dias | AA1: REQUISITO PARA RETOOMA DE LABORES
A2: 44197 | B2: =+MONTH(A2) -> 1 | C2: =+YEAR(A2) -> 2021 | D2: 8458969 | E2: GUILLERMO ALONSO URIBE RIVERA | F2: Masculino | G2: SALUD TOTAL | H2: La EPS | I2: TERCEROS | J2: Conductor | K2: 43082 | L2: EMTELCO MEDELLIN | M2: MEDELLIN | N2: Inc. Enfermedad general | O2: 7 | P2: 44197 | Q2: 44203 | R2: U071 | S2: =VLOOKUP($R2,DX!$A$1:$B$13005,2,FALSE) -> COVID-19 (virus identificado) | T2: PRORROGA
A3: 44197 | B3: =+MONTH(A3) -> 1 | C3: =+YEAR(A3) -> 2021 | D3: 10029456 | E3: ERNESTO DE JESUS TANGARIFE TABARES | F3: Masculino | G3: SALUD TOTAL | H3: La Empresa 2 días el resto de días la EPS | I3: TERCEROS | J3: Conductor | K3: 44092 | L3: EMTELCO PEREIRA | M3: PEREIRA | N3: Inc. Enfermedad general | O3: 6 | P3: 44197 | Q3: 44202 | R3: Z208 | S3: =VLOOKUP($R3,DX!$A$1:$B$13005,2,FALSE) -> Contacto con y exposición a otras enfermedades transmisibles | T3: INICIAL
A4: 44197 | B4: =+MONTH(A4) -> 1 | C4: =+YEAR(A4) -> 2021 | D4: 1020423463 | E4: HENRY DE JESUS HIDALGO MENDEZ | F4: Masculino | G4: EPS SURA | H4: La Empresa 2 días el resto de días la EPS | I4: TERCEROS | J4: Conductor | K4: 43983 | L4: JARDIN BOTANICO | M4: MEDELLIN | N4: Inc. Enfermedad general | O4: 5 | P4: 44197 | Q4: 44317 | R4: U071 | S4: =VLOOKUP($R4,DX!$A$1:$B$13005,2,FALSE) -> COVID-19 (virus identificado) | T4: INICIAL
A5: 44200 | B5: =+MONTH(A5) -> 1 | C5: =+YEAR(A5) -> 2021 | D5: 71654020 | E5: WILSON ANIBAL GARCIA ROJAS | F5: Masculino | G5: EPS SURA | H5: La Empresa | I5: FLOTA PROPIA | J5: Conductor | K5: 42079 | L5: FLOTA PROPIA | M5: MEDELLIN | N5: Inc. Enfermedad general | O5: 1 | P5: 44200 | Q5: 44200 | R5: H811 | S5: =VLOOKUP($R5,DX!$A$1:$B$13005,2,FALSE) -> VERTIGO PAROXISTICO BENIGNO | T5: INICIAL
A6: 44200 | B6: =+MONTH(A6) -> 1 | C6: =+YEAR(A6) -> 2021 | D6: 71669266 | E6: GIOVANY RESTREPO ROLDAN | F6: Masculino | G6: EPS SURA | H6: La Empresa 2 días el resto de días la EPS | I6: FLOTA PROPIA | J6: Conductor | K6: 42780 | L6: FLOTA PROPIA | M6: MEDELLIN | N6: Inc. Enfermedad general | O6: 3 | P6: 44200 | Q6: 44202 | R6: U072 | S6: =VLOOKUP($R6,DX!$A$1:$B$13005,2,FALSE) -> COVID-19 (virus no identificado) | T6: INICIAL
A7: 44200 | B7: =+MONTH(A7) -> 1 | C7: =+YEAR(A7) -> 2021 | D7: 1020407916 | E7: LUIS ANGEL PATIÑO AGUDELO | F7: Masculino | G7: NUEVA EPS | H7: La EPS | I7: TERCEROS | J7: Conductor | K7: 43274 | L7: EPM | M7: MEDELLIN | N7: Inc. Enfermedad general | O7: 30 | P7: 44200 | Q7: 44229 | R7: M179 | S7: =VLOOKUP($R7,DX!$A$1:$B$13005,2,FALSE) -> GONARTROSIS, NO ESPECIFICADA | T7: PRORROGA | AA7: REQUIERE POST INCAPACIDAD
A8: 44202 | B8: =+MONTH(A8) -> 1 | C8: =+YEAR(A8) -> 2021 | D8: 43382074 | E8: LILIANA ISABEL OROZCO OSSA | F8: Femenino | G8: EPS SURA | H8: La Empresa 2 días el resto de días la EPS | I8: ADMINISTRATIVOS | J8: Servicios Generales | K8: 43564 | L8: ADMINISTRATIVOS EMPRESTUR | M8: PEREIRA | N8: Inc. Enfermedad general | O8: 3 | P8: 44202 | Q8: 44204 | R8: U072 | S8: =VLOOKUP($R8,DX!$A$1:$B$13005,2,FALSE) -> COVID-19 (virus no identificado) | T8: INICIAL | AA8: NO REQUIERE POST INCAPACIDAD
A9: 44202 | B9: =+MONTH(A9) -> 1 | C9: =+YEAR(A9) -> 2021 | D9: 1040045426 | E9: YULIANA SERNA OCAMPO | F9: Masculino | G9: EPS SURA | H9: La Empresa 2 días el resto de días la EPS | I9: ADMINISTRATIVOS | J9: Servicios Generales | K9: 44110 | L9: ADMINISTRATIVOS EMPRESTUR | M9: MEDELLIN | N9: Inc. Enfermedad general | O9: 3 | P9: 44202 | Q9: 44204 | R9: U072 | S9: =VLOOKUP($R9,DX!$A$1:$B$13005,2,FALSE) -> COVID-19 (virus no identificado) | T9: INICIAL | AA9: NO REQUIERE POST INCAPACIDAD
A10: 44204 | B10: =+MONTH(A10) -> 1 | C10: =+YEAR(A10) -> 2021 | D10: 98584332 | E10: JIMY EDISON DURANGO OSORIO | F10: Masculino | G10: COOMEVA EPS | H10: La Empresa 2 días el resto de días la EPS | I10: TERCEROS | J10: Conductor | K10: 43626 | L10: EPM | M10: MEDELLIN | N10: Inc. Enfermedad general | O10: 5 | P10: 44204 | Q10: 44208 | R10: U072 | S10: =VLOOKUP($R10,DX!$A$1:$B$13005,2,FALSE) -> COVID-19 (virus no identificado) | T10: INICIAL | AA10: NO REQUIERE POST INCAPACIDAD
A11: 44205 | B11: =+MONTH(A11) -> 1 | C11: =+YEAR(A11) -> 2021 | D11: 15451683 | E11: DANIEL DARIO RODRIGUEZ SALCEDO | F11: Masculino | G11: SAVIA SALUD | H11: La Empresa 2 días el resto de días la EPS | I11: TERCEROS | J11: Conductor | K11: 44068 | L11: EPM | M11: MEDELLIN | N11: Inc. Enfermedad general | O11: 14 | P11: 44205 | Q11: 44218 | R11: U071 | S11: =VLOOKUP($R11,DX!$A$1:$B$13005,2,FALSE) -> COVID-19 (virus identificado) | T11: INICIAL | AA11: NO REQUIERE POST INCAPACIDAD
A12: 44205 | B12: =+MONTH(A12) -> 1 | C12: =+YEAR(A12) -> 2021 | D12: 43382074 | E12: LILIANA ISABEL OROZCO OSSA | F12: Femenino | G12: EPS SURA | H12: La EPS | I12: ADMINISTRATIVOS | J12: Servicios Generales | K12: 43564 | L12: ADMINISTRATIVOS EMPRESTUR | M12: MEDELLIN | N12: Inc. Enfermedad general | O12: 6 | P12: 44205 | Q12: 44210 | R12: U071 | S12: =VLOOKUP($R12,DX!$A$1:$B$13005,2,FALSE) -> COVID-19 (virus identificado) | T12: PRORROGA | AA12: NO REQUIERE POST INCAPACIDAD
A13: 44205 | B13: =+MONTH(A13) -> 1 | C13: =+YEAR(A13) -> 2021 | D13: 71002658 | E13: WILSON DE JESUS BURITICA BUITRAGO | F13: Masculino | G13: SAVIA SALUD | H13: La Empresa 2 días el resto de días la EPS | I13: TERCEROS | J13: Conductor | K13: 43626 | L13: EPM | M13: MEDELLIN | N13: Licencia Paternidad | O13: 8 | P13: 44205 | Q13: 44212 | R13: 2 | S13: =VLOOKUP($R13,DX!$A$1:$B$13005,2,FALSE) -> Licencia Paternidad | T13: INICIAL | AA13: NO REQUIERE POST INCAPACIDAD
A14: 44207 | B14: =+MONTH(A14) -> 1 | C14: =+YEAR(A14) -> 2021 | D14: 8431066 | E14: JOHN FREDY CASTAÑEDA BEDOYA | F14: Masculino | G14: EPS SURA | H14: La Empresa 2 días el resto de días la EPS | I14: FLOTA PROPIA | J14: Conductor | K14: 43787 | L14: FLOTA PROPIA | M14: MEDELLIN | N14: Inc. Enfermedad general | O14: 3 | P14: 44207 | Q14: 44209 | R14: S518 | S14: =VLOOKUP($R14,DX!$A$1:$B$13005,2,FALSE) -> HERIDA DE OTRAS PARTES DEL ANTEBRAZO | T14: INICIAL | AA14: NO REQUIERE POST INCAPACIDAD
A15: 44208 | B15: =+MONTH(A15) -> 1 | C15: =+YEAR(A15) -> 2021 | D15: 71639035 | E15: JHON FREDY HERNANDEZ TEJADA | F15: Masculino | G15: EPS SURA | H15: La Empresa 2 días el resto de días la EPS | I15: TERCEROS | J15: Conductor | K15: 44097 | L15: CORPORACIÓN AYUDA HUMANITARIA | M15: MEDELLIN | N15: Inc. Enfermedad general | O15: 3 | P15: 44208 | Q15: 44210 | R15: U072 | S15: =VLOOKUP($R15,DX!$A$1:$B$13005,2,FALSE) -> COVID-19 (virus no identificado) | T15: INICIAL | AA15: NO REQUIERE POST INCAPACIDAD
A16: 44209 | B16: =+MONTH(A16) -> 1 | C16: =+YEAR(A16) -> 2021 | D16: 1053808794 | E16: ANGELITA REINOSA VILLA | F16: Masculino | G16: EPS SURA | H16: La Empresa 2 días el resto de días la EPS | I16: ADMINISTRATIVOS | J16: Coodinadora de Operaciones Manizales | K16: 42948 | L16: ADMINISTRATIVOS EMPRESTUR | M16: MEDELLIN | N16: Inc. Enfermedad general | O16: 3 | P16: 44209 | Q16: 44211 | R16: N879 | S16: =VLOOKUP($R16,DX!$A$1:$B$13005,2,FALSE) -> DISPLASIA DEL CUELLO DEL UTERO, NO ESPECIFICADA | T16: INICIAL | AA16: NO REQUIERE POST INCAPACIDAD
A17: 44210 | B17: =+MONTH(A17) -> 1 | C17: =+YEAR(A17) -> 2021 | D17: 8431066 | E17: JOHN FREDY CASTAÑEDA BEDOYA | F17: Masculino | G17: EPS SURA | H17: La EPS | I17: FLOTA PROPIA | J17: Conductor | K17: 43787 | L17: FLOTA PROPIA | M17: MEDELLIN | N17: Inc. Enfermedad general | O17: 3 | P17: 44210 | Q17: 44212 | R17: S518 | S17: =VLOOKUP($R17,DX!$A$1:$B$13005,2,FALSE) -> HERIDA DE OTRAS PARTES DEL ANTEBRAZO | T17: PRORROGA | AA17: NO REQUIERE POST INCAPACIDAD
A18: 44211 | B18: =+MONTH(A18) -> 1 | C18: =+YEAR(A18) -> 2021 | D18: 7543791 | E18: GILDARDO ANTONIO CANO MONTOYA | F18: Masculino | G18: MEDIMAS | H18: La Empresa 2 días el resto de días la EPS | I18: TERCEROS | J18: Conductor | K18: 43875 | L18: EMTELCO ARMENIA | M18: ARMENIA | N18: Inc. Enfermedad general | O18: 5 | P18: 44211 | Q18: 44215 | R18: U072 | S18: =VLOOKUP($R18,DX!$A$1:$B$13005,2,FALSE) -> COVID-19 (virus no identificado) | T18: INICIAL | AA18: NO REQUIERE POST INCAPACIDAD
A19: 44212 | B19: =+MONTH(A19) -> 1 | C19: =+YEAR(A19) -> 2021 | D19: 3400128 | E19: JUAN CAMILO GOMEZ TORO | F19: Masculino | G19: EPS SURA | H19: La Empresa 2 días el resto de días la EPS | I19: ADMINISTRATIVOS | J19: Director Talento humano | K19: 41526 | L19: ADMINISTRATIVOS EMPRESTUR | M19: MEDELLIN | N19: Inc. Enfermedad general | O19: 3 | P19: 44212 | Q19: 44214 | R19: U072 | S19: =VLOOKUP($R19,DX!$A$1:$B$13005,2,FALSE) -> COVID-19 (virus no identificado) | T19: INICIAL | AA19: NO REQUIERE POST INCAPACIDAD
A20: 44213 | B20: =+MONTH(A20) -> 1 | C20: =+YEAR(A20) -> 2021 | D20: 71661278 | E20: CARLOS HUMBERTO MUÑOZ CANO | F20: Masculino | G20: EPS SURA | H20: La Empresa 2 días el resto de días la EPS | I20: TERCEROS | J20: Conductor | K20: 43640 | L20: ARGOS | M20: MEDELLIN | N20: Inc. Enfermedad general | O20: 3 | P20: 44213 | Q20: 44215 | R20: U072 | S20: =VLOOKUP($R20,DX!$A$1:$B$13005,2,FALSE) -> COVID-19 (virus no identificado) | T20: INICIAL | AA20: NO REQUIERE POST INCAPACIDAD
A21: 44214 | B21: =+MONTH(A21) -> 1 | C21: =+YEAR(A21) -> 2021 | D21: 8028387 | E21: ANDRES MAURICIO ZAPATA GIRALDO | F21: Masculino | G21: EPS SURA | H21: La Empresa 2 días el resto de días la EPS | I21: TERCEROS | J21: Conductor | K21: 43657 | L21: EPM | M21: MEDELLIN | N21: Inc. Enfermedad general | O21: 3 | P21: 44214 | Q21: 44216 | R21: Z038 | S21: =VLOOKUP($R21,DX!$A$1:$B$13005,2,FALSE) -> OBSERVACION POR SOSPECHA DE OTRAS ENFERMEDADES Y AFECCIONES | T21: INICIAL | AA21: NO REQUIERE POST INCAPACIDAD
A22: 44214 | B22: =+MONTH(A22) -> 1 | C22: =+YEAR(A22) -> 2021 | D22: 8431066 | E22: JOHN FREDY CASTAÑEDA BEDOYA | F22: Masculino | G22: EPS SURA | H22: La EPS | I22: FLOTA PROPIA | J22: Conductor | K22: 43787 | L22: FLOTA PROPIA | M22: MEDELLIN | N22: Inc. Enfermedad general | O22: 1 | P22: 44214 | Q22: 44214 | R22: S518 | S22: =VLOOKUP($R22,DX!$A$1:$B$13005,2,FALSE) -> HERIDA DE OTRAS PARTES DEL ANTEBRAZO | T22: PRORROGA | AA22: NO REQUIERE POST INCAPACIDAD
A23: 44215 | B23: =+MONTH(A23) -> 1 | C23: =+YEAR(A23) -> 2021 | D23: 3400128 | E23: JUAN CAMILO GOMEZ TORO | F23: Masculino | G23: EPS SURA | H23: La EPS | I23: ADMINISTRATIVOS | J23: Director Talento humano | K23: 41526 | L23: ADMINISTRATIVOS EMPRESTUR | M23: MEDELLIN | N23: Inc. Enfermedad general | O23: 4 | P23: 44215 | Q23: 44218 | R23: U071 | S23: =VLOOKUP($R23,DX!$A$1:$B$13005,2,FALSE) -> COVID-19 (virus identificado) | T23: PRORROGA | AA23: NO REQUIERE POST INCAPACIDAD
A24: 44216 | B24: =+MONTH(A24) -> 1 | C24: =+YEAR(A24) -> 2021 | D24: 7543791 | E24: GILDARDO ANTONIO CANO MONTOYA | F24: Masculino | G24: MEDIMAS | H24: La EPS | I24: TERCEROS | J24: Conductor | K24: 43875 | L24: EMTELCO ARMENIA | M24: ARMENIA | N24: Inc. Enfermedad general | O24: 4 | P24: 44216 | Q24: 44219 | R24: U072 | S24: =VLOOKUP($R24,DX!$A$1:$B$13005,2,FALSE) -> COVID-19 (virus no identificado) | T24: PRORROGA | AA24: NO REQUIERE POST INCAPACIDAD
A25: 44216 | B25: =+MONTH(A25) -> 1 | C25: =+YEAR(A25) -> 2021 | D25: 71661278 | E25: CARLOS HUMBERTO MUÑOZ CANO | F25: Masculino | G25: EPS SURA | H25: La EPS | I25: TERCEROS | J25: Conductor | K25: 43640 | L25: ARGOS | M25: MEDELLIN | N25: Inc. Enfermedad general | O25: 5 | P25: 44216 | Q25: 44221 | R25: U071 | S25: =VLOOKUP($R25,DX!$A$1:$B$13005,2,FALSE) -> COVID-19 (virus identificado) | T25: PRORROGA | AA25: NO REQUIERE POST INCAPACIDAD
... A69: 44280 | B69: =+MONTH(A69) -> 3 | C69: =+YEAR(A69) -> 2021 | D69: 1036638930 | E69: SEBASTIAN GARCIA SEPULVEDA | F69: Masculino | G69: EPS SURA | H69: La Empresa 2 días el resto de días la EPS | I69: TERCEROS | J69: Conductor | K69: 44221 | L69: UT MEJIA ACEVEDO | M69: MEDELLIN | N69: Inc. Enfermedad general | O69: 3 | P69: 44280 | Q69: 44282 | R69: U072 | S69: =VLOOKUP($R69,DX!$A$1:$B$13005,2,FALSE) -> COVID-19 (virus no identificado) | T69: INICIAL | AA69: NO REQUIERE POST INCAPACIDAD
A70: 44281 | B70: =+MONTH(A70) -> 3 | C70: =+YEAR(A70) -> 2021 | D70: 1152688913 | E70: BRANDON STEW FIGUEROA MOSQUERA | F70: Masculino | G70: EPS SURA | H70: La Empresa 2 días el resto de días la EPS | I70: ADMINISTRATIVOS | J70: Auxiliar de Operaciones | K70: 44267 | L70: ADMINISTRATIVOS EMPRESTUR | M70: MEDELLIN | N70: Inc. Enfermedad general | O70: 3 | P70: 44281 | Q70: 28/3/0201 | R70: N23X | S70: =VLOOKUP($R70,DX!$A$1:$B$13005,2,FALSE) -> COLICO RENAL, NO ESPECIFICADO | T70: INICIAL | AA70: NO REQUIERE POST INCAPACIDAD
A71: 44282 | B71: =+MONTH(A71) -> 3 | C71: =+YEAR(A71) -> 2021 | D71: 8129549 | E71: LUIS CARLOS RICO MEDRANO | F71: Masculino | G71: EPS SURA | H71: La Empresa 2 días el resto de días la EPS | I71: FLOTA PROPIA | J71: Conductor | K71: 43774 | L71: FLOTA PROPIA | M71: MEDELLIN | N71: Inc. Enfermedad general | O71: 10 | P71: 44282 | Q71: 44291 | R71: N390 | S71: =VLOOKUP($R71,DX!$A$1:$B$13005,2,FALSE) -> INFECCION DE VIAS URINARIAS, SITIO NO ESPECIFICADO | T71: INICIAL | AA71: NO REQUIERE POST INCAPACIDAD
A72: 44283 | B72: =+MONTH(A72) -> 3 | C72: =+YEAR(A72) -> 2021 | D72: 71661367 | E72: CARLOS ALBERTO ALVAREZ ALVAREZ | F72: Masculino | G72: EPS SURA | H72: La EPS | I72: TERCEROS | J72: Conductor | K72: 44268 | L72: EPM | M72: MEDELLIN | N72: Inc. Enfermedad general | O72: 4 | P72: 44283 | Q72: 44286 | R72: U071 | S72: =VLOOKUP($R72,DX!$A$1:$B$13005,2,FALSE) -> COVID-19 (virus identificado) | T72: PRORROGA | AA72: NO REQUIERE POST INCAPACIDAD
A73: 44283 | B73: =+MONTH(A73) -> 3 | C73: =+YEAR(A73) -> 2021 | D73: 98584062 | E73: GUSTAVO ADOLFO MONTOYA ZAPATA | F73: Masculino | G73: EPS SURA | H73: La EPS | I73: TERCEROS | J73: Conductor | K73: 44257 | L73: EPM | M73: MEDELLIN | N73: Inc. Enfermedad general | O73: 5 | P73: 44283 | Q73: 44287 | R73: U072 | S73: =VLOOKUP($R73,DX!$A$1:$B$13005,2,FALSE) -> COVID-19 (virus no identificado) | T73: PRORROGA | AA73: NO REQUIERE POST INCAPACIDAD
A74: 44283 | B74: =+MONTH(A74) -> 3 | C74: =+YEAR(A74) -> 2021 | D74: 1036638930 | E74: SEBASTIAN GARCIA SEPULVEDA | F74: Masculino | G74: EPS SURA | H74: La EPS | I74: TERCEROS | J74: Conductor | K74: 44221 | L74: UT MEJIA ACEVEDO | M74: MEDELLIN | N74: Inc. Enfermedad general | O74: 2 | P74: 44283 | Q74: 44284 | R74: U072 | S74: =VLOOKUP($R74,DX!$A$1:$B$13005,2,FALSE) -> COVID-19 (virus no identificado) | T74: PRORROGA | AA74: NO REQUIERE POST INCAPACIDAD
A75: 44284 | B75: =+MONTH(A75) -> 3 | C75: =+YEAR(A75) -> 2021 | D75: 1128471141 | E75: DAVID ALEXANDER BARRERA CANO | F75: Masculino | G75: EPS SURA | H75: La Empresa 2 días el resto de días la EPS | I75: FLOTA PROPIA | J75: Conductor | K75: 44193 | L75: FLOTA PROPIA | M75: MEDELLIN | N75: Inc. Enfermedad general | O75: 3 | P75: 44284 | Q75: 44286 | R75: U072 | S75: =VLOOKUP($R75,DX!$A$1:$B$13005,2,FALSE) -> COVID-19 (virus no identificado) | T75: INICIAL | AA75: NO REQUIERE POST INCAPACIDAD
A76: 44285 | B76: =+MONTH(A76) -> 3 | C76: =+YEAR(A76) -> 2021 | D76: 35010428 | E76: BERTHA EDITH PALMERA ALVAREZ | F76: Femenino | G76: EPS SURA | H76: La EPS | I76: ADMINISTRATIVOS | J76: Servicios Generales | K76: 42152 | L76: ADMINISTRATIVOS EMPRESTUR | M76: MEDELLIN | N76: Inc. Enfermedad general | O76: 2 | P76: 44285 | Q76: 44286 | R76: U071 | S76: =VLOOKUP($R76,DX!$A$1:$B$13005,2,FALSE) -> COVID-19 (virus identificado) | T76: PRORROGA | AA76: NO REQUIERE POST INCAPACIDAD
A77: 44286 | B77: =+MONTH(A77) -> 3 | C77: =+YEAR(A77) -> 2021 | D77: 71380451 | E77: JULIO ANGEL CORDOBA QUINTO | F77: Masculino | G77: EPS SURA | H77: La Empresa 2 días el resto de días la EPS | I77: TERCEROS | J77: Conductor | K77: 43477 | L77: CORPORACIÓN AYUDA HUMANITARIA | M77: MEDELLIN | N77: Inc. Enfermedad general | O77: 6 | P77: 44286 | Q77: 44291 | R77: U071 | S77: =VLOOKUP($R77,DX!$A$1:$B$13005,2,FALSE) -> COVID-19 (virus identificado) | T77: INICIAL | AA77: NO REQUIERE POST INCAPACIDAD
A78: 44286 | B78: =+MONTH(A78) -> 3 | C78: =+YEAR(A78) -> 2021 | D78: 98606684 | E78: WILLIAN DE JESUS SALAZAR SALAZAR | F78: Masculino | G78: EPS SURA | H78: La Empresa 2 días el resto de días la EPS | I78: TERCEROS | J78: Conductor | K78: 43958 | L78: UT MEJIA ACEVEDO | M78: MEDELLIN | N78: Inc. Enfermedad general | O78: 15 | P78: 44286 | Q78: 44300 | R78: H110 | S78: =VLOOKUP($R78,DX!$A$1:$B$13005,2,FALSE) -> PTERIGION | T78: INICIAL | AA78: NO REQUIERE POST INCAPACIDAD
A79: 44286 | B79: =+MONTH(A79) -> 3 | C79: =+YEAR(A79) -> 2021 | D79: 1040736785 | E79: MIGUEL ANGEL VELEZ POSADA | F79: Masculino | G79: EPS SURA | H79: La Empresa 2 días el resto de días la EPS | I79: TERCEROS | J79: Conductor | K79: 44235 | L79: EPM | M79: MEDELLIN | N79: Inc. Enfermedad general | O79: 3 | P79: 44286 | Q79: 44288 | R79: U072 | S79: =VLOOKUP($R79,DX!$A$1:$B$13005,2,FALSE) -> COVID-19 (virus no identificado) | T79: INICIAL | AA79: NO REQUIERE POST INCAPACIDAD
A80: 44288 | B80: =+MONTH(A80) -> 4 | C80: =+YEAR(A80) -> 2021 | D80: 35602375 | E80: MARIA SANTOS PALACIO ROMAÑA | F80: Femenino | G80: EPS SURA | H80: La Empresa 2 días el resto de días la EPS | I80: ADMINISTRATIVOS | J80: Servicios Generales | K80: 44130 | L80: ADMINISTRATIVOS EMPRESTUR | M80: MEDELLIN | N80: Inc. Enfermedad general | O80: 9 | P80: 44288 | Q80: 44296 | R80: U071 | S80: =VLOOKUP($R80,DX!$A$1:$B$13005,2,FALSE) -> COVID-19 (virus identificado) | T80: INICIAL | AA80: NO REQUIERE POST INCAPACIDAD
A81: 44289 | B81: =+MONTH(A81) -> 4 | C81: =+YEAR(A81) -> 2021 | D81: 71706793 | E81: CARLOS FERNANDO JAIMES RAMOS | F81: Masculino | G81: EPS SURA | H81: La EPS | I81: ADMINISTRATIVOS | J81: Ingeniero Sistemas | K81: 41526 | L81: ADMINISTRATIVOS EMPRESTUR | M81: MEDELLIN | N81: Inc. Enfermedad general | O81: 4 | P81: 44289 | Q81: 44292 | R81: U071 | S81: =VLOOKUP($R81,DX!$A$1:$B$13005,2,FALSE) -> COVID-19 (virus identificado) | T81: PRORROGA | AA81: NO REQUIERE POST INCAPACIDAD
A82: 44289 | B82: =+MONTH(A82) -> 4 | C82: =+YEAR(A82) -> 2021 | D82: 1040736785 | E82: MIGUEL ANGEL VELEZ POSADA | F82: Masculino | G82: EPS SURA | H82: La EPS | I82: TERCEROS | J82: Conductor | K82: 44235 | L82: EPM | M82: MEDELLIN | N82: Inc. Enfermedad general | O82: 2 | P82: 44289 | Q82: 44290 | R82: U072 | S82: =VLOOKUP($R82,DX!$A$1:$B$13005,2,FALSE) -> COVID-19 (virus no identificado) | T82: PRORROGA | AA82: NO REQUIERE POST INCAPACIDAD
... A93: 44302 | B93: =+MONTH(A93) -> 4 | C93: =+YEAR(A93) -> 2021 | D93: 177212 | E93: JOSE PASCUAL NAVARRO GANDIA | F93: Masculino | G93: EPS SANITAS | H93: La Empresa 2 días el resto de días la EPS | I93: TERCEROS | J93: Conductor | K93: 44267 | L93: CHEC | M93: MEDELLIN | N93: Inc. Enfermedad general | O93: 14 | P93: 44302 | Q93: 44315 | R93: U071 | S93: =VLOOKUP($R93,DX!$A$1:$B$13005,2,FALSE) -> COVID-19 (virus identificado) | T93: INICIAL | AA93: NO REQUIERE POST INCAPACIDAD
A94: 44303 | B94: =+MONTH(A94) -> 4 | C94: =+YEAR(A94) -> 2021 | D94: 2471933 | E94: IVAN ALIRIO RIOS SANCHEZ | F94: Masculino | G94: EPS SANITAS | H94: La Empresa 2 días el resto de días la EPS | I94: TERCEROS | J94: Conductor | K94: 43617 | L94: EMTELCO PEREIRA | M94: PEREIRA | N94: Inc. Enfermedad general | O94: 22 | P94: 44303 | Q94: 44324 | R94: S836 | S94: =VLOOKUP($R94,DX!$A$1:$B$13005,2,FALSE) -> ESGUINCES Y TORCEDURAS DE OTRAS PARTES Y LAS NO ESPECIF DE LA RODILLA | T94: INICIAL
A95: 44303 | B95: =+MONTH(A95) -> 4 | C95: =+YEAR(A95) -> 2021 | D95: 70878529 | E95: LISANDO ANDREY CANO BUSTAMANTE | F95: Masculino | G95: EPS SURA | H95: La Empresa 2 días el resto de días la EPS | I95: TERCEROS | J95: Conductor | K95: 44193 | L95: EMTELCO MEDELLIN | M95: MEDELLIN | N95: Inc. Enfermedad general | O95: 3 | P95: 44303 | Q95: 44305 | R95: U072 | S95: =VLOOKUP($R95,DX!$A$1:$B$13005,2,FALSE) -> COVID-19 (virus no identificado) | T95: INICIAL | AA95: NO REQUIERE POST INCAPACIDAD
A96: 44303 | B96: =+MONTH(A96) -> 4 | C96: =+YEAR(A96) -> 2021 | D96: 71557011 | E96: ERMIS ARVEY ROJO CARMONA | F96: Masculino | G96: SAVIA SALUD | H96: La Empresa 2 días el resto de días la EPS | I96: TERCEROS | J96: Conductor | K96: 44152 | L96: EPM | M96: MEDELLIN | N96: Inc. Enfermedad general | O96: 14 | P96: 44303 | Q96: 44316 | R96: U071 | S96: =VLOOKUP($R96,DX!$A$1:$B$13005,2,FALSE) -> COVID-19 (virus identificado) | T96: INICIAL | AA96: NO REQUIERE POST INCAPACIDAD
A97: 44305 | B97: =+MONTH(A97) -> 4 | C97: =+YEAR(A97) -> 2021 | D97: 70101185 | E97: LUIS FELIPE SEGURO PINO | F97: Masculino | G97: EPS SURA | H97: La Empresa 2 días el resto de días la EPS | I97: TERCEROS | J97: Conductor | K97: 43581 | L97: EMTELCO MEDELLIN | M97: MEDELLIN | N97: Inc. Enfermedad general | O97: 3 | P97: 44305 | Q97: 44307 | R97: U072 | S97: =VLOOKUP($R97,DX!$A$1:$B$13005,2,FALSE) -> COVID-19 (virus no identificado) | T97: INICIAL | AA97: NO REQUIERE POST INCAPACIDAD
A98: 44306 | B98: =+MONTH(A98) -> 4 | C98: =+YEAR(A98) -> 2021 | D98: 70878529 | E98: LISANDO ANDREY CANO BUSTAMANTE | F98: Masculino | G98: EPS SURA | H98: La EPS | I98: TERCEROS | J98: Conductor | K98: 44193 | L98: EMTELCO MEDELLIN | M98: MEDELLIN | N98: Inc. Enfermedad general | O98: 6 | P98: 44306 | Q98: 44311 | R98: U071 | S98: =VLOOKUP($R98,DX!$A$1:$B$13005,2,FALSE) -> COVID-19 (virus identificado) | T98: PRORROGA | AA98: NO REQUIERE POST INCAPACIDAD
A99: 44307 | B99: =+MONTH(A99) -> 4 | C99: =+YEAR(A99) -> 2021 | D99: 94350554 | E99: LUIS FERNANDO BOTERO NARANJO | F99: Masculino | G99: EPS SURA | H99: La Empresa 2 días el resto de días la EPS | I99: TERCEROS | J99: Conductor | K99: 44082 | L99: EPM | M99: MEDELLIN | N99: Inc. Enfermedad general | O99: 3 | P99: 44307 | Q99: 44309 | R99: U072 | S99: =VLOOKUP($R99,DX!$A$1:$B$13005,2,FALSE) -> COVID-19 (virus no identificado) | T99: INICIAL | AA99: NO REQUIERE POST INCAPACIDAD
A100: 44307 | B100: =+MONTH(A100) -> 4 | C100: =+YEAR(A100) -> 2021 | D100: 98546391 | E100: WILMAR SEPULVEDA MUÑOZ | F100: Masculino | G100: EPS SURA | H100: La Empresa 2 días el resto de días la EPS | I100: TERCEROS | J100: Conductor | K100: 43940 | L100: CORPORACIÓN AYUDA HUMANITARIA | M100: MEDELLIN | N100: Inc. Enfermedad general | O100: 3 | P100: 44307 | Q100: 44309 | R100: U072 | S100: =VLOOKUP($R100,DX!$A$1:$B$13005,2,FALSE) -> COVID-19 (virus no identificado) | T100: INICIAL | AA100: NO REQUIERE POST INCAPACIDAD
A101: 44307 | B101: =+MONTH(A101) -> 4 | C101: =+YEAR(A101) -> 2021 | D101: 1037571038 | E101: JOSE ALEJANDRO CESPEDES ARAQUE | F101: Masculino | G101: EPS SURA | H101: La Empresa 2 días el resto de días la EPS | I101: TERCEROS | J101: Conductor | K101: 44168 | L101: DINAMICA SURA | M101: MEDELLIN | N101: Inc. Enfermedad general | O101: 3 | P101: 44307 | Q101: 44309 | R101: U072 | S101: =VLOOKUP($R101,DX!$A$1:$B$13005,2,FALSE) -> COVID-19 (virus no identificado) | T101: INICIAL | AA101: NO REQUIERE POST INCAPACIDAD
A102: 44308 | B102: =+MONTH(A102) -> 4 | C102: =+YEAR(A102) -> 2021 | D102: 70101185 | E102: LUIS FELIPE SEGURO PINO | F102: Masculino | G102: EPS SURA | H102: La EPS | I102: TERCEROS | J102: Conductor | K102: 43581 | L102: EMTELCO MEDELLIN | M102: MEDELLIN | N102: Inc. Enfermedad general | O102: 5 | P102: 44308 | Q102: 44312 | R102: U071 | S102: =VLOOKUP($R102,DX!$A$1:$B$13005,2,FALSE) -> COVID-19 (virus identificado) | T102: PRORROGA | AA102: NO REQUIERE POST INCAPACIDAD
A103: 44309 | B103: =+MONTH(A103) -> 4 | C103: =+YEAR(A103) -> 2021 | D103: 1106772607 | E103: EDINSSON CARVAJAL COCOMA | F103: Masculino | G103: MEDIMAS | H103: La Empresa 2 días el resto de días la EPS | I103: FLOTA PROPIA | J103: Conductor | K103: 44245 | L103: FLOTA PROPIA | M103: IBAGUE | N103: Inc. Enfermedad general | O103: 30 | P103: 44309 | Q103: 44338 | R103: S929 | S103: =VLOOKUP($R103,DX!$A$1:$B$13005,2,FALSE) -> FRACTURA DEL PIE, NO ESPECIFICADA | T103: INICIAL | AA103: REQUIERE POST INCAPACIDAD
A104: 44310 | B104: =+MONTH(A104) -> 4 | C104: =+YEAR(A104) -> 2021 | D104: 94350554 | E104: LUIS FERNANDO BOTERO NARANJO | F104: Masculino | G104: EPS SURA | H104: La EPS | I104: TERCEROS | J104: Conductor | K104: 44082 | L104: EPM | M104: MEDELLIN | N104: Inc. Enfermedad general | O104: 2 | P104: 44310 | Q104: 44311 | R104: U072 | S104: =VLOOKUP($R104,DX!$A$1:$B$13005,2,FALSE) -> COVID-19 (virus no identificado) | T104: PRORROGA | AA104: NO REQUIERE POST INCAPACIDAD
A105: 44310 | B105: =+MONTH(A105) -> 4 | C105: =+YEAR(A105) -> 2021 | D105: 98546391 | E105: WILMAR SEPULVEDA MUÑOZ | F105: Masculino | G105: EPS SURA | H105: La EPS | I105: TERCEROS | J105: Conductor | K105: 43940 | L105: CORPORACIÓN AYUDA HUMANITARIA | M105: MEDELLIN | N105: Inc. Enfermedad general | O105: 1 | P105: 44310 | Q105: 44310 | R105: U072 | S105: =VLOOKUP($R105,DX!$A$1:$B$13005,2,FALSE) -> COVID-19 (virus no identificado) | T105: PRORROGA | AA105: NO REQUIERE POST INCAPACIDAD
A106: 44310 | B106: =+MONTH(A106) -> 4 | C106: =+YEAR(A106) -> 2021 | D106: 1152222115 | E106: JEISON SANCHEZ ALCALDE | F106: Masculino | G106: EPS SURA | H106: La Empresa 2 días el resto de días la EPS | I106: ADMINISTRATIVOS | J106: Auxiliar de Operaciones | K106: 43164 | L106: ADMINISTRATIVOS EMPRESTUR | M106: MEDELLIN | N106: Inc. Enfermedad general | O106: 3 | P106: 44310 | Q106: 44312 | R106: U072 | S106: =VLOOKUP($R106,DX!$A$1:$B$13005,2,FALSE) -> COVID-19 (virus no identificado) | T106: INICIAL | AA106: NO REQUIERE POST INCAPACIDAD
... A109: 44312 | B109: =+MONTH(A109) -> 4 | C109: =+YEAR(A109) -> 2021 | D109: 94350554 | E109: LUIS FERNANDO BOTERO NARANJO | F109: Masculino | G109: EPS SURA | H109: La EPS | I109: TERCEROS | J109: Conductor | K109: 44082 | L109: EPM | M109: MEDELLIN | N109: Inc. Enfermedad general | O109: 2 | P109: 44312 | Q109: 44313 | R109: U072 | S109: =VLOOKUP($R109,DX!$A$1:$B$13005,2,FALSE) -> COVID-19 (virus no identificado) | T109: PRORROGA | AA109: NO REQUIERE POST INCAPACIDAD
A110: 44313 | B110: =+MONTH(A110) -> 4 | C110: =+YEAR(A110) -> 2021 | D110: 4560597 | E110: ANGEL MIRO CANO GARCIA | F110: Masculino | G110: COMFENALCO | H110: La Empresa 2 días el resto de días la EPS | I110: TERCEROS | J110: Conductor | K110: 42583 | L110: EMTELCO CALI | M110: CALI | N110: Inc. Enfermedad general | O110: 4 | P110: 44313 | Q110: 04/30/2021 | R110: M544 | S110: =VLOOKUP($R110,DX!$A$1:$B$13005,2,FALSE) -> LUMBAGO CON CIATICA | T110: INICIAL | AA110: NO REQUIERE POST INCAPACIDAD
A111: 44313 | B111: =+MONTH(A111) -> 4 | C111: =+YEAR(A111) -> 2021 | D111: 70101185 | E111: LUIS FELIPE SEGURO PINO | F111: Masculino | G111: EPS SURA | H111: La EPS | I111: TERCEROS | J111: Conductor | K111: 43581 | L111: EMTELCO MEDELLIN | M111: MEDELLIN | N111: Inc. Enfermedad general | O111: 10 | P111: 44313 | Q111: 44322 | R111: U071 | S111: =VLOOKUP($R111,DX!$A$1:$B$13005,2,FALSE) -> COVID-19 (virus identificado) | T111: PRORROGA | AA111: NO REQUIERE POST INCAPACIDAD
A112: 44313 | B112: =+MONTH(A112) -> 4 | C112: =+YEAR(A112) -> 2021 | D112: 70878529 | E112: LISANDRO ANDREY CANO BUSTAMANTE | F112: Masculino | G112: EPS SURA | H112: La Empresa | I112: TERCEROS | J112: Conductor | K112: 44193 | L112: EMTELCO MEDELLIN | M112: MEDELLIN | N112: Inc. Enfermedad general | O112: 2 | P112: 44313 | Q112: 44314 | R112: U071 | S112: =VLOOKUP($R112,DX!$A$1:$B$13005,2,FALSE) -> COVID-19 (virus identificado) | T112: INICIAL | AA112: NO REQUIERE POST INCAPACIDAD
A113: 44313 | B113: =+MONTH(A113) -> 4 | C113: =+YEAR(A113) -> 2021 | D113: 71290845 | E113: JUAN CARLOS MONCADA ORREGO | F113: Masculino | G113: SALUD TOTAL | H113: La Empresa 2 días el resto de días la EPS | I113: TERCEROS | J113: Conductor | K113: 44036 | L113: DINAMICA SURA | M113: MEDELLIN | N113: Inc. Enfermedad general | O113: 3 | P113: 44313 | Q113: 44315 | R113: U071 | S113: =VLOOKUP($R113,DX!$A$1:$B$13005,2,FALSE) -> COVID-19 (virus identificado) | T113: INICIAL | AA113: NO REQUIERE POST INCAPACIDAD
A114: 44314 | B114: =+MONTH(A114) -> 4 | C114: =+YEAR(A114) -> 2021 | D114: 94350554 | E114: LUIS FERNANDO BOTERO NARANJO | F114: Masculino | G114: EPS SURA | H114: La EPS | I114: TERCEROS | J114: Conductor | K114: 44082 | L114: EPM | M114: MEDELLIN | N114: Inc. Enfermedad general | O114: 2 | P114: 44314 | Q114: 44315 | R114: U072 | S114: =VLOOKUP($R114,DX!$A$1:$B$13005,2,FALSE) -> COVID-19 (virus no identificado) | T114: PRORROGA | AA114: NO REQUIERE POST INCAPACIDAD
A115: 44315 | B115: =+MONTH(A115) -> 4 | C115: =+YEAR(A115) -> 2021 | D115: 3474350 | E115: HERNAN ALONSO HINCAPIE BETANCUR | F115: Masculino | G115: EPS SURA | H115: La EPS | I115: TERCEROS | J115: Conductor | K115: 44245 | L115: EPM | M115: MEDELLIN | N115: Inc. Enfermedad general | O115: 2 | P115: 44315 | Q115: 44316 | R115: U071 | S115: =VLOOKUP($R115,DX!$A$1:$B$13005,2,FALSE) -> COVID-19 (virus identificado) | T115: PRORROGA | AA115: NO REQUIERE POST INCAPACIDAD
A116: 44316 | B116: =+MONTH(A116) -> 4 | C116: =+YEAR(A116) -> 2021 | D116: 177212 | E116: JOSE PASCUAL NAVARRO GANDIA | F116: Masculino | G116: EPS SANITAS | H116: La EPS | I116: TERCEROS | J116: Conductor | K116: 44267 | L116: CHEC | M116: MANIZALES | N116: Inc. Enfermedad general | O116: 7 | P116: 44316 | Q116: 44322 | R116: U071 | S116: =VLOOKUP($R116,DX!$A$1:$B$13005,2,FALSE) -> COVID-19 (virus identificado) | T116: PRORROGA | AA116: NO REQUIERE POST INCAPACIDAD
A117: 44316 | B117: =+MONTH(A117) -> 4 | C117: =+YEAR(A117) -> 2021 | D117: 71670203 | E117: JAIRO ALBERTO MONTOYA RENDON | F117: Masculino | G117: EPS SURA | H117: La Empresa 2 días el resto de días la EPS | I117: FLOTA PROPIA | J117: Conductor | K117: 43617 | L117: FLOTA PROPIA | M117: MEDELLIN | N117: Inc. Enfermedad general | O117: 3 | P117: 44316 | Q117: 44318 | R117: L029 | S117: =VLOOKUP($R117,DX!$A$1:$B$13005,2,FALSE) -> ABSCESO CUTANEO, FURUNCULO Y CARBUNCO DE SITIO NO ESPECIFICADO | T117: INICIAL | AA117: NO REQUIERE POST INCAPACIDAD
A118: 44319 | B118: =+MONTH(A118) -> 5 | C118: =+YEAR(A118) -> 2021 | D118: 98714517 | E118: FREDY LONDOÑO MONTOYA | F118: Masculino | G118: NUEVA EPS | H118: La Empresa 2 días el resto de días la EPS | I118: FLOTA PROPIA | J118: Conductor | K118: 43782 | L118: FLOTA PROPIA | M118: MEDELLIN | N118: Inc. Enfermedad general | O118: 3 | P118: 44319 | Q118: 44321 | R118: U072 | S118: =VLOOKUP($R118,DX!$A$1:$B$13005,2,FALSE) -> COVID-19 (virus no identificado) | T118: INICIAL | AA118: NO REQUIERE POST INCAPACIDAD
A119: 44320 | B119: =+MONTH(A119) -> 5 | C119: =+YEAR(A119) -> 2021 | D119: 75082318 | E119: JULIO CESAR LONDOÑO HINCAPIE | F119: Masculino | G119: NUEVA EPS | H119: La Empresa 2 días el resto de días la EPS | I119: TERCEROS | J119: Conductor | K119: 44267 | L119: CHEC | M119: MANIZALES | N119: Inc. Enfermedad general | O119: 10 | P119: 44320 | Q119: 44329 | R119: U071 | S119: =VLOOKUP($R119,DX!$A$1:$B$13005,2,FALSE) -> COVID-19 (virus identificado) | T119: INICIAL | AA119: NO REQUIERE POST INCAPACIDAD
A120: 44320 | B120: =+MONTH(A120) -> 5 | C120: =+YEAR(A120) -> 2021 | D120: 79051457 | E120: HUGO ARMANDO SUAREZ CORTES | F120: Masculino | G120: MEDIMAS | H120: La Empresa 2 días el resto de días la EPS | I120: TERCEROS | J120: Conductor | K120: 44265 | L120: EMTELCO ARMENIA | M120: ARMENIA | N120: Inc. Enfermedad general | O120: 5 | P120: 44320 | Q120: 44324 | R120: U072 | S120: =VLOOKUP($R120,DX!$A$1:$B$13005,2,FALSE) -> COVID-19 (virus no identificado) | T120: INICIAL | AA120: NO REQUIERE POST INCAPACIDAD
A121: 44320 | B121: =+MONTH(A121) -> 5 | C121: =+YEAR(A121) -> 2021 | D121: 1053792029 | E121: FRANCINE LORENA ACOSTA GOMEZ | F121: Femenino | G121: EPS SURA | H121: La Empresa | I121: ADMINISTRATIVOS | J121: Responsable SST Isagen | K121: 44256 | L121: ADMINISTRATIVOS EMPRESTUR | M121: MEDELLIN | N121: Inc. Enfermedad general | O121: 2 | P121: 44320 | Q121: 44321 | R121: U072 | S121: =VLOOKUP($R121,DX!$A$1:$B$13005,2,FALSE) -> COVID-19 (virus no identificado) | T121: INICIAL | AA121: NO REQUIERE POST INCAPACIDAD
A122: 44321 | B122: =+MONTH(A122) -> 5 | C122: =+YEAR(A122) -> 2021 | D122: 1017159861 | E122: YULY TATIANA ZAPATA ESCOBAR | F122: Femenino | G122: EPS SURA | H122: La Empresa | I122: ADMINISTRATIVOS | J122: Auxiliar contable | K122: 41499 | L122: ADMINISTRATIVOS EMPRESTUR | M122: MEDELLIN | N122: Inc. Enfermedad general | O122: 2 | P122: 44321 | Q122: 44322 | R122: G439 | S122: =VLOOKUP($R122,DX!$A$1:$B$13005,2,FALSE) -> MIGRAÑA, NO ESPECIFICADA | T122: INICIAL | AA122: NO REQUIERE POST INCAPACIDAD
... A134: 44332 | B134: =+MONTH(A134) -> 5 | C134: =+YEAR(A134) -> 2021 | D134: 10080826 | E134: LUIS CARLOS OLAYA MORALES | F134: Masculino | G134: EPS SURA | H134: La EPS | I134: TERCEROS | J134: Conductor | K134: 44305 | L134: TIGO | M134: PEREIRA | N134: Inc. Enfermedad general | O134: 15 | P134: 44332 | Q134: 44345 | R134: U072 | S134: =VLOOKUP($R134,DX!$A$1:$B$13005,2,FALSE) -> COVID-19 (virus no identificado) | T134: PRORROGA | AA134: NO REQUIERE POST INCAPACIDAD
A135: 44333 | B135: =+MONTH(A135) -> 5 | C135: =+YEAR(A135) -> 2021 | D135: 70101185 | E135: LUIS FELIPE SEGURO PINO | F135: Masculino | G135: EPS SURA | H135: La EPS | I135: TERCEROS | J135: Conductor | K135: 43581 | L135: EMTELCO MEDELLIN | M135: MEDELLIN | N135: Inc. Enfermedad general | O135: 25 | P135: 44333 | Q135: 44357 | R135: U071 | S135: =VLOOKUP($R135,DX!$A$1:$B$13005,2,FALSE) -> COVID-19 (virus identificado) | T135: PRORROGA
A136: 44334 | B136: =+MONTH(A136) -> 5 | C136: =+YEAR(A136) -> 2021 | D136: 4560597 | E136: ANGEL MIRO CANO GARCIA | F136: Masculino | G136: COMFENALCO | H136: La Empresa 2 días el resto de días la EPS | I136: TERCEROS | J136: Conductor | K136: 42583 | L136: EMTELCO CALI | M136: CALI | N136: Inc. Enfermedad general | O136: 10 | P136: 44334 | Q136: 44343 | R136: M544 | S136: =VLOOKUP($R136,DX!$A$1:$B$13005,2,FALSE) -> LUMBAGO CON CIATICA | T136: INICIAL | AA136: NO REQUIERE POST INCAPACIDAD
A137: 44334 | B137: =+MONTH(A137) -> 5 | C137: =+YEAR(A137) -> 2021 | D137: 1037605994 | E137: JHON STIVEN RODRIGUEZ OTALVARO | F137: Masculino | G137: EPS SURA | H137: La Empresa 2 días el resto de días la EPS | I137: TERCEROS | J137: Conductor | K137: 44236 | L137: DINAMICA SURA | M137: MEDELLIN | N137: Inc. Enfermedad general | O137: 3 | P137: 44334 | Q137: 44336 | R137: U072 | S137: =VLOOKUP($R137,DX!$A$1:$B$13005,2,FALSE) -> COVID-19 (virus no identificado) | T137: INICIAL | AA137: NO REQUIERE POST INCAPACIDAD
A138: 44335 | B138: =+MONTH(A138) -> 5 | C138: =+YEAR(A138) -> 2021 | D138: 10183148 | E138: RUBIER ANTONIO SANCHEZ GALVIS | F138: Masculino | G138: NUEVA EPS | H138: La EPS | I138: FLOTA PROPIA | J138: Conductor | K138: 44245 | L138: FLOTA PROPIA | M138: MEDELLIN | N138: Inc. Enfermedad general | O138: 4 | P138: 44335 | Q138: 44338 | R138: U072 | S138: =VLOOKUP($R138,DX!$A$1:$B$13005,2,FALSE) -> COVID-19 (virus no identificado) | T138: PRORROGA | AA138: NO REQUIERE POST INCAPACIDAD
A139: 44335 | B139: =+MONTH(A139) -> 5 | C139: =+YEAR(A139) -> 2021 | D139: 85164936 | E139: RICARDO BAENA SAUCEDO | F139: Masculino | G139: EPS SURA | H139: La Empresa 2 días el resto de días la EPS | I139: TERCEROS | J139: Conductor | K139: 43689 | L139: EMTELCO MEDELLIN | M139: MEDELLIN | N139: Inc. Enfermedad general | O139: 3 | P139: 44335 | Q139: 44337 | R139: U071 | S139: =VLOOKUP($R139,DX!$A$1:$B$13005,2,FALSE) -> COVID-19 (virus identificado) | T139: INICIAL | AA139: NO REQUIERE POST INCAPACIDAD
A140: 44336 | B140: =+MONTH(A140) -> 5 | C140: =+YEAR(A140) -> 2021 | D140: 1144200413 | E140: MARLON GIRALDO HERRERA | F140: Masculino | G140: EPS SURA | H140: La Empresa 2 días el resto de días la EPS | I140: ADMINISTRATIVOS | J140: Coordinador de operaciones | K140: 44312 | L140: ADMINISTRATIVOS EMPRESTUR | M140: RIONEGRO | N140: Inc. Enfermedad general | O140: 3 | P140: 44336 | Q140: 44338 | R140: U072 | S140: =VLOOKUP($R140,DX!$A$1:$B$13005,2,FALSE) -> COVID-19 (virus no identificado) | T140: INICIAL | AA140: NO REQUIERE POST INCAPACIDAD
A141: 44337 | B141: =+MONTH(A141) -> 5 | C141: =+YEAR(A141) -> 2021 | D141: 71265993 | E141: JEIMAR ALONSO BUITRAGO GOMEZ | F141: Masculino | G141: EPS SURA | H141: La Empresa 2 días el resto de días la EPS | I141: TERCEROS | J141: Conductor | K141: 44293 | L141: UT MEJIA ACEVEDO | M141: MEDELLIN | N141: Inc. Enfermedad general | O141: 3 | P141: 44337 | Q141: 44339 | R141: U072 | S141: =VLOOKUP($R141,DX!$A$1:$B$13005,2,FALSE) -> COVID-19 (virus no identificado) | T141: INICIAL | AA141: NO REQUIERE POST INCAPACIDAD
A142: 44338 | B142: =+MONTH(A142) -> 5 | C142: =+YEAR(A142) -> 2021 | D142: 85164936 | E142: RICARDO BAENA SAUCEDO | F142: Masculino | G142: EPS SURA | H142: La EPS | I142: TERCEROS | J142: Conductor | K142: 43689 | L142: EMTELCO MEDELLIN | M142: MEDELLIN | N142: Inc. Enfermedad general | O142: 2 | P142: 44338 | Q142: 44339 | R142: U071 | S142: =VLOOKUP($R142,DX!$A$1:$B$13005,2,FALSE) -> COVID-19 (virus identificado) | T142: PRORROGA | AA142: NO REQUIERE POST INCAPACIDAD
A143: 44339 | B143: =+MONTH(A143) -> 5 | C143: =+YEAR(A143) -> 2021 | D143: 1144200413 | E143: MARLON GIRALDO HERRERA | F143: Masculino | G143: EPS SURA | H143: La EPS | I143: ADMINISTRATIVOS | J143: Coordinador de operaciones | K143: 44312 | L143: ADMINISTRATIVOS EMPRESTUR | M143: RIONEGRO | N143: Inc. Enfermedad general | O143: 5 | P143: 44339 | Q143: 44343 | R143: U071 | S143: =VLOOKUP($R143,DX!$A$1:$B$13005,2,FALSE) -> COVID-19 (virus identificado) | T143: PRORROGA | AA143: NO REQUIERE POST INCAPACIDAD
A144: 44340 | B144: =+MONTH(A144) -> 5 | C144: =+YEAR(A144) -> 2021 | D144: 43591584 | E144: MARIA CRISTINA ECHAVARRIA PRESIGA | F144: Femenino | G144: EPS SURA | H144: La Empresa 2 días el resto de días la EPS | I144: ADMINISTRATIVOS | J144: Control de tráfico | K144: 44123 | L144: ADMINISTRATIVOS EMPRESTUR | M144: MEDELLIN | N144: Inc. Enfermedad general | O144: 3 | P144: 44340 | Q144: 44342 | R144: H813 | S144: =VLOOKUP($R144,DX!$A$1:$B$13005,2,FALSE) -> OTROS VERTIGOS PERIFERICOS | T144: INICIAL | AA144: NO REQUIERE POST INCAPACIDAD
A145: 44340 | B145: =+MONTH(A145) -> 5 | C145: =+YEAR(A145) -> 2021 | D145: 1013557161 | E145: MARTIN ALONSO RODRIGUEZ VASCO | F145: Masculino | G145: EPS SURA | H145: La Empresa | I145: TERCEROS | J145: Conductor | K145: 44279 | L145: UT MEJIA ACEVEDO | M145: MEDELLIN | N145: Inc. Enfermedad general | O145: 1 | P145: 44340 | Q145: 44340 | R145: A09X | S145: =VLOOKUP($R145,DX!$A$1:$B$13005,2,FALSE) -> DIARREA Y GASTROENTERITIS DE PRESUNTO ORIGEN INFECCIOSO | T145: INICIAL | AA145: NO REQUIERE POST INCAPACIDAD
A146: 44341 | B146: =+MONTH(A146) -> 5 | C146: =+YEAR(A146) -> 2021 | D146: 3350985 | E146: LUIS EDUARDO CUARTAS GAVIRIA | F146: Masculino | G146: COOMEVA EPS | H146: La Empresa 2 días el resto de días la EPS | I146: TERCEROS | J146: Conductor | K146: 42583 | L146: EMTELCO MEDELLIN | M146: MEDELLIN | N146: Inc. Enfermedad general | O146: 30 | P146: 44341 | Q146: 44341 | R146: 5 | S146: FALLECIDO | T146: INICIAL | AA146: REQUIERE POST INCAPACIDAD
A147: 44342 | B147: =+MONTH(A147) -> 5 | C147: =+YEAR(A147) -> 2021 | D147: 71294482 | E147: JULIAN AUGUSTO MOSQUERA ROJAS | F147: Masculino | G147: EPS SURA | H147: La Empresa 2 días el resto de días la EPS | I147: ADMINISTRATIVOS | J147: Auxiliar contable | K147: 43650 | L147: ADMINISTRATIVOS EMPRESTUR | M147: MEDELLIN | N147: Inc. Enfermedad general | O147: 3 | P147: 44342 | Q147: 44344 | R147: U072 | S147: =VLOOKUP($R147,DX!$A$1:$B$13005,2,FALSE) -> COVID-19 (virus no identificado) | T147: INICIAL | AA147: NO REQUIERE POST INCAPACIDAD
A148: 44342 | B148: =+MONTH(A148) -> 5 | C148: =+YEAR(A148) -> 2021 | D148: 71686854 | E148: WILMAR AGUDELO BEDOYA | F148: Masculino | G148: SALUD TOTAL | H148: La Empresa 2 días el resto de días la EPS | I148: FLOTA PROPIA | J148: Conductor | K148: 44109 | L148: FLOTA PROPIA | M148: MEDELLIN | N148: Inc. Enfermedad general | O148: 8 | P148: 44342 | Q148: 44349 | R148: U071 | S148: =VLOOKUP($R148,DX!$A$1:$B$13005,2,FALSE) -> COVID-19 (virus identificado) | T148: INICIAL | AA148: NO REQUIERE POST INCAPACIDAD
A149: 44342 | B149: =+MONTH(A149) -> 5 | C149: =+YEAR(A149) -> 2021 | D149: 1017153007 | E149: YOJANA LOPEZ VALENCIA | F149: Femenino | G149: EPS SURA | H149: La Empresa 2 días el resto de días la EPS | I149: ADMINISTRATIVOS | J149: Líder Soluciones empresariales | K149: 39762 | L149: ADMINISTRATIVOS EMPRESTUR | M149: MEDELLIN | N149: Inc. Enfermedad general | O149: 3 | P149: 44342 | Q149: 44344 | R149: U072 | S149: =VLOOKUP($R149,DX!$A$1:$B$13005,2,FALSE) -> COVID-19 (virus no identificado) | T149: INICIAL | AA149: NO REQUIERE POST INCAPACIDAD
A150: 44342 | B150: =+MONTH(A150) -> 5 | C150: =+YEAR(A150) -> 2021 | D150: 1036952662 | E150: ANA MARIA GALLO MONTOYA | F150: Femenino | G150: EPS SURA | H150: La Empresa 2 días el resto de días la EPS | I150: ADMINISTRATIVOS | J150: Auxiliar Juridica - Abogada | K150: 43435 | L150: ADMINISTRATIVOS EMPRESTUR | M150: MEDELLIN | N150: Inc. Enfermedad general | O150: 9 | P150: 44342 | Q150: 44350 | R150: U071 | S150: =VLOOKUP($R150,DX!$A$1:$B$13005,2,FALSE) -> COVID-19 (virus identificado) | T150: INICIAL | AA150: NO REQUIERE POST INCAPACIDAD
A151: 44343 | B151: =+MONTH(A151) -> 5 | C151: =+YEAR(A151) -> 2021 | D151: 18518338 | E151: JHON ALEXANDER LOPEZ HERRERA | F151: Masculino | G151: S.O.S | H151: La Empresa 2 días el resto de días la EPS | I151: TERCEROS | J151: Conductor | K151: 43647 | L151: TIGO | M151: PEREIRA | N151: Inc. Enfermedad general | O151: 3 | P151: 44343 | Q151: 44345 | R151: U072 | S151: =VLOOKUP($R151,DX!$A$1:$B$13005,2,FALSE) -> COVID-19 (virus no identificado) | T151: INICIAL | AA151: NO REQUIERE POST INCAPACIDAD
A152: 44344 | B152: =+MONTH(A152) -> 5 | C152: =+YEAR(A152) -> 2021 | D152: 4560597 | E152: ANGEL MIRO CANO GARCIA | F152: Masculino | G152: COMFENALCO | H152: La Empresa 2 días el resto de días la EPS | I152: TERCEROS | J152: Conductor | K152: 42583 | L152: EMTELCO CALI | M152: CALI | N152: Inc. Enfermedad general | O152: 15 | P152: 44344 | Q152: 44358 | R152: M511 | S152: =VLOOKUP($R152,DX!$A$1:$B$13005,2,FALSE) -> TRASTORNOS DE DISCO LUMBAR Y OTROS, CON RADICULOPATIA | T152: INICIAL | AA152: NO REQUIERE POST INCAPACIDAD
A153: 44344 | B153: =+MONTH(A153) -> 5 | C153: =+YEAR(A153) -> 2021 | D153: 71743554 | E153: CARLOS ALVEIRO CARMONA | F153: Masculino | G153: EPS SURA | H153: La Empresa | I153: FLOTA PROPIA | J153: Conductor | K153: 43745 | L153: FLOTA PROPIA | M153: MEDELLIN | N153: Inc. Enfermedad general | O153: 2 | P153: 44344 | Q153: 44345 | R153: U072 | S153: =VLOOKUP($R153,DX!$A$1:$B$13005,2,FALSE) -> COVID-19 (virus no identificado) | T153: INICIAL | AA153: NO REQUIERE POST INCAPACIDAD
A154: 44344 | B154: =+MONTH(A154) -> 5 | C154: =+YEAR(A154) -> 2021 | D154: 75075956 | E154: HUGO ALEXANDER MEJIA NUÑEZ | F154: Masculino | G154: COOMEVA EPS | H154: La Empresa 2 días el resto de días la EPS | I154: TERCEROS | J154: Conductor | K154: 44267 | L154: CHEC | M154: MANIZALES | N154: Inc. Enfermedad general | O154: 10 | P154: 44344 | Q154: 44354 | R154: U071 | S154: =VLOOKUP($R154,DX!$A$1:$B$13005,2,FALSE) -> COVID-19 (virus identificado) | T154: INICIAL | AA154: NO REQUIERE POST INCAPACIDAD
A155: 44345 | B155: =+MONTH(A155) -> 5 | C155: =+YEAR(A155) -> 2021 | D155: 71294482 | E155: JULIAN AUGUSTO MOSQUERA ROJAS | F155: Masculino | G155: EPS SURA | H155: La Empresa 2 días el resto de días la EPS | I155: ADMINISTRATIVOS | J155: Auxiliar contable | K155: 43650 | L155: ADMINISTRATIVOS EMPRESTUR | M155: MEDELLIN | N155: Inc. Enfermedad general | O155: 4 | P155: 44345 | Q155: 44348 | R155: U071 | S155: =VLOOKUP($R155,DX!$A$1:$B$13005,2,FALSE) -> COVID-19 (virus identificado) | T155: INICIAL | AA155: NO REQUIERE POST INCAPACIDAD
A156: 44345 | B156: =+MONTH(A156) -> 5 | C156: =+YEAR(A156) -> 2021 | D156: 98623281 | E156: CARLOS RUBEN PEDRAZA VILLA | F156: Masculino | G156: COOMEVA EPS | H156: La Empresa 2 días el resto de días la EPS | I156: FLOTA PROPIA | J156: Conductor | K156: 43617 | L156: FLOTA PROPIA | M156: MEDELLIN | N156: Inc. Enfermedad general | O156: 5 | P156: 44345 | Q156: 44349 | R156: U071 | S156: =VLOOKUP($R156,DX!$A$1:$B$13005,2,FALSE) -> COVID-19 (virus identificado) | T156: INICIAL | AA156: NO REQUIERE POST INCAPACIDAD
A157: 44346 | B157: =+MONTH(A157) -> 5 | C157: =+YEAR(A157) -> 2021 | D157: 71743554 | E157: CARLOS ALVEIRO CARMONA | F157: Masculino | G157: EPS SURA | H157: La EPS | I157: FLOTA PROPIA | J157: Conductor | K157: 43745 | L157: FLOTA PROPIA | M157: MEDELLIN | N157: Inc. Enfermedad general | O157: 4 | P157: 44346 | Q157: 44349 | R157: U071 | S157: =VLOOKUP($R157,DX!$A$1:$B$13005,2,FALSE) -> COVID-19 (virus identificado) | T157: PRORROGA | AA157: NO REQUIERE POST INCAPACIDAD
A158: 44347 | B158: =+MONTH(A158) -> 5 | C158: =+YEAR(A158) -> 2021 | D158: 1017184433 | E158: JUAN CAMILO MONTOYA OBANDO | F158: Masculino | G158: EPS SURA | H158: La Empresa 2 días el resto de días la EPS | I158: ADMINISTRATIVOS | J158: Auxiliar de Operaciones | K158: 42761 | L158: ADMINISTRATIVOS EMPRESTUR | M158: MEDELLIN | N158: Inc. Enfermedad general | O158: 3 | P158: 44347 | Q158: 44349 | R158: U072 | S158: =VLOOKUP($R158,DX!$A$1:$B$13005,2,FALSE) -> COVID-19 (virus no identificado) | T158: INICIAL | AA158: NO REQUIERE POST INCAPACIDAD
... A181: 44356 | B181: =+MONTH(A181) -> 6 | C181: =+YEAR(A181) -> 2021 | D181: 71743554 | E181: CARLOS ALVEIRO CARMONA | F181: Masculino | G181: EPS SURA | H181: La EPS | I181: FLOTA PROPIA | J181: Conductor | K181: 43745 | L181: FLOTA PROPIA | M181: MEDELLIN | N181: Inc. Enfermedad general | O181: 2 | P181: 44356 | Q181: 44357 | R181: U071 | S181: =VLOOKUP($R181,DX!$A$1:$B$13005,2,FALSE) -> COVID-19 (virus identificado) | T181: PRORROGA | AA181: NO REQUIERE POST INCAPACIDAD
A182: 44357 | B182: =+MONTH(A182) -> 6 | C182: =+YEAR(A182) -> 2021 | D182: 79136622 | E182: JUAN CARLOS CUERVO CALVO | F182: Masculino | G182: NUEVA EPS | H182: La EPS | I182: TERCEROS | J182: Conductor | K182: 44106 | L182: EMTELCO RIONEGRO | M182: RIONEGRO | N182: Inc. Enfermedad general | O182: 30 | P182: 44357 | Q182: 09/072021 | R182: U071 | S182: =VLOOKUP($R182,DX!$A$1:$B$13005,2,FALSE) -> COVID-19 (virus identificado) | T182: PRORROGA | AA182: REQUIERE POST INCAPACIDAD
A183: 44357 | B183: =+MONTH(A183) -> 6 | C183: =+YEAR(A183) -> 2021 | D183: 1128269859 | E183: JUAN CAMILO FRANCO OROZCO | F183: Masculino | G183: EPS SURA | H183: La Empresa | I183: TERCEROS | J183: Conductor | K183: 44326 | L183: EPM | M183: MEDELLIN | N183: Inc. Enfermedad general | O183: 2 | P183: 44357 | Q183: 44358 | R183: U072 | S183: =VLOOKUP($R183,DX!$A$1:$B$13005,2,FALSE) -> COVID-19 (virus no identificado) | T183: INICIAL | AA183: NO REQUIERE POST INCAPACIDAD
A184: 44358 | B184: =+MONTH(A184) -> 6 | C184: =+YEAR(A184) -> 2021 | D184: 4385768 | E184: OSCAR DE JESUS MEJIA OCAMPO | F184: Masculino | G184: ARL BOLIVAR | H184: La ARL | I184: TERCEROS | J184: Conductor | K184: 44267 | L184: CHEC | M184: MANIZALES | N184: Inc. Accidente laboral | O184: 2 | P184: 44358 | Q184: 44359 | R184: S602 | S184: =VLOOKUP($R184,DX!$A$1:$B$13005,2,FALSE) -> CONTUSION DE OTRAS PARTES DE LA MUÑECA Y DE LA MANO | T184: INICIAL | AA184: NO REQUIERE POST INCAPACIDAD
A185: 44358 | B185: =+MONTH(A185) -> 6 | C185: =+YEAR(A185) -> 2021 | D185: 43152669 | E185: PAULA ANDREA OLARTE TORRES | F185: Femenino | G185: ARL BOLIVAR | H185: La ARL | I185: TERCEROS | J185: Conductor | K185: 43703 | L185: EMTELCO MEDELLIN | M185: MEDELLIN | N185: Inc. Accidente laboral | O185: 30 | P185: 44358 | Q185: 44387 | R185: M239 | S185: =VLOOKUP($R185,DX!$A$1:$B$13005,2,FALSE) -> TRASTORNO INTERNO DE LA RODILLA, NO ESPECIFICADO | T185: PRORROGA | AA185: REQUIERE POST INCAPACIDAD
A186: 44358 | B186: =+MONTH(A186) -> 6 | C186: =+YEAR(A186) -> 2021 | D186: 71273275 | E186: JUAN DAVID DURANGO LOPEZ | F186: Masculino | G186: EPS SURA | H186: La Empresa 2 días el resto de días la EPS | I186: TERCEROS | J186: Conductor | K186: 44265 | L186: DINAMICA SURA | M186: MEDELLIN | N186: Inc. Enfermedad general | O186: 3 | P186: 44358 | Q186: 44360 | R186: U072 | S186: =VLOOKUP($R186,DX!$A$1:$B$13005,2,FALSE) -> COVID-19 (virus no identificado) | T186: INICIAL | AA186: NO REQUIERE POST INCAPACIDAD
A187: 44358 | B187: =+MONTH(A187) -> 6 | C187: =+YEAR(A187) -> 2021 | D187: 98546391 | E187: WILMAR SEPULVEDA MUÑOZ | F187: Masculino | G187: EPS SURA | H187: La EPS | I187: TERCEROS | J187: Conductor | K187: 43940 | L187: CORPORACIÓN AYUDA HUMANITARIA | M187: MEDELLIN | N187: Inc. Enfermedad general | O187: 4 | P187: 44358 | Q187: 44361 | R187: U071 | S187: =VLOOKUP($R187,DX!$A$1:$B$13005,2,FALSE) -> COVID-19 (virus identificado) | T187: PRORROGA | AA187: NO REQUIERE POST INCAPACIDAD
A188: 44358 | B188: =+MONTH(A188) -> 6 | C188: =+YEAR(A188) -> 2021 | D188: 1017148606 | E188: WILDER PARDO PAMPLONA | F188: Masculino | G188: EPS SURA | H188: La Empresa 2 días el resto de días la EPS | I188: FLOTA PROPIA | J188: Conductor | K188: 44090 | L188: FLOTA PROPIA | M188: MEDELLIN | N188: Inc. Enfermedad general | O188: 3 | P188: 44358 | Q188: 44360 | R188: U072 | S188: =VLOOKUP($R188,DX!$A$1:$B$13005,2,FALSE) -> COVID-19 (virus no identificado) | T188: INICIAL | AA188: NO REQUIERE POST INCAPACIDAD
...

Sheet DX
A1: Dx | B1: Diagnóstico
A2: A000 | B2: COLERA DEBIDO A VIBRIO CHOLERAE O1, BIOTIPO CHOLERAE
A3: A001 | B3: COLERA DEBIDO A VIBRIO CHOLERAE O1, BIOTIPO EL TOR
A4: A009 | B4: COLERA, NO ESPECIFICADO
A5: A010 | B5: FIEBRE TIFOIDEA
A6: A011 | B6: FIEBRE PARATIFOIDEA A
A7: A012 | B7: FIEBRE PARATIFOIDEA B
A8: A013 | B8: FIEBRE PARATIFOIDEA C
A9: A014 | B9: FIEBRE PARATIFOIDEA, NO ESPECIFICADA
A10: A020 | B10: ENTERITIS DEBIDA A SALMONELLA
A11: A021 | B11: SEPTICEMIA DEBIDA A SALMONELLA
A12: A022 | B12: INFECCIONES LOCALIZADAS DEBIDAS A SALMONELLA
... A12991: Y98 | B12991: AFECCION RELACIONADA CON EL ESTILO DE VIDA
A12992: 1 | B12992: Licencia Maternidad
A12993: 2 | B12993: Licencia Paternidad
A12994: 3 | B12994: Calamidad domestica
A12995: 4 | B12995: Otras ausencias por permisos
A12996: 5 | B12996: Fallecido
A12997: J09X | B12997: Influenza debida a ciertos virus de la influenza identificados. Influenza aviar (gripe aviar), influenza a (H1N1)
A12998: C865 | B12998: Linfoma Angiono imuno blasticode celulas T
A12999: A09 | B12999: Otras gastroenteritis y colitis de origen infeccioso y no especificado
A13000: A099 | B13000: Gastroenteritis y colitis de origen no especificado
A13001: A97 | B13001: Dengue
A13002: A979 | B13002: Dengue no especificado

Sheet DX ADICIONAL
A6: TITULO: Catálogo de patologías CIE-10
A7: FECHA DE ACTUALIZACION: 08-02-2021
A8: DIRECCIÓN/ OFICINA: Dirección de Demografía y Epidemiología
A9: Capitulo | B9: Nombre Capitulo | C9: Código de la CIE-10 tres caracteres | D9: Descripcion de codigos a tres caracteres | E9: Código de la CIE-10 cuatro caracteres | F9: Descripcion de códigos a cuatro caracteres
A10: 1 | B10: Ciertas enfermedades infecciosas y parasitarias (A00-B99) | C10: A00 | D10: Colera | E10: A000 | F10: Colera debido a Vibrio cholerae 01, biotipo cholerae
A11: 1 | B11: Ciertas enfermedades infecciosas y parasitarias (A00-B99) | C11: A00 | D11: Colera | E11: A001 | F11: Colera debido a Vibrio cholerae 01, biotipo el Tor
A12: 1 | B12: Ciertas enfermedades infecciosas y parasitarias (A00-B99) | C12: A00 | D12: Colera | E12: A009 | F12: Colera, no especificado
A13: 1 | B13: Ciertas enfermedades infecciosas y parasitarias (A00-B99) | C13: A01 | D13: Fiebres Tifoidea Y Paratifoidea | E13: A010 | F13: Fiebre tifoidea
A14: 1 | B14: Ciertas enfermedades infecciosas y parasitarias (A00-B99) | C14: A01 | D14: Fiebres Tifoidea Y Paratifoidea | E14: A011 | F14: Fiebre paratifoidea A
A15: 1 | B15: Ciertas enfermedades infecciosas y parasitarias (A00-B99) | C15: A01 | D15: Fiebres Tifoidea Y Paratifoidea | E15: A012 | F15: Fiebre paratifoidea B
A16: 1 | B16: Ciertas enfermedades infecciosas y parasitarias (A00-B99) | C16: A01 | D16: Fiebres Tifoidea Y Paratifoidea | E16: A013 | F16: Fiebre paratifoidea C
A17: 1 | B17: Ciertas enfermedades infecciosas y parasitarias (A00-B99) | C17: A01 | D17: Fiebres Tifoidea Y Paratifoidea | E17: A014 | F17: Fiebre paratifoidea, no especificada
A18: 1 | B18: Ciertas enfermedades infecciosas y parasitarias (A00-B99) | C18: A02 | D18: Otras Infecciones Debidas Salmonella | E18: A020 | F18: Enteritis debida a Salmonella
A19: 1 | B19: Ciertas enfermedades infecciosas y parasitarias (A00-B99) | C19: A02 | D19: Otras Infecciones Debidas Salmonella | E19: A021 | F19: Sepsis debida a Salmonella
A20: 1 | B20: Ciertas enfermedades infecciosas y parasitarias (A00-B99) | C20: A02 | D20: Otras Infecciones Debidas Salmonella | E20: A022 | F20: Infecciones localizadas debidas a Salmonella
A21: 1 | B21: Ciertas enfermedades infecciosas y parasitarias (A00-B99) | C21: A02 | D21: Otras Infecciones Debidas Salmonella | E21: A028 | F21: Otras infecciones especificadas como debidas a Salmonella
... A12577: 22 | B12577: Códigos para propósitos especiales (U00-U99) | C12577: U85 | D12577: Resistencia a drogas antineoplásicas | E12577: U85X | F12577: Resistencia a drogas antineoplásicas
