Workbook

Sheet report
A1: Hora de inicio | B1: Hora de finalización | C1: Correo electrónico | D1: Nombre | E1: Jefe directo responsable del reporte | F1: Fecha de la novedad o accidente | G1: A que horas le reportan que ocurrieron los hechos | H1: Placa del vehículo (si es administrativo colocar NO APLICA) | I1: Contrato o cliente | J1: Los hechos ocurrieron durante la prestación del servicio | K1: Código Servicio | L1: Nombre de Empleado que presenta el accidente o la novedad | M1: Cedula del Empleado que presenta el accidente o la novedad | N1: Número Celular del Empleado que presenta el accidente o la novedad | O1: Identifique que tipo de novedad o accidente le indican en el reporte inicial, y describa si fue: | P1: Que Afectación identifica usted inicialmente en la versión dada en el reporte | Q1: Causa que genera el evento | R1: Lesionados | S1: Nombre y teléfono de Funcionario (Empleado del Cliente) lesionado | T1: Nombre y teléfono de Tercero (otro actor vial) lesionado | U1: Por favor, DESCRIBA la versión de los hechos que le da el empleado en el reporte inicial | V1: ACCIONES TOMADAS POR EL JEFE DIRECTO DE EMPRESTUR S.A.S.: Se reemplaza el servicio | W1: ACCIONES TOMADAS POR EL JEFE DIRECTO DE EMPRESTUR S.A.S.: Se informa al cliente verbalmente | X1: ACCIONES TOMADAS POR EL JEFE DIRECTO DE EMPRESTUR S.A.S.: Se dan indicaciones al conductor (llamar tránsito, ambulancia) | Y1: ACCIONES TOMADAS POR EL JEFE DIRECTO DE EMPRESTUR S.A.S.: Realiza acompañamiento en sitio | Z1: ACCIONES TOMADAS POR EL JEFE DIRECTO DE EMPRESTUR S.A.S.: Se reporta inmediatamente a SSTA de Emprestur | AA1: Acciones adicionales realizadas por el Gestor logístico de Emprestur o Jefe Directo | AB1: Registro Fotográfico Características del registro fotográfico: Frente, laterales, panorámica de los vehículos implicados; afectación a tercero foto escenario completo; Posición bosquejo o zona lugar d | AC1: SOPORTES PARA ANEXAR (Registro fotográfico, preoperacional de la ultima semana, bimestral vigente, soportes de mantenimiento, Reporte de GPS, planilla de servicio o asignación del servicio, Ficha del
A2: 45743.363 | B2: 45743.373 | C2: anonymous | E2: JUAN DAVID BLANDON ARENAS | F2: 45736 | G2: 08:51 | H2: NNM056 | I2: FUNDACION EPM | J2: Si | K2: SE008805 | L2: DIEGO ALEXIS MONGUA GARCIA | M2: 98702123 | N2: 311 7137391 | O2: Incidente de trabajo (Se pudo presentar una lesión en el trabajador) | P2: Daño Material a Tercero | Q2: Acto inseguro de Tercero | R2: N/A | S2: N/A | T2: N/A | U2: JUAN DAVID BLANDON Logistico de Transporte Emprestur Asunto: Informe de Novedad Vehiculo NNM 056 Respetuosamente me dirijo a usted con e fin de poner en conocimiento los hechos ocurridos el dia de hoy 20 de marzo del presente año, en las instalaciones de la UVA Pedregal de EPM. Siendo aproximadamente las 05:45 am me dispuse a recoger a la señorita Laura Llanos funcionaria de la Fundacion EPM en el sector de la terminal de transporte del Norte de Medellin, seguid a esto aproximadamente las 06: 00 horas me dirigi a la uva pederegal de acuerdo a lo coordinado con la funcionaria, ingresamos a las instalaciones luego de cumplir con los requisitos de seguridad. Siendo las 08:45 am la funcionaria luego de realizar sus labores en las instalaciones, nos dispusimos a continuar la ruta establecida, al momento de llegar a la porteria pase la tarjeta chip para abrir la talanquera de salida, en este punto se encontrba el vigilante de turno al cual le entregue el carnet de chip luego de pasar la talanquera, en este punto la funcionaria descendio del vehiculo para salir por el sector peatonal y marcar la salida, al pasar por el torniquete nuevamente ingreso a vehiculo e iniciamos la marcha para continuar con la ruta, cuando el heiculo a la altura de los espejos retrovisores cruza el porton siento un golpe al lado derecho del vehiculo, observo y me percato que la puerta del lado derecho del porton habia golpeado el vehiculo ya que habia iniciado a cerrarse. Al ver lo que estaba sucendiendo busco visualmente al vigilante la para que detuviera la puerta que intentaba cerrase y al ver que esto no paraba y seguia golpenando el vehiculo lo lleve hacia adelante para evitar algun daño. Luego de esto deciendo del vehiculo para verificar el vehiculo y encuentro que el retrovisor en la punta estaba tallado y otro en el centro, la presion tambien habia sacado el borde de la tapa del retrovisor del marco del espejo, ya en la puerta derecha tenia un tallon a lo lago de la puerta que saco un trapo del carro para mirara si solo eran residuos de la puerta del porton. Pero cuando veo que no desaparece procedo a pasar la mano sobre el sitio afectado y al tacto siento que tiene un sumido a lo largo del tallon siendo un poco mas profundo al inicio tomandolo de arriba hacia abajo. Al ver lo anterior mecinado me dirijo hacia la caseta donde se encuentra el vigilante y le informo que al cerrar la puerta golpeo el carro ya que no dejo que el carro saliera en su totalidad, quien respondio lo siguiente cito “que el penso que ya habia salido y que ademas la puerta tenia sensores y que si eso paso fue que habian fallado los sensores”, ha esto le respondi que el deberia estar pendiente que el carro salga, el señor responde “yo debo mantener la puerta cerrada” e ingreso a la caseta. Aunque es de logica y politicas de seguridad de la empresa, tambien es de logica que debe estar pendiente y cumplir las demas medidas de seguridad, como verificar que los carros crusen la linea amarilla que delimita el alcance de la puerta asi como se debe verificar que los carros que van a ingresar no sobre pasen la linea ya que los puede golpear tal cual como lo advierte el letrero que esta instalado en el porton. Al escuchar estas respuestas y ver la actitud poco consiliadora y falta de interes por lo sucedido decido informarle a don Juan logistico Emprestur y al señor Andres Ramirez dueño del vehiculo con el fin de dar a conocer lo sucedido en tiempo real. Quiero resaltar que todo lo anterior puede ser verificado con la funcionaria Laura Llanos y dentro de lo posible en los vedeos de las camaras de seguridad que vigilan el sector asi mismo en las ayudas fotograficas y audiovisuales que anexo al presente documento como tambien la cotizacion del costo de la correccion de las novedades presentadas al vehiculo la cual es algo modesta teniendo en cuenta que no se realizo atraves del consecionario ya que alli los costo puede ser mas elevado. | V2: NO | W2: SI | X2: NO | Y2: NO | Z2: SI | AA2: Se reporta vía telefónica al cliente y luego se envía el correo, explicando lo sucedido y se adjuntan registros fotográficos y la cotización de la reparación de los daños. | AB2: SI | AC2: https://emprestur-my.sharepoint.com/personal/alejandra_betancur_emprestur_com/Documents/Aplicaciones/Microsoft%20Forms/INFORMACI%C3%93N%20NOVEDAD%20_%20ACCIDENTES%2026042022%20(2)/SOPORTES%20PARA%20ANEXAR/WhatsApp%20Image%202025-03-20%20at%209.14.39%20AM_anonymous.jpeg; https://emprestur-my.sharepoint.com/personal/alejandra_betancur_emprestur_com/Documents/Aplicaciones/Microsoft%20Forms/INFORMACI%C3%93N%20NOVEDAD%20_%20ACCIDENTES%2026042022%20(2)/SOPORTES%20PARA%20ANEXAR/WhatsApp%20Video%202025-03-20%20at%2010.01.49%20PM_anonymous.mp4; https://emprestur-my.sharepoint.com/personal/alejandra_betancur_emprestur_com/Documents/Aplicaciones/Microsoft%20Forms/INFORMACI%C3%93N%20NOVEDAD%20_%20ACCIDENTES%2026042022%20(2)/SOPORTES%20PARA%20ANEXAR/WhatsApp%20Image%202025-03-20%20at%2010.01.49%20PM_anonymous.jpeg; https://emprestur-my.sharepoint.com/personal/alejandra_betancur_emprestur_com/Documents/Aplicaciones/Microsoft%20Forms/INFORMACI%C3%93N%20NOVEDAD%20_%20ACCIDENTES%2026042022%20(2)/SOPORTES%20PARA%20ANEXAR/WhatsApp%20Video%202025-03-20%20at%2010.01.48%20PM_anonymous.mp4; https://emprestur-my.sharepoint.com/personal/alejandra_betancur_emprestur_com/Documents/Aplicaciones/Microsoft%20Forms/INFORMACI%C3%93N%20NOVEDAD%20_%20ACCIDENTES%2026042022%20(2)/SOPORTES%20PARA%20ANEXAR/WhatsApp%20Image%202025-03-20%20at%209.55.20%20PM_anonymous.jpeg; https://emprestur-my.sharepoint.com/personal/alejandra_betancur_emprestur_com/Documents/Aplicaciones/Microsoft%20Forms/INFORMACI%C3%93N%20NOVEDAD%20_%20ACCIDENTES%2026042022%20(2)/SOPORTES%20PARA%20ANEXAR/WhatsApp%20Image%202025-03-20%20at%209.55.19%20PM_anonymous.jpeg; https://emprestur-my.sharepoint.com/personal/alejandra_betancur_emprestur_com/Documents/Aplicaciones/Microsoft%20Forms/INFORMACI%C3%93N%20NOVEDAD%20_%20ACCIDENTES%2026042022%20(2)/SOPORTES%20PARA%20ANEXAR/Cotizaci%C3%B3n%20NNM%20056_anonymous.pdf
A3: 45743.417 | B3: 45743.421 | C3: anonymous | E3: Diego Mendez | F3: 45737 | G3: 12 del dia | H3: EQX451 | I3: EPM | J3: Si | K3: 0 | L3: LUIS EDUARDO AGUDELO SALAS | M3: 98545061 | N3: 3046399455 | O3: Accidente de tránsito y transporte dentro del desarrollo de la labor (Si ocurre en la vía con otros vehículos o con otros actores viales implicados) | P3: Afectación a Personas (lesionados) | Q3: Acto inseguro propio (conductor) | R3: Tercero (Comunidad) | S3: 0 | T3: CAMILO MESA 3207078251 | U3: El día 21/03/2025 siendo las 12:00m, salía del del Campamento Tacuí con 3 funcionarios de EPM, durante el recorrido ninguna anomalía, vinimos a parar en Betania almorzar y a descansar un poco, al salir de Betania directo a Medellín justo después del Peaje de Don Matías en la recta después de estadero mm me encontré un mula a baja velocidad que iba aproximadamente 40 km/h y en uno de esos espacios identifiqué de que podía hacer el adelantamiento de ella, procedí hacer el adelantamiento ya que vi que no venía ningún vehículo, pero cuando estaba terminando de adelantar la mula, ella saca el cabezote para esquivar un vehículo que se encontraba estacionado entre la berma y la vía. Al ver la maniobra de la tractomula, me dispongo a parar en el carril contrario y en ese momento veo un ciclista que venía en el carril contrario mirando hacía atrás y al ver que la camioneta estaba parada logra esquivar y colisiona con el lado izquierdo del vehículo. Después de eso, procedo a estacionar el vehículo en el carril derecho para identificar lo que había sucedido y auxiliar el ciclista. Cuando nos bajamos del vehículo, el ciclista ya venía hacia el vehículo, se logra identificar unos leves raspones en los codos, en la cabeza y en la palma de la mano, se le presto la atención correspondiente y se realizo el traslado hacía el Hospital de Don Matías. Cuando llegamos al hospital le realizaron el proceso de ingreso y revisión para descartar lesiones de gravedad, yo procedo a entregar lo documento del vehículo para que fuera atendido. Mientras realizaban el proceso de atención del ciclista llegaron los agentes de tránsito de Don Matías, pero indican que el proceso no era con ellos y proceden a llamar al policía de carretera, este llega y damos versión de lo sucedido, pero en común acuerdo con el ciclista logramos conciliar y llegar a un acuerdo, ya que el policía de carretera indica que no hay necesidad de hacer algún procedimiento legal, ya que el ciclista se encontraba bien. El ciclista y su mamá todo el tiempo estuvo en buena actitud, agradeciendo todo el acompañamiento en el momento del evento. Incluso el ciclista en todo momento se declaraba culpable ya que venía mirando hacia atrás." | V3: NO | W3: NO | X3: SI | Y3: NO | Z3: SI | AA3: Se le indica que debe de hacer acompañamiento a la tercero lesionado y estar atento a instrucciones del area SST | AB3: NO
A4: 45743.471 | B4: 45743.48 | C4: anonymous | E4: JOHN FREDY CALLE RESTREPO | F4: 45742 | G4: 17:30 HORAS | H4: GDZ164 | I4: ISAGEN | J4: Si | K4: NO APLICA | L4: ACOSTA RODAS GUILLERMO LEON | M4: 98586405 | N4: 3146393071 | O4: Accidente de tránsito y transporte dentro del desarrollo de la labor (Si ocurre en la vía con otros vehículos o con otros actores viales implicados) | P4: Daño Material propio | Q4: Condición insegura | R4: N/A | S4: NO APLICA | T4: NO APLICA | U4: Siendo las 17:20 horas aproximadamente mientras el conductor en mención realizaba maniobra de reversa (sin usuarios) en Casa de Maquinas para colocar el bus en posición de salida golpeo con la parte superior trasera derecha del bus el ducto de ventilación que esta en la "Y" ocasionando que el vidrio de la ventanilla se agrietara. | V4: NO | W4: SI | X4: NO | Y4: SI | Z4: SI | AA4: Se informa al SST de ISAGEN Oscar Cano y también al Coordinador Administrativo Alejandro Berrio. | AB4: SI | AC4: https://emprestur-my.sharepoint.com/personal/alejandra_betancur_emprestur_com/Documents/Aplicaciones/Microsoft%20Forms/INFORMACI%C3%93N%20NOVEDAD%20_%20ACCIDENTES%2026042022%20(2)/SOPORTES%20PARA%20ANEXAR/WhatsApp%20Image%202025-03-27%20at%2011.19.21%20AM%20(1)_anonymous.jpeg; https://emprestur-my.sharepoint.com/personal/alejandra_betancur_emprestur_com/Documents/Aplicaciones/Microsoft%20Forms/INFORMACI%C3%93N%20NOVEDAD%20_%20ACCIDENTES%2026042022%20(2)/SOPORTES%20PARA%20ANEXAR/WhatsApp%20Image%202025-03-27%20at%2011.19.21%20AM_anonymous.jpeg; https://emprestur-my.sharepoint.com/personal/alejandra_betancur_emprestur_com/Documents/Aplicaciones/Microsoft%20Forms/INFORMACI%C3%93N%20NOVEDAD%20_%20ACCIDENTES%2026042022%20(2)/SOPORTES%20PARA%20ANEXAR/WhatsApp%20Image%202025-03-27%20at%2011.19.18%20AM%20(1)_anonymous.jpeg; https://emprestur-my.sharepoint.com/personal/alejandra_betancur_emprestur_com/Documents/Aplicaciones/Microsoft%20Forms/INFORMACI%C3%93N%20NOVEDAD%20_%20ACCIDENTES%2026042022%20(2)/SOPORTES%20PARA%20ANEXAR/WhatsApp%20Image%202025-03-27%20at%2011.19.18%20AM_anonymous.jpeg; https://emprestur-my.sharepoint.com/personal/alejandra_betancur_emprestur_com/Documents/Aplicaciones/Microsoft%20Forms/INFORMACI%C3%93N%20NOVEDAD%20_%20ACCIDENTES%2026042022%20(2)/SOPORTES%20PARA%20ANEXAR/WhatsApp%20Image%202025-03-27%20at%2011.18.44%20AM_anonymous.jpeg; https://emprestur-my.sharepoint.com/personal/alejandra_betancur_emprestur_com/Documents/Aplicaciones/Microsoft%20Forms/INFORMACI%C3%93N%20NOVEDAD%20_%20ACCIDENTES%2026042022%20(2)/SOPORTES%20PARA%20ANEXAR/WhatsApp%20Image%202025-03-27%20at%2011.18.43%20AM_anonymous.jpeg
A5: 45749.338 | B5: 45749.372 | C5: anónimo | E5: EDWIN AGUIRRE | F5: 45748 | G5: 14:30 | H5: ESR437 | I5: CHEMICAL | J5: Si | K5: 758 | L5: ZAPATA GUZMAN HECTOR ELI | M5: 70128434 | N5: 314 7701452 | O5: Incidente de trabajo (Se pudo presentar una lesión en el trabajador) | P5: Afectación al Cliente | Q5: Acto inseguro propio (conductor) | R5: Funcionario de cliente | S5: Karina Silgado Silgado - 310 4043694 | T5: n/a | U5: Conductor al momento de dar reversa atrapa funcionaria contra cajas de icopor que se encuentran contra la pared, aprisionando las dos rodillas provocando un leve dolor en la rodilla derecha, | V5: SI | W5: SI | X5: NO | Y5: NO | Z5: SI | AA5: En compañía de Daniela Vergara, se llama al conductor para a hondar un poco mas en lo sucedido. Me comunico con la funcionaria me expresa que no es grave que se tomara un par un par de antibióticos, se le ofrece vehículo para llevarle a un centro medico, me dice que no es necesario que se tomara un par de pastillas | AB5: SI | AC5: https://emprestur-my.sharepoint.com/personal/alejandra_betancur_emprestur_com/Documents/Aplicaciones/Microsoft%20Forms/INFORMACI%C3%93N%20NOVEDAD%20_%20ACCIDENTES%2026042022%20(2)/SOPORTES%20PARA%20ANEXAR/WhatsApp%20Image%202025-04-01%20at%203.17.01%20PM_anonymous.jpeg
A6: 45754.559 | B6: 45754.565 | C6: anónimo | E6: DAYHANA SOSSA GIRALDO | F6: 45748 | G6: 3:00 PM | H6: N/A | I6: JARDIN BOTANICO | J6: Si | K6: 01046 | L6: DENNIS VILLA | M6: 98571216 | N6: 305 2656118 | O6: Incidente de trabajo (Se pudo presentar una lesión en el trabajador) | P6: Daño Material a Tercero | Q6: Acto inseguro propio (conductor) | R6: N/A | S6: N/A | T6: N/A | U6: El ing a cargo del proyecto le solicito trasladar un maquina podadora, y el conductor la sube a la camioneta sin amarrarla ni asegurarla. | V6: SI | W6: SI | X6: SI | Y6: SI | Z6: SI | AA6: N/A | AB6: SI | AC6: https://emprestur-my.sharepoint.com/personal/alejandra_betancur_emprestur_com/Documents/Aplicaciones/Microsoft%20Forms/INFORMACI%C3%93N%20NOVEDAD%20_%20ACCIDENTES%2026042022%20(2)/SOPORTES%20PARA%20ANEXAR/WhatsApp%20Video%202025-04-01%20at%203.43.18%20PM_anonymous.mp4
A7: 45761.39 | B7: 45761.406 | C7: anónimo | E7: DIANA ALVAREZ | F7: 45758 | G7: 14:50 | H7: GDY059 | I7: ISAGEN | J7: Si | K7: N/A | L7: MANUEL ANTONIO CARMONA MONTAÑO | M7: 70568599 | N7: 3212583021 | O7: Accidente de tránsito y transporte dentro del desarrollo de la labor (Si ocurre en la vía con otros vehículos o con otros actores viales implicados) | P7: Daño Material propio | Q7: Condición insegura | R7: N/A | S7: N/A | T7: N/A | U7: El conductor iba en masivo de JAGUAS, pasando por la vía de SAN RAFAEL hacia MEDELLIN, el conductor da paso a un camión que llevaba una maquina, luego el conductor saca un poco el carro para continuar con la marcha, pero con la parte trasera del bus, toca una moto en el manubrio, el conductor se baja del carro para organizar con el dueño de la moto, (la cual se encontraba mal parqueada, ya que es un espacio de vía principal), en ese momento pasaron 3 volquetas, dos de ellas pasaron normal, pero la tercera, pasó y tenia un tornillo en el volco y con ese daño el espejo del bus. se hizo presencia el transito, evidenciaron que ninguno de los dos implicados externos tenían documentos, hicieron mover los vehículos para no obstaculizar el paso y se retiran sin dar solución. | V7: NO | W7: NO | X7: NO | Y7: NO | Z7: NO | AA7: Solicitar fotos e informe de lo sucedido | AB7: SI | AC7: https://emprestur-my.sharepoint.com/personal/alejandra_betancur_emprestur_com/Documents/Aplicaciones/Microsoft%20Forms/INFORMACI%C3%93N%20NOVEDAD%20_%20ACCIDENTES%2026042022%20(2)/SOPORTES%20PARA%20ANEXAR/WhatsApp%20Image%202025-04-11%20at%207.53.06%20PM_anonymous.jpeg; https://emprestur-my.sharepoint.com/personal/alejandra_betancur_emprestur_com/Documents/Aplicaciones/Microsoft%20Forms/INFORMACI%C3%93N%20NOVEDAD%20_%20ACCIDENTES%2026042022%20(2)/SOPORTES%20PARA%20ANEXAR/WhatsApp%20Image%202025-04-11%20at%207.53.05%20PM%20(3)_anonymous.jpeg; https://emprestur-my.sharepoint.com/personal/alejandra_betancur_emprestur_com/Documents/Aplicaciones/Microsoft%20Forms/INFORMACI%C3%93N%20NOVEDAD%20_%20ACCIDENTES%2026042022%20(2)/SOPORTES%20PARA%20ANEXAR/WhatsApp%20Image%202025-04-11%20at%207.53.05%20PM%20(2)_anonymous.jpeg; https://emprestur-my.sharepoint.com/personal/alejandra_betancur_emprestur_com/Documents/Aplicaciones/Microsoft%20Forms/INFORMACI%C3%93N%20NOVEDAD%20_%20ACCIDENTES%2026042022%20(2)/SOPORTES%20PARA%20ANEXAR/WhatsApp%20Image%202025-04-11%20at%207.53.05%20PM%20(1)_anonymous.jpeg; https://emprestur-my.sharepoint.com/personal/alejandra_betancur_emprestur_com/Documents/Aplicaciones/Microsoft%20Forms/INFORMACI%C3%93N%20NOVEDAD%20_%20ACCIDENTES%2026042022%20(2)/SOPORTES%20PARA%20ANEXAR/WhatsApp%20Image%202025-04-11%20at%207.53.05%20PM_anonymous.jpeg; https://emprestur-my.sharepoint.com/personal/alejandra_betancur_emprestur_com/Documents/Aplicaciones/Microsoft%20Forms/INFORMACI%C3%93N%20NOVEDAD%20_%20ACCIDENTES%2026042022%20(2)/SOPORTES%20PARA%20ANEXAR/WhatsApp%20Image%202025-04-11%20at%207.53.04%20PM_anonymous.jpeg
A8: 45770.631 | B8: 45770.635 | C8: anónimo | E8: JUAN DAVID BLANDÓN | F8: 45770 | G8: 14:20 | H8: NLW531 | I8: TELEMEDELLIN | J8: Si | K8: 995 | L8: YAMID SERNA | M8: 8005509 | N8: 310 4688172 | O8: Accidente de tránsito y transporte dentro del desarrollo de la labor (Si ocurre en la vía con otros vehículos o con otros actores viales implicados) | P8: Daño Material propio | Q8: Acto inseguro de Tercero | R8: N/A | S8: N/A | T8: N/A | U8: Siendo las 13:10 aproximadamente del día 23-04-2025 se presenta novedad con vehículo tipo jaula, éste se presentó sobre la Carrera 43F con 18, al frente del Canal de Televisión Telemedellín. Me dirigía en sentido Norte-Sur y antes de llegar al retorno había fila para regresar, así que procedo a detenerme, estando ya quieto esperando el avance de los carros de adelante siento el impacto por detrás del otro vehículo. Desciendo del carro, se revisa el estado de los daños, el Presentador y Camarografo del canal deciden descender, cruzar la calle y llegar al canal a pie. Yo continuo con el registro fotográfico, el otro conductor acepta la responsabilidad y asume los gastos del ése daño. Hablando con Alejandro Gomez autoriza llevar el vehículo afectado al taller, donde se cotiza el daño y la persona responsable paga el total, quedando pendiente el arreglo para el día 24-04-2025 a las 8:00 am. | V8: NO | W8: NO | X8: NO | Y8: NO | Z8: SI | AA8: N/A | AB8: SI | AC8: https://emprestur-my.sharepoint.com/personal/alejandra_betancur_emprestur_com/Documents/Aplicaciones/Microsoft%20Forms/INFORMACI%C3%93N%20NOVEDAD%20_%20ACCIDENTES%2026042022%20(2)/SOPORTES%20PARA%20ANEXAR/WhatsApp%20Image%202025-04-23%20at%202.49.52%20PM%20(1)_anonymous.jpeg; https://emprestur-my.sharepoint.com/personal/alejandra_betancur_emprestur_com/Documents/Aplicaciones/Microsoft%20Forms/INFORMACI%C3%93N%20NOVEDAD%20_%20ACCIDENTES%2026042022%20(2)/SOPORTES%20PARA%20ANEXAR/WhatsApp%20Image%202025-04-23%20at%202.49.52%20PM_anonymous.jpeg
A9: 45776.582 | B9: 45776.588 | C9: anónimo | E9: JONATHAN GIRALDO ORREGO | F9: 45771 | G9: 06:12 AM | H9: JYO404 | I9: ISAGEN | J9: Si | K9: RUTA METRO | L9: CRISTIAN ANDRES TABORDA TABORDA | M9: 1128438613 | N9: 3124601727 | O9: Accidente de tránsito y transporte dentro del desarrollo de la labor (Si ocurre en la vía con otros vehículos o con otros actores viales implicados) | P9: Afectación a Personas (lesionados) | Q9: Acto inseguro de Tercero | R9: Conductor y/o Empleado | S9: CRISTIAN ANDRES TABORDA TABORDA 3124601727 | T9: N/A | U9: El conductor CRISTIAN ANDRES TABORDA TABORDA se encontraba realizando la ruta Metro el día 24 de abril, y sale de la estación del metro siendo aproximadamente las 6:10 am. saliendo con el personal de ISAGEN, cuando mas o menos a las 6:12 am antes de llegar al semáforo de la glorieta de Monterrey (Carrera48c con la calle 10 cerca del rompoy de Monterrey) se me atraviesa un taxista y se baja del taxi a agredirme diciendo que yo lo había cerrado cosa que no fue así ya que desde que salí del punto de recogida salí por el carril izquierdo ya que el costado derecho se encontraban los taxis estacionados. el taxista abrió la puerta de mi carro y me agredió físicamente. | V9: NO | W9: SI | X9: NO | Z9: NO | AA9: se toma versión de los hechos, se revisa la novedad en cámaras de video y se le comparten al cliente. | AB9: SI
A10: 45782.242 | B10: 45782.245 | C10: anónimo | E10: JONATHAN GIRALDO ORREGO | F10: 45780 | G10: 07:37 AM | H10: GTW934 | I10: AYUDA HUMANITARIA | J10: No | K10: EMERGENCIA 123 | L10: JUAN MANUEL GALINDO GOMEZ | M10: 1000644388 | N10: 3019029552 - 3128810679 | O10: Accidente de tránsito (se produce en las vías y fuera de horario laboral) | P10: Daño Material propio | Q10: Acto inseguro propio (conductor) | R10: N/A | S10: N/A | T10: N/A | U10: "El conductor JUAN MANUEL GALINDO GOMEZ con cedula de ciudadanía numero 1000644388 y número de teléfono 3019029552 - 3128810679, quien se encuentra asignado al vehículo de flota propia de placas GTW934 para el contrato de AYUDA HUMANITARIA - Componente Emergencias 123, el día sábado 3 de mayo del 2025 siendo las 7:37 de la mañana aproximadamente el conductor se dirigía hacia la corporación para iniciar turno; el conductor iba en el carro bajando por la avenida Ferrocarril a la altura del puente peatonal de plaza mayor (para entrar a la alpujarra), transitaba por carril del medio y enciende direccional para pasar al carril de la derecha y voltear para coger la calle 42 (plaza de la libertad), cuando se pasa al carril derecho una moto que venia muy rápido golpea contra el carro en un costado del vehículo al lado derecho, el conductor Juan Manuel Galindo al decirle al conductor de la moto que iba a llamar al transito, este le contesta que la culpa era de nuestro conductor por meterse así en el carril, nuestro conductor le dice que llamaran ambulancia que si estaba aporreado y este le contesta que no que porque le quitaban la porque no tenía papeles y salió y se fue del lugar. El conductor de los nervios que tenia por el accidente, no alcanza a tomar la placa de la moto ni los datos de la persona, realiza el reporte de la novedad al coordinador Edwin y al día siguiente nos realiza el reporte a Flota propia (Director). Al momento de los hechos no se tenia presencia de funcionarios en el vehículo. Para hacer el análisis del accidente le solicito al conductor que me haga el reporte de lo ocurrido y me envié las fotos del evento, donde se evidencia que el carro sufre daños en nave trasera derecha y rin de la llanta trasera lado derecho. Teniendo en cuenta que en el reporte, el conductor indica que va por el carril del medio y se pasa al carril derecho para voltear en la calle 42, asumo una presunta invasión del carril por lo que reviso el GPS y puedo evidenciar que a la altura del carril donde el conductor hace el giro hacia el lado derecho ya había una línea blanca continua en la via lo que me ratificaba lo que estaba pensando, por lo cual le escalo la pregunta al conductor Juan Manuel donde le consulto que si el era consciente que debía haber buscado pasar al carril derecho mucho antes lo que este me contesta ""Si jefe mirando el retrovisor de pronto no vi que cambiaba la línea descontinúa ahi, Si hay tuve el error"". en el momento de los hechos no se realiza reporte a la aseguradora ya que como lo indique solo hasta el día siguiente el conductor reporta a Flota." | V10: NO | W10: NO | X10: NO | Y10: NO | Z10: NO | AA10: Se realiza reporte del accidente de transito con la informacion que el conductor nos suministra al area de SST, Juridica, Talento humano y agencia de seguros para realiza el reporte a la aseguradora." | AB10: SI | AC10: https://emprestur-my.sharepoint.com/personal/alejandra_betancur_emprestur_com/Documents/Aplicaciones/Microsoft%20Forms/INFORMACI%C3%93N%20NOVEDAD%20_%20ACCIDENTES%2026042022%20(2)/SOPORTES%20PARA%20ANEXAR/ACIDENTE%20DE%20TRANSITO%20VEHICULO%20GTW934%20-%20JUAN%20M_anonymous.pdf
A11: 45793.71 | B11: 45793.719 | C11: anónimo | E11: Alejandra Velasquez | F11: 45793 | G11: 4:30 pm | H11: WCQ263 | I11: Mejia y Acevedo | J11: Si | K11: 0 | L11: Ronald Graterol Quintero | M11: 1434177 | N11: 3011414949 | O11: Accidente de trabajo (Empleado de Emprestur Lesionado) | P11: Afectación a Personas (lesionados) | Q11: Condición insegura | R11: Conductor y/o Empleado | S11: Ronald Graterol Quintero 3011414949 | T11: No | U11: El conductor de emprestur Ronal graterol reporta sufrió una caida el dia de hoy mientras cargaba un balde con agua, refiere mucho dolor en hombro y pierna. | V11: NO | W11: SI | X11: SI | Y11: NO | Z11: SI | AA11: Se informa a SST emprestur, se comunica y da indicaciones al conductor implicado y se indica información solicitada con el cliente Mejia y Acevedo | AB11: NO
A12: 45803.292 | B12: 45803.308 | C12: anónimo | E12: Ramon Andres Quintero Cardona | F12: 45800 | G12: 23:36 | H12: NLW559 | I12: Corporación Ayuda Humanitaria | J12: Si | K12: OS0305496 | L12: JUAN JOSE ROA GARCIA | M12: 1062088177 | N12: 3245030239 | O12: Accidente de tránsito y transporte dentro del desarrollo de la labor (Si ocurre en la vía con otros vehículos o con otros actores viales implicados) | P12: Daño Material a Tercero | Q12: Acto inseguro de Tercero | R12: N/A | S12: N/A | T12: N/A | U12: Venía por la avenida regional lado derecho y en el instante se me atraviesa un motociclista sin casco y sin ningúna señalización como la direccional afortunadamente no hubo perdidas humanas ni lecciones personales solo hubieron perdidas materiales, El siniestro ocurrió debido al mal manejo del motociclista y condiciones climáticas, Realicé varias llamadas a la aseguradora en diferentes momentos, pero lamentablemente no obtuve respuesta en ninguna de ellas, y el motociclista no contaba con documentación y fue inmovilizado | V12: NO | W12: SI | X12: NO | Y12: NO | Z12: NO | AA12: Debido a que el incidente de transito fue a altas horas de la noche, se toma la versión de los acontecimientos del conductor al otro día y se reporta al área encargada | AB12: SI | AC12: https://emprestur-my.sharepoint.com/personal/alejandra_betancur_emprestur_com/Documents/Aplicaciones/Microsoft%20Forms/INFORMACI%C3%93N%20NOVEDAD%20_%20ACCIDENTES%2026042022%20(2)/SOPORTES%20PARA%20ANEXAR/Evidencia%20Fotografica_anonymous.pdf
A13: 45805.267 | B13: 45805.273 | C13: anónimo | E13: Julián david Valencia Ballesteros | F13: 45804 | G13: 12:36 | H13: ETL617 | I13: CHEC | J13: No | K13: TR2509173 | L13: DEYDI LEANDRO HEANO | M13: 1053863471 | N13: +57 324 4539219 | O13: Accidente de tránsito (se produce en las vías y fuera de horario laboral) | P13: Daño Material propio | Q13: Condición insegura | R13: Conductor y/o Empleado | S13: NO IBA FUNCIONARIO | T13: NO IBA FUNCIONARIO | U13: El conductor informa que el funcionario lo despacho a la 8 pm saliendo de victoria caldas hacia Manizales, después de pasar el sector el 8, el conductor informa sobre las 11:23 pm al coger una curva pierde el control y golpea el contra borde de la vía, se activó el airbag, el conductor indica no presentar lesiones. | V13: SI | W13: SI | X13: NO | Y13: NO | Z13: NO | AA13: se reemplaza el servicio del dia 28 de mayo, se comunica con el conductor para solicitar desplazarse a revisión medica independiente de sentirse bien | AB13: SI | AC13: https://emprestur-my.sharepoint.com/personal/alejandra_betancur_emprestur_com/Documents/Aplicaciones/Microsoft%20Forms/INFORMACI%C3%93N%20NOVEDAD%20_%20ACCIDENTES%2026042022%20(2)/SOPORTES%20PARA%20ANEXAR/Imagen%20de%20WhatsApp%202025-05-28%20a%20las%2006.01.07__anonymous.jpg; https://emprestur-my.sharepoint.com/personal/alejandra_betancur_emprestur_com/Documents/Aplicaciones/Microsoft%20Forms/INFORMACI%C3%93N%20NOVEDAD%20_%20ACCIDENTES%2026042022%20(2)/SOPORTES%20PARA%20ANEXAR/Imagen%20de%20WhatsApp%202025-05-28%20a%20las%2006.01.00__anonymous.jpg
A14: 45805.4 | B14: 45805.426 | C14: anónimo | E14: Ramon Andres Quintero Cardona | F14: 45804 | G14: 13:22 | H14: SNW912 | I14: EPM | J14: Si | K14: ID86 | L14: JONATHAN ATEHORTUA USME | M14: 1001452215 | N14: 310 7272289 | O14: Accidente de tránsito y transporte dentro del desarrollo de la labor (Si ocurre en la vía con otros vehículos o con otros actores viales implicados) | P14: Afectación a Personas (lesionados) | Q14: Acto inseguro de Tercero | R14: Tercero (Comunidad) | S14: N/A | T14: Wilson Alesis Marin Marin - 3239729782 | U14: Me desplazada en la vía peñol marinilla los vehículos de adelante se detuvieron por la presencia de una animal en la vía yo me detuve detrás iba una motocicleta de placas RBG03F conducida por el sr. Wilson Alesis Marin Marin cel. 3239729782 la cual no estaba respetando la distancia establecida no alcanzo a frenar me golpeó por la parte trasera del vehículo | V14: SI | W14: SI | X14: SI | Y14: NO | Z14: SI | AA14: Se entregan orientaciones via telefonica al conductor para proceder frente al desarrollo del evento, con respecto al reporte a la aseguradora y juridica de la compañia. | AB14: SI | AC14: https://emprestur-my.sharepoint.com/personal/alejandra_betancur_emprestur_com/Documents/Aplicaciones/Microsoft%20Forms/INFORMACI%C3%93N%20NOVEDAD%20_%20ACCIDENTES%2026042022%20(2)/SOPORTES%20PARA%20ANEXAR/Evidencia%20Fotografica_anonymous%201.pdf
A15: 45808.885 | B15: 45808.891 | C15: anónimo | E15: JONATHAN GIRALDO ORREGO | F15: 45807 | G15: 09:30 Pm | H15: FWK341 | I15: CORPORACION AYUA HUMANITARIA | J15: No | K15: 123 EMERGENCIA | L15: MIGUEL ANGEL BEDOYA CASTAÑEDA | M15: 1018229452 | N15: 3205182447 | O15: Accidente de tránsito y transporte dentro del desarrollo de la labor (Si ocurre en la vía con otros vehículos o con otros actores viales implicados) | P15: Afectación a Personas (lesionados) | Q15: Condición insegura | R15: N/A | S15: N/A | T15: N/A | U15: Buenas tardes a todos Espero estén muy bien. Quiero informar que el día de ayer viernes 30 de mayo, el conductor de flota propia MIGUEL ANGEL BEDOYA CASTAÑEDA cc 1018229452 asignado al vehículo de placas FWK341 y quien labora para el contrato de la corporación Ayuda humanitaria, se encoraba cubriendo le turno de 10 de la mañana a 9 de la noche. luego de descargar a la funcionaria en su casa, siendo aproximadamente las 9:30 de la noche, ya se dirigía para el parqueadero de la empresa cuando en la Avenida 80 Con calle 78 Sentido norte-sur, el conductor venia por el carril derecho a 40 Km/h (según informa el conductor), el piso se encontraba mojado porque estaba lloviendo, cuando al momento de frenar el carro cuando transitaba sobre una de las demarcaciones (pintura) que tiene en la vía para las paradas del metro plus, el vehículo pierde la tracción y el conductor pierde el control del vehículo lo cual genera que el carro le haga una especie de trompo he imparte contra dos vehículo y al final contra el separador (baranda tubos) ocasionando daños a los dos vehículos terceros, un carro de comidas rápidas que estaba siendo halado en esos momentos por uno de los vehículos con que se colisiona y el carro propio quien lleva la peor parte en el accidente por haber golpeado contra el separador. los datos de los vehículos afectados son: VEHICULO # 1 PLACA: IOV085 TIPO DE VEHICULO: Renault Logan NOMBRE: Juan Santiago Velasco TELÉFONO: 3014047238 DAÑO: Afectación en bómper delantero derecho VEHICULO # 2 PLACA: ISS752 TIPO DE VEHICULO: Renault Duster NOMBRE: Jorge andres onofre TELEFONO: 3216840974 DAÑOS: Afectacion en parte trasera y daños al carro de comidas rapidas en general. El conductor se pone en contacto conmigo, y le pregunto si en el evento se presentan lesionados a lo que este me informa que ni el ni los tripulantes de los dos carros afectados estaban lesionados y que el accidente solo habia sido daños materiales, de inmediato le solicito que se ponga en contacto con la aseguradora SBS al #360 para que le presten la asistencia juridica en el sitio, ademas de servicio de grua y asignacion de taller para la reparacion del vehiculo propios. El abogado de la aseguradora, llega al sitio y le explica a los terceros afectados como pueden realizar el proceso de reclamacion ante la aseguradora para la reparacion de los daños ocacionados por nuestro vehiculo. ademas se comunica tambien conmigo el abogado quien me informa el proceso que realizo con los terceros y que explica que debemos solicitar cita en el taller Multimarca de Envigado para que reciban el carro y valoren lo daños; por la hora del evento nos vimos en la necesidad de trasladar el carro en grua hasta nuestras intalaciones para ya el martes solicitar la cita en el taller que nos designo la aseguradora. El día de hoy analice el accidente teniendo en cuenta las imágenes y el reportes del conductor donde evidencio por reporte de GPS que el conductor nuestro segundos antes de accidente iba a una velocidad de 52,2 Km/h. y la velocidad máxima permitida en la via por donde transitaba es de 50Km/H. | V15: SI | W15: NO | X15: SI | Y15: NO | Z15: SI | AA15: Se llama al conductor y le dan las infracciones de llamar a la aseguradora y se reporta a SST y abogadas. | AB15: SI
A16: 45808.978 | B16: 45808.98 | C16: anónimo | E16: Jonathan Giraldo Orrego | F16: 45808 | G16: 5:20 am | H16: FWK341 | I16: CORPORACION | J16: Si | K16: CONHYDRA | L16: EDUAR ALEXANDER LONDOÑO CARO | M16: 98710320 | N16: 3022234175 | O16: Accidente de trabajo (Empleado de Emprestur Lesionado) | P16: Afectación a Personas (lesionados) | Q16: Acto inseguro propio (conductor) | R16: N/A | S16: N/A | T16: N/A | U16: Quiero informar que el día de hoy sábado 31 de mayo, el conductor de flota propia EDUAR ALEXANDER LONDOÑO CARO cc 98710320 asignado al vehículo de placas SNR611 y quien labora para el contrato de la CONHYDRA, se encoraba cubriendo le turno de la noche de 9 Pm hasta las 5 de la mañana. El conductor siendo aproximadamente las 5:20 de la mañana me llama y me informa que ya había terminado el turno de trabajo y que cuando iba por la calle 62 A en el sector de fuente clara con destino para su casa, indica que le dio un micro sueño y que por ello se había chocado contra una motocicleta que estaba estacionada y que además se había golpeado el contra el timón del carro por lo que se había reventado un poco la boca. informa también que no hubieron más afectaciones ni heridos en el accidente. De inmediato le doy indicación al conductor de que se ponga en contacto con nuestra aseguradora SBS en el #360 para que solicite asistencia de grúa y de abogado en sitio para que se atendiera la moto afectada y el tránsito. Pasados más o menos 30 minutos me comunico con el conductor nuevamente ya que no me respondía los mensajes para consultarle que si ya había solicitado la asistencia y que le habían respondido, a lo que este me informa que ya estaba por llegar el abogado de la aseguradora, también me indico que no solicitaría transito porque no habían lesionados, de inmediato le pido al conductor que llame al tránsito pues el cómo conductor si estaba lastimado por el golpe en la boca. Paso seguido y como acción tomada por mi parte fue enviar dos conductores de la flota al sitio para que realizaran el acompañamiento a Aduar Londoño ya que como había trasnochado y había reportado micro sueño lo ms prudente era llevarlo a la casa y que los compañeros terminaran el proceso con la aseguradora; no obstante, cuando los conductores de apoyo llegaron al lugar encontraron un escenario muy diferente a lo que el conductor aduar había reportado, resulta que nuestro conductor choco primero a una camioneta que estaba estacionada a un lado de la vía y luego golpeo dos motos que estaban estacionadas. Los daños de los carros fueron CARRO PROPIO SNR611: Daños en bómper delantero farola izquierda - persiana - boca llantas delantero izquierdo, guardabarros, capot MOTO # 1 Bóxer 100: la moto se ve muy deteriorada y acabada, no se puede determinar si es que esta moto estaba desvalijada o en que estado estaba. MOTO # 2 QWD19G: la moto se ve muy deteriorada y acabada, no se puede determinar si es que esta moto estaba desvalijada o en que estado estaba. CAMIONETA PARTICULAR KHS242: El carro tiene daños en bómper lado izquierdo, nave delantero, persiana. Cuando llego el tránsito y el abogado de la aseguradora, se realizaron los procesos correspondientes, el abogado informó a todos los propietarios de los afectados que debían realizar la reclamación a la aseguradora, también me llamo y me informo que el transito se llevaría el carro para los patios pues debían realizar prueba de alcohol al conductor, pues se evidenciaba que estaba embriagado, por lo cual procedí a solicitarle a los conductores que envié, que se fueran con ellos para el transito y luego pudiera transportar al conductor a su casa. Luego del procedimiento de prueba de alcohol el abogado me contacta y me informa que la prueba había salido positiva con grado 3 de alcalemia, le informe al conductor que se viniera para la empresa junto con los conductores para tomarle la versión de los hechos , no obstante, este se negó y dijo que no vendría a la empresa. El abogado me informa que el carro debe quedar retenido en patios hasta 10 días hábiles (17 de junio) y que al conductor le debían suspender la licencia de conducción. Le escribí al conductor aduar para solicitarle que llegara a la empresa para que nos contara lo ocurrido y me dijo que estaba muy apenado que el si se había tomado una cerveza que le había ofrecido uno de los contratistas y que luego lo venció el sueño. el conductor no llego a | V16: SI | W16: NO | X16: SI | Y16: SI | Z16: SI | AA16: Se hace presencia en sitio, se hace investigacion., se reporta a operaciones | AB16: SI | AC16: https://emprestur-my.sharepoint.com/personal/alejandra_betancur_emprestur_com/Documents/Aplicaciones/Microsoft%20Forms/INFORMACI%C3%93N%20NOVEDAD%20_%20ACCIDENTES%2026042022%20(2)/SOPORTES%20PARA%20ANEXAR/FOTOS%20DEL%20ACCIDENTE%20-%20SNR611_anonymous.pdf
A17: 45809.576 | B17: 45809.584 | C17: anónimo | E17: JHON HAWER MURCIA OROZCO | F17: 45809 | G17: 12:27 PM | H17: LKL437 | I17: SALUD EN CASA (SURA) | J17: Si | K17: le solicitan el soat al vehículo por que la funcionaria fua a la clinica para ser atendida | L17: ANDRES DE JESUS TABORDA BOTERO | M17: 71222989 | N17: 324 2433112 | O17: Accidente de tránsito y transporte dentro del desarrollo de la labor (Si ocurre en la vía con otros vehículos o con otros actores viales implicados) | P17: Afectación al Cliente | Q17: Acto inseguro de Tercero | R17: Funcionario de cliente | S17: 3115209242 | T17: YADIT REQUEME | U17: Dirección Calle 30 # 136-106 Belén aguas frías En camino se interpone motorizado el cual esquivó para ebitar incidente. Por lo tanto la llanta trasera del lado derecho del vehículo pasa una piedra por encima. | V17: NO | W17: SI | X17: NO | Y17: NO | Z17: SI | AA17: comunicarme con el conductor para saber que sucedió y ayudarlo en lo que necesitaba | AB17: NO
A18: 45817.379 | B18: 45817.38 | C18: anónimo | E18: ANDRES QUINTERO CARDONA | F18: 45814 | G18: 13:17 | H18: EXU714 | I18: TELEMEDELLIN | J18: Si | K18: OS0321710 | L18: EDISON STIVEN SALDARRIAGA HENAO | M18: 1007669856 | N18: 3226609827 | O18: Accidente de tránsito y transporte dentro del desarrollo de la labor (Si ocurre en la vía con otros vehículos o con otros actores viales implicados) | P18: Daño Material a Tercero | Q18: Acto inseguro de Tercero | R18: N/A | S18: N/A | T18: N/A | U18: vehículo tercero realiza giro a la izquierda en una vía doble sentido, frena de manera repentina por dar paso a peatón en la vía, frene tambien inmediatamente pero alcance a impactarlo en la parte de atras, Ocasionando solo pintura pequeña en ambos vehículos Sin heridos ni afectados | V18: NO | W18: SI | X18: SI | Y18: NO | Z18: NO | AA18: Se acompaña telefónicamente al conductor hasta finalizar el proceso. | AB18: SI | AC18: https://emprestur-my.sharepoint.com/personal/alejandra_betancur_emprestur_com/Documents/Aplicaciones/Microsoft%20Forms/INFORMACI%C3%93N%20NOVEDAD%20_%20ACCIDENTES%2026042022%20(2)/SOPORTES%20PARA%20ANEXAR/Registro%20fotografico_anonymous.pdf
A19: 45818.347 | B19: 45818.36 | C19: anónimo | E19: Carlos Franco | F19: 45815 | G19: 10:00 am | H19: NNM458 | I19: EPM | J19: Si | K19: SDT. 111166 | L19: ALEJANDRO LOPERA BEDOYA | M19: 1007243076 | N19: 3173471864 | O19: Accidente de tránsito y transporte dentro del desarrollo de la labor (Si ocurre en la vía con otros vehículos o con otros actores viales implicados) | P19: Daño Material propio | Q19: Acto inseguro propio (conductor) | R19: N/A | S19: CESAR ALFONSO TOVAR ARIAS Teléfono 3015182469 | T19: N/A | U19: "Yo venía por la autopista norte, sentido sur - norte a la altura de la feria de ganado, específicamente donde se realizan las subastas. Al rededor de las 10 de la mañana, venía delante de mi un vehículo tipo furgón el cual frena repentinamente por otro vehículo que frena delante de él ocasionando que yo impacte en la parte trasera del furgón" | V19: SI | W19: NO | X19: SI | Y19: NO | Z19: SI | AA19: Se establece conversación con el funcionario donde manifiesta que no les pasó nada y que sólo fue el susto para que se le asigne vehículo de reemplazo y continuar con el recorrido programado | AB19: SI | AC19: https://emprestur-my.sharepoint.com/personal/alejandra_betancur_emprestur_com/Documents/Aplicaciones/Microsoft%20Forms/INFORMACI%C3%93N%20NOVEDAD%20_%20ACCIDENTES%2026042022%20(2)/SOPORTES%20PARA%20ANEXAR/WhatsApp%20Image%202025-06-08%20at%2020.26.17_anonymous.jpeg; https://emprestur-my.sharepoint.com/personal/alejandra_betancur_emprestur_com/Documents/Aplicaciones/Microsoft%20Forms/INFORMACI%C3%93N%20NOVEDAD%20_%20ACCIDENTES%2026042022%20(2)/SOPORTES%20PARA%20ANEXAR/WhatsApp%20Image%202025-06-08%20at%2020.26.18_anonymous.jpeg; https://emprestur-my.sharepoint.com/personal/alejandra_betancur_emprestur_com/Documents/Aplicaciones/Microsoft%20Forms/INFORMACI%C3%93N%20NOVEDAD%20_%20ACCIDENTES%2026042022%20(2)/SOPORTES%20PARA%20ANEXAR/WhatsApp%20Image%202025-06-08%20at%2020.26.20_anonymous.jpeg; https://emprestur-my.sharepoint.com/personal/alejandra_betancur_emprestur_com/Documents/Aplicaciones/Microsoft%20Forms/INFORMACI%C3%93N%20NOVEDAD%20_%20ACCIDENTES%2026042022%20(2)/SOPORTES%20PARA%20ANEXAR/WhatsApp%20Image%202025-06-08%20at%2020.26.20%20(1)_anonymous.jpeg; https://emprestur-my.sharepoint.com/personal/alejandra_betancur_emprestur_com/Documents/Aplicaciones/Microsoft%20Forms/INFORMACI%C3%93N%20NOVEDAD%20_%20ACCIDENTES%2026042022%20(2)/SOPORTES%20PARA%20ANEXAR/WhatsApp%20Image%202025-06-08%20at%2020.26.21_anonymous.jpeg; https://emprestur-my.sharepoint.com/personal/alejandra_betancur_emprestur_com/Documents/Aplicaciones/Microsoft%20Forms/INFORMACI%C3%93N%20NOVEDAD%20_%20ACCIDENTES%2026042022%20(2)/SOPORTES%20PARA%20ANEXAR/WhatsApp%20Image%202025-06-09%20at%2013.55.09_anonymous.jpeg
A20: 45828.572 | B20: 45828.575 | C20: anónimo | E20: Jeiner Morales | F20: 45828 | G20: 1 pm | H20: SNV726 | I20: EEP | J20: Si | K20: NA | L20: Wilder Ramos | M20: 18516706 | N20: +57 318 5094343 | O20: Accidente Ambienta (afectación al ecosistema por derrames, impacto con animal en la vía) | P20: Afectación al medio ambiente | Q20: Acto inseguro de Tercero | R20: Tercero (Comunidad) | S20: na | T20: na | U20: Sobre el medio día el conductor es chocado por un perro que se lanzo a la carretera generándole lesiones al perro | V20: NO | W20: NO | X20: SI | Y20: NO | Z20: SI | AA20: Se reporta a SST | AB20: NO
A21: 45842.585 | B21: 45842.585 | C21: anónimo | E21: JONATHAN GIRALDO ORREGO | F21: 45840 | G21: 10:51 AM | H21: SNV729 | I21: CHEC | J21: Si | K21: CHEC | L21: FABIAN GENARO CARDENAS SANCHEZ | M21: 1053849967 | N21: 3117672947 | O21: Accidente de tránsito y transporte dentro del desarrollo de la labor (Si ocurre en la vía con otros vehículos o con otros actores viales implicados) | P21: Daño Material propio | Q21: Condición insegura | R21: N/A | S21: N/A | T21: N/A | U21: Quiero realizar el reporte del accidente ocurrido el pasado miércoles 2 de julio del 2025; donde el conductor del vehículo administrado de placas SNV729 quien es conducido por nuestro colaborador FABIAN GENARO CARDENAS SANCHEZ CC 1053849967, teléfono 3117672947,se encontraba prestando servicio para el cliente CHEC. estando en inmediaciones de la base militar Montezuma - parque nacional natural Tatamá y que queda a mas o menos 2 horas y media de Pueblo rico Risaralda; los funcionarios descienden del vehículo, puesto que debían hacer unos trabajos de reconocimiento del terreno y este recorrido lo realizaban caminando; mientras tanto nuestro conductor seguía a los funcionarios montado en el vehículo a un una baja velocidad (7Km/h aproximadamente). siendo aproximadamente las 10:51 mientras iban bajando por una pendiente, el conductor siente que el pedal del freno no le responde y su reacción fue recostar el carro contra el barranco lo cual genera que el vehículo sufra un volcamiento, el conductor no sufre lesiones y los funcionarios al estar un poco retirados del vehículo tampoco sufren lesiones. al lugar de los hechos, llegaron unos soldados quienes ayudaron a nuevamente voltear el vehículo y ponerlo sobre las ruedas; dado que el carro permaneció por un buen rato con las llantas hacia arriba, este no se debía encender pues podría generar afectaciones significativas dado que el aceite del vehículo pudo ingresar a las recamaras del motor; además el carro quedaba No operativo por las afectaciones que tenia. Luego de que el carro estuvo sobre las Ruedas solicite al conductor que me realizara un video donde se evidenciara que el freno estaba "blandito" y no cogía, a lo que el conductor me informa "Jefe el freno está duro pero cuando yo empecé a bajar el pedal se fue a fondo". por lo que mi hipótesis es que el carro si le freno pero al ser un terreno de lodo amarrillo el carro se le fue resbalado, desde operaciones Manizales activaron el protocolo de mandar un carro de remplazo pero mientras llegaba el vehículo, tanto los funcionarios como el conductor se bajaron en un jeep para Pueblo Rico dejando el vehículo en el lugar de los hechos. Se activo el protocolo de reporte de la novedad a la aseguradora SBS el cual quedo bajo el radicado (1708033), donde nos informan que debido a que donde quedo el carro es una zona roja y por lo inclinado del terreno y ser destapado, la grúa no entraba por el vehículo lo que nos llevo a tener que pagarle a un señor de un jeep para que subiera y arrastrara el carro hasta la entrada al parque nacional (pueblo rico) el cual nos cobro 600.000 mil pesos. luego de que sacaron el carro de la zona lo recogió la grúa de la aseguradora y lo traslado a Manizales para el taller casa López el cual nos designo la aseguradora para la reparación. Esta novedad se le informo al propietario del vehículo (Juan Jose Roa) y el protocolo que esto tenia. | V21: SI | W21: SI | X21: SI | Y21: NO | Z21: SI | AA21: desde operaciones Manizales activaron el protocolo de mandar un carro de remplazo pero mientras llegaba el vehículo, tanto los funcionarios como el conductor se bajaron en un jeep para Pueblo Rico dejando el vehículo en el lugar de los hechos. Se activo el protocolo de reporte de la novedad a la aseguradora SBS el cual quedo bajo el radicado (1708033), donde nos informan que debido a que donde quedo el carro es una zona roja y por lo inclinado del terreno y ser destapado, la grúa no entraba por el vehículo lo que nos llevo a tener que pagarle a un señor de un jeep para que subiera y arrastrara el carro hasta la entrada al parque nacional (pueblo rico) el cual nos cobro 600.000 mil pesos. luego de que sacaron el carro de la zona lo recogió la grúa de la aseguradora y lo traslado a Manizales para el taller casa López el cual nos designo la aseguradora para la reparación. Se envia notificacion a las areas encargadas para el proceso de investigacion del evento. | AB21: SI | AC21: https://emprestur-my.sharepoint.com/personal/alejandra_betancur_emprestur_com/Documents/Aplicaciones/Microsoft%20Forms/INFORMACI%C3%93N%20NOVEDAD%20_%20ACCIDENTES%2026042022%20(2)/SOPORTES%20PARA%20ANEXAR/FOTOS%20DEL%20ACCIDENTE%20SNV729%20-%20REPORTE%20GPS_anonymous.pdf
A22: 45856.62 | B22: 45856.621 | C22: anónimo | E22: Julian Davi Valencia Ballesteros | F22: 45856 | G22: 12:50 pm | H22: EXU705 | I22: CHEC | J22: Si | K22: TR2512634 | L22: Milton Stivel Cardona Castaño | M22: 1060650008 | N22: +573165799327 | O22: Accidente Ambienta (afectación al ecosistema por derrames, impacto con animal en la vía) | P22: Daño Material a Tercero | Q22: Acto inseguro de Tercero | R22: Tercero (Comunidad) | S22: n/a | T22: No se tiene contacto | U22: El día 18/07/2025, el conductor se dirigía a la residencia del funcionario para finalizar el servicio asignado. Al ingresar a la calle donde se encuentra la vivienda, observó que había varios caninos en el sector, por lo cual redujo la velocidad y continuó avanzando con precaución. En ese momento, sintió un golpe en la llanta trasera del vehículo, acompañado de un chillido. Al detenerse y descender del vehículo, una vecina se acercó y le preguntó si había atropellado a un perro, a lo que el conductor respondió que no lo sabía con certeza. Seguidamente, observó que un canino de gran tamaño salía por la parte delantera del vehículo, y al revisar por debajo, notó que había un canino más pequeño que estaba lesionado. El conductor procedió a retroceder el vehículo ligeramente para observar con mayor claridad el estado del animal. En ese momento, un menor salió de una vivienda cercana, recogió al perro y lo ingresó a la casa. Posteriormente, una joven salió y preguntó por el estado del perro. Desde el interior de la vivienda se escuchaban llantos, pero ninguna otra persona salió a atender la situación. Tanto el funcionario como algunos vecinos que presenciaron lo ocurrido le manifestaron al conductor que no había tenido la culpa y que podía retirarse del lugar. El conductor intentó hacer señas a los dueños del perro para obtener algún tipo de respuesta, pero no obtuvo ninguna y se retiro del sitio. | V22: NO | W22: NO | X22: NO | Y22: NO | Z22: SI | AA22: Se le solicito al conductor evidencia fotografica del lugar del incidente. | AB22: SI | AC22: https://emprestur-my.sharepoint.com/personal/alejandra_betancur_emprestur_com/Documents/Aplicaciones/Microsoft%20Forms/INFORMACI%C3%93N%20NOVEDAD%20_%20ACCIDENTES%2026042022%20(2)/SOPORTES%20PARA%20ANEXAR/IMG-20250718-WA0017_anonymous.jpg; https://emprestur-my.sharepoint.com/personal/alejandra_betancur_emprestur_com/Documents/Aplicaciones/Microsoft%20Forms/INFORMACI%C3%93N%20NOVEDAD%20_%20ACCIDENTES%2026042022%20(2)/SOPORTES%20PARA%20ANEXAR/IMG-20250718-WA0018_anonymous.jpg; https://emprestur-my.sharepoint.com/personal/alejandra_betancur_emprestur_com/Documents/Aplicaciones/Microsoft%20Forms/INFORMACI%C3%93N%20NOVEDAD%20_%20ACCIDENTES%2026042022%20(2)/SOPORTES%20PARA%20ANEXAR/IMG-20250718-WA0016_anonymous.jpg; https://emprestur-my.sharepoint.com/personal/alejandra_betancur_emprestur_com/Documents/Aplicaciones/Microsoft%20Forms/INFORMACI%C3%93N%20NOVEDAD%20_%20ACCIDENTES%2026042022%20(2)/SOPORTES%20PARA%20ANEXAR/IMG-20250718-WA0014_anonymous.jpg; https://emprestur-my.sharepoint.com/personal/alejandra_betancur_emprestur_com/Documents/Aplicaciones/Microsoft%20Forms/INFORMACI%C3%93N%20NOVEDAD%20_%20ACCIDENTES%2026042022%20(2)/SOPORTES%20PARA%20ANEXAR/IMG-20250718-WA0015_anonymous.jpg; https://emprestur-my.sharepoint.com/personal/alejandra_betancur_emprestur_com/Documents/Aplicaciones/Microsoft%20Forms/INFORMACI%C3%93N%20NOVEDAD%20_%20ACCIDENTES%2026042022%20(2)/SOPORTES%20PARA%20ANEXAR/IMG-20250718-WA0013_anonymous.jpg
A23: 45868.659 | B23: 45868.698 | C23: anónimo | E23: Adriana Castillo | F23: 45868 | G23: 13:30 p.m. | H23: NNN344 | I23: SURA | J23: No | K23: N/A | L23: YEISON ACEVEDO ARIAS | M23: 1007567428 | N23: 3052001475 | O23: Accidente de tránsito y transporte dentro del desarrollo de la labor (Si ocurre en la vía con otros vehículos o con otros actores viales implicados) | P23: Daño Material propio | Q23: Acto inseguro propio (conductor) | R23: N/A | S23: N/A | T23: 3003456544 Juan Pablo Sanchez | U23: Yo Yeison Acevedo Arias El día 30 de julio del 2025 A las 13:45 en la calle 14 me dirigía a la empresa a entregar el vehículo al frente de la terminal del Sur ingresando a la glorieta del aeropuerto Olaya Herrera tuve un choque simple contra otro automóvil. Lo que paso fue que el señor conductor arrancó a incorporace y yo también arranque en ese momento paso una motocicleta por la glorieta y el conductor del particulat se frenó de forma brusca no tuve tiempo de reacción y lo choque con el bomper delantero lado derecho en la parte izquierda trasera del otro vehículo | V23: NO | W23: NO | X23: SI | Y23: NO | Z23: SI | AA23: Se le indica que llame a la aseguradora, toma de fotograficas y traer el vehículo al parqueadero | AB23: SI | AC23: https://emprestur-my.sharepoint.com/personal/alejandra_betancur_emprestur_com/Documents/Aplicaciones/Microsoft%20Forms/INFORMACI%C3%93N%20NOVEDAD%20_%20ACCIDENTES%2026042022%20(2)/SOPORTES%20PARA%20ANEXAR/REGISTRO%20FOTOGRAFICO%20NNN344_anonymous.pdf
A24: 45869.302 | B24: 45869.306 | C24: anónimo | E24: JONATHAN GIRALDO ORREGO | F24: 45865 | G24: 7:40 AM | H24: FWL446 | I24: FLOTA PROPIA | J24: No | K24: CARAVANA RUTA 2025 | L24: JUAN CAMILO SEPULVEDA MORALES | M24: 1037618189 | N24: 3019640447 | O24: Accidente de tránsito y transporte dentro del desarrollo de la labor (Si ocurre en la vía con otros vehículos o con otros actores viales implicados) | P24: Daño Material propio | Q24: Acto inseguro propio (conductor) | R24: Conductor y/o Empleado | S24: Angie Arzuza | T24: N/A | U24: Quiero oficializar el reporte del accidente que ocurrió el pasado domingo 27 de julio del 2025. En el evento llamado caravana Ruta 2025 que la empresa organizo como parte de la celebración del día del conductor y la familia; 5 minutos luego de haber iniciado la caravana que salió de Ayurá motor de la avenida las Vegas, siendo aproximadamente las 7:40 de la mañana el conductor de flota propia JUAN CAMILO SEPULVEDA MORALES CC 1037618189 quien conducía el vehículo de placas FWL446 me reporta que había acabado de tener un accidente por la avenida regional a la altura de la calle 14, indica que el compañero LUIS FERNANDO GAVIRIA DURANGO cc 71753945 del vehículo de placas LKL570 que iba adelante de él freno y que no alcanzó a frenar el carro chocando contra el carro del compañero. Ambos vehículos sufren afectaciones en su estructura, el carro de placas FWL446 es quien tiene mas afectaciones, pues se generan daños de bómper delantero, persiana, nave delantera, capot, calandria, radiador, farolas; por otro lado el vehículo de placas LKL570 sufre daños en bómper trasero, compuerta, stop y nave trasera. Al momento del accidente en el vehículo de placas FWL446 viajaba nuestro conductor Juan camilo y su esposa, quienes indicaron no haber sufrido ninguna lesión; por otro lado en el carro de placas LKL570 viajaba nuestro conductor Luis Gaviria en compañía de Angie Arzuza, quien luego del evento si manifestó tener sensación de dolor en su cuerpo por el evento. Se valida el GPS y se identifica que al momento del evento el carro FWL446 iba a una velocidad de 38 Km/h. el caso fue reportado a la aseguradora Zurich Colombia Seguros el cual quedo bajo el radicado # -175129. agradezco por favor realicemos el proceso de investigación del evento y dejemos los registros necesarios. @Manuela Jaramillo - @Nancy Arias Antes de iniciar la caravana todos los conductores firmaron un documento llamado exoneración de responsabilidad de la empresa donde ellos asumían cualquier daño o afectación. estos documentos los tenia Angie, por favor vinculemos el documento que debió firmar juan camilo para que realicemos el descuento de nomina del deducible por afectaciones 2 SMMLV. Se anexan fotos de los carros. reporte GPS Se registra evento en el enlace. | V24: NO | W24: SI | X24: NO | Y24: NO | Z24: SI | AA24: Se realiza reporte de la novedad SST - y talento humano, se reporta aseguradora | AB24: SI | AC24: https://emprestur-my.sharepoint.com/personal/alejandra_betancur_emprestur_com/Documents/Aplicaciones/Microsoft%20Forms/INFORMACI%C3%93N%20NOVEDAD%20_%20ACCIDENTES%2026042022%20(2)/SOPORTES%20PARA%20ANEXAR/FOTOS%20DEL%20EVENTO%20FWL446%20-%20LKL570_anonymous.pdf
A25: 45869.586 | B25: 45869.594 | C25: anónimo | E25: Adriana Castillo | F25: 45866 | G25: 17:30 p.m. | H25: JYO404 | I25: ISAGEN | J25: Si | K25: N/A | L25: Yeison Acevedo Arias | M25: 1007567428 | N25: 3052001475 | O25: Accidente de tránsito y transporte dentro del desarrollo de la labor (Si ocurre en la vía con otros vehículos o con otros actores viales implicados) | P25: Daño Material propio | Q25: Acto inseguro de Tercero | R25: N/A | S25: N/A | T25: Henry de Jesus Lopera | U25: El día 28 de julio a las 17:30 En la carrera 48c a la altura del centro comercial monterrey Me desplazaba en el bus de placa JYO404 con la ruta del masivo de ISAGEN., Un taxi iba adelante y pone su direccional izquierda y se empieza a mover a el carril izquierdo, adelante del taxi había otros vehículos lo cierran y el devuelve la dirección hacia la derecha yo iba a seguir derecho me cierra y no pude frenar totalmente y lo choque en la parte trasera. Yo creo que el incidente pasó porque el otro conductor no puso direccional y se salió de imprevisto lo cual me dejó sin tiempo de reacción aunque logre frenar lo más que pude! Pensando en los usuarios que llevaba | V25: NO | W25: NO | X25: NO | Y25: NO | Z25: NO | AA25: El Director de flota es a quien le reporta la novedad y procede a revisar las cámaras del vehículo para dar la respuesta inicial a Jorge Correa Coordinador Lider | AB25: SI | AC25: https://emprestur-my.sharepoint.com/personal/alejandra_betancur_emprestur_com/Documents/Aplicaciones/Microsoft%20Forms/INFORMACI%C3%93N%20NOVEDAD%20_%20ACCIDENTES%2026042022%20(2)/SOPORTES%20PARA%20ANEXAR/REGISTRO%20FOTOGR%C3%81FICO%20JYO404_anonymous.pdf
A26: 45870.36 | B26: 45870.365 | C26: anónimo | E26: Jeiner Morales | F26: 45870 | G26: 08:12 | H26: GDW822 | I26: NO APLICA | J26: No | K26: NO APLICA | L26: CARLOS ARTURO GOMEZ ESPINOSA | M26: 7547809 | N26: 3155550550 | O26: Accidente de tránsito y transporte dentro del desarrollo de la labor (Si ocurre en la vía con otros vehículos o con otros actores viales implicados) | P26: Daño Material a Tercero | Q26: Acto inseguro propio (conductor) | R26: N/A | S26: NO APLICA | T26: NO APLICA | U26: El conductor llama sobre las 08:12 am a informar que tuvo accidente, no explica muy bien la situación, se entiende que es un choque con otro vehículo | V26: NO | W26: NO | X26: SI | Y26: NO | Z26: SI | AA26: Se llama a Dalila para informar del evento, aclarando que, si bien la camioneta es afiliada a Emprestur, en la actualidad no labora con nuestra empresa, labora mediante convenio con la empresa Trandecol. De acuerdo a la información proporcionada por Dalila se le informa al conductor que debe hacer el reporte a la empresa para la que presta el servicio. | AB26: NO
A27: 45870.637 | B27: 45870.64 | C27: anónimo | E27: Alejandra Velasquez | F27: 45870 | G27: 3:15 pm | H27: TMZ390 | I27: MEJIA ACEVEDO | J27: Si | K27: 0 | L27: WILSON EUGENIO CALLE HENAO | M27: 98589488 | N27: 3128040278 | O27: Accidente de trabajo (Empleado de Emprestur Lesionado) | P27: Afectación a Personas (lesionados) | Q27: Condición insegura | R27: Conductor y/o Empleado | S27: WILSON EUGENIO CALLE HENAO 3128040278 | T27: NO | U27: El conductor en labor de cargue se cortó con unas latas | V27: NO | W27: SI | X27: NO | Y27: NO | Z27: SI | AA27: Se recibe el reporte e inmediatamente se reporta a SSTA de Emprestur | AB27: NO
A28: 45873.427 | B28: 45873.433 | C28: anónimo | E28: Kevin Arenas - Director contable | F28: 45865 | G28: 11:00 am | H28: NO APLICA | I28: NO APLICA | J28: No | K28: NO APLICA | L28: Viviana Sepúlveda | M28: 1151447574 | N28: 3104682615 | O28: Accidente de trabajo (Empleado de Emprestur Lesionado) | P28: Afectación a Personas (lesionados) | Q28: Condición insegura | R28: Conductor y/o Empleado | S28: NO APLICA | T28: NO APLICA | U28: Viviana Sepúlveda me informa que se encontraba con su hija en el parque de las aguas en la actividad del día de la familia, al bajar las escalas en uno de sus trayectos resbala y cae sobre su coxis, inicialmente lesión no le impide caminar, pero el dolor se mantiene en el tiempo. | V28: NO | W28: NO | X28: NO | Y28: NO | Z28: NO | AA28: Una vez se me informe del accidente y el dolor constante le recomiendo que pida cita en su EPS. | AB28: NO
A29: 45873.664 | B29: 45873.696 | C29: anónimo | E29: Alejandra faisuri botero | F29: 45873 | G29: 12 pm | H29: JOW870 | I29: Chec pasajeros | J29: Si | K29: TR2513673 | L29: Diego Alejandro ramirez | M29: 1057788127 | N29: 3044860852 | O29: Accidente de tránsito y transporte dentro del desarrollo de la labor (Si ocurre en la vía con otros vehículos o con otros actores viales implicados) | P29: Daño Material propio | Q29: Acto inseguro de Tercero | R29: N/A | S29: Anyinson scappeta | T29: 3128732688 | U29: En la carretera destapada una motocicleta invadiendo el caril de la camioneta | V29: NO | W29: SI | X29: NO | Y29: NO | Z29: SI | AA29: Se realiza llamada para realizar seguimiento qué todos estén bien | AB29: NO
A30: 45882.37 | B30: 45882.579 | C30: anónimo | E30: Adriana Castillo | F30: 45882 | G30: 8:51 a.m. | H30: LKK451 | I30: TELEMEDELLIN | J30: Si | K30: TELEMEDELLIN | L30: JHON DAYRO COLORADO OSORIO | M30: 71263405 | N30: 3137526315 | O30: Accidente de tránsito y transporte dentro del desarrollo de la labor (Si ocurre en la vía con otros vehículos o con otros actores viales implicados) | P30: Daño Material propio | Q30: Acto inseguro propio (conductor) | R30: N/A | S30: N/A | T30: Daniel Alexis 3233988099 | U30: El conductor se le había dado la indicación que debía llevar unos funcionarios de Telemedellin para el Municipio de Barbosa, al cruzar el peaje uno de los tripulantes le indicó que debía haber volteado en el ingreso para la subestación Tasajera, como el conductor ya había pasado este cruce procede a frenar y empezar a dar reversa, en la reversa no se fijó que un tractocamión se encontraba saliendo y el tractocamión al no percatarse del vehículo ocurrió el choque. No se presentaron afectados, se tomó registro fotográfico, el conductor procede a realizar el reporte a la aseguradora. | V30: SI | W30: SI | X30: SI | Y30: NO | Z30: SI | AA30: Se procede a indicarle al conductor que reporte a la aseguradora y el Gestor logístico procede a realizar el relevo del vehículo. | AB30: SI | AC30: https://emprestur-my.sharepoint.com/personal/alejandra_betancur_emprestur_com/Documents/Aplicaciones/Microsoft%20Forms/INFORMACI%C3%93N%20NOVEDAD%20_%20ACCIDENTES%2026042022%20(2)/SOPORTES%20PARA%20ANEXAR/REGISTRO%20FOTOGR%C3%81FICO%20ACCIDENTE%20VIAL%20LKK451_anonymous.pdf
A31: 45885.419 | B31: 45885.432 | C31: anónimo | E31: Adriana Castillo | F31: 45884 | G31: 10:50 p.m. | H31: SNU647 | I31: Conhydra | J31: Si | K31: Conhydra | L31: Wilson Orlando Mora Marin | M31: 98704217 | N31: 3196835309 | O31: Accidente de tránsito y transporte dentro del desarrollo de la labor (Si ocurre en la vía con otros vehículos o con otros actores viales implicados) | P31: Daño Material a Tercero | Q31: Acto inseguro de Tercero | R31: N/A | S31: N/A | T31: N/A | U31: El conductor manifiesto que iba subiendo por la calle 24A por cabañas y había un vehículo adelante muy lento, entonces el señor como sabia que iba lento, el señor se corrió al costado derecho para dejarme pasar y cuando se iba a adelantar, un señor de la moto de una de las casas salió sin percatarse que iba adelantando, por no coger el de la moto lo que hice fué irme al lado derecho lo que ocasionó que le pegara al vehículo que me estaba dando paso, una vez lo adelanté me hice al costado derecho para revisar el daño, el señor pensó que me iba a volar y lo que hizo fue adelantarme y se hizo al lado y ya parqueo adelante mío. | V31: NO | W31: SI | X31: SI | Y31: NO | Z31: NO | AA31: Se solicita llamar a la aseguradora reportar | AB31: SI | AC31: https://emprestur-my.sharepoint.com/personal/alejandra_betancur_emprestur_com/Documents/Aplicaciones/Microsoft%20Forms/INFORMACI%C3%93N%20NOVEDAD%20_%20ACCIDENTES%2026042022%20(2)/SOPORTES%20PARA%20ANEXAR/REGISTRO%20FOTOGR%C3%81FICO%20SNU647_anonymous.pdf
A32: 45889.361 | B32: 45889.557 | C32: anónimo | E32: Adriana Marcela Castillo | F32: 45888 | G32: 15:30 p.m. | H32: NNL058 | I32: Corporación Ayuda Humanitaria | J32: Si | K32: Corporación Ayuda Humanitaria | L32: Wilder Pardo Pamplona | M32: 1017148606 | N32: 3023837194 | O32: Accidente de tránsito y transporte dentro del desarrollo de la labor (Si ocurre en la vía con otros vehículos o con otros actores viales implicados) | P32: Daño Material propio | Q32: Acto inseguro de Tercero | R32: N/A | S32: N/A | T32: N/A | U32: Iba transitando por el parque de San Antonio de prado y anterior a una cebra iba una adulta mayor cruzando lo cual detuve el vehículo con luces estacionarias para darle paso y la moto que venía detrás de mí no le dio tiempo de frenar y me impactó, se procede a hablar con el de la moto para arreglar y conciliamos con 200 mil pesos. | V32: NO | W32: NO | X32: SI | Y32: NO | Z32: SI | AA32: Una vez indicado el reporte se le indica al conductor que por favor concilie con el señor de la moto, para no afectar la póliza, el motorizado le cancela al conductor la suma de 200 mil pesos, se adjunta evidencia de la consignación del dinero a la cuenta de Emprestur. | AB32: SI | AC32: https://emprestur-my.sharepoint.com/personal/alejandra_betancur_emprestur_com/Documents/Aplicaciones/Microsoft%20Forms/INFORMACI%C3%93N%20NOVEDAD%20_%20ACCIDENTES%2026042022%20(2)/SOPORTES%20PARA%20ANEXAR/REGISTRO%20FOTOGR%C3%81FICO%20NNN058_anonymous.pdf
A33: 45894.359 | B33: 45894.671 | C33: anónimo | E33: Adriana Castillo | F33: 45892 | G33: 7:15 p.m. | H33: FLOTA PROPIA | I33: CORPORACION AYUDA HUMANITARIA | J33: Si | K33: CORPORACION AYUDA HUMANITARIA | L33: JUAN PABLO GONZALEZ PADILLA | M33: 1007979469 | N33: 3024190757 | O33: Accidente de tránsito y transporte dentro del desarrollo de la labor (Si ocurre en la vía con otros vehículos o con otros actores viales implicados) | P33: Daño Material propio | Q33: Acto inseguro de Tercero | R33: N/A | S33: N/A | T33: N/A | U33: Fecha y hora del incidente: 23 de agosto de 2025, aproximadamente a las 19:15 horas. Lugar: Autopista Norte, sentido sur–norte, en desplazamiento hacia el municipio de Bello, barrio París, a la dirección carrera 72 #20–36. Descripción de los hechos: A las 19:00 horas se inició un servicio con destino a recoger a una pasajera en el sector de París, municipio de Bello. Durante el trayecto, me desplazaba por la Autopista Norte en el carril izquierdo. Alrededor de las 19:15 horas procedí a realizar un cambio de carril hacia la derecha, momento en el cual se presentó un incidente de tránsito en dicho carril, donde ya se encontraban involucrados cuatro vehículos. El quinto vehículo, que circulaba adelante, se encontraba detenido. Al intentar incorporarme al carril derecho, el vehículo que iba delante frenó de manera repentina. A pesar de accionar los frenos, no fue posible detener el vehículo a tiempo y se produjo una colisión en la parte frontal izquierda del vehículo que yo conducía contra la parte trasera del otro automotor. Consecuencias: Daños materiales en el vehículo de la empresa, específicamente: Farola izquierda. Bomper delantero. Capó delantero (principalmente en el costado izquierdo). No se presentaron personas lesionadas, únicamente daños materiales. | V33: NO | W33: SI | X33: SI | Y33: NO | Z33: NO | AA33: Se le solicita al conductor llamar a la aseguradora | AB33: SI | AC33: https://emprestur-my.sharepoint.com/personal/alejandra_betancur_emprestur_com/Documents/Aplicaciones/Microsoft%20Forms/INFORMACI%C3%93N%20NOVEDAD%20_%20ACCIDENTES%2026042022%20(2)/SOPORTES%20PARA%20ANEXAR/REGISTRO%20FOTOGR%C3%81FICO%20LKL631_anonymous.pdf
A34: 45910.347 | B34: 45910.382 | C34: anónimo | E34: JOHN FREDY CALLE RESTREPO | F34: 45910 | G34: 04:40 HORAS | H34: NNN253 | I34: ISAGEN | J34: Si | K34: N/A | L34: VARGAS GARCÍA LEONEL ALEXANDER | M34: 71174247 | N34: 3146391790 | O34: Accidente de tránsito y transporte dentro del desarrollo de la labor (Si ocurre en la vía con otros vehículos o con otros actores viales implicados) | P34: Daño Material propio | Q34: Condición insegura | R34: N/A | S34: EXPRESO BRASILIA | T34: NO SE TIENE | U34: El conductor reporta a las 06:30 horas aproximadamente que siendo las 04:45 horas de la mañana de hoy cuando llego a la Bahía de la Terminal del Norte mientras estaba estacionado para recoger los usuarios de ISAGEN, un bus de la empresa Expreso Brasilia golpeo la parte trasera izquierda del bómper y la parte lateral izquierda desde atrás. Manifiesta que no llamo al transito porque el golpe había sido muy leve y aparentemente salía con copao. Cuando llego al Palacio de los Frijoles en Cocorná y que ya estaba con mas luz de dia fue que evidencio que el rayón era mas profundo. | V34: NO | W34: NO | X34: NO | Y34: NO | Z34: SI | AA34: Se reporto a Jonathan Giraldo y Angie Arzuza después de haber recibido reporte por parte del conductor Leonel Vargas. | AB34: SI | AC34: https://emprestur-my.sharepoint.com/personal/alejandra_betancur_emprestur_com/Documents/Aplicaciones/Microsoft%20Forms/INFORMACI%C3%93N%20NOVEDAD%20_%20ACCIDENTES%2026042022%20(2)/SOPORTES%20PARA%20ANEXAR/WhatsApp%20Image%202025-09-10%20at%206.36.21%20AM_anonymous.jpeg; https://emprestur-my.sharepoint.com/personal/alejandra_betancur_emprestur_com/Documents/Aplicaciones/Microsoft%20Forms/INFORMACI%C3%93N%20NOVEDAD%20_%20ACCIDENTES%2026042022%20(2)/SOPORTES%20PARA%20ANEXAR/WhatsApp%20Image%202025-09-10%20at%206.36.15%20AM_anonymous.jpeg; https://emprestur-my.sharepoint.com/personal/alejandra_betancur_emprestur_com/Documents/Aplicaciones/Microsoft%20Forms/INFORMACI%C3%93N%20NOVEDAD%20_%20ACCIDENTES%2026042022%20(2)/SOPORTES%20PARA%20ANEXAR/WhatsApp%20Image%202025-09-10%20at%206.36.14%20AM%20(1)_anonymous.jpeg; https://emprestur-my.sharepoint.com/personal/alejandra_betancur_emprestur_com/Documents/Aplicaciones/Microsoft%20Forms/INFORMACI%C3%93N%20NOVEDAD%20_%20ACCIDENTES%2026042022%20(2)/SOPORTES%20PARA%20ANEXAR/WhatsApp%20Image%202025-09-10%20at%206.36.14%20AM_anonymous.jpeg
A35: 45910.449 | B35: 45910.463 | C35: anónimo | E35: Carlos Franco | F35: 45909 | G35: 16:30 | H35: FWL212 | I35: EPM | J35: Si | K35: SDT. 103128 | L35: EMANUEL YESID CORREA QUINTERO | M35: 1036963501 | N35: 3225207591 | O35: Accidente de tránsito y transporte dentro del desarrollo de la labor (Si ocurre en la vía con otros vehículos o con otros actores viales implicados) | P35: Daño Material propio | Q35: Acto inseguro de Tercero | R35: N/A | S35: N/A | T35: N/A | U35: "Venía con los funcionarios por la autopista Medellín - Bogotá desde Rionegro y antes de llegar a Guarne en el PR 25, hay un paso peatonal y yo disminuí velocidad pero cuando menos pensé sentí un golpe fuerte atrás y era un bus que me había dado" | V35: SI | W35: SI | X35: SI | Y35: NO | Z35: SI | AA35: Se hace acompañamiento vía telefónica validando el estado de salud del conductor y los acompañantes donde confirman que no les pasó nada, sólo el conductor manifiesta un leve dolor en el cuello que más tarde le pasó y se dieron indicaciones para que se comunique con la aseguradora | AB35: SI | AC35: https://emprestur-my.sharepoint.com/personal/alejandra_betancur_emprestur_com/Documents/Aplicaciones/Microsoft%20Forms/INFORMACI%C3%93N%20NOVEDAD%20_%20ACCIDENTES%2026042022%20(2)/SOPORTES%20PARA%20ANEXAR/WhatsApp%20Image%202025-09-09%20at%2016.41.22_anonymous.jpeg; https://emprestur-my.sharepoint.com/personal/alejandra_betancur_emprestur_com/Documents/Aplicaciones/Microsoft%20Forms/INFORMACI%C3%93N%20NOVEDAD%20_%20ACCIDENTES%2026042022%20(2)/SOPORTES%20PARA%20ANEXAR/WhatsApp%20Video%202025-09-09%20at%2016.43.23_anonymous.mp4
A36: 45916.317 | B36: 45916.395 | C36: anónimo | E36: Adriana Castillo | F36: 45911 | G36: 7:45 p.m. | H36: NLW529 | I36: Corporación Ayuda Humanitaria | J36: Si | K36: N/A | L36: OVIDIO DE JESUS VARGAS BAENA | M36: 71677396 | N36: 3117188011 | O36: Accidente de tránsito y transporte dentro del desarrollo de la labor (Si ocurre en la vía con otros vehículos o con otros actores viales implicados) | P36: Daño Material propio | Q36: Acto inseguro de Tercero | R36: N/A | S36: Fernando de Jesús Hincapié | T36: No tiene número | U36: El dia11 de septiembre de2025, siendo aprox.las7:45pm.me dirigía, junto con un equipo psico social en sentido oriente ,occidente tomando el puente que cruza la Av.80. Mientras ascendíamos por el carril izquierdo, se presentó una colisión en el carril derecho entre 2 motos, una biwis de placaVKG86D.y pulsar de placa SIO82G. Está al frenar de repente por un cuarto VH fue impactada por la biwis, que a su vez al caer ,hacia la izquierda alcanza a impactar al vehiculo NLW559 en la puerta delantera derecha. El conductor de la moto biwis presento un golpe en rodilla derecha, por tal motivo se procede a llamar asistencia. el conductor de la moto biwis en negativa de ser atendido, se pacta por medio de documento ,eximir a la empresa de alguna responsabilidad. En análisis: La imprudencia de ambos conductores (motos). Por no guardar distancia ,pierden capacidad en maniobrar y evitar Daños materiales a propiedad ajena. | V36: NO | W36: SI | X36: SI | Y36: NO | Z36: NO | AA36: Jonathan asistió el evento por celular y adicional hizo firmar | AB36: SI | AC36: https://emprestur-my.sharepoint.com/personal/alejandra_betancur_emprestur_com/Documents/Aplicaciones/Microsoft%20Forms/INFORMACI%C3%93N%20NOVEDAD%20_%20ACCIDENTES%2026042022%20(2)/SOPORTES%20PARA%20ANEXAR/REGISTRO%20FOTOGR%C3%81FICO%20NLW559_anonymous.pdf
A37: 45918.461 | B37: 45918.471 | C37: anónimo | E37: JULIAN DAVID VALENCIA BALLESTEROS | F37: 45918 | G37: 08:38 AM | H37: GTU760 | I37: CHEC | J37: Si | K37: TR2516891 | L37: GILBERTO VARGAS | M37: 10231695 | N37: 3054487899 | O37: Incidente de trabajo (Se pudo presentar una lesión en el trabajador) | P37: Daño Material a Tercero | Q37: Acto inseguro propio (conductor) | R37: N/A | S37: JOHN JAIRO PIEDRAHITA HURTADO y telefono 3137195143 | T37: JOHN JAIRO PIEDRAHITA HURTADO y telefono 3137195143 | U37: Descripción del incidente: El conductor se encontraba realizando maniobra en reversa con el fin de parquear el vehículo y proceder con la carga de material. Durante dicha maniobra, el conductor manifiesta que no observó un vehículo que se encontraba estacionado en el área, percatándose de su presencia únicamente en el momento en que se produjo el golpe. Daños: Se registraron daños en el vehículo parqueado. Posteriormente, el conductor conversó directamente con el funcionario propietario del vehículo afectado, llegando a un acuerdo de reparación por un valor de $1.000.000 COP. | V37: NO | W37: SI | X37: NO | Y37: NO | Z37: SI | AA37: Se estableció comunicación entre las partes involucradas. Se pactó el valor de la compensación de manera directa. | AB37: SI | AC37: https://emprestur-my.sharepoint.com/personal/alejandra_betancur_emprestur_com/Documents/Aplicaciones/Microsoft%20Forms/INFORMACI%C3%93N%20NOVEDAD%20_%20ACCIDENTES%2026042022%20(2)/SOPORTES%20PARA%20ANEXAR/IMG-20250918-WA0011_anonymous.jpg; https://emprestur-my.sharepoint.com/personal/alejandra_betancur_emprestur_com/Documents/Aplicaciones/Microsoft%20Forms/INFORMACI%C3%93N%20NOVEDAD%20_%20ACCIDENTES%2026042022%20(2)/SOPORTES%20PARA%20ANEXAR/IMG-20250918-WA0012_anonymous.jpg; https://emprestur-my.sharepoint.com/personal/alejandra_betancur_emprestur_com/Documents/Aplicaciones/Microsoft%20Forms/INFORMACI%C3%93N%20NOVEDAD%20_%20ACCIDENTES%2026042022%20(2)/SOPORTES%20PARA%20ANEXAR/IMG-20250918-WA0013_anonymous.jpg; https://emprestur-my.sharepoint.com/personal/alejandra_betancur_emprestur_com/Documents/Aplicaciones/Microsoft%20Forms/INFORMACI%C3%93N%20NOVEDAD%20_%20ACCIDENTES%2026042022%20(2)/SOPORTES%20PARA%20ANEXAR/IMG-20250918-WA0014_anonymous.jpg; https://emprestur-my.sharepoint.com/personal/alejandra_betancur_emprestur_com/Documents/Aplicaciones/Microsoft%20Forms/INFORMACI%C3%93N%20NOVEDAD%20_%20ACCIDENTES%2026042022%20(2)/SOPORTES%20PARA%20ANEXAR/IMG-20250918-WA0009_anonymous.jpg; https://emprestur-my.sharepoint.com/personal/alejandra_betancur_emprestur_com/Documents/Aplicaciones/Microsoft%20Forms/INFORMACI%C3%93N%20NOVEDAD%20_%20ACCIDENTES%2026042022%20(2)/SOPORTES%20PARA%20ANEXAR/IMG-20250918-WA0010_anonymous.jpg
A38: 45918.567 | B38: 45918.68 | C38: anónimo | E38: Carlos Franco | F38: 45918 | G38: 6:30 | H38: SNX276 | I38: EPM | J38: Si | K38: SDT. 114927 | L38: SEBASTIAN CUERVO GEORGE | M38: 1041204179 | N38: 3122611347 | O38: Accidente de tránsito y transporte dentro del desarrollo de la labor (Si ocurre en la vía con otros vehículos o con otros actores viales implicados) | P38: Daño Material propio | Q38: Condición insegura | R38: N/A | S38: N/A | T38: N/A | U38: "Venía de Yarumal sólo y recoger un funcionario en Bello para regresar, pero 3 kilómetros después de Don Matías de un momento a otro perdí el control de la camioneta y al evitar que se saliera de la vía y rodara por la manga se fue contra el barranco y volqué de lado. No me pasó nada y salí del vehículo para hacer el reporte y al revisar el piso que estaba mojado por la lluvia, identifiqué que había mucho reguero de combustible lo q probablemente fue la causa de la pérdida del control del vehículo" | V38: SI | W38: SI | X38: SI | Y38: NO | Z38: SI | AA38: Se da la instrucción de llamar a la aseguradora, después de haber sido atendido por la concesión de la vía y policía de carreteras quienes le facilitaron la grúa para traerlo hasta el parque de las aguas en Barbosa donde lo recogía la grúa de la aseguradora quien dejó el vehículo en custodia | AB38: SI | AC38: https://emprestur-my.sharepoint.com/personal/alejandra_betancur_emprestur_com/Documents/Aplicaciones/Microsoft%20Forms/INFORMACI%C3%93N%20NOVEDAD%20_%20ACCIDENTES%2026042022%20(2)/SOPORTES%20PARA%20ANEXAR/WhatsApp%20Image%202025-09-18%20at%2008.02.49_anonymous.jpeg; https://emprestur-my.sharepoint.com/personal/alejandra_betancur_emprestur_com/Documents/Aplicaciones/Microsoft%20Forms/INFORMACI%C3%93N%20NOVEDAD%20_%20ACCIDENTES%2026042022%20(2)/SOPORTES%20PARA%20ANEXAR/6e75ba91-4097-4bbc-89c3-ccadfad8000d_anonymous.jpg; https://emprestur-my.sharepoint.com/personal/alejandra_betancur_emprestur_com/Documents/Aplicaciones/Microsoft%20Forms/INFORMACI%C3%93N%20NOVEDAD%20_%20ACCIDENTES%2026042022%20(2)/SOPORTES%20PARA%20ANEXAR/WhatsApp%20Image%202025-09-18%20at%2008.03.02_anonymous.jpeg; https://emprestur-my.sharepoint.com/personal/alejandra_betancur_emprestur_com/Documents/Aplicaciones/Microsoft%20Forms/INFORMACI%C3%93N%20NOVEDAD%20_%20ACCIDENTES%2026042022%20(2)/SOPORTES%20PARA%20ANEXAR/WhatsApp%20Image%202025-09-18%20at%2008.03.03_anonymous.jpeg; https://emprestur-my.sharepoint.com/personal/alejandra_betancur_emprestur_com/Documents/Aplicaciones/Microsoft%20Forms/INFORMACI%C3%93N%20NOVEDAD%20_%20ACCIDENTES%2026042022%20(2)/SOPORTES%20PARA%20ANEXAR/WhatsApp%20Image%202025-09-18%20at%2008.03.03%20(1)_anonymous.jpeg; https://emprestur-my.sharepoint.com/personal/alejandra_betancur_emprestur_com/Documents/Aplicaciones/Microsoft%20Forms/INFORMACI%C3%93N%20NOVEDAD%20_%20ACCIDENTES%2026042022%20(2)/SOPORTES%20PARA%20ANEXAR/WhatsApp%20Image%202025-09-18%20at%2008.09.28_anonymous.jpeg; https://emprestur-my.sharepoint.com/personal/alejandra_betancur_emprestur_com/Documents/Aplicaciones/Microsoft%20Forms/INFORMACI%C3%93N%20NOVEDAD%20_%20ACCIDENTES%2026042022%20(2)/SOPORTES%20PARA%20ANEXAR/WhatsApp%20Image%202025-09-18%20at%2008.09.27_anonymous.jpeg
A39: 45918.68 | B39: 45918.696 | C39: anónimo | E39: Carlos Franco | F39: 45918 | G39: 9:25 | H39: WNP927 | I39: EPM | J39: Si | K39: SDT. 112071 | L39: DAVID ALEXANDER GOMEZ GALVIS | M39: 98495157 | N39: 3122726717 | O39: Accidente de tránsito y transporte dentro del desarrollo de la labor (Si ocurre en la vía con otros vehículos o con otros actores viales implicados) | P39: Daño Material propio | Q39: Condición insegura | R39: N/A | S39: N/A | T39: N/A | U39: "Iba camino a La Sierra sin funcionarios para regresarme desde allá mañana por la programación que me habían dado y después de Cisneros en el PR 13-6206 en una curva la camioneta sacó la cola y se me fue al barranco la vía estaba muy mojada pero no pude frenar bien. No me pasó nada" | V39: SI | W39: SI | X39: SI | Y39: NO | Z39: SI | AA39: Se da la instrucción de reportar a la policía de carreteras quienes llegan con la ambulancia y la grúa de la concesión para llevar el vehículo hasta Cisneros y lo pueda recoger la otra grúa que lo traiga a Medellín | AB39: SI | AC39: https://emprestur-my.sharepoint.com/personal/alejandra_betancur_emprestur_com/Documents/Aplicaciones/Microsoft%20Forms/INFORMACI%C3%93N%20NOVEDAD%20_%20ACCIDENTES%2026042022%20(2)/SOPORTES%20PARA%20ANEXAR/WhatsApp%20Image%202025-09-18%20at%2013.56.52_anonymous.jpeg; https://emprestur-my.sharepoint.com/personal/alejandra_betancur_emprestur_com/Documents/Aplicaciones/Microsoft%20Forms/INFORMACI%C3%93N%20NOVEDAD%20_%20ACCIDENTES%2026042022%20(2)/SOPORTES%20PARA%20ANEXAR/WhatsApp%20Image%202025-09-18%20at%2013.56.54_anonymous.jpeg; https://emprestur-my.sharepoint.com/personal/alejandra_betancur_emprestur_com/Documents/Aplicaciones/Microsoft%20Forms/INFORMACI%C3%93N%20NOVEDAD%20_%20ACCIDENTES%2026042022%20(2)/SOPORTES%20PARA%20ANEXAR/WhatsApp%20Image%202025-09-18%20at%2013.56.56_anonymous.jpeg; https://emprestur-my.sharepoint.com/personal/alejandra_betancur_emprestur_com/Documents/Aplicaciones/Microsoft%20Forms/INFORMACI%C3%93N%20NOVEDAD%20_%20ACCIDENTES%2026042022%20(2)/SOPORTES%20PARA%20ANEXAR/WhatsApp%20Image%202025-09-18%20at%2013.56.56%20(1)_anonymous.jpeg; https://emprestur-my.sharepoint.com/personal/alejandra_betancur_emprestur_com/Documents/Aplicaciones/Microsoft%20Forms/INFORMACI%C3%93N%20NOVEDAD%20_%20ACCIDENTES%2026042022%20(2)/SOPORTES%20PARA%20ANEXAR/WhatsApp%20Image%202025-09-18%20at%2013.56.57_anonymous.jpeg
A40: 45923.341 | B40: 45923.472 | C40: anónimo | E40: Adriana Castillo | F40: 45922 | G40: 18:56 p.m. | H40: FLOTA PROPIA SNU647 | I40: JARDIN BOTÁNICO | J40: No | K40: N/A | L40: YEISON ACEVEDO ARIAS | M40: 1007567428 | N40: 3052001475 | O40: Accidente de tránsito (se produce en las vías y fuera de horario laboral) | P40: Daño Material propio | Q40: Acto inseguro de Tercero | R40: N/A | S40: N/A | T40: No cuenta con datos | U40: Me permito informar que el día 22 de Septiembre a las 5:57 p.m., el conductor C.C. 1007567428 Yeison Acevedo Arias, se encontraba desplazándose para su lugar de residencia en Bello, cuando se encontraba en la Carrera 52 con calle 55 en Bello, iba atravesando la calle y había un señor de una moto montándose en un andén en contravía para devolverse, más sin embargo tenía una parte de la moto sobre la vía a lo que el conductor se dispuso a pitarle y esquivar la moto para continuar el trayecto, en el semáforo el señor de la moto se le hizo al costado del copiloto y empezó a golpear las ventanas, y lo estaba insultando, el conductor bajó un poco la ventana para hablar con el señor e intentar mediar con él, sin embargo el señor siguió golpeando y metiendo el brazo para intentar golpearlo, cuando cambió el semáforo el conductor avanzó un poco colocó estacionarias y el señor recogió la moto y la colocó detrás del vehículo y continuó golpeando el carro, el conductor indica que colocó el freno de emergencia y que esta no se activó sino que el carro se rodó e hizo caer la moto, y con esta situación el señor terminó de ofuscarse y le siguió golpeando el carro tumbó el retrovisor del conductor, el hundió el capó, le dañó una direccional de guardabarros. El conductor en todo este tiempo intentó comunicarse con el cuadrante más sin embargo no hicieron presencia en el sitio, y el conductor se quedó esperando, y el conductor llamó a una persona conocida como los de la vuelta para que lo pudiera respaldar, el hizo presencia en el sitio para mediar la situación y calmar al conductor de la moto, le indicaron que el conductor tenia que responder por los daños de la moto, y que él señor de la moto tenía que responder por los daños del vehículo, pero que tenía que ser cotizado los daños del vehículo en un taller de Bello, pero el conductor les indicó que el vehículo es de una empresa y es donde la empresa indique que debe realizarse el arreglo. | V40: NO | W40: NO | X40: SI | Y40: NO | Z40: NO | AA40: Se toma la versión inicial, y se le indica llegar al parqueadero a traer el vehículo. | AB40: SI | AC40: https://emprestur-my.sharepoint.com/personal/alejandra_betancur_emprestur_com/Documents/Aplicaciones/Microsoft%20Forms/INFORMACI%C3%93N%20NOVEDAD%20_%20ACCIDENTES%2026042022%20(2)/SOPORTES%20PARA%20ANEXAR/REPORTE%20GPS%20SNU647_anonymous.pdf
A41: 45926.564 | B41: 45926.572 | C41: anónimo | E41: Carlos Franco | F41: 45922 | G41: 13:20 | H41: LKP040 | I41: EPM | J41: Si | K41: SDT. 115657 | L41: LUIS FERNANDO GAVIRIA ESPINOSA | M41: 15321769 | N41: 3017500902 | O41: Accidente de tránsito y transporte dentro del desarrollo de la labor (Si ocurre en la vía con otros vehículos o con otros actores viales implicados) | P41: Daño Material a Tercero | Q41: Acto inseguro propio (conductor) | R41: N/A | S41: N/A | T41: N/A | U41: "tuve una colisión con otro vehículo, pero gracias a Dios solo fueron latas y el carro está trabajando normal, ya reportamos el incidente a la aseguradora. Esto fue en la Vereda El Machete entre la 1 y 1:30 pm subiendo hacia Guadalupe III, en una curva habían unas piedras, yo me abrí a la izquierda y en este momento bajaba un vehículo con el cual tuve la colisión." | V41: NO | W41: NO | X41: NO | Y41: NO | Z41: NO | AA41: Se hace reporte extemporáneo ya que el conductor no reportó el incidente y por esto tampoco hubo acciones o se dieron indicaciones en el momento de lo sucedido | AB41: SI | AC41: https://emprestur-my.sharepoint.com/personal/alejandra_betancur_emprestur_com/Documents/Aplicaciones/Microsoft%20Forms/INFORMACI%C3%93N%20NOVEDAD%20_%20ACCIDENTES%2026042022%20(2)/SOPORTES%20PARA%20ANEXAR/LKP040-FOTO_anonymous.jpg; https://emprestur-my.sharepoint.com/personal/alejandra_betancur_emprestur_com/Documents/Aplicaciones/Microsoft%20Forms/INFORMACI%C3%93N%20NOVEDAD%20_%20ACCIDENTES%2026042022%20(2)/SOPORTES%20PARA%20ANEXAR/LKP040-FOTO2_anonymous.jpg; https://emprestur-my.sharepoint.com/personal/alejandra_betancur_emprestur_com/Documents/Aplicaciones/Microsoft%20Forms/INFORMACI%C3%93N%20NOVEDAD%20_%20ACCIDENTES%2026042022%20(2)/SOPORTES%20PARA%20ANEXAR/LKP040-FOTO3_anonymous.jpg; https://emprestur-my.sharepoint.com/personal/alejandra_betancur_emprestur_com/Documents/Aplicaciones/Microsoft%20Forms/INFORMACI%C3%93N%20NOVEDAD%20_%20ACCIDENTES%2026042022%20(2)/SOPORTES%20PARA%20ANEXAR/WhatsApp%20Image%202025-09-23%20at%2009.02.22_anonymous.jpeg
... A48: 45945.868 | B48: 45945.874 | C48: anónimo | E48: JHON HAWER MURCIA | F48: 45945 | G48: 9:32 AM | H48: KTN382 | I48: FUNDACION | J48: Si | K48: SE020842 | L48: LEONARDO VILLEGAS | M48: 96186728 | N48: 3102019074 | O48: Accidente de tránsito y transporte dentro del desarrollo de la labor (Si ocurre en la vía con otros vehículos o con otros actores viales implicados) | P48: Daño Material propio | Q48: Acto inseguro de Tercero | R48: N/A | S48: Cristian Morales - 3102019074 | T48: N/A | U48: EL VEHICULO PASA POR LA DERECHA Y GOLPEA EL VEHICULO EN LA PARTE DELANTERA | V48: NO | W48: SI | X48: NO | Y48: NO | Z48: NO | AA48: INDICARLE AL CONDUCTOR QUE CONCILIARA CON EL CONDUCTOR DEL OTRO VEHICULO POR LO QUE FUE SOLO LATAS | AB48: SI | AC48: https://emprestur-my.sharepoint.com/personal/alejandra_betancur_emprestur_com/Documents/Aplicaciones/Microsoft%20Forms/INFORMACI%C3%93N%20NOVEDAD%20_%20ACCIDENTES%2026042022%20(2)/SOPORTES%20PARA%20ANEXAR/WhatsApp%20Image%202025-10-15%20at%209.32.35%20AM%20(1)_anonymous.jpeg; https://emprestur-my.sharepoint.com/personal/alejandra_betancur_emprestur_com/Documents/Aplicaciones/Microsoft%20Forms/INFORMACI%C3%93N%20NOVEDAD%20_%20ACCIDENTES%2026042022%20(2)/SOPORTES%20PARA%20ANEXAR/WhatsApp%20Image%202025-10-15%20at%209.32.35%20AM_anonymous.jpeg; https://emprestur-my.sharepoint.com/personal/alejandra_betancur_emprestur_com/Documents/Aplicaciones/Microsoft%20Forms/INFORMACI%C3%93N%20NOVEDAD%20_%20ACCIDENTES%2026042022%20(2)/SOPORTES%20PARA%20ANEXAR/WhatsApp%20Image%202025-10-15%20at%209.32.36%20AM%20(1)_anonymous.jpeg; https://emprestur-my.sharepoint.com/personal/alejandra_betancur_emprestur_com/Documents/Aplicaciones/Microsoft%20Forms/INFORMACI%C3%93N%20NOVEDAD%20_%20ACCIDENTES%2026042022%20(2)/SOPORTES%20PARA%20ANEXAR/WhatsApp%20Image%202025-10-15%20at%209.32.36%20AM%20(2)_anonymous.jpeg; https://emprestur-my.sharepoint.com/personal/alejandra_betancur_emprestur_com/Documents/Aplicaciones/Microsoft%20Forms/INFORMACI%C3%93N%20NOVEDAD%20_%20ACCIDENTES%2026042022%20(2)/SOPORTES%20PARA%20ANEXAR/WhatsApp%20Image%202025-10-15%20at%209.32.36%20AM_anonymous.jpeg
A49: 45950.565 | B49: 45950.574 | C49: anónimo | E49: DIANA PATRICIA ALVAREZ PEREZ | F49: 45950 | G49: 12:42 | H49: LKK246 | I49: ISAGEN | J49: Si | K49: N/A | L49: IVAN GARZON | M49: 70162911 | N49: 321 2584220 | O49: Accidente Ambienta (afectación al ecosistema por derrames, impacto con animal en la vía) | P49: Afectación al medio ambiente | Q49: Condición insegura | R49: Tercero (Comunidad) | S49: N/A | T49: MARINA - 3136776060 | U49: El conductor informa que no se dio cuenta que el perro estaba cerca, el salía en el vehículo hacia la central calderas cuando escuchó el chillido, ´pero no sabe donde estaba situado el perro. el conductor se hace presente en el sitio nuevamente después de terminar el recorrido con los usuarios y la señora le dice que se puede retirar que no hay inconveniente, que cualquier cosa le avisa. | V49: NO | W49: SI | X49: NO | Y49: NO | Z49: SI | AA49: Me comuniqué con la dueña el perro, la señora Marina de alcatraz, ella me indica que fue un incidente sin culpa, que el conductor no vio al perro, le indicó a la señora si lo llevamos al veterinario y me dice que no, que el veterinario le mando unas gotas y que a las 4p, ira a verlo, estaremos atentos a la evolución. | AB49: NO
A50: 45957.341 | B50: 45957.364 | C50: anónimo | E50: Alexander López Orozco | F50: 45953 | G50: 13:07 | H50: TTR852 | I50: SUN COLOMBIA | J50: Si | K50: N/A | L50: ALEXANDER PEÑA RESTREPO | M50: 9923838 | N50: 3172825740 | O50: Incidente de trabajo (Se pudo presentar una lesión en el trabajador) | P50: Daño Material propio | Q50: Acto inseguro de Tercero | R50: N/A | S50: N/A | T50: N/A | U50: Me permito informar un incidente ocurrido el día de hoy con el vehículo de placas TTR852, el cual se encuentra prestando servicios para el cliente Sun Colombia. Durante el desplazamiento hacia la vereda Alto de la Cruz en Villamaría, Caldas, el vehículo presentó un inconveniente debido a la topografía del terreno, registrando únicamente un daño en el bomper delantero. El conductor y el personal que lo acompañaban no presentaron ningún tipo de afectación o incidente personal. Se realizó la retroalimentación al conductor, recordándole que, en futuras ocasiones, debe verificar previamente si el acceso y las vías se encuentran en condiciones adecuadas para el tránsito normal del vehículo. | V50: NO | W50: NO | X50: NO | Y50: NO | Z50: NO | AA50: No se presentaron lesiones al personal transportado, únicamente se registró un daño en el bomper delantero del vehículo. Se realiza retroalimentación al conductor, indicándole que, para futuras ocasiones, debe revisar o indagar previamente si las vías cuentan con un acceso adecuado y en condiciones apropiadas para poder transitar. | AB50: SI | AC50: https://emprestur-my.sharepoint.com/personal/alejandra_betancur_emprestur_com/Documents/Aplicaciones/Microsoft%20Forms/INFORMACI%C3%93N%20NOVEDAD%20_%20ACCIDENTES%2026042022%20(2)/SOPORTES%20PARA%20ANEXAR/WhatsApp%20Image%202025-10-23%20at%201.39.35%20PM%20(1)_anonymous.jpeg; https://emprestur-my.sharepoint.com/personal/alejandra_betancur_emprestur_com/Documents/Aplicaciones/Microsoft%20Forms/INFORMACI%C3%93N%20NOVEDAD%20_%20ACCIDENTES%2026042022%20(2)/SOPORTES%20PARA%20ANEXAR/WhatsApp%20Image%202025-10-23%20at%201.39.35%20PM_anonymous.jpeg; https://emprestur-my.sharepoint.com/personal/alejandra_betancur_emprestur_com/Documents/Aplicaciones/Microsoft%20Forms/INFORMACI%C3%93N%20NOVEDAD%20_%20ACCIDENTES%2026042022%20(2)/SOPORTES%20PARA%20ANEXAR/WhatsApp%20Image%202025-10-23%20at%201.12.02%20PM_anonymous.jpeg; https://emprestur-my.sharepoint.com/personal/alejandra_betancur_emprestur_com/Documents/Aplicaciones/Microsoft%20Forms/INFORMACI%C3%93N%20NOVEDAD%20_%20ACCIDENTES%2026042022%20(2)/SOPORTES%20PARA%20ANEXAR/WhatsApp%20Image%202025-10-23%20at%201.12.03%20PM_anonymous.jpeg; https://emprestur-my.sharepoint.com/personal/alejandra_betancur_emprestur_com/Documents/Aplicaciones/Microsoft%20Forms/INFORMACI%C3%93N%20NOVEDAD%20_%20ACCIDENTES%2026042022%20(2)/SOPORTES%20PARA%20ANEXAR/WhatsApp%20Image%202025-10-23%20at%201.12.04%20PM%20(1)_anonymous.jpeg; https://emprestur-my.sharepoint.com/personal/alejandra_betancur_emprestur_com/Documents/Aplicaciones/Microsoft%20Forms/INFORMACI%C3%93N%20NOVEDAD%20_%20ACCIDENTES%2026042022%20(2)/SOPORTES%20PARA%20ANEXAR/WhatsApp%20Image%202025-10-23%20at%201.12.04%20PM_anonymous.jpeg; https://emprestur-my.sharepoint.com/personal/alejandra_betancur_emprestur_com/Documents/Aplicaciones/Microsoft%20Forms/INFORMACI%C3%93N%20NOVEDAD%20_%20ACCIDENTES%2026042022%20(2)/SOPORTES%20PARA%20ANEXAR/GPS%20TTR852%2023-10-2025_anonymous.jpg
A51: 45961.658 | B51: 45961.696 | C51: anónimo | E51: DAYHANA SOSSA GIRALDO | F51: 45960 | G51: 12:00 | H51: FVY742 | I51: CAH | J51: Si | K51: 1238 | L51: HERNANDEZ MIRANDA CARLOS ALBERTO | M51: 1042090113 | N51: 3218549625 | O51: Accidente de trabajo (Empleado de Emprestur Lesionado) | P51: Afectación a Personas (lesionados) | Q51: Condición insegura | R51: Conductor y/o Empleado | S51: N/A | T51: N/A | U51: El propietario del vehículo me manifiesta que el conductor tuvo un microsueño ocasionado el accidente | V51: SI | W51: SI | X51: SI | Y51: SI | Z51: SI | AA51: Me comunique inmediatamente con SST | AB51: SI
A52: 45962.508 | B52: 45962.529 | C52: anónimo | E52: JOHN FREDY CALLE RESTREPO | F52: 45961 | G52: 15:10 HORAS | H52: JYO995 | I52: ISAGEN | J52: Si | K52: 1 | L52: HENAO ROJAS OSCAR JAVIER | M52: 1128624260 | N52: 3146389269 | O52: Accidente de tránsito y transporte dentro del desarrollo de la labor (Si ocurre en la vía con otros vehículos o con otros actores viales implicados) | P52: Daño Material propio | Q52: Condición insegura | R52: N/A | S52: NO HUBO LESIONADOS. ESTABAN EN EL VEHIUCLO LOS USUARIOS ISAGEN CLARA PEREZ cel 3104562182 Y DIANA CAMPOS cel 3158160214 | T52: EL PROPIETARIO DEL MOTO CARGUERO NO QUISO DAR DATOS Y SE RETIRO DEL SITIO YA QUE NO HABIA AFECTACION EN SU VEHÍCULO | U52: El conductor reporta que siendo las 15:05 horas aproximadamente del dia 31 de octubre cuando se desplazaba en el Municipio de la Dorada sector conocido como Punto los Andes estaba llegando a encontrarse con el Masivo de Miel a Medellín para entregar a las usuarias Diana Campos y Clara Pérez de ISAGEN, llegando al sitio baja la velocidad ya que hay un reductor de velocidad para posteriormente ingresar a la bahía donde dejaría a las usuarias, delante del vehículo va un moto carguero con dos personas a bordo. Después del reductor de velocidad el conductor Oscar se dispone a realizar maniobra para orillarse a mano derecha para ingresar a la bahía donde se estaciona el masivo, se cerciora que no viniera vehículo (motocicleta) por su lado derecho y en ese instante de manera repentina el moto carguero frena generando que el conductor Oscar lo golpee con la parte delantera izquierda de la camioneta a la parte trasera derecha del moto carguero, el conductor del moto carguero manifiesta que freno repentinamente a causa de evitar caer en un hueco de la vía. Luego de verificar que las usuarias no estuvieran lesionadas, desciende del vehículo para verificar como estaban las personas del moto carguero pero manifestaron no haber sufrido tampoco ningún golpe. Las usuarias se desplazaron para abordar el bus del Masivo NNN253 el cual en ese momento también llego al punto. Luego de ayudarles con las maletas se dispuso a hablar con el propietario del moto carguero el cual reviso su vehículo y manifestó que como no le había pasado nada a su vehículo no se podía quedar allí porque no podía perder un compromiso que tenia de llevar unas cosas y procedió a retirarse del sitio sin permitir tomarle datos. | V52: NO | W52: SI | X52: SI | Y52: NO | Z52: SI | AA52: LLamé a Daniela SST emprestur, a Jorge Correa Coordinador Líder, y Gustavo jefe de flota propia | AB52: SI | AC52: https://emprestur-my.sharepoint.com/personal/alejandra_betancur_emprestur_com/Documents/Aplicaciones/Microsoft%20Forms/INFORMACI%C3%93N%20NOVEDAD%20_%20ACCIDENTES%2026042022%20(2)/SOPORTES%20PARA%20ANEXAR/WhatsApp%20Image%202025-10-31%20at%203.45.58%20PM_anonymous.jpeg; https://emprestur-my.sharepoint.com/personal/alejandra_betancur_emprestur_com/Documents/Aplicaciones/Microsoft%20Forms/INFORMACI%C3%93N%20NOVEDAD%20_%20ACCIDENTES%2026042022%20(2)/SOPORTES%20PARA%20ANEXAR/WhatsApp%20Image%202025-10-31%20at%203.45.57%20PM_anonymous.jpeg; https://emprestur-my.sharepoint.com/personal/alejandra_betancur_emprestur_com/Documents/Aplicaciones/Microsoft%20Forms/INFORMACI%C3%93N%20NOVEDAD%20_%20ACCIDENTES%2026042022%20(2)/SOPORTES%20PARA%20ANEXAR/WhatsApp%20Image%202025-10-31%20at%203.45.56%20PM%20(1)_anonymous.jpeg; https://emprestur-my.sharepoint.com/personal/alejandra_betancur_emprestur_com/Documents/Aplicaciones/Microsoft%20Forms/INFORMACI%C3%93N%20NOVEDAD%20_%20ACCIDENTES%2026042022%20(2)/SOPORTES%20PARA%20ANEXAR/WhatsApp%20Image%202025-10-31%20at%203.45.56%20PM_anonymous.jpeg; https://emprestur-my.sharepoint.com/personal/alejandra_betancur_emprestur_com/Documents/Aplicaciones/Microsoft%20Forms/INFORMACI%C3%93N%20NOVEDAD%20_%20ACCIDENTES%2026042022%20(2)/SOPORTES%20PARA%20ANEXAR/WhatsApp%20Image%202025-10-31%20at%203.45.55%20PM_anonymous.jpeg; https://emprestur-my.sharepoint.com/personal/alejandra_betancur_emprestur_com/Documents/Aplicaciones/Microsoft%20Forms/INFORMACI%C3%93N%20NOVEDAD%20_%20ACCIDENTES%2026042022%20(2)/SOPORTES%20PARA%20ANEXAR/WhatsApp%20Image%202025-11-01%20at%207.50.57%20AM%20(1)_anonymous.jpeg; https://emprestur-my.sharepoint.com/personal/alejandra_betancur_emprestur_com/Documents/Aplicaciones/Microsoft%20Forms/INFORMACI%C3%93N%20NOVEDAD%20_%20ACCIDENTES%2026042022%20(2)/SOPORTES%20PARA%20ANEXAR/WhatsApp%20Image%202025-11-01%20at%207.50.57%20AM_anonymous.jpeg; https://emprestur-my.sharepoint.com/personal/alejandra_betancur_emprestur_com/Documents/Aplicaciones/Microsoft%20Forms/INFORMACI%C3%93N%20NOVEDAD%20_%20ACCIDENTES%2026042022%20(2)/SOPORTES%20PARA%20ANEXAR/WhatsApp%20Image%202025-11-01%20at%207.50.56%20AM_anonymous.jpeg
A53: 45965.607 | B53: 45965.611 | C53: anónimo | E53: DAYHANA SOSSA | F53: 45965 | G53: 2:30 PM | H53: LKK422 | I53: CAH | J53: Si | K53: 1245 | L53: JUAN MANUEL MADRID | M53: 1047996959 | N53: 3147919991 | O53: Accidente de tránsito y transporte dentro del desarrollo de la labor (Si ocurre en la vía con otros vehículos o con otros actores viales implicados) | P53: Daño Material a Tercero | Q53: Acto inseguro de Tercero | R53: N/A | S53: N/A | T53: N/A | U53: El conductor informa que un tercero en medio de un despiste le choca la parte trasera de su vehículo | V53: SI | W53: SI | X53: SI | Y53: SI | Z53: SI | AA53: informe de manera inmediata al área de SST | AB53: SI | AC53: https://emprestur-my.sharepoint.com/personal/alejandra_betancur_emprestur_com/Documents/Aplicaciones/Microsoft%20Forms/INFORMACI%C3%93N%20NOVEDAD%20_%20ACCIDENTES%2026042022%20(2)/SOPORTES%20PARA%20ANEXAR/WhatsApp%20Image%202025-11-04%20at%202.32.12%20PM_anonymous.jpeg
A54: 45968.306 | B54: 45968.318 | C54: anónimo | E54: JORGE IVAN CORREA PEREZ | F54: 45967 | G54: 15:54 | H54: GTY556 | I54: ISAGEN | J54: Si | K54: RECORRIDO FIJO DE CARGA | L54: YUNIER ALEXANDER ATEHORTUA ZAPATA | M54: 1146434995 | N54: 319 3036406 | O54: Accidente de tránsito y transporte dentro del desarrollo de la labor (Si ocurre en la vía con otros vehículos o con otros actores viales implicados) | P54: Daño Material propio | Q54: Acto inseguro propio (conductor) | R54: N/A | S54: N/A | T54: N/A | U54: El día de ayer jueves 06 de noviembre a las 15:54 el conductor Yunier Alexander Atehortúa Zapata me llama para informarme que habían acabado de volcarse en el Camión de placas GTY556, cuando transitaban por la Ruta del Sol, entre el Municipio de Puerto Salgar (Cundinamarca) y el sector conocido como Puerto Libre (Rionegrito). Me dice que tanto él como Cristian Andrés Taborda Taborda (quien lo acompañaba en el recorrido) resultaron ilesos, que sólo se presentaron daños materiales. El vehículo venía vacío pues acabada de descargar materiales en la Central Hidroeléctrica MIEL I (ISAGEN). Se le informa a Daniela Vergara (Profesional SST del contrato) y al Señor Jonathan Giraldo (Director Flota Propia), lo mismo que a Juan Pablo Gallo (GPS y CCTV) para las gestiones correspondientes de cada uno según su rol. Adicionalmente se mantiene el contacto con los conductores durante la maniobra de izaje del vehículo y el traslado hasta su sitio de descanso a las 19:30 horas. Dado que el vehículo no tuvo afectaciones mecánicas, se toma la decisión de que el recorrido hacia Medellín se reinicie el día 07 de noviembre. A continuación, la versión del conductor (se adjuntan registro fotográfico enviado por WhatsApp): “Para reportar la novedad del siniestro del vehículo GTY556 siendo las 03:50 pm del 06/11/2025 veníamos el compañero Cristian Taborda y mi persona Yunier Atehortúa desde Norcasia luego de descargar materiales en la central MIEL venia conduciendo a uno velocidad moderada por el carril derecho en la ruta del sol entre Puerto Salgar y Puerto Libre sentido Sur - Norte (vía la cual en el momento no está demarcada por pavimentación) me aproximé mucho a la berma, razón por lo cual me fui saliendo de la vía y al intentar recuperar el carril perdí el control del vehículo, lo cual ocasionó el volcamiento del mismo. Afortunadamente sin lesionados ni daños a terceros, Inmediatamente procedemos a informar a los Jefes inmediatos y a la aseguradora con la cual no pusimos comunicarnos por mala señal. Tuvimos acompañamiento de la policía de carretera y apoyo de la Concesión Vial parar el vehículo y revisión médica en la cual resultamos sin lesiones. Se realiza material fotográfico para adjuntar a la versión de lo sucedido.” Quedo atento a cualquier requerimiento adicional que tengan. Feliz día, Jorge Iván Correa Pérez Coordinador Líder Contrato ISAGEN | V54: NO | W54: SI | X54: SI | Y54: NO | Z54: SI | AA54: Acompañamiento telefónico durante las labores de atención y valoración de los conductores, al igual que durante la maniobra de izaje del vehículo hasta las 19:30 cuando los conductores se reportan en su sitio de descanso. Dado que el vehículo no sufre afectaciones mecánicas, se decide que continúen el recorrido al día siguiente (07 de noviembre). | AB54: SI | AC54: https://emprestur-my.sharepoint.com/personal/alejandra_betancur_emprestur_com/Documents/Aplicaciones/Microsoft%20Forms/INFORMACI%C3%93N%20NOVEDAD%20_%20ACCIDENTES%2026042022%20(2)/SOPORTES%20PARA%20ANEXAR/Evento_GTY556_06_Noviembre_2025%20-%204_anonymous.jpeg; https://emprestur-my.sharepoint.com/personal/alejandra_betancur_emprestur_com/Documents/Aplicaciones/Microsoft%20Forms/INFORMACI%C3%93N%20NOVEDAD%20_%20ACCIDENTES%2026042022%20(2)/SOPORTES%20PARA%20ANEXAR/Evento_GTY556_06_Noviembre_2025%20-%203_anonymous.jpeg; https://emprestur-my.sharepoint.com/personal/alejandra_betancur_emprestur_com/Documents/Aplicaciones/Microsoft%20Forms/INFORMACI%C3%93N%20NOVEDAD%20_%20ACCIDENTES%2026042022%20(2)/SOPORTES%20PARA%20ANEXAR/Evento_GTY556_06_Noviembre_2025%20-%202_anonymous.jpeg; https://emprestur-my.sharepoint.com/personal/alejandra_betancur_emprestur_com/Documents/Aplicaciones/Microsoft%20Forms/INFORMACI%C3%93N%20NOVEDAD%20_%20ACCIDENTES%2026042022%20(2)/SOPORTES%20PARA%20ANEXAR/Evento_GTY556_06_Noviembre_2025%20-%201_anonymous.jpeg
A55: 45972.252 | B55: 45972.272 | C55: anónimo | E55: JHON HAWER MURCIA OROZCO | F55: 45972 | G55: 4:30 AM | H55: SNW288 | I55: SURA | J55: Si | K55: SE026046 | L55: GUILLERMO TAMAYO | M55: 71315786 | N55: 3192478944 | O55: Incidente de trabajo (Se pudo presentar una lesión en el trabajador) | P55: Daño Material propio | Q55: Condición insegura | R55: N/A | S55: JADER ANDRES NIEVES PEREZ | T55: 3148473441 | U55: me indica el conductor a las 4:30 am que al subir la loma en el barrio PARIS en la dirección CALLE 102 CON 82F que al voltear a la izquierda el carro pierde estabilidad y se desliza ya que no tenia agarre una de las llantas delanteras lo cual el vehículo se desliza. no hubo lesionados | V55: SI | W55: SI | X55: NO | Y55: NO | Z55: SI | AA55: darle indicaciones al conductor de como proceder en el evento ocurrido | AB55: SI | AC55: https://emprestur-my.sharepoint.com/personal/alejandra_betancur_emprestur_com/Documents/Aplicaciones/Microsoft%20Forms/INFORMACI%C3%93N%20NOVEDAD%20_%20ACCIDENTES%2026042022%20(2)/SOPORTES%20PARA%20ANEXAR/WhatsApp%20Image%202025-11-11%20at%204.37.36%20AM_anonymous.jpeg; https://emprestur-my.sharepoint.com/personal/alejandra_betancur_emprestur_com/Documents/Aplicaciones/Microsoft%20Forms/INFORMACI%C3%93N%20NOVEDAD%20_%20ACCIDENTES%2026042022%20(2)/SOPORTES%20PARA%20ANEXAR/WhatsApp%20Video%202025-11-11%20at%204.37.56%20AM_anonymous.mp4; https://emprestur-my.sharepoint.com/personal/alejandra_betancur_emprestur_com/Documents/Aplicaciones/Microsoft%20Forms/INFORMACI%C3%93N%20NOVEDAD%20_%20ACCIDENTES%2026042022%20(2)/SOPORTES%20PARA%20ANEXAR/WhatsApp%20Image%202025-11-11%20at%205.20.35%20AM_anonymous.jpeg; https://emprestur-my.sharepoint.com/personal/alejandra_betancur_emprestur_com/Documents/Aplicaciones/Microsoft%20Forms/INFORMACI%C3%93N%20NOVEDAD%20_%20ACCIDENTES%2026042022%20(2)/SOPORTES%20PARA%20ANEXAR/WhatsApp%20Image%202025-11-11%20at%205.17.57%20AM_anonymous.jpeg; https://emprestur-my.sharepoint.com/personal/alejandra_betancur_emprestur_com/Documents/Aplicaciones/Microsoft%20Forms/INFORMACI%C3%93N%20NOVEDAD%20_%20ACCIDENTES%2026042022%20(2)/SOPORTES%20PARA%20ANEXAR/WhatsApp%20Image%202025-11-11%20at%205.17.48%20AM_anonymous.jpeg; https://emprestur-my.sharepoint.com/personal/alejandra_betancur_emprestur_com/Documents/Aplicaciones/Microsoft%20Forms/INFORMACI%C3%93N%20NOVEDAD%20_%20ACCIDENTES%2026042022%20(2)/SOPORTES%20PARA%20ANEXAR/WhatsApp%20Image%202025-11-10%20at%205.07.50%20PM_anonymous.jpeg
A56: 45972.412 | B56: 45972.419 | C56: anónimo | E56: Carlos Franco | F56: 45954 | G56: 15:00 horas más o menos | H56: NNN124 | I56: EPM | J56: Si | K56: 103433 | L56: JORGE ALEJANDRO LOPEZ GUTIERREZ | M56: 98567367 | N56: 3006125946 | O56: Incidente de trabajo (Se pudo presentar una lesión en el trabajador) | P56: Afectación a Personas (lesionados) | Q56: Acto inseguro propio (conductor) | R56: N/A | S56: N/A | T56: N/A | U56: "bajándome del carro me apoyé en el estribo para bajarme y me lisé, como q tuve un movimiento de rodilla maluco" | V56: NO | W56: NO | X56: NO | Y56: NO | Z56: SI | AA56: Se le dan instrucciones de reportar a SST para que reciba instrucciones | AB56: NO
A57: 45972.42 | B57: 45972.438 | C57: anónimo | E57: Carlos Franco | F57: 45955 | G57: 11:00 | H57: JYN546 | I57: EPM | J57: Si | K57: 103069 | L57: OMAR DE JESUS RIOS RESTREPO | M57: 15507579 | N57: 3223804432 | O57: Incidente de trabajo (Se pudo presentar una lesión en el trabajador) | P57: Afectación a Personas (lesionados) | Q57: Condición insegura | R57: Conductor y/o Empleado | S57: N/A | T57: N/A | U57: "me tocó consultar por unos granos que me salieron en el cuerpo y se están llenando de pus. Me dijeron que podía ser Leishmaniasis" | V57: SI | W57: NO | X57: NO | Y57: NO | Z57: SI | AA57: Se reporta novedad con SST ya que el conductor fue hospitalizado por confirmación de diagnóstico por Leishmaniasis | AB57: SI
A58: 45980.603 | B58: 45980.608 | C58: anónimo | E58: Dayhana sossa | F58: 45980 | G58: 9:40 am | H58: LKO886 | I58: CAH | J58: Si | K58: 1754 | L58: GUSTAVO ALONSO CORREA | M58: 98495157 | N58: 312 2726717 | O58: Accidente de trabajo (Empleado de Emprestur Lesionado) | P58: Afectación a Personas (lesionados) | Q58: Acto inseguro propio (conductor) | R58: Conductor y/o Empleado | S58: N/A | T58: N/A | U58: Cerrando la puerta del vehículo se le quedo el dedo allí | V58: SI | W58: SI | X58: SI | Y58: SI | Z58: SI | AA58: Pase el reporte al área encargada | AB58: SI | AC58: https://emprestur-my.sharepoint.com/personal/alejandra_betancur_emprestur_com/Documents/Aplicaciones/Microsoft%20Forms/INFORMACI%C3%93N%20NOVEDAD%20_%20ACCIDENTES%2026042022%20(2)/SOPORTES%20PARA%20ANEXAR/WhatsApp%20Image%202025-11-19%20at%209.37.08%20AM_anonymous.jpeg
A59: 45987.625 | B59: 45987.633 | C59: anónimo | E59: DAYHANA SOSSA | F59: 45962 | G59: N/A | H59: SNV955 | I59: CAH | J59: Si | K59: 1754 | L59: Kevin Esteban Aguirre Torres | M59: 1115083755 | N59: 3187000706 | O59: Accidente de trabajo (Empleado de Emprestur Lesionado) | P59: Daño Material propio | Q59: Acto inseguro propio (conductor) | R59: N/A | S59: N/A | T59: N/A | U59: N/A | V59: SI | W59: SI | X59: SI | Y59: SI | Z59: SI | AA59: N/A | AB59: SI
A60: 45988.388 | B60: 45988.419 | C60: anónimo | E60: Alejandra Faisuri Botero | F60: 45988 | G60: 8:20 am | H60: JTZ891 | I60: CHEC Pasajeros | J60: Si | K60: TR2519193 | L60: Héctor Rodrigo Nieto Gallego | M60: 10280691 | N60: 3136555037 | O60: Accidente de tránsito y transporte dentro del desarrollo de la labor (Si ocurre en la vía con otros vehículos o con otros actores viales implicados) | P60: Daño Material a Tercero | Q60: Acto inseguro de Tercero | R60: N/A | S60: JOSE LEONARDO ACEVEDO JARAMILLO | T60: 3127151357 | U60: El conductor informa que una tractomula estaba ingresando a una bodega de Coordinadora. Debido a esta maniobra, el conductor redujo la velocidad y se detuvo para permitir el ingreso del vehículo pesado. En ese momento, el vehículo que venía detrás no alcanzó a frenar a tiempo y colisionó por la parte trasera. A causa del impacto, el vehículo del conductor afectado fue impulsado hacia adelante, golpeando a su vez al vehículo que tenía al frente. | V60: SI | W60: SI | X60: SI | Y60: NO | Z60: SI | AA60: Se realizó el seguimiento al conductor, verificando que todos los involucrados se encontraran en buen estado. Posteriormente, se le informó que debía realizar el reporte correspondiente ante la aseguradora. De inmediato, comuniqué la situación a la abogada de la empresa y al equipo de Seguridad y Salud en el Trabajo (SST) para que tuvieran conocimiento de lo ocurrido. los funcionarios fueron finalmente transportado por un compañero que en ese momento también transitaba por la vía. | AB60: SI | AC60: https://emprestur-my.sharepoint.com/personal/alejandra_betancur_emprestur_com/Documents/Aplicaciones/Microsoft%20Forms/INFORMACI%C3%93N%20NOVEDAD%20_%20ACCIDENTES%2026042022%20(2)/SOPORTES%20PARA%20ANEXAR/WhatsApp%20Image%202025-11-27%20at%2008.21.00%20(1)_anonymous.jpeg; https://emprestur-my.sharepoint.com/personal/alejandra_betancur_emprestur_com/Documents/Aplicaciones/Microsoft%20Forms/INFORMACI%C3%93N%20NOVEDAD%20_%20ACCIDENTES%2026042022%20(2)/SOPORTES%20PARA%20ANEXAR/WhatsApp%20Image%202025-11-27%20at%2008.21.00_anonymous.jpeg; https://emprestur-my.sharepoint.com/personal/alejandra_betancur_emprestur_com/Documents/Aplicaciones/Microsoft%20Forms/INFORMACI%C3%93N%20NOVEDAD%20_%20ACCIDENTES%2026042022%20(2)/SOPORTES%20PARA%20ANEXAR/WhatsApp%20Image%202025-11-27%20at%2008.20.59%20(2)_anonymous.jpeg; https://emprestur-my.sharepoint.com/personal/alejandra_betancur_emprestur_com/Documents/Aplicaciones/Microsoft%20Forms/INFORMACI%C3%93N%20NOVEDAD%20_%20ACCIDENTES%2026042022%20(2)/SOPORTES%20PARA%20ANEXAR/WhatsApp%20Image%202025-11-27%20at%2008.20.59%20(1)_anonymous.jpeg; https://emprestur-my.sharepoint.com/personal/alejandra_betancur_emprestur_com/Documents/Aplicaciones/Microsoft%20Forms/INFORMACI%C3%93N%20NOVEDAD%20_%20ACCIDENTES%2026042022%20(2)/SOPORTES%20PARA%20ANEXAR/WhatsApp%20Image%202025-11-27%20at%2008.20.59_anonymous.jpeg; https://emprestur-my.sharepoint.com/personal/alejandra_betancur_emprestur_com/Documents/Aplicaciones/Microsoft%20Forms/INFORMACI%C3%93N%20NOVEDAD%20_%20ACCIDENTES%2026042022%20(2)/SOPORTES%20PARA%20ANEXAR/WhatsApp%20Image%202025-11-27%20at%2008.20.58%20(3)_anonymous.jpeg; https://emprestur-my.sharepoint.com/personal/alejandra_betancur_emprestur_com/Documents/Aplicaciones/Microsoft%20Forms/INFORMACI%C3%93N%20NOVEDAD%20_%20ACCIDENTES%2026042022%20(2)/SOPORTES%20PARA%20ANEXAR/WhatsApp%20Image%202025-11-27%20at%2008.20.58%20(2)_anonymous.jpeg; https://emprestur-my.sharepoint.com/personal/alejandra_betancur_emprestur_com/Documents/Aplicaciones/Microsoft%20Forms/INFORMACI%C3%93N%20NOVEDAD%20_%20ACCIDENTES%2026042022%20(2)/SOPORTES%20PARA%20ANEXAR/WhatsApp%20Image%202025-11-27%20at%2008.20.58%20(1)_anonymous.jpeg; https://emprestur-my.sharepoint.com/personal/alejandra_betancur_emprestur_com/Documents/Aplicaciones/Microsoft%20Forms/INFORMACI%C3%93N%20NOVEDAD%20_%20ACCIDENTES%2026042022%20(2)/SOPORTES%20PARA%20ANEXAR/WhatsApp%20Image%202025-11-27%20at%2008.20.58_anonymous.jpeg
A61: 46000.364 | B61: 46000.382 | C61: anónimo | E61: Lizzeth Arbelaez Soto | F61: 45997 | G61: 17:45 | H61: LKL570 | I61: ISAGEN | J61: Si | K61: S739067 | L61: Luis Fernando Gaviria Durango | M61: 71.753.945 | N61: 3127548726 | O61: Accidente de tránsito y transporte dentro del desarrollo de la labor (Si ocurre en la vía con otros vehículos o con otros actores viales implicados) | P61: Daño Material propio | Q61: Acto inseguro de Tercero | R61: N/A | S61: N/A | T61: N/A | U61: Inmediatamente después de los hechos, el conductor se comunica para informar lo sucedido. Siendo las 5:45 p. m., un vehículo particular que transitaba por la vía entre la Medellín–Bogotá y PCH San Miguel tomó una curva demasiado abierta. Al frenar, el vehículo perdió adherencia debido a que la vía está compuesta de piedra, lo que ocasionó que impactara el lateral izquierdo del vehículo de Emprestur. Nuestro conductor realizó una maniobra de evasión que evitó un choque frontal, logrando que el impacto fuera únicamente lateral. | V61: NO | W61: SI | X61: NO | Y61: NO | Z61: SI | AA61: Se verifica con el conductor, mediante comunicación verbal y con apoyo de fotografías y vídeos, el estado del vehículo. No se reemplaza el servicio, ya que el incidente únicamente ocasionó daños en la carrocería. El vehículo permanece 100% operativo y en condiciones seguras para continuar prestando el servicio. | AB61: SI | AC61: https://emprestur-my.sharepoint.com/personal/alejandra_betancur_emprestur_com/Documents/Aplicaciones/Microsoft%20Forms/INFORMACI%C3%93N%20NOVEDAD%20_%20ACCIDENTES%2026042022%20(2)/SOPORTES%20PARA%20ANEXAR/WhatsApp%20Image%202025-12-06%20at%207.15.26%20PM%20(1)_anonymous.jpeg; https://emprestur-my.sharepoint.com/personal/alejandra_betancur_emprestur_com/Documents/Aplicaciones/Microsoft%20Forms/INFORMACI%C3%93N%20NOVEDAD%20_%20ACCIDENTES%2026042022%20(2)/SOPORTES%20PARA%20ANEXAR/WhatsApp%20Image%202025-12-06%20at%207.15.26%20PM_anonymous.jpeg; https://emprestur-my.sharepoint.com/personal/alejandra_betancur_emprestur_com/Documents/Aplicaciones/Microsoft%20Forms/INFORMACI%C3%93N%20NOVEDAD%20_%20ACCIDENTES%2026042022%20(2)/SOPORTES%20PARA%20ANEXAR/WhatsApp%20Image%202025-12-06%20at%207.15.25%20PM%20(2)_anonymous.jpeg; https://emprestur-my.sharepoint.com/personal/alejandra_betancur_emprestur_com/Documents/Aplicaciones/Microsoft%20Forms/INFORMACI%C3%93N%20NOVEDAD%20_%20ACCIDENTES%2026042022%20(2)/SOPORTES%20PARA%20ANEXAR/WhatsApp%20Image%202025-12-06%20at%207.15.25%20PM%20(1)_anonymous.jpeg
A62: 46007.433 | B62: 46007.442 | C62: anónimo | E62: GUSTAVO ALONSO ZAPATA MUÑOZ | F62: 46004 | G62: 18:40 | H62: NNN346 | I62: TELEMEDELLIN | J62: No | K62: N/A | L62: LUIS FERNANDO CIRO CIRO | M62: 1152452982 | N62: 3003647380 | O62: Accidente de tránsito (se produce en las vías y fuera de horario laboral) | P62: Daño Material propio | Q62: Acto inseguro propio (conductor) | R62: Tercero (Comunidad) | S62: EL LESIONADO TERCERO NO QUISO BRINDAR DATOS | T62: EL LESIONADO TERCERO NO QUISO BRINDAR DATOS | U62: Recibo llamado del Sr. Ciro, informando incidente de tránsito con motocicleta (Anexos Matricula 1-2 Tercero) en vía pública del barrio Manrique La Cruz (Anexo Ubicación Novedad). Donde al momento de abrir la puerta del conductor y bajarse del vehículo la motocicleta impacta contra este y queda aprisionada (Anexos Sitio 1-2-3). El Conductor de la moto un hombre joven de aproximadamente 26 años, nacionalidad venezolana y que no portaba casco, permiso de permanencia en el país ni licencia de conducción o documento alguno que pudiese individualizar y validar datos personales. Presento rasguños mínimos ocasionados en la caída del incidente a lo cual no manifestó mayor importancia y desiste de la asistencia medica en sitio (Ver anexo reporte aseguradora – NNN346). Se procedió a llamar las autoridades de tránsito y policía para que asistieran al lugar, sin éxito. Por lo que se contacto a la aseguradora para solicitar acompañamiento jurídico y asistencia de grúa dado el impacto en la puerta el cual no permitía el cierre y en caso de movilizar al parqueadero de la empresa se corría el riesgo de un comparendo e inmovilización por conducción insegura. El abogado se presenta a las 20:13 e inicia el procedimiento jurídico levantando la información requerida de la novedad. La grúa llega a sitio a las 00:05 de la madrugada (Anexo grúa 1-2 ) retirando el vehículo del lugar quedando en custodia de la aseguradora y con destino a parqueadero Emprestur para continuidad de la atención y debido proceso de la novedad. | V62: NO | W62: NO | X62: SI | Y62: NO | Z62: SI | AA62: SE REALIZA ACOMPAÑAMIENTO TELEFONICO EN TODO EL PROCESO DEL INCIDENTE | AB62: SI | AC62: https://emprestur-my.sharepoint.com/personal/alejandra_betancur_emprestur_com/Documents/Aplicaciones/Microsoft%20Forms/INFORMACI%C3%93N%20NOVEDAD%20_%20ACCIDENTES%2026042022%20(2)/SOPORTES%20PARA%20ANEXAR/Reporte%20Aseguradora%20-%20NNN346_anonymous.pdf; https://emprestur-my.sharepoint.com/personal/alejandra_betancur_emprestur_com/Documents/Aplicaciones/Microsoft%20Forms/INFORMACI%C3%93N%20NOVEDAD%20_%20ACCIDENTES%2026042022%20(2)/SOPORTES%20PARA%20ANEXAR/Ubicacion%20novedad_anonymous.jpg; https://emprestur-my.sharepoint.com/personal/alejandra_betancur_emprestur_com/Documents/Aplicaciones/Microsoft%20Forms/INFORMACI%C3%93N%20NOVEDAD%20_%20ACCIDENTES%2026042022%20(2)/SOPORTES%20PARA%20ANEXAR/Grua%201_anonymous.jpeg; https://emprestur-my.sharepoint.com/personal/alejandra_betancur_emprestur_com/Documents/Aplicaciones/Microsoft%20Forms/INFORMACI%C3%93N%20NOVEDAD%20_%20ACCIDENTES%2026042022%20(2)/SOPORTES%20PARA%20ANEXAR/Grua%202_anonymous.jpeg; https://emprestur-my.sharepoint.com/personal/alejandra_betancur_emprestur_com/Documents/Aplicaciones/Microsoft%20Forms/INFORMACI%C3%93N%20NOVEDAD%20_%20ACCIDENTES%2026042022%20(2)/SOPORTES%20PARA%20ANEXAR/Sitio%201_anonymous.jpeg; https://emprestur-my.sharepoint.com/personal/alejandra_betancur_emprestur_com/Documents/Aplicaciones/Microsoft%20Forms/INFORMACI%C3%93N%20NOVEDAD%20_%20ACCIDENTES%2026042022%20(2)/SOPORTES%20PARA%20ANEXAR/Sitio%202_anonymous.jpeg; https://emprestur-my.sharepoint.com/personal/alejandra_betancur_emprestur_com/Documents/Aplicaciones/Microsoft%20Forms/INFORMACI%C3%93N%20NOVEDAD%20_%20ACCIDENTES%2026042022%20(2)/SOPORTES%20PARA%20ANEXAR/Sitio%203_anonymous.jpeg; https://emprestur-my.sharepoint.com/personal/alejandra_betancur_emprestur_com/Documents/Aplicaciones/Microsoft%20Forms/INFORMACI%C3%93N%20NOVEDAD%20_%20ACCIDENTES%2026042022%20(2)/SOPORTES%20PARA%20ANEXAR/Matricula%201%20Tercero_anonymous.jpeg; https://emprestur-my.sharepoint.com/personal/alejandra_betancur_emprestur_com/Documents/Aplicaciones/Microsoft%20Forms/INFORMACI%C3%93N%20NOVEDAD%20_%20ACCIDENTES%2026042022%20(2)/SOPORTES%20PARA%20ANEXAR/Matricula%202%20Tercero_anonymous.jpeg
A63: 46007.597 | B63: 46007.611 | C63: anónimo | E63: Carlos Franco | F63: 45989 | G63: 6:20 am | H63: LKK245 | I63: EPM | J63: Si | K63: SDTP-01745 | L63: JUAN CAMILO HERRERA CARO | M63: 71290145 | N63: 3194038676 | O63: Accidente de tránsito y transporte dentro del desarrollo de la labor (Si ocurre en la vía con otros vehículos o con otros actores viales implicados) | P63: Afectación al Cliente | Q63: Acto inseguro de Tercero | R63: Funcionario de cliente | S63: NATALIA EUSSE | T63: 3044197312 | U63: "Cuando íbamos a la altura de la Cra 52 # 44C-07, vía San Pedro de los Milagros, a un vehículo lechero se le cae algo por debajo y alcanza a impactar el panorámico de la camioneta y volaron algunas esquirlas que le alcanzaron a caer a la funcionaria. A mi no me pasó nada" | V63: NO | W63: SI | X63: NO | Y63: NO | Z63: NO | AA63: La funcionaria reporta la novedad y recibe la instrucción de dirigirse a la clínica Bolivariana donde el conductor la lleva para ser atendida y de igual forma el conductor manifiesta que el propietario del otro vehículo reconoció su culpa y dio la instrucción de llevar la camioneta a un lugar donde le pudieran cambiar el panorámico y que él asumiría todos los costos | AB63: NO | AC63: https://emprestur-my.sharepoint.com/personal/alejandra_betancur_emprestur_com/Documents/Aplicaciones/Microsoft%20Forms/INFORMACI%C3%93N%20NOVEDAD%20_%20ACCIDENTES%2026042022%20(2)/SOPORTES%20PARA%20ANEXAR/Reporte%20Aseguradora%20-%20NNN346_anonymous.pdf; https://emprestur-my.sharepoint.com/personal/alejandra_betancur_emprestur_com/Documents/Aplicaciones/Microsoft%20Forms/INFORMACI%C3%93N%20NOVEDAD%20_%20ACCIDENTES%2026042022%20(2)/SOPORTES%20PARA%20ANEXAR/Ubicacion%20novedad_anonymous.jpg; https://emprestur-my.sharepoint.com/personal/alejandra_betancur_emprestur_com/Documents/Aplicaciones/Microsoft%20Forms/INFORMACI%C3%93N%20NOVEDAD%20_%20ACCIDENTES%2026042022%20(2)/SOPORTES%20PARA%20ANEXAR/Grua%201_anonymous.jpeg; https://emprestur-my.sharepoint.com/personal/alejandra_betancur_emprestur_com/Documents/Aplicaciones/Microsoft%20Forms/INFORMACI%C3%93N%20NOVEDAD%20_%20ACCIDENTES%2026042022%20(2)/SOPORTES%20PARA%20ANEXAR/Grua%202_anonymous.jpeg; https://emprestur-my.sharepoint.com/personal/alejandra_betancur_emprestur_com/Documents/Aplicaciones/Microsoft%20Forms/INFORMACI%C3%93N%20NOVEDAD%20_%20ACCIDENTES%2026042022%20(2)/SOPORTES%20PARA%20ANEXAR/Sitio%201_anonymous.jpeg; https://emprestur-my.sharepoint.com/personal/alejandra_betancur_emprestur_com/Documents/Aplicaciones/Microsoft%20Forms/INFORMACI%C3%93N%20NOVEDAD%20_%20ACCIDENTES%2026042022%20(2)/SOPORTES%20PARA%20ANEXAR/Sitio%202_anonymous.jpeg; https://emprestur-my.sharepoint.com/personal/alejandra_betancur_emprestur_com/Documents/Aplicaciones/Microsoft%20Forms/INFORMACI%C3%93N%20NOVEDAD%20_%20ACCIDENTES%2026042022%20(2)/SOPORTES%20PARA%20ANEXAR/Sitio%203_anonymous.jpeg; https://emprestur-my.sharepoint.com/personal/alejandra_betancur_emprestur_com/Documents/Aplicaciones/Microsoft%20Forms/INFORMACI%C3%93N%20NOVEDAD%20_%20ACCIDENTES%2026042022%20(2)/SOPORTES%20PARA%20ANEXAR/Matricula%201%20Tercero_anonymous.jpeg; https://emprestur-my.sharepoint.com/personal/alejandra_betancur_emprestur_com/Documents/Aplicaciones/Microsoft%20Forms/INFORMACI%C3%93N%20NOVEDAD%20_%20ACCIDENTES%2026042022%20(2)/SOPORTES%20PARA%20ANEXAR/Matricula%202%20Tercero_anonymous.jpeg
A64: 46007.433 | B64: 46007.665 | C64: anónimo | E64: Jonathan Giraldo | F64: 46007 | G64: 3:30 p.m. | H64: NO APLICA | I64: FLOTA PROPIA | J64: Si | K64: NO APLICA | L64: Simon David Benjumea | M64: 1152465154 | N64: 3218030532 | O64: Incidente de trabajo (Se pudo presentar una lesión en el trabajador) | P64: Daño Material propio | Q64: Condición insegura | R64: N/A | S64: No aplica | T64: No aplica | U64: Me encontraba almorzando en el corredor de la oficina de flota, estaba en las sillas cafe que estan afuera, y me recosté, cuando senti que la silla se cedió ocasionando que me cayera | V64: NO | W64: NO | X64: NO | Y64: SI | Z64: SI | AA64: Se toma registro fotográfico de como queda la silla, se le consulta a Simón si tiene alguna dolencia, mas sin embargo informa que le dio fué mas el susto. | AB64: SI | AC64: https://emprestur-my.sharepoint.com/personal/alejandra_betancur_emprestur_com/Documents/Aplicaciones/Microsoft%20Forms/INFORMACI%C3%93N%20NOVEDAD%20_%20ACCIDENTES%2026042022%20(2)/SOPORTES%20PARA%20ANEXAR/WhatsApp%20Image%202025-12-16%20at%203.43.23%20PM_anonymous.jpeg
A65: 46009.681 | B65: 46009.689 | C65: anónimo | E65: Adriana Castillo | F65: 46008 | G65: 8:00 a.m. | H65: FWK701 | I65: EPM | J65: Si | K65: SDTP-02552 | L65: Fabian Eduardo Garcia Ramirez | M65: 98572372 | N65: 3108317558 | O65: Incidente de trabajo (Se pudo presentar una lesión en el trabajador) | P65: Afectación a Personas (lesionados) | Q65: Acto inseguro propio (conductor) | R65: Conductor y/o Empleado | S65: n/a | T65: n/a | U65: En el día de ayer cuando se cargaron unas herramientas en el volco del vehiculo la compuerta se iba a abrir después de que ya la habias cerrado y se el devolvio y la cogio con la mano izquierda sintiendo un dolor durito en la muñeca, y cerro normal la compuerta y continuo con el servicio, en la noche cuando ya estabas descansando empece a sentir una molestia en la muñeca y empezo a aumentar el dolor, no reporte en el momento pensando que no era nada, y procedi a envolverme en esparadrapo y hoy 18/12/2025 continuo con el dolor, veo la mano inflamada y me imposibilita conducir. | V65: NO | W65: NO | X65: NO | Y65: NO | Z65: SI | AA65: Se le hace retroalimentación al conductor de reporte oportuno a la novedad. | AB65: NO | AC65: https://emprestur-my.sharepoint.com/personal/alejandra_betancur_emprestur_com/Documents/Aplicaciones/Microsoft%20Forms/INFORMACI%C3%93N%20NOVEDAD%20_%20ACCIDENTES%2026042022%20(2)/SOPORTES%20PARA%20ANEXAR/WhatsApp%20Image%202025-12-18%20at%204.28.40%20PM_anonymous.jpeg
A66: 46011.364 | B66: 46011.379 | C66: anónimo | E66: Carlos Franco | F66: 46009 | G66: 16:48 | H66: FVY876 | I66: EPM | J66: Si | K66: SDTP-01440 | L66: DIOMER ENEL FRANCO TOBÓN | M66: 98552179 | N66: 3043198388 | O66: Accidente de tránsito y transporte dentro del desarrollo de la labor (Si ocurre en la vía con otros vehículos o con otros actores viales implicados) | P66: Daño Material propio | Q66: Acto inseguro propio (conductor) | R66: N/A | S66: N/A | T66: N/A | U66: "Me estacioné en unas celdas de parqueo autorizadas le puse la emergencia al vehículo pasé el andén y sentí un golpe y el carro comenzó a desplazarse lentamente. Y me fui corriendo para ver si podría abrir la puerta pero no fue posible por qué el carro tiene bloqueo y adelantico por ahí a los diez metros había un carro y mi vehículo chocó contra ese vehículo causándole daños y también dañarse mi vehículo los hechos ocurrieron en el municipio de Yarumal departamento de Antioquia si asistió el transito. Al vehículo afectado se le daño bomper trasero stop trasero derecho la maleta. delante del Logan había una moto la tumbó con la llanta izquierda y le estalló una llanta al Logan y le desajuste el bomper delantero del Logan. al vehículo Dimax le daño bomper delantero farola izquierda capo guardabarros izquierdo protector de guardabarros Interno la persiana" | V66: NO | W66: NO | X66: NO | Y66: NO | Z66: NO | AA66: El reporte no fue de inmediato y no se ejecutó ninguna acción o se dieron indicaciones | AB66: SI | AC66: https://emprestur-my.sharepoint.com/personal/alejandra_betancur_emprestur_com/Documents/Aplicaciones/Microsoft%20Forms/INFORMACI%C3%93N%20NOVEDAD%20_%20ACCIDENTES%2026042022%20(2)/SOPORTES%20PARA%20ANEXAR/WhatsApp%20Image%202025-12-19%20at%2012.02.28_anonymous.jpeg; https://emprestur-my.sharepoint.com/personal/alejandra_betancur_emprestur_com/Documents/Aplicaciones/Microsoft%20Forms/INFORMACI%C3%93N%20NOVEDAD%20_%20ACCIDENTES%2026042022%20(2)/SOPORTES%20PARA%20ANEXAR/WhatsApp%20Image%202025-12-19%20at%2012.02.29_anonymous.jpeg; https://emprestur-my.sharepoint.com/personal/alejandra_betancur_emprestur_com/Documents/Aplicaciones/Microsoft%20Forms/INFORMACI%C3%93N%20NOVEDAD%20_%20ACCIDENTES%2026042022%20(2)/SOPORTES%20PARA%20ANEXAR/WhatsApp%20Image%202025-12-19%20at%2012.02.29%20(1)_anonymous.jpeg
A67: 46018.363 | B67: 46018.388 | C67: anónimo | E67: Carlos Franco | F67: 46018 | G67: 6:00 | H67: TOR349 | I67: N/A | J67: No | K67: N/A | L67: OMAR ORLANDO MOGOLLON PEREZ | M67: 14321209 | N67: 3023627914 | O67: Accidente de tránsito (se produce en las vías y fuera de horario laboral) | P67: Daño Material propio | Q67: Acto inseguro de Tercero | R67: N/A | S67: N/A | T67: N/A | U67: "Iba 7 km abajo de Cocorná cuando un vehículo invadió el carril y al intentar esquivarlo me alcanza a dar en todo el lado izquierdo de la camioneta donde perdí el control y me fui al otro lado de la vía. El conductor del otro vehículo reconoce que le dio un micro sueño y que venía viajando desde Neiva hacia Medellín. Al lugar llegó la ambulancia de Cocorná para llevar por precaución a mi esposa y mi suegra al hospital para ser revisadas porque se alcanzaron a golpear por el impacto. Las otras personas que se transportaban en el vehículo son Claudia Hincapié, Nicole Mogollón Hincapié, Fidelina Torres Velasquez, Simón Vélez Henao" | V67: NO | W67: NO | X67: NO | Y67: NO | Z67: SI | AA67: Cuando se recibe la información, el conductor manifiesta que ya ha llamado a la aseguradora y la ambulancia para que lleguen al sitio y trasladar por precaución 2 personas al hospital para ser revisadas. También está a la espera de que llegue la grúa la cual fue programada para llegar a las 10:30 am al sitio | AB67: SI | AC67: https://emprestur-my.sharepoint.com/personal/alejandra_betancur_emprestur_com/Documents/Aplicaciones/Microsoft%20Forms/INFORMACI%C3%93N%20NOVEDAD%20_%20ACCIDENTES%2026042022%20(2)/SOPORTES%20PARA%20ANEXAR/WhatsApp%20Video%202025-12-27%20at%2008.26.52_anonymous.mp4; https://emprestur-my.sharepoint.com/personal/alejandra_betancur_emprestur_com/Documents/Aplicaciones/Microsoft%20Forms/INFORMACI%C3%93N%20NOVEDAD%20_%20ACCIDENTES%2026042022%20(2)/SOPORTES%20PARA%20ANEXAR/WhatsApp%20Image%202025-12-27%20at%2008.26.53_anonymous.jpeg; https://emprestur-my.sharepoint.com/personal/alejandra_betancur_emprestur_com/Documents/Aplicaciones/Microsoft%20Forms/INFORMACI%C3%93N%20NOVEDAD%20_%20ACCIDENTES%2026042022%20(2)/SOPORTES%20PARA%20ANEXAR/WhatsApp%20Image%202025-12-27%20at%2008.26.55_anonymous.jpeg; https://emprestur-my.sharepoint.com/personal/alejandra_betancur_emprestur_com/Documents/Aplicaciones/Microsoft%20Forms/INFORMACI%C3%93N%20NOVEDAD%20_%20ACCIDENTES%2026042022%20(2)/SOPORTES%20PARA%20ANEXAR/WhatsApp%20Image%202025-12-27%20at%2008.26.57_anonymous.jpeg; https://emprestur-my.sharepoint.com/personal/alejandra_betancur_emprestur_com/Documents/Aplicaciones/Microsoft%20Forms/INFORMACI%C3%93N%20NOVEDAD%20_%20ACCIDENTES%2026042022%20(2)/SOPORTES%20PARA%20ANEXAR/WhatsApp%20Image%202025-12-27%20at%2008.26.58_anonymous.jpeg; https://emprestur-my.sharepoint.com/personal/alejandra_betancur_emprestur_com/Documents/Aplicaciones/Microsoft%20Forms/INFORMACI%C3%93N%20NOVEDAD%20_%20ACCIDENTES%2026042022%20(2)/SOPORTES%20PARA%20ANEXAR/WhatsApp%20Image%202025-12-27%20at%2008.26.53%20(1)_anonymous.jpeg
A68: 46024.264 | B68: 46024.268 | C68: anónimo | E68: JHON HAWER MURCIA | F68: 46023 | G68: 1:30 AM | H68: PXK177 | I68: SURA | J68: Si | K68: 0 | L68: JUAN DAVID CARVAJAL | M68: 71368861 | N68: 305 4014081 | O68: Accidente de trabajo (Empleado de Emprestur Lesionado) | P68: Afectación a Personas (lesionados) | Q68: Acto inseguro de Tercero | R68: Tercero (Comunidad) | S68: 0 | T68: 0 | U68: EL CONDUCTOR NOS INDICA QUE LAS AFECTADAS SE PASARON EL SEMAFORO EN ROJO | V68: NO | W68: SI | X68: SI | Y68: NO | Z68: SI | AA68: REALIZAR ACOMPAÑAMIENTO VIA TELEFONICA HASTA QUE LLEGARA LA AMBULANCIA | AB68: SI | AC68: https://emprestur-my.sharepoint.com/personal/alejandra_betancur_emprestur_com/Documents/Aplicaciones/Microsoft%20Forms/INFORMACI%C3%93N%20NOVEDAD%20_%20ACCIDENTES%2026042022%20(2)/SOPORTES%20PARA%20ANEXAR/WhatsApp%20Image%202026-01-02%20at%204.28.09%20AM%20(2)_anonymous.jpeg; https://emprestur-my.sharepoint.com/personal/alejandra_betancur_emprestur_com/Documents/Aplicaciones/Microsoft%20Forms/INFORMACI%C3%93N%20NOVEDAD%20_%20ACCIDENTES%2026042022%20(2)/SOPORTES%20PARA%20ANEXAR/WhatsApp%20Image%202026-01-02%20at%204.28.09%20AM%20(1)_anonymous.jpeg; https://emprestur-my.sharepoint.com/personal/alejandra_betancur_emprestur_com/Documents/Aplicaciones/Microsoft%20Forms/INFORMACI%C3%93N%20NOVEDAD%20_%20ACCIDENTES%2026042022%20(2)/SOPORTES%20PARA%20ANEXAR/WhatsApp%20Image%202026-01-02%20at%204.28.09%20AM_anonymous.jpeg; https://emprestur-my.sharepoint.com/personal/alejandra_betancur_emprestur_com/Documents/Aplicaciones/Microsoft%20Forms/INFORMACI%C3%93N%20NOVEDAD%20_%20ACCIDENTES%2026042022%20(2)/SOPORTES%20PARA%20ANEXAR/WhatsApp%20Image%202026-01-02%20at%204.28.08%20AM%20(4)_anonymous.jpeg; https://emprestur-my.sharepoint.com/personal/alejandra_betancur_emprestur_com/Documents/Aplicaciones/Microsoft%20Forms/INFORMACI%C3%93N%20NOVEDAD%20_%20ACCIDENTES%2026042022%20(2)/SOPORTES%20PARA%20ANEXAR/WhatsApp%20Image%202026-01-02%20at%204.28.08%20AM%20(3)_anonymous.jpeg; https://emprestur-my.sharepoint.com/personal/alejandra_betancur_emprestur_com/Documents/Aplicaciones/Microsoft%20Forms/INFORMACI%C3%93N%20NOVEDAD%20_%20ACCIDENTES%2026042022%20(2)/SOPORTES%20PARA%20ANEXAR/WhatsApp%20Image%202026-01-02%20at%204.28.08%20AM%20(2)_anonymous.jpeg; https://emprestur-my.sharepoint.com/personal/alejandra_betancur_emprestur_com/Documents/Aplicaciones/Microsoft%20Forms/INFORMACI%C3%93N%20NOVEDAD%20_%20ACCIDENTES%2026042022%20(2)/SOPORTES%20PARA%20ANEXAR/WhatsApp%20Image%202026-01-02%20at%204.28.08%20AM%20(1)_anonymous.jpeg; https://emprestur-my.sharepoint.com/personal/alejandra_betancur_emprestur_com/Documents/Aplicaciones/Microsoft%20Forms/INFORMACI%C3%93N%20NOVEDAD%20_%20ACCIDENTES%2026042022%20(2)/SOPORTES%20PARA%20ANEXAR/WhatsApp%20Image%202026-01-02%20at%204.28.08%20AM_anonymous.jpeg; https://emprestur-my.sharepoint.com/personal/alejandra_betancur_emprestur_com/Documents/Aplicaciones/Microsoft%20Forms/INFORMACI%C3%93N%20NOVEDAD%20_%20ACCIDENTES%2026042022%20(2)/SOPORTES%20PARA%20ANEXAR/WhatsApp%20Image%202026-01-02%20at%204.28.07%20AM_anonymous.jpeg
A69: 46024.271 | B69: 46024.282 | C69: anónimo | E69: JHON HAWER MURCIA | F69: 46023 | G69: 17:12 | H69: LKK334 | I69: SURA | J69: Si | K69: 0 | L69: JUAN MANUEL TRIVINO MARTINEZ | M69: 80032485 | N69: 305 3816384 | O69: Accidente Ambienta (afectación al ecosistema por derrames, impacto con animal en la vía) | P69: Daño Material a Tercero | Q69: Acto inseguro de Tercero | R69: N/A | S69: 0 | T69: 0 | U69: ME INDICA EL CONDUCTOR QUE EL PERRO SE GOLPEA CON LAS LLANTAS TRASERAS DEL VEHICULO Y LO LLEVAN A UNA CLINICA VETERINARIA | V69: NO | W69: SI | X69: NO | Y69: NO | Z69: SI | AA69: HACER ACOMPAÑAMIENTO TELEFONICO HASTA SOLUCIONAR LA NOVEDAD | AB69: NO
A70: 46028.457 | B70: 46028.464 | C70: anónimo | E70: DAYHANA SOSSA | F70: 46022 | G70: EN HORAS DE LA TARDE 1:36 PM | H70: LKK722 | I70: CAH | J70: Si | K70: 1754 | L70: GIOVANNY ESPINAL DEOSA | M70: 71260182 | N70: 3185998960 | O70: Accidente de trabajo (Empleado de Emprestur Lesionado) | P70: Afectación a Personas (lesionados) | Q70: Acto inseguro de Tercero | R70: Conductor y/o Empleado | S70: N/A | T70: N/A | U70: En la prestación del servicio se destinaban a trasladar a un habitante de calle y este le proporciona unos rasguños en el brazo. | V70: SI | W70: SI | X70: SI | Y70: NO | Z70: SI | AA70: Se informa al coordinador de SST | AB70: SI
A71: 46028.525 | B71: 46028.537 | C71: anónimo | E71: JHON HAWER MURCIA OROZCO | F71: 46021 | G71: 15:36 | H71: NNL996 | I71: SURA | J71: Si | K71: 0 | L71: Dr Alejandro Molina | M71: 0 | N71: 0 | O71: Accidente de tránsito y transporte dentro del desarrollo de la labor (Si ocurre en la vía con otros vehículos o con otros actores viales implicados) | P71: Daño Material propio | Q71: Acto inseguro de Tercero | R71: N/A | S71: 0 | T71: 0 | U71: indica el conductor que el otro vehículo salió sin mirar lo cual lo colisiono por la parte de atrás | V71: NO | W71: SI | X71: NO | Y71: NO | Z71: NO | AA71: realizar acompañamiento telefónico hasta que soluciono la novedad con el otro vehículo | AB71: NO
A72: 46037.279 | B72: 46037.285 | C72: anónimo | E72: JONATHAN GIRALDO ORREGO | F72: 46035 | G72: 5 PM | H72: KTN224 | I72: SURA | J72: No | K72: SURA | L72: YAID ALEXIS SERNA ZULUAGA | M72: 1017153519 | N72: 3023952192 | O72: Accidente de tránsito y transporte dentro del desarrollo de la labor (Si ocurre en la vía con otros vehículos o con otros actores viales implicados) | P72: Daño Material propio | Q72: Acto inseguro de Tercero | R72: N/A | S72: N/A | T72: N/A | U72: El conductor YAID ALEXIS SERNA ZULUAGA cc 1017153519 telefono 3023952192, quien se movilizaba en el vehículo de placas KTN224, se comunicó conmigo para informarme que, en la esquina de la calle 29 con carrera 52, sector Guayabal, fue colisionado en la parte trasera derecha por el camión de placas NLW138. El impacto se presentó específicamente en la nave trasera, cerca del bocallantas, hacia el bómper, generando un hundimiento en la latonería. El conductor del camión manifestó que el vehículo no contaba con aseguradora y expresó su intención de llegar a un acuerdo para asumir la reparación de los daños ocasionados. Luego de validar las fotografías enviadas por el conductor Alexis vía WhatsApp y realizar una estimación preliminar del costo de la reparación, se solicitó inicialmente un valor de $800.000. No obstante, el tercero indicó que no contaba con ese momento y que únicamente contaba con $500.000, valor que fue aceptado por mi parte para llegar a un acuerdo para la reparación. Dicho dinero fue consignado directamente a la cuenta corriente de EMPRESTUR, tal como se evidencia en el soporte de transferencia que se adjunta a este correo. Con base en lo anterior agradezco lo siguiente: @Tesoreria Por favor me confirmas el ingreso del dinero a la cuenta de Emprestur @Simon David Por favor programar la intervención y reparación del vehículo KTN224 con Humberto valiente lo mas pronto posible. @Gustavo Zapata - @Simon David - @Paola Arcila - @Leidy Bolivar Una vez se reciba la factura correspondiente, esta será cruzada contablemente con el valor consignado por el tercero, muchachos por favor dejar el comentario en el digital para que se cruce con este valor recuperado. En caso de que el valor total de la reparación supere el monto recibido, la diferencia será asumida por la compañía es decir se lleva al centro de costos del vehículo. @Jennifer Posada - @Alejandra Betancur Se dejo el registro en el enlace correspondiente sin embargo considero que como se llego a una solución no requiere investigación, sin embargo lo dejo a su criterio. | V72: NO | W72: NO | X72: NO | Y72: NO | Z72: NO | AA72: Se realiza negociacion con el tercero por medio del conductor y se le dan indicaciones de como proceder. | AB72: SI | AC72: https://emprestur-my.sharepoint.com/personal/alejandra_betancur_emprestur_com/Documents/Aplicaciones/Microsoft%20Forms/INFORMACI%C3%93N%20NOVEDAD%20_%20ACCIDENTES%2026042022%20(2)/SOPORTES%20PARA%20ANEXAR/FOTOS%20ACCIDENTE%20KTN224_anonymous.pdf
A73: 46037.3 | B73: 46037.31 | C73: anónimo | E73: JONATHAN GIRALDO ORREGO | F73: 46036 | G73: 5:45 PM | H73: GTX035 | I73: SURA | J73: No | K73: SURA | L73: LEONARDO ANTONIO BAQUERO LASTRE | M73: 1047460435 | N73: 3227577650 | O73: Accidente de tránsito y transporte dentro del desarrollo de la labor (Si ocurre en la vía con otros vehículos o con otros actores viales implicados) | P73: Daño Material propio | Q73: Acto inseguro de Tercero | R73: N/A | S73: N/A | T73: N/A | U73: El día de ayer, miércoles 14 de enero, siendo aproximadamente las 5:45 p. m., el conductor LEONARDO ANTONIO BAQUERO LASTRE cc 1047460435 tel: 3227577650, asignado al vehículo de placas GTX035, se comunica conmigo para informarme sobre una novedad presentada con el vehículo. El conductor indica que, al llegar a su lugar de residencia, dejó el vehículo estacionado frente a su vivienda. Posteriormente, al salir nuevamente, un vehículo perteneciente a un vecino, de placas MNX840, que se encontraba realizando maniobras en reversa para estacionarse, colisiona el vehículo GTX035, generando una afectación en la nave delantera izquierda. Como resultado del impacto, se evidencia: Hundimiento de la nave delantera izquierda Rayones visibles en la misma pieza, (según registro fotográfico adjunto) El conductor manifiesta que el responsable del hecho es un vecino que reside a aproximadamente tres casas de su domicilio, quien expresa su disposición para llegar a un acuerdo directo con nosotros. El tercero informa que no cuenta con póliza de seguros, pero está dispuesto a asumir el costo de la reparación mediante una negociación directa. Con base en las imágenes enviadas, se realiza una estimación preliminar del costo de reparación por un valor aproximado de $900.000, cifra que fue comunicada al conductor para que este la informara directamente al tercero responsable. Se le indicó que, de estar de acuerdo, se le facilitaría la cuenta para realizar la consignación correspondiente. No obstante, el tercero manifiesta que en ese momento no cuenta con los recursos, pero que podría efectuar el pago el próximo sábado 24 de enero. Teniendo en cuenta lo anterior, se definen las siguientes acciones: @Jennifer Posada Nos puedes apoyar por favor elaborando un documento de acuerdo de pago, en el cual el tercero se comprometa al pago del valor estipulado en la fecha acordada. Para este próximo 24 de enero, se comparten los datos y documentos del propietario del vehículo MNX840 pues la idea es que nuestro conductor lo haga firmar hoy mismo en la medida de lo posible por su vecino. @Simon David - @Gustavo Zapata Por favor programemos la reparación del carro par el próximo sábado 24 de enero para subsanar la novedad, cuando ingrese el dinero por parte del tercero tenerlo en cuenta para dejar la claridad en el digital de que ese dinero es para cubrir el costo de esa reparación; en caso de que el valor supere lo que el tercero nos pague el valor si tendría que llevarse al costo, en ese caso le deben informar a @Paola Arcila. @Alejandra Betancur - @Nancy Arias Se dejo el registro en el enlace correspondiente sin embargo considero que como se llego a una solución no requiere investigación, sin embargo lo dejo a su criterio. | V73: NO | W73: NO | X73: NO | Y73: NO | Z73: NO | AA73: Se le dan las indicaciones al conductor para buscar un acuerdo entre las partes. y se habla con el tercero que genero la afectacion. | AB73: SI | AC73: https://emprestur-my.sharepoint.com/personal/alejandra_betancur_emprestur_com/Documents/Aplicaciones/Microsoft%20Forms/INFORMACI%C3%93N%20NOVEDAD%20_%20ACCIDENTES%2026042022%20(2)/SOPORTES%20PARA%20ANEXAR/FOTOS%20ACCIDENTE%20GTX035%20Y%20DOCUMENTOS%20DEL%20TERCE_anonymous.pdf
A74: 46042.554 | B74: 46042.565 | C74: anónimo | E74: JULIAN DAVID VALENCIA BALLESTEROS | F74: 46037 | G74: 15:30 | H74: THZ316 | I74: CHEC | J74: Si | K74: TR2523808 | L74: BLADIMIR SALAZAR GARCIA | M74: 75064914 | N74: 3002772070 | O74: Accidente de trabajo (Empleado de Emprestur Lesionado) | P74: Afectación a Personas (lesionados) | Q74: Acto inseguro propio (conductor) | R74: Conductor y/o Empleado | S74: ANDRES TORO CEL 3217811878 | T74: N/A | U74: Versión de los hechos – ARL El día de los hechos, mientras me encontraba realizando mis labores como conductor y me desplazaba hacia el sector de Manga Bonita, el vehículo presentó una falla mecánica debido al pinchazo de la llanta trasera. Por tal motivo, me detuve en un sector de trocha para realizar el cambio de la llanta. Al momento de ubicar y posicionar el gato para levantar el vehículo, sentí un ardor leve en la zona abdominal. Posteriormente, durante la instalación de la llanta de repuesto y el ajuste de los pernos, el ardor se intensificó, presentándose una sensación fuerte similar a una quemadura o a la picadura de un insecto (avispa). Ante esta situación, procedí a revisarme levantando la camisa, evidenciando que en la zona del ombligo se presentaba enrojecimiento e inflamación (brotado), motivo por el cual se reporta la novedad como posible accidente/incidente de origen laboral. | V74: NO | W74: NO | X74: SI | Y74: NO | Z74: SI | AA74: Una vez conocida la novedad presentada, el Gestor Logístico informa de manera inmediata a la Jefe de SGI, con el fin de recibir las indicaciones correspondientes frente a la situación reportada por el conductor. De acuerdo con las orientaciones brindadas y lo informado por el médico de la empresa, se le comunica al conductor que debe solicitar cita con médico general para la valoración clínica y la identificación del origen de la molestia presentada. | AB74: NO
A75: 46056.359 | B75: 46056.428 | C75: anónimo | E75: Adriana Castillo | F75: 46055 | G75: 1:30 p.m. | H75: PXK221 | I75: SURA | J75: No | K75: N/A | L75: Elkin Dario Correa Zapata | M75: 71718086 | N75: 3175031373 | O75: Accidente de tránsito (se produce en las vías y fuera de horario laboral) | P75: Daño Material propio | Q75: Acto inseguro de Tercero | R75: N/A | S75: N/A | T75: N/A | U75: El día de ayer me dirigía hacia el cliente SURA a las 13:30 p.m., bajando por el barrio las palmas, nos encontrábamos 2 vehículos estacionados en sentido contrario, por en medio de los 2 pasó un motociclista con maletero, no calculo si podía pasar por en medio de los 2 realizando el daño a los vehículos estacionados, el señor se fugó, yo sentí el estruendo me bajé a mirar el vehículo y me di cuenta que había rayado el vehículo. | V75: NO | W75: NO | X75: NO | Y75: NO | Z75: SI | AA75: Se toma la versión de los hechos y se relaciona, el registro fotográfico | AB75: SI | AC75: https://emprestur-my.sharepoint.com/personal/alejandra_betancur_emprestur_com/Documents/Aplicaciones/Microsoft%20Forms/INFORMACI%C3%93N%20NOVEDAD%20_%20ACCIDENTES%2026042022%20(2)/SOPORTES%20PARA%20ANEXAR/REGISTRO%20FOTOGR%C3%81FICO%20PXK221_anonymous.pdf; https://emprestur-my.sharepoint.com/personal/alejandra_betancur_emprestur_com/Documents/Aplicaciones/Microsoft%20Forms/INFORMACI%C3%93N%20NOVEDAD%20_%20ACCIDENTES%2026042022%20(2)/SOPORTES%20PARA%20ANEXAR/RECORRIDO%20PXK221%20desde%20las%2013_anonymous.pdf
A76: 46059.42 | B76: 46059.584 | C76: anónimo | E76: GUSTAVO ALONSO ZAPATA MUÑOZ | F76: 46048 | G76: 10:27 am | H76: PXK186 | I76: MEDICARTE | J76: Si | K76: MEDICARTE | L76: MARIA TERESA JIMENEZ GUTIERREZ | M76: 43253094 | N76: 3243682867 | O76: Incidente de trabajo (Se pudo presentar una lesión en el trabajador) | P76: Daño Material propio | Q76: Acto inseguro propio (conductor) | R76: N/A | S76: N/A | T76: N/A | U76: La conductora Maria Teresa Jiménez informa vía whatsapp que presenta novedad con el vehículo al golpear una baranda metálica del parqueadero de almacentro mientras estaba en servicio con la enfermera de turno. se le indica que el golpe no afecta el desarrollo de la novedad y que una vez finalice el servicio deberá presentarse en taller para su valoración y cotización del proveedor de latonería y pintura; el cual informa que el valor del trabajo es de $800.000 y se aplicara a la conductora el descuento de nomina por este valor. | V76: NO | W76: NO | X76: NO | Y76: NO | Z76: SI | AA76: Se brinda acompañamiento durante la novedad hasta que la conductora realiza la cotización, conoce el valor y acepta el valor a descontar por la novedad. | AB76: SI | AC76: https://emprestur-my.sharepoint.com/personal/alejandra_betancur_emprestur_com/Documents/Aplicaciones/Microsoft%20Forms/INFORMACI%C3%93N%20NOVEDAD%20_%20ACCIDENTES%2026042022%20(2)/SOPORTES%20PARA%20ANEXAR/PXK186-1_anonymous.jpeg; https://emprestur-my.sharepoint.com/personal/alejandra_betancur_emprestur_com/Documents/Aplicaciones/Microsoft%20Forms/INFORMACI%C3%93N%20NOVEDAD%20_%20ACCIDENTES%2026042022%20(2)/SOPORTES%20PARA%20ANEXAR/PXK186-2_anonymous.jpeg
A77: 46064.411 | B77: 46064.625 | C77: anónimo | E77: Adriana Castillo | F77: 46064 | G77: 7:40 a.m | H77: JYX640 | I77: Corporación Ayuda Humanitaria | J77: Si | K77: N/A | L77: Juan Felipe Guzman Monsalve | M77: 1007243522 | N77: 3044750923 | O77: Accidente de tránsito y transporte dentro del desarrollo de la labor (Si ocurre en la vía con otros vehículos o con otros actores viales implicados) | P77: Daño Material propio | Q77: Acto inseguro de Tercero | R77: N/A | S77: N/A | T77: N/A | U77: El día de hoy 11/02/2025 llevé funcionarios de EPM para el Santuario, me parquee detrás de un vehículo para que se bajaran los funcionarios y adicional venia un vehículo subiendo, en la misma acera donde estaba parqueado salió un vehículo del parqueadero y se parqueo detrás mío, para darle paso al vehículo que estaba subiendo, al ver que no dejo el espacio suficiente para que pasara el vehículo empezó a realizar la maniobra de reversa y tratarse de meter detrás mío, lo realizó varias veces y no lo pudo lograr, en la ultima maniobra como tenia una camioneta automática la niña pensó que había puesto reversa y realmente puso la de marcha adelante, lo que causo que me estrellara por la puerta de la maleta, y me empujo haciéndome subir al andén, y adelante había otro vehículo parqueado lo que ocasionó que lo golpeara, quedando los 3 involucrados, no hubieron lesionados, se llamo a las aseguradoras y quedaron encargadas los familiares de la niña, ya que ella era menor de edad y manifestó que iba para el colegio. | V77: NO | W77: NO | X77: SI | Y77: NO | Z77: SI | AA77: Se le indica que llame a la aseguradora y tome registro fotográfico | AB77: SI | AC77: https://emprestur-my.sharepoint.com/personal/alejandra_betancur_emprestur_com/Documents/Aplicaciones/Microsoft%20Forms/INFORMACI%C3%93N%20NOVEDAD%20_%20ACCIDENTES%2026042022%20(2)/SOPORTES%20PARA%20ANEXAR/REGISTRO%20FOTOGR%C3%81FICO%20Y%20REPORTE%20GPS%20DEL%20ACCIDE_anonymous.pdf
A78: 46066.385 | B78: 46066.4 | C78: anónimo | E78: Adriana Castillo | F78: 46066 | G78: 9:00 a.m. | H78: NO APLICA | I78: NO APLICA | J78: No | K78: N/A | L78: FABIO ENRIQUE CARO GIRALDO | M78: 70852770 | N78: 3218614585 | O78: Incidente de trabajo (Se pudo presentar una lesión en el trabajador) | P78: Afectación a Personas (lesionados) | Q78: Acto inseguro propio (conductor) | R78: N/A | S78: N/A | T78: N/A | U78: Me encontraba en la portería, esperando que me imprimieran las planillas para iniciar servicios en Sura, me agaché donde están las canecas para botar basura, cuando Juan Pablo me estaba dando la espalda y dándoles indicaciones a otra persona sobre una dirección cuando con el brazo izquierdo estaba hizo un movimiento hacia atrás y me encontraba agachado me pegó en el ojo izquierdo cerca del lagrimal con el reloj que tenia en la muñeca, me metió el reloj en el ojo, donde me arde y me duele. | V78: NO | W78: NO | X78: NO | Y78: SI | Z78: SI | AA78: Se toma la versión del conductor, se cambia de conductor ya que iba a inciar servicio | AB78: SI | AC78: https://emprestur-my.sharepoint.com/personal/alejandra_betancur_emprestur_com/Documents/Aplicaciones/Microsoft%20Forms/INFORMACI%C3%93N%20NOVEDAD%20_%20ACCIDENTES%2026042022%20(2)/SOPORTES%20PARA%20ANEXAR/REGISTRO%20FOTOGR%C3%81FICO%20INCIDENTE_anonymous.pdf
A79: 46066.385 | B79: 46066.412 | C79: anónimo | E79: GUSTAVO ALONSO ZAPATA MUÑOZ | F79: 45989 | G79: 06:06AM | H79: LKK245 | I79: EPM | J79: Si | K79: N/A | L79: JUAN CAMILO HERRERA | M79: 71290145 | N79: 3194038676 | O79: Accidente de tránsito y transporte dentro del desarrollo de la labor (Si ocurre en la vía con otros vehículos o con otros actores viales implicados) | P79: Daño Material propio | Q79: Acto inseguro de Tercero | R79: N/A | S79: N/A | T79: N/A | U79: Siendo las 06:06am recibo video llamada del conductor Juan Camilo Herrera donde me informa que tuvo un incidente de transito. Estando en movimiento un vehículo tipo camión planchón cargado con madera sobredimensionada arroja un objeto metálico que al parecer se reventó de la sujeción de la carga y golpeo el panorámico de la camioneta LKK245. Este ocasiono daño al panorámico (fisuras) por lo que se detiene para verificar lo sucedido, identificar el conductor y vehículo involucrado. Se le indica tomar fotos de la novedad, informar si existen lesionados por el evento. A lo cual me informa que su integridad y la del funcionario se encuentran bien, no hay ninguna persona afectada y que solo son daños materiales mínimos. Adicional, el funcionario se comunica con su empleador para que asignen otro vehículo o si reprograman la actividad que iban a realizar. Al conocer esto, se procede a interactuar con las personas del camión (Conductor y propietario), quienes manifiestan su voluntad de pagar y reparar el daño de inmediato. Por lo que solicitan la posibilidad de que la camioneta pudiese asistir de inmediato a talleres conocidos para su inmediata reparación. Al conocer esta propuesta el funcionario informa que desde su oficina le reprograman la actividad, permitiendo que el conductor lo lleve hasta su domicilio y luego pase a taller para el cambio del panorámico. El conductor informa siendo las 10:03am que la novedad fue solucionada, el vidrio instalado y se dirige a la empresa para quedar a disposición de servicio. | V79: SI | W79: SI | X79: SI | Y79: NO | Z79: NO | AA79: Una vez el vehículo llega a patio Emprestur se dialoga de nuevo con el conductor, corroborando que los hechos iniciales e informados por este sean los mismos y que no tengan variación alguna, a lo cual todo corresponde. Verifico la instalación del panorámico afectado y no presenta novedad. | AB79: SI | AC79: https://emprestur-my.sharepoint.com/personal/alejandra_betancur_emprestur_com/Documents/Aplicaciones/Microsoft%20Forms/INFORMACI%C3%93N%20NOVEDAD%20_%20ACCIDENTES%2026042022%20(2)/SOPORTES%20PARA%20ANEXAR/WhatsApp%20Image%202025-11-28%20at%209.11.44%20AM_anonymous.jpeg; https://emprestur-my.sharepoint.com/personal/alejandra_betancur_emprestur_com/Documents/Aplicaciones/Microsoft%20Forms/INFORMACI%C3%93N%20NOVEDAD%20_%20ACCIDENTES%2026042022%20(2)/SOPORTES%20PARA%20ANEXAR/WhatsApp%20Image%202025-11-28%20at%2010.03.06%20AM_anonymous.jpeg; https://emprestur-my.sharepoint.com/personal/alejandra_betancur_emprestur_com/Documents/Aplicaciones/Microsoft%20Forms/INFORMACI%C3%93N%20NOVEDAD%20_%20ACCIDENTES%2026042022%20(2)/SOPORTES%20PARA%20ANEXAR/WhatsApp%20Image%202025-11-28%20at%209.11.53%20AM_anonymous.jpeg; https://emprestur-my.sharepoint.com/personal/alejandra_betancur_emprestur_com/Documents/Aplicaciones/Microsoft%20Forms/INFORMACI%C3%93N%20NOVEDAD%20_%20ACCIDENTES%2026042022%20(2)/SOPORTES%20PARA%20ANEXAR/WhatsApp%20Image%202025-11-28%20at%209.06.44%20AM_anonymous.jpeg; https://emprestur-my.sharepoint.com/personal/alejandra_betancur_emprestur_com/Documents/Aplicaciones/Microsoft%20Forms/INFORMACI%C3%93N%20NOVEDAD%20_%20ACCIDENTES%2026042022%20(2)/SOPORTES%20PARA%20ANEXAR/WhatsApp%20Image%202025-11-28%20at%209.03.00%20AM_anonymous.jpeg; https://emprestur-my.sharepoint.com/personal/alejandra_betancur_emprestur_com/Documents/Aplicaciones/Microsoft%20Forms/INFORMACI%C3%93N%20NOVEDAD%20_%20ACCIDENTES%2026042022%20(2)/SOPORTES%20PARA%20ANEXAR/WhatsApp%20Image%202025-11-28%20at%206.37.32%20AM_anonymous.jpeg; https://emprestur-my.sharepoint.com/personal/alejandra_betancur_emprestur_com/Documents/Aplicaciones/Microsoft%20Forms/INFORMACI%C3%93N%20NOVEDAD%20_%20ACCIDENTES%2026042022%20(2)/SOPORTES%20PARA%20ANEXAR/WhatsApp%20Image%202025-11-28%20at%206.37.11%20AM_anonymous.jpeg; https://emprestur-my.sharepoint.com/personal/alejandra_betancur_emprestur_com/Documents/Aplicaciones/Microsoft%20Forms/INFORMACI%C3%93N%20NOVEDAD%20_%20ACCIDENTES%2026042022%20(2)/SOPORTES%20PARA%20ANEXAR/WhatsApp%20Image%202025-11-28%20at%206.36.58%20AM_anonymous.jpeg; https://emprestur-my.sharepoint.com/personal/alejandra_betancur_emprestur_com/Documents/Aplicaciones/Microsoft%20Forms/INFORMACI%C3%93N%20NOVEDAD%20_%20ACCIDENTES%2026042022%20(2)/SOPORTES%20PARA%20ANEXAR/WhatsApp%20Image%202025-11-28%20at%206.12.05%20AM_anonymous.jpeg
A80: 46066.375 | B80: 46066.443 | C80: anónimo | E80: LEIDY JULIETH HIGUITA BUSTAMANTE | F80: 46065 | G80: 19:10 | H80: LPK784 | I80: CIENCIA Y TECNOLOGÍA | J80: Si | K80: 1298 | L80: DARIO MANCILLA TOVAR | M80: 10182967 | N80: 300 3790499 | O80: Accidente de tránsito y transporte dentro del desarrollo de la labor (Si ocurre en la vía con otros vehículos o con otros actores viales implicados) | P80: Daño Material propio | Q80: Acto inseguro de Tercero | R80: N/A | S80: JOHANA FLOREZ - RYUCHI MURAYMA - FREDDY ALONSO VAHOS | T80: JESÚS CASTRO | U80: En vía Cocorná una moto salió sin percatarse si en la vía había otros vehículos, lo cual ocasiono que el vehículo de marca PRADO frenará de manera repentina, de igual manera vehículo tipo DUSTER con placas LPK784 también freno, posterior a esto el vehículo tipo NPR con placas NUX444 colisiona con la DUSTER, ya que no tuvo mucho tiempo de reacción frente a la maniobra de los vehículos que frenaron de imprevisto para evitar un accidente de mayor proporción | V80: NO | W80: SI | X80: SI | Y80: NO | Z80: SI | AA80: Me comunico con el conductor para escuchar la versión de los hechos, dado que el reporte del accidente me lo realizó el propietario del vehículo. Al estar en contacto con el conductor le pregunto por el estado de él y de los ocupantes, a lo cual me indican que todos están bien, que solo fue un golpe en la parte trasera. Procede a ponerme en contacto con uno de los funcionarios, los cuales me informan que están bien y que estarán esperando al abogado de la asegurada y que ellos se quedarán con el conductor para retornar a Medellín. NO se realizó cambio de vehículo debido a que se encontraban a 3h de la cuidad, además de que los funcionarios indicaron que no era necesario hacer el reemplazo. | AB80: SI
A81: 46069.528 | B81: 46069.539 | C81: anónimo | E81: Carlos Franco | F81: 46069 | G81: 6:15 | H81: GTX204 | I81: EPM | J81: No | K81: N/A | L81: JUAN GUILLERMO VELEZ HOYOS | M81: 71777107 | N81: 3218726418 | O81: Accidente de tránsito (se produce en las vías y fuera de horario laboral) | P81: Daño Material propio | Q81: Condición insegura | R81: N/A | S81: N/A | T81: N/A | U81: "Venía por la variante de Caldas sentido sur - norte a la altura de El Tablazo y tuvimos un choque múltiple entre 4 vehículos y una moto, yo quedé de tercero pero a ninguno nos pasó nada" | V81: SI | W81: SI | X81: SI | Y81: NO | Z81: SI | AA81: Se le indica al conductor comunicarse con la aseguradora para que atiendan en el lugar y reciba asesoría | AB81: SI | AC81: https://emprestur-my.sharepoint.com/personal/alejandra_betancur_emprestur_com/Documents/Aplicaciones/Microsoft%20Forms/INFORMACI%C3%93N%20NOVEDAD%20_%20ACCIDENTES%2026042022%20(2)/SOPORTES%20PARA%20ANEXAR/WhatsApp%20Video%202026-02-16%20at%2007.31.16_anonymous.mp4
A82: 46073.639 | B82: 46073.644 | C82: anónimo | E82: Juliana Carvajal | F82: 46073 | G82: 2.30 pm | H82: NO APLICA | I82: NO APLICA | J82: Si | K82: N/A | L82: Paola Arcila | M82: 1004671855 | N82: 3001832029 | O82: Incidente de trabajo (Se pudo presentar una lesión en el trabajador) | P82: Daño Material propio | Q82: Condición insegura | R82: N/A | S82: N/A | T82: N/A | U82: * | V82: NO | W82: NO | X82: NO | Y82: NO | Z82: NO | AA82: Reportar el incidente al área SST | AB82: NO
A83: 46074.435 | B83: 46074.487 | C83: anónimo | E83: Carlos Franco | F83: 46073 | G83: 6:51 | H83: FVY879 | I83: EPM | J83: Si | K83: SDTP-00066 | L83: WILLIAM ALBERTO ESPINAL BOTERO | M83: 98571036 | N83: 3005501654 | O83: Accidente de tránsito y transporte dentro del desarrollo de la labor (Si ocurre en la vía con otros vehículos o con otros actores viales implicados) | P83: Daño Material a Tercero | Q83: Acto inseguro propio (conductor) | R83: N/A | S83: N/A | T83: N/A | U83: Llega correo con la siguiente información: "Buenos días, estimados: El día de hoy se presenta incidente vehícular por choque simple entre los vehículos de placas FVY879 de Ingetec y JXT154 de la empresa Emprestur. ¿Que sucedió?: El conductor del vehículo de placas FVY879 de la empresa Emprestur se encontraba dando reversa en el parqueadero del casino Cuní, el conductor de la camioneta de placas JXT154 de Ingetec activa la bocina para advertir al conductor que retrocedía del posible impacto, sin embargo el conductor hace caso omiso a la bocina e impactó la camioneta de Ingetec que se encontraba detenida. El conductor de la camioneta FVY879 baja del vehículo y arremete de forma grosera contra el conductor de Ingetec, no espera para revisar los daños y se va del lugar indicando que tiene afán. (Adjunto evidencia fotográfica de personal que presenció el incidente)" | V83: NO | W83: NO | X83: NO | Y83: NO | Z83: SI | AA83: Se envía correo con la novedad a SST y Talento Humano para que sea citado el conductor y dar la versión de lo hechos | AB83: SI | AC83: https://emprestur-my.sharepoint.com/personal/alejandra_betancur_emprestur_com/Documents/Aplicaciones/Microsoft%20Forms/INFORMACI%C3%93N%20NOVEDAD%20_%20ACCIDENTES%2026042022%20(2)/SOPORTES%20PARA%20ANEXAR/FVY879-INCIDENTE%20PHI_anonymous.png; https://emprestur-my.sharepoint.com/personal/alejandra_betancur_emprestur_com/Documents/Aplicaciones/Microsoft%20Forms/INFORMACI%C3%93N%20NOVEDAD%20_%20ACCIDENTES%2026042022%20(2)/SOPORTES%20PARA%20ANEXAR/FVY879-INCIDENTE%20PHI2_anonymous.png; https://emprestur-my.sharepoint.com/personal/alejandra_betancur_emprestur_com/Documents/Aplicaciones/Microsoft%20Forms/INFORMACI%C3%93N%20NOVEDAD%20_%20ACCIDENTES%2026042022%20(2)/SOPORTES%20PARA%20ANEXAR/2026-02-20%20Versi%C3%B3n%20escrita%20de%20incidentes%20Mari_anonymous.pdf
A84: 46078.634 | B84: 46078.659 | C84: anónimo | E84: JOHN FREDY CALLE RESTREPO | F84: 46078 | G84: 13:42 HORAS | H84: GTY542 | I84: ISAGEN | J84: Si | K84: no aplica | L84: ROJAS GUZMAN JUAN CARLOS | M84: 1128628081 | N84: 3146394301 | O84: Accidente de tránsito y transporte dentro del desarrollo de la labor (Si ocurre en la vía con otros vehículos o con otros actores viales implicados) | P84: Daño Material propio | Q84: Condición insegura | R84: N/A | S84: NO APLICA | T84: NO APLICA | U84: El dia miercoles 25 de febrero de 2026 siendo las 13:40 horas aproximadamente mientras el conductor Juan Carlos Rojas se desplazaba de la Dorada hacia Central Miel en la Master de placas GTY542 con los usuarios Walter Valencia, Elkin Valencia, Fredy Ortiz, Juan Felipe Saldarriaga y Claudia Rojas, a la altura del sector conocido como el km 30 corregimiento de Isaza sobre la Variante en la recta el conductor realizo maniobra de adelantamiento a un vehículo tipo camion y cuando ya estaba terminando de sobrepasarlo aparecio de frente una moto saliendo de la curva, esta situacion genero que el conductor Juan Carlos tomara la desicion de adelantar el camion incorporandose de manera inmediata al carril golpeando la parte trasera derecha de la Master contra el camion. No hubo afectacion a conductores, usuarios o terceros y tampoco afectacion física al camion. Solo se evidencia un golpe y rayones a la parte lateral derecha de la Master cerca al stop. | V84: NO | W84: SI | X84: SI | Y84: NO | Z84: SI | AA84: Se reporta a Jorge Correa y personal SST de Central Miel ISAGEN (Paulo Campiño) | AB84: SI | AC84: https://emprestur-my.sharepoint.com/personal/alejandra_betancur_emprestur_com/Documents/Aplicaciones/Microsoft%20Forms/INFORMACI%C3%93N%20NOVEDAD%20_%20ACCIDENTES%2026042022%20(2)/SOPORTES%20PARA%20ANEXAR/WhatsApp%20Image%202026-02-25%20at%203.03.13%20PM_anonymous.jpeg; https://emprestur-my.sharepoint.com/personal/alejandra_betancur_emprestur_com/Documents/Aplicaciones/Microsoft%20Forms/INFORMACI%C3%93N%20NOVEDAD%20_%20ACCIDENTES%2026042022%20(2)/SOPORTES%20PARA%20ANEXAR/WhatsApp%20Image%202026-02-25%20at%203.03.14%20PM_anonymous.jpeg; https://emprestur-my.sharepoint.com/personal/alejandra_betancur_emprestur_com/Documents/Aplicaciones/Microsoft%20Forms/INFORMACI%C3%93N%20NOVEDAD%20_%20ACCIDENTES%2026042022%20(2)/SOPORTES%20PARA%20ANEXAR/WhatsApp%20Image%202026-02-25%20at%203.03.15%20PM_anonymous.jpeg
A85: 46079.488 | B85: 46079.65 | C85: anónimo | E85: Adriana Castillo | F85: 46079 | G85: 10:54 a.m. | H85: EQT285 | I85: EPM | J85: Si | K85: N/A | L85: Diego Fernando Tavera | M85: 71941297 | N85: 3235848096 | O85: Incidente de trabajo (Se pudo presentar una lesión en el trabajador) | P85: Daño Material propio | Q85: Acto inseguro de Tercero | R85: N/A | S85: N/A | T85: N/A | U85: Yo me encontraba transportando una funcionaria de EPM estaba por el rio voy para Barbosa y una gamina le lanzó una piedra al vehículo, yo me baje a ver que le había pasado al carro y los gamines que estaban ahí le pegaron a ella, no me pude quedar mucho ahí porque estaba con funcionaria y tenia que llevarla. | V85: NO | W85: NO | X85: NO | Y85: NO | Z85: SI | AA85: Se toma la versión de los hechos, e indica que los daños solo fueron materiales y no afectaba la prestación del servicio | AB85: SI | AC85: https://emprestur-my.sharepoint.com/personal/alejandra_betancur_emprestur_com/Documents/Aplicaciones/Microsoft%20Forms/INFORMACI%C3%93N%20NOVEDAD%20_%20ACCIDENTES%2026042022%20(2)/SOPORTES%20PARA%20ANEXAR/WhatsApp%20Image%202026-02-26%20at%2011.40.12%20AM_anonymous.jpeg
A86: 46080.572 | B86: 46080.717 | C86: anónimo | E86: Adriana Castillo | F86: 45937 | G86: 4:10 p.m. | H86: JYO404 | I86: FLOTA PROPIA | J86: Si | K86: N/A | L86: Jose Marcelino Zambrano | M86: 4882920 | N86: 3046361976 | O86: Accidente de tránsito y transporte dentro del desarrollo de la labor (Si ocurre en la vía con otros vehículos o con otros actores viales implicados) | P86: Daño Material propio | Q86: Acto inseguro de Tercero | R86: N/A | S86: N/A | T86: N/A | U86: Buenas tardes : Mi nombre es José Zambrano le aclaro los hechos del golpe al vehículo JYO404 dando reversa en el parqueadero golpee el bus con el vehículo GTY556 con la carrocería . Luego salí hacer la ruta metro x la tarde ya terminando el viaje de las 4:10 pm regreso x el viaje 5:10 pm entrando a la glorieta de Monterrey había una marcha de personas x la avenida las vegas ya que un guarda de tránsito me mando a meterme en contra vía x la glorieta hacia la avenida regional y venía un motorizado con un tubo atravesado en la parrilla de la moto y me golpeo con el tubo que llevaba en la parrilla de la moto donde yo había golpeado el carro y me termino de arrancar el bomper dándose a la fuga .att: José Marcelino Zambrano Sandoval. | V86: NO | W86: NO | X86: NO | Y86: NO | Z86: NO | AA86: Se recibe las fotos de la novedad | AB86: SI | AC86: https://emprestur-my.sharepoint.com/personal/alejandra_betancur_emprestur_com/Documents/Aplicaciones/Microsoft%20Forms/INFORMACI%C3%93N%20NOVEDAD%20_%20ACCIDENTES%2026042022%20(2)/SOPORTES%20PARA%20ANEXAR/REGISTRO%20FOTOGR%C3%81FICO%20JYO404%202_anonymous.pdf
A87: 46083.461 | B87: 46083.47 | C87: anónimo | E87: Adriana Castillo | F87: 46083 | G87: 10:15 a.m. | H87: FLOTA PROPIA | I87: EPM | J87: Si | K87: N/A | L87: Diego Fernando Tavera Gomez | M87: 71941297 | N87: 3235848096 | O87: Incidente de trabajo (Se pudo presentar una lesión en el trabajador) | P87: Afectación a Personas (lesionados) | Q87: Condición insegura | R87: Conductor y/o Empleado | S87: N/A | T87: N/A | U87: Me encontraba parqueado en el edificio inteligente de EPM, esperando la funcionaria cuando paso un carro de la basura y me cayó en el ojo, me atendió una paramédico que estaba cerca donde me encontraba, me lavaron el ojo pero yo sigo sintiendo molestia, entonces me voy al centro medico | V87: SI | W87: NO | X87: SI | Y87: NO | Z87: SI | AA87: Debido a que indica que sigue con la molestia se le indica que vaya al centro medico | AB87: NO
A88: 46086.303 | B88: 46086.369 | C88: anónimo | E88: Adriana Castillo | F88: 46085 | G88: 9:25 a.m. | H88: FLOTA PROPIA | I88: EPM | J88: Si | K88: N/A | L88: Yaid Alexis Serna Zuluaga | M88: 1017153519 | N88: 3023952192 | O88: Incidente de trabajo (Se pudo presentar una lesión en el trabajador) | P88: Daño Material propio | Q88: Acto inseguro de Tercero | R88: N/A | S88: N/A | T88: N/A | U88: Yo me encontraba con el ingeniero nos encontrábamos por el alto de matasanos, para ir a Valparaíso, y en una curva me encontré un motociclista invadiendo mi carril completamente, a alta velocidad y en el momento de esquivarlo, fue cuando el vehículo terminó encunetado, al borde de la montaña, en esa maniobra se rayó el llanta derecha y se rompió la luna del retrovisor, y continué con el servicio. | V88: NO | W88: NO | X88: NO | Y88: NO | Z88: NO | AA88: Se le realiza seguimiento satelital al vehículo, y se le realiza acompañamiento. | AB88: SI | AC88: https://emprestur-my.sharepoint.com/personal/alejandra_betancur_emprestur_com/Documents/Aplicaciones/Microsoft%20Forms/INFORMACI%C3%93N%20NOVEDAD%20_%20ACCIDENTES%2026042022%20(2)/SOPORTES%20PARA%20ANEXAR/REGISTRO%20FOTOGR%C3%81FICO%20KTN224_anonymous.pdf
A89: 46086.58 | B89: 46086.602 | C89: anónimo | E89: JULIAN DAVID VALENCIA BALLESTERO | F89: 46086 | G89: 12:00 | H89: NUW974 | I89: CHEC | J89: Si | K89: TR2603269 | L89: ROBERTO FABIO GALVIS VALENCIA | M89: 4416185 | N89: 3225671638 | O89: Accidente de tránsito y transporte dentro del desarrollo de la labor (Si ocurre en la vía con otros vehículos o con otros actores viales implicados) | P89: Daño Material propio | Q89: Acto inseguro de Tercero | R89: N/A | S89: JOHN ALEXANDER VILLAMIL PATIÑO | T89: 3217014868 | U89: Reporte de Incidente Se informa que el incidente ocurrió con un camión grua, vehículo que se encuentra prestando servicio en labores con ISA. Es importante resaltar que ya se han presentado dos incidentes previos con este mismo vehículo. El hecho ocurrió cuando se desplazaba por la vía en dirección hacia Ínsula. Al tomar una curva, el camión invadió mi carril y con exceso de velocidad, quedando prácticamente encima de mi vehículo. Ante esta situación, reacciono de manera inmediata realizando una maniobra evasiva para evitar la colisión. Como consecuencia de la maniobra, el vehículo se salió hacia la cuneta, lo que ocasionó daños mecánicos, específicamente la torsión del plato del eje. Cabe resaltar que, de no haber realizado la maniobra de esquiva, el impacto se habría producido directamente en el lado donde se encontraba el funcionario, lo que pudo haber generado consecuencias graves para su integridad. | V89: NO | W89: NO | X89: SI | Y89: NO | Z89: SI | AA89: Se informa la novedad a CHEC con relación al camión involucrado en el incidente, teniendo en cuenta que dicho vehículo se encuentra prestando servicio dentro de un contrato con esta entidad. Según lo informado, el cliente correspondiente es HMV, por lo cual se procede a poner en conocimiento la situación para las verificaciones y acciones que consideren pertinentes. | AB89: SI | AC89: https://emprestur-my.sharepoint.com/personal/alejandra_betancur_emprestur_com/Documents/Aplicaciones/Microsoft%20Forms/INFORMACI%C3%93N%20NOVEDAD%20_%20ACCIDENTES%2026042022%20(2)/SOPORTES%20PARA%20ANEXAR/WhatsApp%20Image%202026-03-05%20at%2012.52.49%20PM_anonymous.jpeg; https://emprestur-my.sharepoint.com/personal/alejandra_betancur_emprestur_com/Documents/Aplicaciones/Microsoft%20Forms/INFORMACI%C3%93N%20NOVEDAD%20_%20ACCIDENTES%2026042022%20(2)/SOPORTES%20PARA%20ANEXAR/WhatsApp%20Image%202026-03-05%20at%2012.52.48%20PM%20(2)_anonymous.jpeg; https://emprestur-my.sharepoint.com/personal/alejandra_betancur_emprestur_com/Documents/Aplicaciones/Microsoft%20Forms/INFORMACI%C3%93N%20NOVEDAD%20_%20ACCIDENTES%2026042022%20(2)/SOPORTES%20PARA%20ANEXAR/WhatsApp%20Image%202026-03-05%20at%2012.52.48%20PM%20(1)_anonymous.jpeg; https://emprestur-my.sharepoint.com/personal/alejandra_betancur_emprestur_com/Documents/Aplicaciones/Microsoft%20Forms/INFORMACI%C3%93N%20NOVEDAD%20_%20ACCIDENTES%2026042022%20(2)/SOPORTES%20PARA%20ANEXAR/WhatsApp%20Image%202026-03-05%20at%2012.52.48%20PM_anonymous.jpeg; https://emprestur-my.sharepoint.com/personal/alejandra_betancur_emprestur_com/Documents/Aplicaciones/Microsoft%20Forms/INFORMACI%C3%93N%20NOVEDAD%20_%20ACCIDENTES%2026042022%20(2)/SOPORTES%20PARA%20ANEXAR/WhatsApp%20Image%202026-03-05%20at%2012.52.45%20PM%20(2)_anonymous.jpeg; https://emprestur-my.sharepoint.com/personal/alejandra_betancur_emprestur_com/Documents/Aplicaciones/Microsoft%20Forms/INFORMACI%C3%93N%20NOVEDAD%20_%20ACCIDENTES%2026042022%20(2)/SOPORTES%20PARA%20ANEXAR/WhatsApp%20Image%202026-03-05%20at%2012.52.45%20PM%20(1)_anonymous.jpeg; https://emprestur-my.sharepoint.com/personal/alejandra_betancur_emprestur_com/Documents/Aplicaciones/Microsoft%20Forms/INFORMACI%C3%93N%20NOVEDAD%20_%20ACCIDENTES%2026042022%20(2)/SOPORTES%20PARA%20ANEXAR/WhatsApp%20Image%202026-03-05%20at%2012.52.45%20PM_anonymous.jpeg
A90: 46091.54 | B90: 46091.55 | C90: anónimo | E90: Carlos Franco | F90: 46085 | G90: 16:37 | H90: ESR661 | I90: EPM | J90: Si | K90: SDTP-00069 | L90: HUGO ANDRES SANCHEZ MONTOYA | M90: 1026134434 | N90: 3122802780 | O90: Accidente de tránsito y transporte dentro del desarrollo de la labor (Si ocurre en la vía con otros vehículos o con otros actores viales implicados) | P90: Daño Material propio | Q90: Acto inseguro de Tercero | R90: N/A | S90: N/A | T90: N/A | U90: "Estaba reversando en el parqueadero de Cuní y sentí un golpe en la parte trasera y era que el otro vehículo también estaba reversando y nos dimos" | V90: NO | W90: NO | X90: NO | Y90: NO | Z90: NO | AA90: Cuando el conductor reportó ya había gestionado todo lo pertinente en el campamento con el personal encargado | AB90: SI | AC90: https://emprestur-my.sharepoint.com/personal/alejandra_betancur_emprestur_com/Documents/Aplicaciones/Microsoft%20Forms/INFORMACI%C3%93N%20NOVEDAD%20_%20ACCIDENTES%2026042022%20(2)/SOPORTES%20PARA%20ANEXAR/WhatsApp%20Video%202026-03-04%20at%2018.08.12_anonymous.mp4
A91: 46092.59 | B91: 46092.627 | C91: anónimo | E91: Adriana Castillo | F91: 46092 | G91: 7:19 a.m. | H91: Flota Propia | I91: Corporación Ayuda Humanitaria | J91: Si | K91: N/A | L91: Juan Pablo Gonzalez Padilla | M91: 1007979469 | N91: 3024190757 | O91: Incidente de trabajo (Se pudo presentar una lesión en el trabajador) | P91: Afectación a Personas (lesionados) | Q91: Acto inseguro de Tercero | R91: N/A | S91: N/A | T91: N/A | U91: Me asignaron un servicio a las 7:19 a.m., para el barrio la candelaria, en el parque Llinares, eso es en el Bronx de Medellín la muchacha se monta en el vehículo a las 7:34, para llevarla a la registraduría que queda en el 20 de Julio por san Javier, la espere y luego la lleve a las 8:50 a.m., la lleve a la fiscalía general de la nación, ya la volví a dejar en el barrio la Candelaria a las 9:15 a.m., durante los desplazamientos la muchacha tosía mucha y yo mantuve los vidrios del vehículo arriba, no tenia tapabocas en el momento. | V91: NO | W91: NO | X91: NO | Y91: NO | Z91: SI | AA91: Se reporta a SST por llamada sobre el incidente sobre una posible sospecha de persona atendida por los conductores por tuberculosis. | AB91: NO
A92: 46092.635 | B92: 46092.651 | C92: anónimo | E92: Adriana Castillo | F92: 46091 | G92: 14:13 p.m. | H92: Flota Propia | I92: Corporación Ayuda Humanitaria | J92: Si | K92: n/a | L92: Sneider Londoño Guzmán | M92: 71226535 | N92: 3136171981 | O92: Incidente de trabajo (Se pudo presentar una lesión en el trabajador) | P92: Afectación a Personas (lesionados) | Q92: Acto inseguro de Tercero | R92: N/A | S92: n/a | T92: n/a | U92: El día de ayer 10/03/2026 a las 14:13 p.m., me dirigí para Salud Total de San Diego a recoger a la usuaria, de ahí después de recogerla salimos para la fiscalia, en la fiscalia nos tocó cambiar de ruta para la vivienda de ella que es en el centro, de ahí del centro arrancamos para la playa al Epifarma a reclamar una droga, ahí la esperé ella no hacia sino toser y toser, con los vidrios cerrados por lo que estaba lloviendo no habia forma de abrir vidrios y ella tosia y tosia, fuera de eso le presté el celular como unas 6 veces ya que como ella no tenia celular en la agencia me llamaban y me indicaban que la pasara al celular, la deje en el centro a las 16:42 p.m. | V92: NO | W92: NO | X92: NO | Y92: NO | Z92: SI | AA92: Se les solicita el reporte de cuando sucedieron los hechos, y se les refuerza la indicación de las coordinadoras de CAH sobre el lavado del vehiculo y el de ir a bañarse y cambiarse de ropa | AB92: NO
A93: 46098.351 | B93: 46098.351 | C93: anónimo | E93: Adriana Castillo | F93: 46095 | G93: 11:01 a.m. | H93: flota propia | I93: N/A | J93: No | K93: N/A | L93: Mauricio Alberto Herrera Palacio | M93: 98522986 | N93: 3108865523 | O93: Incidente de trabajo (Se pudo presentar una lesión en el trabajador) | P93: Daño Material propio | Q93: Acto inseguro propio (conductor) | R93: N/A | S93: N/A | T93: N/A | U93: Buenas tardes:en el mencionado día, yo Mauricio Herrera palacio en Calidad de colaborador en el parqueadero y con plena facultad dada por el jefe de mtto. Reversando la camioneta JYO420 colisione con el manubrio de una bicicleta que se encontraba en la celda de parqueo y perdiendo visión una vez con el objeto de choque, ya cuadrado el vehículo , me bajé para revisar y efectivamente con una punta de manubrio de la bicicleta hice el daño. | V93: NO | W93: NO | X93: NO | Y93: NO | Z93: NO | AA93: Se revisa el estado del daño del vehículo. | AB93: SI | AC93: https://emprestur-my.sharepoint.com/personal/alejandra_betancur_emprestur_com/Documents/Aplicaciones/Microsoft%20Forms/INFORMACI%C3%93N%20NOVEDAD%20_%20ACCIDENTES%2026042022%20(2)/SOPORTES%20PARA%20ANEXAR/REGISTRO%20FOTOGRAFICO%20JYO420_anonymous.pdf
A94: 46100.495 | B94: 46100.499 | C94: anónimo | E94: Adriana Castillo | F94: 46097 | G94: 8:05 a.m. | H94: FLOTA PROPIA | I94: N/A | J94: No | K94: N/A | L94: Frey Jovan Alberto Londoño | M94: 98502321 | N94: 3023818072 | O94: Incidente de trabajo (Se pudo presentar una lesión en el trabajador) | P94: Daño Material propio | Q94: Acto inseguro propio (conductor) | R94: N/A | S94: N/A | T94: N/A | U94: Es para decirle de un incidente que me pasó esta mañana en mi casa cuando fui a sacar el carro a las 8:05 a.m., se me rodó y se me daño la puerta de atrás y un poco el bomper trasero eso fue con la ventana y la placa del gas de la casa | V94: NO | W94: NO | X94: NO | Y94: NO | Z94: NO | AA94: Se recibe la novedad por parte del conductor y queda a la espera de indicaciones para la reparación | AB94: SI
A95: 46100.56 | B95: 46100.566 | C95: anónimo | E95: Carlos Franco | F95: 46097 | G95: No se reporta | H95: FVY537 | I95: EPM | J95: No | K95: N/A | L95: SEBASTIAN VELASQUEZ CADAVID | M95: 1128460588 | N95: 3013294390 | O95: Accidente de tránsito (se produce en las vías y fuera de horario laboral) | P95: Daño Material a Tercero | Q95: Acto inseguro propio (conductor) | R95: N/A | S95: N/A | T95: N/A | U95: El conductor sólo informa que, reversando el bomper se le enredó en un pasamanos y se desencajó de la estructura reventándolo en una punta | V95: NO | W95: SI | X95: NO | Y95: NO | Z95: NO | AA95: N/A | AB95: SI | AC95: https://emprestur-my.sharepoint.com/personal/alejandra_betancur_emprestur_com/Documents/Aplicaciones/Microsoft%20Forms/INFORMACI%C3%93N%20NOVEDAD%20_%20ACCIDENTES%2026042022%20(2)/SOPORTES%20PARA%20ANEXAR/WhatsApp%20Image%202026-03-16%20at%2011.19.31_anonymous.jpeg
A96: 46101.423 | B96: 46101.439 | C96: anónimo | E96: Adriana Castillo | F96: 46101 | G96: 8:00 a.m. | H96: FLOTA PROPIA | I96: ISAGEN | J96: Si | K96: N/A | L96: Didier de Jesus Roldan Gaviria | M96: 98636087 | N96: 3116495275 | O96: Incidente de trabajo (Se pudo presentar una lesión en el trabajador) | P96: Daño Material propio | Q96: Acto inseguro propio (conductor) | R96: N/A | S96: N/A | T96: N/A | U96: En la mañana del día 20 de marzo de 2026, mientras me desplazaba por el sector de Pinsqui en dirección a la Central Jaguas, conduciendo el vehículo de placa GDZ086 y sin pasajeros a bordo, se presentó un incidente en la vía. En sentido contrario descendía un vehículo tipo volqueta de color rojo, el cual transitaba a alta velocidad. Con el fin de ceder el paso y evitar una posible colisión, procedí a orillarme hacia el costado derecho de la vía. Durante esta maniobra, me aproximé demasiado al borde de la carretera, sin percatarme de la presencia de un palo oculto entre el rastrojo. Este elemento impactó contra el vehículo, ocasionando la ruptura de un vidrio ubicado en el costado derecho, específicamente en la puerta de acceso de pasajeros. Consecuencias: Daño material: ruptura de un vidrio lateral derecho del vehículo. No se presentaron personas lesionadas. Observaciones: No fue posible identificar la placa del vehículo tipo volqueta involucrado, debido a la rapidez con la que ocurrieron los hechos. | V96: NO | W96: NO | X96: NO | Y96: NO | Z96: SI | AA96: realiza la toma de versión | AB96: SI | AC96: https://emprestur-my.sharepoint.com/personal/alejandra_betancur_emprestur_com/Documents/Aplicaciones/Microsoft%20Forms/INFORMACI%C3%93N%20NOVEDAD%20_%20ACCIDENTES%2026042022%20(2)/SOPORTES%20PARA%20ANEXAR/REGISTRO%20FOTOGR%C3%81FICO%20GDZ086_anonymous.pdf
A97: 46105.636 | B97: 46105.642 | C97: anónimo | E97: Carlos Franco | F97: 46103 | G97: No se tiene información | H97: NNN114 | I97: EPM | J97: No | K97: N/A | L97: FABIO NELSON CADAVID GOMEZ | M97: 9977142 | N97: 3007501624 | O97: Accidente de tránsito (se produce en las vías y fuera de horario laboral) | P97: Daño Material propio | Q97: Acto inseguro de Tercero | R97: Tercero (Comunidad) | S97: No se tiene información | T97: N/A | U97: Se recibe mensaje el domingo en la mañana donde el conductor reporta accidente porque un motocarro invadió su carril y al preguntarle que si le había pasado algo manifiesta que no y al preguntar por el conductor del otro vehículo informa que falleció camino al hospital. | V97: NO | W97: NO | X97: NO | Y97: NO | Z97: NO | AA97: Desde ese día estoy pendiente de la información completa de lo sucedido (fecha, hora, lugar exacto, lesionados, etc.) para hacer el reporte por este medio, pero no ha sido posible | AB97: SI | AC97: https://emprestur-my.sharepoint.com/personal/alejandra_betancur_emprestur_com/Documents/Aplicaciones/Microsoft%20Forms/INFORMACI%C3%93N%20NOVEDAD%20_%20ACCIDENTES%2026042022%20(2)/SOPORTES%20PARA%20ANEXAR/WhatsApp%20Image%202026-03-24%20at%2015.14.35_anonymous.jpeg; https://emprestur-my.sharepoint.com/personal/alejandra_betancur_emprestur_com/Documents/Aplicaciones/Microsoft%20Forms/INFORMACI%C3%93N%20NOVEDAD%20_%20ACCIDENTES%2026042022%20(2)/SOPORTES%20PARA%20ANEXAR/WhatsApp%20Image%202026-03-24%20at%2015.14.35%20(1)_anonymous.jpeg; https://emprestur-my.sharepoint.com/personal/alejandra_betancur_emprestur_com/Documents/Aplicaciones/Microsoft%20Forms/INFORMACI%C3%93N%20NOVEDAD%20_%20ACCIDENTES%2026042022%20(2)/SOPORTES%20PARA%20ANEXAR/WhatsApp%20Image%202026-03-24%20at%2015.14.35%20(2)_anonymous.jpeg; https://emprestur-my.sharepoint.com/personal/alejandra_betancur_emprestur_com/Documents/Aplicaciones/Microsoft%20Forms/INFORMACI%C3%93N%20NOVEDAD%20_%20ACCIDENTES%2026042022%20(2)/SOPORTES%20PARA%20ANEXAR/WhatsApp%20Image%202026-03-24%20at%2015.14.35%20(3)_anonymous.jpeg
A98: 46112.521 | B98: 46112.649 | C98: anónimo | E98: Adriana Castillo | F98: 46112 | G98: 12:18 p.m. | H98: Flota Propia | I98: Corporación Ayuda Humanitaria | J98: Si | K98: N/A | L98: CARLOS MARIO GUZMAN LOTERO | M98: 1017154790 | N98: 3136882386 | O98: Accidente de tránsito y transporte dentro del desarrollo de la labor (Si ocurre en la vía con otros vehículos o con otros actores viales implicados) | P98: Daño Material propio | Q98: Acto inseguro de Tercero | R98: N/A | S98: n/a | T98: N/A | U98: Buenas tardes, me encontraba en la sede del 123 para salir a hacer un desplazamiento, cuando me dispongo a salir al otro carril por la izquierda, el vehículo que iba adelante deja rodar el carro y me le pega al bómper del vehículo. | V98: NO | W98: NO | X98: SI | Y98: NO | Z98: SI | AA98: Se le toma la versión inicial, y se realiza acompañamiento sobre la negociación del daño | AB98: SI | AC98: https://emprestur-my.sharepoint.com/personal/alejandra_betancur_emprestur_com/Documents/Aplicaciones/Microsoft%20Forms/INFORMACI%C3%93N%20NOVEDAD%20_%20ACCIDENTES%2026042022%20(2)/SOPORTES%20PARA%20ANEXAR/REGISTRO%20FOTOGRAFICO%20LKL764_anonymous.pdf
A99: 46114.425 | B99: 46114.431 | C99: anónimo | E99: JONATHAN GIRALDO ORREGO | F99: 46113 | G99: 4:20 PM | H99: PXK627 | I99: ISAGEN | J99: Si | K99: MASIVO SAN CARLOS - MEDELLIN | L99: LEONEL ALEXANDER VARGAS GARCIA | M99: 71174247 | N99: 3146391790 | O99: Accidente de tránsito y transporte dentro del desarrollo de la labor (Si ocurre en la vía con otros vehículos o con otros actores viales implicados) | P99: Daño Material a Tercero | Q99: Acto inseguro propio (conductor) | R99: N/A | S99: N/A | T99: N/A | U99: Por medio del presente, me permito notificar un incidente ocurrido el día 01 de abril de 2026, con el conductor LEONEL ALEXANDER VARGAS GARCIA cc 71174247, quien se encuentra asignado al contrato de ISAGEN y operaba el vehículo de placas PXK627 mientras cubría la ruta central San Carlos - Medellín. Según información del conductor siendo aproximadamente a las 4:20 p.m., en el parque principal del municipio de San Rafael, Antioquia, zona con alta congestión vehicular y presencia de vehículos y motocicletas estacionadas en ambos costados de la vía— realizó una maniobra de giro hacia la derecha con espacio reducido. Durante dicha maniobra, y debido a las condiciones de visibilidad limitada (retrovisor izquierdo mojado por lluvia y poco margen de maniobra), una motocicleta estacionada en el costado izquierdo fue impactada levemente con el carro de la empresa, ocasionando caída al suelo. En el lugar se encontraba una agente de tránsito, quien procedió a levantar la motocicleta con el fin de despejar la vía. Según lo manifestado por el conductor, se realizó una revisión visual junto con la agente, sin evidenciar daños aparentes en la motocicleta. El propietario de la moto no se encontraba en el lugar al momento del incidente, por lo que no fue posible realizar verificación conjunta ni dejar registro directo con el tercero afectado. Observaciones relevantes: No se cuenta con registro fotográfico del evento ni del estado de la motocicleta y no contamos con la placa de ella. La motocicleta fue levantada del suelo por la autoridad de tránsito (según versión del conductor). Existe riesgo de posible reclamación posterior por parte del propietario, debido a la ausencia de evidencia fotográfica y del tercero en el sitio. El vehículo de la Empresa PXK627 sufre rayón leve en parte trasera izquierda. (Ver foto anexa) El conductor no reporto la novedad de manera inmediata a flota propia, solo hasta las 8:50 pm fuimos enterados por el conductor. Se anexa version de los hechos del conductor. Teniendo en cuenta lo anterior, agradezco por favor me ayuden con lo siguiente: @Angie Arzuza - @Alejandra Betancur Por favor su ayuda realizando el proceso de investigación del incidente, conforme a los procedimientos establecidos. el evento se registro en el enlace. @Juridica Emprestur - @Jennifer Posada - @Manuela Jaramillo Se pone en conocimiento del área jurídica, agencia de seguros y talento humano el presente caso, con el fin de evaluar y anticipar posibles acciones ante una eventual reclamación derivada de este evento. @Juan Gallo Por favor nos compartes los videos del evento dado que no logre sacarlos del sistema (no me aparece este vehículo en la plataforma) ademas del registro de velocidad al que iba el vehículo. Quedo atento a cualquier requerimiento adicional. | V99: NO | W99: NO | X99: NO | Y99: NO | Z99: SI | AA99: El conductor informo que le reporto el evento a Angie y ella informo que debia reportarnos a flota. | AB99: NO
A100: 46119.46 | B100: 46119.578 | C100: anónimo | E100: Adriana Castillo | F100: 46113 | G100: 13:07 p.m. | H100: JRP195 | I100: ISAGEN | J100: No | K100: N/A | L100: Juan Carlos Rojas Guzman | M100: 1128628081 | N100: 3146394301 | O100: Incidente de trabajo (Se pudo presentar una lesión en el trabajador) | P100: Daño Material propio | Q100: Acto inseguro propio (conductor) | R100: N/A | S100: N/A | T100: N/A | U100: Yo salí a tanquear el bus de placas JRP 195 a Norcasia , regresando de tanquear hacía la central cuando cojo el cruce que viene de la variante hacia la central, paro a saludar a un compañero que trabaja en el casino y en el momento de abrir la ventanilla del conductor se estalla , en el momento que abro y llegar al tope de la ventanilla, golpea con una esquina del marco de la ventanilla y se estalla. | V100: NO | W100: NO | X100: SI | Y100: NO | Z100: NO | AA100: se da las indicaciones de reportar al área de flota propia | AB100: SI | AC100: https://emprestur-my.sharepoint.com/personal/alejandra_betancur_emprestur_com/Documents/Aplicaciones/Microsoft%20Forms/INFORMACI%C3%93N%20NOVEDAD%20_%20ACCIDENTES%2026042022%20(2)/SOPORTES%20PARA%20ANEXAR/REGISTRO%20FOTOGRAFICO%20JRP195_anonymous.pdf
A101: 46122.331 | B101: 46122.336 | C101: anónimo | E101: JONATHAN GIRALDO ORREGO | F101: 46120 | G101: 9:25 PM | H101: GTX035 | I101: CORPORACION AYUDA HUMANITARIA | J101: Si | K101: NIÑES | L101: LEONARDO ANTONIO BAQUERO LASTRE | M101: 1047460435 | N101: 3227577650 | O101: Accidente de tránsito y transporte dentro del desarrollo de la labor (Si ocurre en la vía con otros vehículos o con otros actores viales implicados) | P101: Daño Material propio | Q101: Acto inseguro de Tercero | R101: N/A | S101: N/A | T101: N/A | U101: Buenos días a todos Espero estén muy bien. Informamos que el día de Miércoles 8 de abril, aproximadamente a las 9:25 p.m., el conductor LEONARDO ANTONIO BAQUERO LASTRE CC 1047460435 del vehículo de placas GTX035 presentó una novedad al ser impactado por un taxi de placas STW118 en la parte trasera, generando una afectación leve en el bómper. El conductor del taxi manifestó su intensión de que se llegara a un acuerdo entre las partes por lo cual inicialmente le solicite 300.000 mil pesos por la afectación sin embargo este manifestó no tener esa cantidad de dinero y nos hizo una contrapropuesta por 200.000 mil pesos, recibiendo la suma de $200.000 en efectivo, los cuales serán entregados al área de Tesorería el día de hoy. Se deja en copia a Contabilidad para que este valor sea tenido en cuenta como ingreso de flota, asociado a la futura reparación del vehículo. se registra novedad en el enlace. Quedamos atentos a sus comentarios. | V101: NO | W101: NO | X101: NO | Y101: NO | Z101: NO | AA101: Se llega a acuerdo con el tecero que nos genero afectacion. | AB101: SI | AC101: https://emprestur-my.sharepoint.com/personal/alejandra_betancur_emprestur_com/Documents/Aplicaciones/Microsoft%20Forms/INFORMACI%C3%93N%20NOVEDAD%20_%20ACCIDENTES%2026042022%20(2)/SOPORTES%20PARA%20ANEXAR/FOTOS%20ACCIDENTE%20GTX035._anonymous.pdf
A102: 46125.503 | B102: 46125.531 | C102: anónimo | E102: Santiago Amaya | F102: 46124 | G102: 13:00 horas | H102: PXK507 | I102: SURA | J102: Si | K102: 1221 | L102: JORGE ARMANDO ZAPATA SALINAS | M102: 8032911 | N102: 3106507501 | O102: Accidente de tránsito y transporte dentro del desarrollo de la labor (Si ocurre en la vía con otros vehículos o con otros actores viales implicados) | P102: Daño Material propio | Q102: Acto inseguro propio (conductor) | R102: N/A | S102: Cristhell salcededo | T102: . | U102: Yo estaba detrás del bus parado en semáforo apenas cambio el semaforo arrancamos el bus giro a la derecha igual yo como estaba buscando un restaurante para la médica mire por la ventanilla izquierda en el momento el bus paro ni me fijé colisione contra el bus | V102: SI | W102: SI | X102: SI | Y102: NO | Z102: NO | AA102: Se envia relevo al lugar del accidente y se indica que haga la llamada a la aseguradora | AB102: SI | AC102: https://emprestur-my.sharepoint.com/personal/alejandra_betancur_emprestur_com/Documents/Aplicaciones/Microsoft%20Forms/INFORMACI%C3%93N%20NOVEDAD%20_%20ACCIDENTES%2026042022%20(2)/SOPORTES%20PARA%20ANEXAR/WhatsApp%20Image%202026-04-12%20at%208.09.07%20PM_anonymous.jpeg; https://emprestur-my.sharepoint.com/personal/alejandra_betancur_emprestur_com/Documents/Aplicaciones/Microsoft%20Forms/INFORMACI%C3%93N%20NOVEDAD%20_%20ACCIDENTES%2026042022%20(2)/SOPORTES%20PARA%20ANEXAR/WhatsApp%20Image%202026-04-12%20at%208.09.06%20PM_anonymous.jpeg; https://emprestur-my.sharepoint.com/personal/alejandra_betancur_emprestur_com/Documents/Aplicaciones/Microsoft%20Forms/INFORMACI%C3%93N%20NOVEDAD%20_%20ACCIDENTES%2026042022%20(2)/SOPORTES%20PARA%20ANEXAR/WhatsApp%20Image%202026-04-12%20at%208.09.03%20PM%20(2)_anonymous.jpeg; https://emprestur-my.sharepoint.com/personal/alejandra_betancur_emprestur_com/Documents/Aplicaciones/Microsoft%20Forms/INFORMACI%C3%93N%20NOVEDAD%20_%20ACCIDENTES%2026042022%20(2)/SOPORTES%20PARA%20ANEXAR/WhatsApp%20Image%202026-04-12%20at%208.09.03%20PM%20(1)_anonymous.jpeg; https://emprestur-my.sharepoint.com/personal/alejandra_betancur_emprestur_com/Documents/Aplicaciones/Microsoft%20Forms/INFORMACI%C3%93N%20NOVEDAD%20_%20ACCIDENTES%2026042022%20(2)/SOPORTES%20PARA%20ANEXAR/WhatsApp%20Image%202026-04-12%20at%208.09.03%20PM_anonymous.jpeg; https://emprestur-my.sharepoint.com/personal/alejandra_betancur_emprestur_com/Documents/Aplicaciones/Microsoft%20Forms/INFORMACI%C3%93N%20NOVEDAD%20_%20ACCIDENTES%2026042022%20(2)/SOPORTES%20PARA%20ANEXAR/WhatsApp%20Image%202026-04-12%20at%208.09.02%20PM%20(1)_anonymous.jpeg; https://emprestur-my.sharepoint.com/personal/alejandra_betancur_emprestur_com/Documents/Aplicaciones/Microsoft%20Forms/INFORMACI%C3%93N%20NOVEDAD%20_%20ACCIDENTES%2026042022%20(2)/SOPORTES%20PARA%20ANEXAR/WhatsApp%20Image%202026-04-12%20at%208.09.02%20PM_anonymous.jpeg
A103: 46127.603 | B103: 46127.608 | C103: anónimo | E103: DAYHANA SOSSA | F103: 46127 | G103: 10:58 | H103: JYM622 | I103: CAH | J103: Si | K103: 2094 | L103: DAVINSON ARLEY CORREA SUCERQUIA | M103: 1037776812 | N103: 1037776812 | O103: Accidente de tránsito y transporte dentro del desarrollo de la labor (Si ocurre en la vía con otros vehículos o con otros actores viales implicados) | P103: Daño Material propio | Q103: Acto inseguro de Tercero | R103: N/A | S103: N/A | T103: N/A | U103: El conductor manifiesta que se le atraviesa un taxi que viene a su lado izquierdo, ocasionado que este frene de inmediato, en medio del freno en seco, dos vehículos lo impactan por la parte trasera... | V103: SI | W103: SI | X103: SI | Y103: SI | Z103: SI | AA103: Me comunico con el conductor para preguntar por el estado de salud y por la gravedad del siniestro. Reporto de manera inmediata al ARL | AB103: SI
A104: 46132.58 | B104: 46132.666 | C104: anónimo | E104: Carlos Franco | F104: 46131 | G104: 20:00 | H104: FWK335 | I104: EPM | J104: No | K104: N/A | L104: NELSON DE JESUS TABORDA GOMEZ | M104: 70253116 | N104: 3116136770 | O104: Accidente de tránsito (se produce en las vías y fuera de horario laboral) | P104: Afectación a Personas (lesionados) | Q104: Acto inseguro de Tercero | R104: Tercero (Comunidad) | S104: Willian | T104: N/A | U104: "Iba para mi casa después de haber llevado el carro a lavar y cuando iba por la autopista sentido norte - sur por Zenú al intentar girar a mano derecha un motociclista se adelantó por ese lado y lo alcancé a golpear tirándolo al suelo con la parrillera, después llegó el tránsito y la ambulancia para revisarlos, pero no les pasó nada y a mí me hicieron prueba de alcohol y me inmovilizaron el vehículo y quitaron la licencia ya que me había tomado 2 cervezas y salió positiva" | V104: NO | W104: NO | X104: NO | Y104: NO | Z104: NO | AA104: El conductor apenas informó de la novedad el día de hoy enviando una sólo foto de lo sucedido y presenta carta de renuncia | AB104: SI | AC104: https://emprestur-my.sharepoint.com/personal/alejandra_betancur_emprestur_com/Documents/Aplicaciones/Microsoft%20Forms/INFORMACI%C3%93N%20NOVEDAD%20_%20ACCIDENTES%2026042022%20(2)/SOPORTES%20PARA%20ANEXAR/WhatsApp%20Image%202026-04-20%20at%2013.26.31_anonymous.jpeg
A105: 46133.654 | B105: 46133.657 | C105: anónimo | E105: DAYHANA SOSSA | F105: 46133 | G105: 03:41 | H105: NLW559 | I105: CAH | J105: Si | K105: 2094 | L105: OVIDIO DE JESUS | M105: 71677396 | N105: 311 7188011 | O105: Accidente de tránsito y transporte dentro del desarrollo de la labor (Si ocurre en la vía con otros vehículos o con otros actores viales implicados) | P105: Daño Material propio | Q105: Acto inseguro de Tercero | R105: N/A | S105: N/A | T105: N/A | U105: AUN NO SE ME REPORTAN | V105: SI | W105: SI | X105: SI | Y105: SI | Z105: SI | AA105: N/A | AB105: SI
