Workbook

Sheet 2026 INFRACCIONES 
A1: Cedula | B1: Nombre completo | C1: CLIENTE | D1: Tipo de Contrato | E1: Ciudad | F1: Fecha Infracción | G1: Lugar de la Infraccion | H1: Código infracción | I1: Placa | J1: Descripción Infracciones | K1: Valor Infracción | L1: Mes | M1: Año | N1: Tipo de Acción | O1: Fecha de Notificación | P1: Clase de Capacitación | Q1: Control Infracciones | R1: ESTADO DEL EMPLEADO EN LA EMPRESA | S1: DEVOLUCION NOTIFICACION FIRMADA | T1: CAPACITACION Y EVALUACION | U1: INFRACCIÓN SE DA EN DESARROLLO DE LA LABOR | V1: ENTREGA COMPROBANTE DE PAGO | W1: Observaciones
A2: 1036132399 | B2: =VLOOKUP(A2,'[1] BD CONDUCTORES'!$A$2:$B$691,2,FALSE) -> ARAGON JIMENEZ EDUARD YAIR | C2: UT MEJIA Y ACEVEDO SYE VOLQUET | D2: TERCEROS | E2: MEDELLIN | F2: 45681 | G2: Bello | H2: C02 | I2: TAV412 | J2: =VLOOKUP(H2,VALIDACIONES!$A$2:$B$138,2,0) -> Estacionar un vehículo en los sitios prohibidos por el Código Nacional de Tránsito, reglamentado por la Res.3027. | K2: 603917 | L2: =MONTH(F2) -> 1 | M2: =YEAR(F2) -> 2025 | N2: CAPACITACIÓN | O2: 45747 | P2: CAPACITACIÓN MANEJO DEFENSIVO | Q2: NO PAGO | R2: ACTIVO | S2: NO | T2: SI | U2: SI | V2: NO | W2: Se le envia el mensaje los doccumenos pero solo contesta con un "OK", no se a podido tener una conversacion con el señor ya que no contesta llamadas
A3: 71666329 | B3: =VLOOKUP(A3,'[1] BD CONDUCTORES'!$A$2:$B$691,2,FALSE) -> ORTIZ FORONDA JORGE ALBERTO | C3: EPM NUEVO | D3: TERCEROS | E3: MEDELLIN | F3: 45670 | G3: Medellin | H3: C02 | J3: =VLOOKUP(H3,VALIDACIONES!$A$2:$B$138,2,0) -> Estacionar un vehículo en los sitios prohibidos por el Código Nacional de Tránsito, reglamentado por la Res.3027. | K3: 604054 | L3: =MONTH(F3) -> 1 | M3: =YEAR(F3) -> 2025 | N3: CAPACITACIÓN | O3: 45747 | P3: CAPACITACIÓN MANEJO DEFENSIVO | Q3: PAGO | R3: ACTIVO | S3: SI | T3: SI | U3: SI | V3: NO | W3: el señor tiene una tutela por ese motivo no la a pagado esperando que le quiten este informe, esta con el abogado.
A4: 8152105 | B4: =VLOOKUP(A4,'[1] BD CONDUCTORES'!$A$2:$B$691,2,FALSE) -> RESTREPO MESA CARLOS ALBEIRO | C4: EPM NUEVO | D4: TERCEROS | E4: MEDELLIN | F4: 45677 | G4: Santa Rosa de Osos | H4: C02 | J4: =VLOOKUP(H4,VALIDACIONES!$A$2:$B$138,2,0) -> Estacionar un vehículo en los sitios prohibidos por el Código Nacional de Tránsito, reglamentado por la Res.3027. | K4: 377448 | L4: =MONTH(F4) -> 1 | M4: =YEAR(F4) -> 2025 | N4: CAPACITACIÓN | O4: 45747 | P4: CAPACITACIÓN MANEJO DEFENSIVO | Q4: PAGO | R4: ACTIVO | S4: NO | T4: SI | U4: SI | V4: SI
A5: 98624721 | B5: =VLOOKUP(A5,'[1] BD CONDUCTORES'!$A$2:$B$691,2,FALSE) -> SANCHEZ OTALVARO WILFER ELIECE | C5: CORPORACION AYUDA HUMANITARIA | D5: TERCEROS | E5: MEDELLIN | F5: 45686 | G5: Medellin | H5: C02 | J5: =VLOOKUP(H5,VALIDACIONES!$A$2:$B$138,2,0) -> Estacionar un vehículo en los sitios prohibidos por el Código Nacional de Tránsito, reglamentado por la Res.3027. | K5: 604054 | L5: =MONTH(F5) -> 1 | M5: =YEAR(F5) -> 2025 | N5: CAPACITACIÓN | O5: 45747 | P5: CAPACITACIÓN MANEJO DEFENSIVO | Q5: PAGO | R5: ACTIVO | S5: NO | T5: SI | U5: SI | V5: NO
A6: 70565141 | B6: =VLOOKUP(A6,'[1] BD CONDUCTORES'!$A$2:$B$691,2,FALSE) -> JARAMILLO GIL CARLOS ALBERTO | C6: EPM NUEVO | D6: TERCEROS | E6: MEDELLIN | F6: 45693 | G6: Medellin | H6: C02 | J6: =VLOOKUP(H6,VALIDACIONES!$A$2:$B$138,2,0) -> Estacionar un vehículo en los sitios prohibidos por el Código Nacional de Tránsito, reglamentado por la Res.3027. | K6: 603917 | L6: =MONTH(F6) -> 2 | M6: =YEAR(F6) -> 2025 | N6: CAPACITACIÓN | O6: 45747 | P6: CAPACITACIÓN MANEJO DEFENSIVO | Q6: PAGO | R6: ACTIVO | S6: NO | T6: NO | V6: NO
A7: 71784723 | B7: =VLOOKUP(A7,'[1] BD CONDUCTORES'!$A$2:$B$691,2,FALSE) -> MARIN MUÑOZ JOSE ALEXANDER | C7: EPM NUEVO | D7: TERCEROS | E7: MEDELLIN | F7: 45712 | G7: Medellin | H7: C02 | J7: =VLOOKUP(H7,VALIDACIONES!$A$2:$B$138,2,0) -> Estacionar un vehículo en los sitios prohibidos por el Código Nacional de Tránsito, reglamentado por la Res.3027. | K7: 604054 | L7: =MONTH(F7) -> 2 | M7: =YEAR(F7) -> 2025 | N7: CAPACITACIÓN | O7: 45747 | P7: CAPACITACIÓN MANEJO DEFENSIVO | Q7: NO PAGO | R7: ACTIVO | S7: NO | T7: NO | U7: NO | V7: NO
A8: 1023831141 | B8: =VLOOKUP(A8,'[1] BD CONDUCTORES'!$A$2:$B$691,2,FALSE) -> ARBOLEDA GALLEGO JORGE LUIS | C8: EPM NUEVO | D8: TERCEROS | E8: MEDELLIN | F8: 44745 | G8: Medellin | H8: F | J8: se refiere a la infracción de conducir bajo el influjo del alcohol o bajo los efectos de sustancias psicoactivas | K8: 22485447 | L8: =MONTH(F8) -> 7 | M8: =YEAR(F8) -> 2022 | N8: RETIRO
A9: 75087065 | B9: =VLOOKUP(A9,'[1] BD CONDUCTORES'!$A$2:$B$691,2,FALSE) -> CORTES MONTES JUAN DAVID | C9: CHEC | D9: TERCEROS | E9: MANIZALES | F9: 45728 | G9: Manizales | H9: D04 | I9: AXC30E | J9: =VLOOKUP(H9,VALIDACIONES!$A$2:$B$138,2,0) -> Nodetenerseanteunaluzrojaoamarilladesemáforo,unaseñalde"PARE"ounsemáforointermitenteenrojo.Enelcasodemotocicletaseprocederaasuinmovilizaciónhastatantonosepagueelvalordelamultaolaautoridadcompetentedecidasobresuimposicionenlosterminosdelosarticulos135y136delcódigonacionaldetránsito. | K9: 1207855 | L9: =MONTH(F9) -> 3 | M9: =YEAR(F9) -> 2025 | N9: CAPACITACIÓN | O9: 45777 | P9: CAPACITACIÓN MANEJO DEFENSIVO | Q9: NO PAGO | R9: ACTIVO | S9: SI | T9: SI | U9: NO | V9: NO
A10: 70033808 | B10: LOPEZ ECHEVERRY HECTOR RAMIRO | C10: EPM NUEVO | D10: TERCEROS | E10: MEDELLIN | F10: 45736 | G10: La Dorada | H10: C29 | J10: =VLOOKUP(H10,VALIDACIONES!$A$2:$B$138,2,0) -> Conducir un vehículo a velocidad superior a la máxima permitida, la cual deberá estar señalizada en forma sectorizada, no obstante esta no podrá ser superior a (verlistado) | K10: 603930 | L10: =MONTH(F10) -> 3 | M10: =YEAR(F10) -> 2025 | N10: CAPACITACIÓN | O10: 45777 | P10: CAPACITACIÓN MANEJO DEFENSIVO | Q10: PAGO | R10: ACTIVO | S10: NO | T10: NO | V10: NO
A11: 15509092 | B11: =VLOOKUP(A11,'[1] BD CONDUCTORES'!$A$2:$B$691,2,FALSE) -> MISAS RUEDA LUIS ALBEIRO | C11: GRUPO SURA | D11: TERCEROS | E11: MEDELLIN | F11: 45745 | G11: Medellin | H11: C02 | J11: =VLOOKUP(H11,VALIDACIONES!$A$2:$B$138,2,0) -> Estacionar un vehículo en los sitios prohibidos por el Código Nacional de Tránsito, reglamentado por la Res.3027. | K11: 604054 | L11: =MONTH(F11) -> 3 | M11: =YEAR(F11) -> 2025 | N11: CAPACITACIÓN | O11: 45777 | P11: CAPACITACIÓN MANEJO DEFENSIVO | Q11: PAGO | R11: ACTIVO | S11: NO | T11: NO | V11: NO
A12: 1017153007 | B12: LOPEZ VALENCIA YOJANA | C12: ADMINISTRATIVO | D12: TERCEROS | E12: MEDELLIN | F12: 45766 | G12: Itagui | H12: C29 | I12: FVY741 | J12: =VLOOKUP(H12,VALIDACIONES!$A$2:$B$138,2,0) -> Conducir un vehículo a velocidad superior a la máxima permitida, la cual deberá estar señalizada en forma sectorizada, no obstante esta no podrá ser superior a (verlistado) | K12: 603930 | L12: =MONTH(F12) -> 4 | M12: =YEAR(F12) -> 2025 | N12: CAPACITACIÓN | O12: 45793 | P12: CAPACITACIÓN MANEJO DEFENSIVO | Q12: NO PAGO | R12: ACTIVO | S12: NO | T12: SI | U12: SI | V12: NO
A13: 79909780 | B13: =VLOOKUP(A13,'[1] BD CONDUCTORES'!$A$2:$B$691,2,FALSE) -> LOPEZ MARTINEZ DARLEY | C13: CHEC | D13: TERCEROS | E13: MANIZALES | F13: 45758 | G13: Manizales | H13: D04 | I13: ESL086 | J13: =VLOOKUP(H13,VALIDACIONES!$A$2:$B$138,2,0) -> Nodetenerseanteunaluzrojaoamarilladesemáforo,unaseñalde"PARE"ounsemáforointermitenteenrojo.Enelcasodemotocicletaseprocederaasuinmovilizaciónhastatantonosepagueelvalordelamultaolaautoridadcompetentedecidasobresuimposicionenlosterminosdelosarticulos135y136delcódigonacionaldetránsito. | K13: 1207855 | L13: =MONTH(F13) -> 4 | M13: =YEAR(F13) -> 2025 | N13: CAPACITACIÓN | O13: 45793 | P13: CAPACITACIÓN MANEJO DEFENSIVO | Q13: PAGO | R13: ACTIVO | S13: SI | T13: SI | U13: SI | V13: SI
A14: 71223585 | B14: =VLOOKUP(A14,'[1] BD CONDUCTORES'!$A$2:$B$691,2,FALSE) -> CASTRILLON LOPEZ CARLOS ANDRES | C14: EPM NUEVO | D14: TERCEROS | E14: MEDELLIN | F14: 45754 | G14: Medellin | H14: C02 | I14: JYY056 | J14: =VLOOKUP(H14,VALIDACIONES!$A$2:$B$138,2,0) -> Estacionar un vehículo en los sitios prohibidos por el Código Nacional de Tránsito, reglamentado por la Res.3027. | K14: 604054 | L14: =MONTH(F14) -> 4 | M14: =YEAR(F14) -> 2025 | N14: CAPACITACIÓN | O14: 45793 | P14: CAPACITACIÓN MANEJO DEFENSIVO | Q14: NO PAGO | R14: ACTIVO | S14: SI | T14: SI | U14: SI | V14: NO
A15: 1036638930 | B15: =VLOOKUP(A15,'[1] BD CONDUCTORES'!$A$2:$B$691,2,FALSE) -> GARCIA SEPULVEDA SEBASTIAN | C15: JARDIN BOTANICO | D15: TERCEROS | E15: MEDELLIN | F15: 45749 | G15: Bello | H15: H13 | I15: ABS962 | J15: =VLOOKUP(H15,VALIDACIONES!$A$2:$B$138,2,0) -> Las demas conductas que constituyan infraccion a las normas de transito y que no se encuentren descritas en este acto administrativo. | K15: 201351 | L15: =MONTH(F15) -> 4 | M15: =YEAR(F15) -> 2025 | N15: CAPACITACIÓN | Q15: PAGO | R15: ACTIVO | S15: NO | T15: NO | V15: NO
A16: 1060649387 | B16: =VLOOKUP(A16,'[1] BD CONDUCTORES'!$A$2:$B$691,2,FALSE) -> PATIÑO ALVAREZ JOHAN SEBASTIAN | C16: CHEC | D16: TERCEROS | E16: MANIZALES | F16: 45770 | G16: Manizales | H16: C35 | I16: NQV89F | J16: =VLOOKUP(H16,VALIDACIONES!$A$2:$B$138,2,0) -> No realizar la revisión técnico mecánica y de emisiones en los siguientes plazos o cuando aún portando los certificados correspondientes no cuenta con las siguientes condiciones tecnicomecánica y de emisiones contaminantes, además el vehiculo será inmovilizado.(verlistado) | K16: 603928 | L16: =MONTH(F16) -> 4 | M16: =YEAR(F16) -> 2025 | N16: CAPACITACIÓN | O16: 45793 | P16: CAPACITACIÓN MANEJO DEFENSIVO | Q16: PAGO | R16: ACTIVO | S16: SI | T16: SI | U16: NO | V16: SI
A17: 1060649387 | B17: =VLOOKUP(A17,'[1] BD CONDUCTORES'!$A$2:$B$691,2,FALSE) -> PATIÑO ALVAREZ JOHAN SEBASTIAN | C17: CHEC | D17: TERCEROS | E17: MANIZALES | F17: 45770 | G17: Manizales | H17: D02 | I17: NQV89F | J17: =VLOOKUP(H17,VALIDACIONES!$A$2:$B$138,2,0) -> ConducirsinportarelSeguroObligatoriodeAccidentesdetránsitoordenadoporlaley.Además,elvehículoseráinmovilizado. | K17: 1207855 | L17: =MONTH(F17) -> 4 | M17: =YEAR(F17) -> 2025 | N17: CAPACITACIÓN | O17: 45793 | P17: CAPACITACIÓN MANEJO DEFENSIVO | Q17: PAGO | R17: ACTIVO | S17: SI | T17: SI | U17: NO | V17: SI
A18: 1018376618 | B18: BOLIVAR IBARRA YOVAN ESTEBAN | C18: UT MEJIA Y ACEVEDO SYE VOLQUET | D18: TERCEROS | E18: MEDELLIN | F18: 45806 | G18: Medellin | H18: C35 | J18: =VLOOKUP(H18,VALIDACIONES!$A$2:$B$138,2,0) -> No realizar la revisión técnico mecánica y de emisiones en los siguientes plazos o cuando aún portando los certificados correspondientes no cuenta con las siguientes condiciones tecnicomecánica y de emisiones contaminantes, además el vehiculo será inmovilizado.(verlistado) | K18: 604054 | L18: =MONTH(F18) -> 5 | M18: =YEAR(F18) -> 2025 | N18: CAPACITACIÓN | O18: 45819 | P18: CAPACITACIÓN MANEJO DEFENSIVO | Q18: PAGO | R18: ACTIVO | S18: SI | T18: SI | U18: SI | V18: SI
A19: 75092999 | B19: BURITICA ROJAS LUIS FELIPE | C19: CHEC | D19: TERCEROS | E19: MANIZALES | F19: 45806 | G19: Manizales | H19: C35 | J19: =VLOOKUP(H19,VALIDACIONES!$A$2:$B$138,2,0) -> No realizar la revisión técnico mecánica y de emisiones en los siguientes plazos o cuando aún portando los certificados correspondientes no cuenta con las siguientes condiciones tecnicomecánica y de emisiones contaminantes, además el vehiculo será inmovilizado.(verlistado) | K19: 603939 | L19: =MONTH(F19) -> 5 | M19: =YEAR(F19) -> 2025 | N19: CAPACITACIÓN | O19: 45819 | P19: CAPACITACIÓN MANEJO DEFENSIVO | Q19: PAGO | R19: ACTIVO | S19: NO | T19: NO | U19: SI
A20: 8111021 | B20: ESPINOZA GUZMAN JUAN BAUTISTA | C20: UT MEJIA Y ACEVEDO SYE VOLQUET | D20: TERCEROS | E20: MEDELLIN | F20: 45805 | G20: Manizales | H20: C35 | J20: =VLOOKUP(H20,VALIDACIONES!$A$2:$B$138,2,0) -> No realizar la revisión técnico mecánica y de emisiones en los siguientes plazos o cuando aún portando los certificados correspondientes no cuenta con las siguientes condiciones tecnicomecánica y de emisiones contaminantes, además el vehiculo será inmovilizado.(verlistado) | K20: 604054 | L20: =MONTH(F20) -> 5 | M20: =YEAR(F20) -> 2025 | N20: CAPACITACIÓN | O20: 45819 | P20: CAPACITACIÓN MANEJO DEFENSIVO | Q20: PAGO | R20: ACTIVO | S20: NO | T20: NO | U20: SI
A21: 1144173726 | B21: MURCIA OROZCO JOHN HAWER | C21: ADMINISTRATIVO | D21: TERCEROS | E21: MEDELLIN | F21: 45806 | G21: Medellin | H21: C02 | J21: =VLOOKUP(H21,VALIDACIONES!$A$2:$B$138,2,0) -> Estacionar un vehículo en los sitios prohibidos por el Código Nacional de Tránsito, reglamentado por la Res.3027. | K21: 604054 | L21: =MONTH(F21) -> 5 | M21: =YEAR(F21) -> 2025 | N21: CAPACITACIÓN | O21: 45819 | P21: CAPACITACIÓN MANEJO DEFENSIVO | Q21: PAGO | R21: ACTIVO | S21: SI | T21: NO | U21: NO | V21: SI
A22: 1152466310 | B22: ZULUAGA VASQUEZ STIVEN | C22: UT MEJIA Y ACEVEDO SYE VOLQUET | D22: TERCEROS | E22: MEDELLIN | F22: 45800 | G22: Envigado | H22: C14 | I22: EQX587 | J22: =VLOOKUP(H22,VALIDACIONES!$A$2:$B$138,2,0) -> Transitar por los siguientes sitios restringidos o en horas prohibidas por laautoridad competente. Además, el vehículo será inmovilizado.(verlistado) | K22: 604000 | L22: =MONTH(F22) -> 5 | M22: =YEAR(F22) -> 2025 | N22: CAPACITACIÓN | O22: 45819 | P22: CAPACITACIÓN MANEJO DEFENSIVO | Q22: NO PAGO | R22: ACTIVO | S22: NO | U22: SI
A23: 1089718997 | B23: SANCHEZ JARAMILLO GUSTAVO DE JESUS | C23: CHEC | D23: TERCEROS | E23: MANIZALES | F23: 45826 | G23: La Dorada | H23: C29 | I23: JTY069 | J23: =VLOOKUP(H23,VALIDACIONES!$A$2:$B$138,2,0) -> Conducir un vehículo a velocidad superior a la máxima permitida, la cual deberá estar señalizada en forma sectorizada, no obstante esta no podrá ser superior a (verlistado) | K23: 603930 | L23: =MONTH(F23) -> 6 | M23: =YEAR(F23) -> 2025 | N23: CAPACITACION | O23: 45842 | P23: CAPACITACIÓN MANEJO DEFENSIVO
A24: 1036132399 | B24: SANCHEZ JARAMILLO GUSTAVO DE JESUS | C24: UT MEJIA Y ACEVEDO SYE VOLQUET | D24: TERCEROS | E24: MEDELLIN | F24: 45852 | G24: Barbosa | H24: C11 | I24: TAV412 | J24: =VLOOKUP(H24,VALIDACIONES!$A$2:$B$138,2,0) -> Noportarcomomínimoelsiguienteequipodeprevenciónyseguridad.(verlistado) | K24: 603930 | L24: =MONTH(F24) -> 7 | M24: =YEAR(F24) -> 2025 | N24: CAPACITACION | O24: 45877 | P24: CAPACITACIÓN MANEJO DEFENSIVO | R24: ACTIVO
A25: 10271854 | B25: GUTIERREZ JHON JAIRO | C25: CHEC | D25: TERCEROS | E25: MANIZALES | F25: 45879 | G25: Manizales | H25: D04 | I25: NAH330 | J25: =VLOOKUP(H25,VALIDACIONES!$A$2:$B$138,2,0) -> Nodetenerseanteunaluzrojaoamarilladesemáforo,unaseñalde"PARE"ounsemáforointermitenteenrojo.Enelcasodemotocicletaseprocederaasuinmovilizaciónhastatantonosepagueelvalordelamultaolaautoridadcompetentedecidasobresuimposicionenlosterminosdelosarticulos135y136delcódigonacionaldetránsito. | K25: 1207855 | L25: =MONTH(F25) -> 8 | M25: =YEAR(F25) -> 2025 | N25: CAPACITACION | O25: 45911 | P25: CAPACITACIÓN EN NORMAS DE TRANSITO | Q25: PAGO | R25: ACTIVO | S25: SI | T25: NO | U25: SI | V25: SI
A26: 71692190 | B26: LEON MEJIA DARIO | C26: FLOTA PROPIA | D26: FLOTA PROPIA | E26: MEDELLIN | F26: 45898 | G26: Bello | H26: H13 | I26: TDK561 | J26: =VLOOKUP(H26,VALIDACIONES!$A$2:$B$138,2,0) -> Las demas conductas que constituyan infraccion a las normas de transito y que no se encuentren descritas en este acto administrativo. | K26: 201351 | L26: 8 | M26: 2025 | N26: CAPACITACION | O26: 45911 | P26: CAPACITACIÓN EN NORMAS DE TRANSITO | Q26: ACUERDO DE PAGO | R26: ACTIVO | U26: Si | V26: No | W26: No tiene que realizar pago, solo curso
A27: 8402361 | B27: LLANO PEREZ ARMANDO ELADIO | C27: FUNDACION EPM | D27: TERCEROS | E27: MEDELLIN | F27: 45892 | G27: La Dorada | H27: C29 | I27: WCQ092 | J27: =VLOOKUP(H27,VALIDACIONES!$A$2:$B$138,2,0) -> Conducir un vehículo a velocidad superior a la máxima permitida, la cual deberá estar señalizada en forma sectorizada, no obstante esta no podrá ser superior a (verlistado) | K27: 603930 | L27: =MONTH(F27) -> 8 | M27: =YEAR(F27) -> 2025 | N27: CAPACITACION | O27: 45911 | P27: CAPACITACIÓN MANEJO DEFENSIVO | R27: ACTIVO
A28: 98570609 | B28: RODRIGUEZ CASTANO SERGIO | C28: GRUPO SURA | D28: TERCEROS | E28: MEDELLIN | F28: 45878 | G28: Medellin | H28: C35 | J28: =VLOOKUP(H28,VALIDACIONES!$A$2:$B$138,2,0) -> No realizar la revisión técnico mecánica y de emisiones en los siguientes plazos o cuando aún portando los certificados correspondientes no cuenta con las siguientes condiciones tecnicomecánica y de emisiones contaminantes, además el vehiculo será inmovilizado.(verlistado) | K28: 604054 | L28: =MONTH(F28) -> 8 | M28: =YEAR(F28) -> 2025 | N28: CAPACITACION | O28: 45911 | P28: CAPACITACIÓN EN NORMAS DE TRANSITO | Q28: PAGO | R28: ACTIVO | S28: SI | T28: NO | U28: SI | V28: SI
A29: 71613262 | B29: VELEZ VELEZ LUIS ORLANDO | C29: UT MEJIA Y ACEVEDO SYE VOLQUET | D29: TERCEROS | E29: MEDELLIN | F29: 45873 | G29: Sabaneta | H29: C26 | I29: SLP053 | J29: =VLOOKUP(H29,VALIDACIONES!$A$2:$B$138,2,0) -> Transitarenvehículosde3.5omástoneladasporelcarrilizquierdodelavíacuandohubieremásdeuncarril. | K29: 603939 | L29: =MONTH(F29) -> 8 | M29: =YEAR(F29) -> 2025 | N29: CAPACITACION | O29: 45911 | P29: CAPACITACIÓN EN NORMAS DE TRANSITO | Q29: PAGO | R29: ACTIVO | S29: NO | T29: NO | U29: SI | V29: NO
A30: 71268105 | B30: TORO LONDONO ANDRES ANTONIO | C30: ISAGEN - JAGUAS | D30: FLOTA PROPIA | E30: MEDELLIN | F30: 45887 | G30: BUGALAGRANDE - DEPT VALLE | H30: C29 | I30: YBE02E | J30: =VLOOKUP(H30,VALIDACIONES!$A$2:$B$138,2,0) -> Conducir un vehículo a velocidad superior a la máxima permitida, la cual deberá estar señalizada en forma sectorizada, no obstante esta no podrá ser superior a (verlistado) | K30: 603939 | L30: =MONTH(F30) -> 8 | M30: =YEAR(F30) -> 2025 | N30: CAPACITACION | O30: 45911 | P30: CAPACITACIÓN MANEJO DEFENSIVO | Q30: NO PAGO | R30: ACTIVO | S30: SI | T30: SI | U30: SI | V30: NO
A31: 1070603395 | B31: UGHETTI ECHEVERRIA DAVID | C31: EPM NUEVO | D31: TERCEROS | E31: MEDELLIN | F31: 45884 | G31: San Jeronimo - Dept Antioquia | H31: C02 | I31: SNX263 | J31: =VLOOKUP(H31,VALIDACIONES!$A$2:$B$138,2,0) -> Estacionar un vehículo en los sitios prohibidos por el Código Nacional de Tránsito, reglamentado por la Res.3027. | K31: 603939 | L31: =MONTH(F31) -> 8 | M31: =YEAR(F31) -> 2025 | N31: CAPACITACION | O31: 45911 | P31: CAPACITACIÓN EN NORMAS DE TRANSITO | Q31: NO PAGO | R31: ACTIVO | U31: SI
A32: 1001237255 | B32: AGUIRRE OSORIO JUAN CAMILO | C32: UT MEJIA Y ACEVEDO SYE VOLQUET | D32: TERCEROS | E32: MEDELLIN | F32: 45909 | G32: Bello | H32: C06 | I32: STE056 | J32: =VLOOKUP(H32,VALIDACIONES!$A$2:$B$138,2,0) -> Noutilizarelcinturóndeseguridadporpartedelosocupantesdelvehículoyloscinturonesdeseguridadenlosasientostraserosenlosvehículosfabricadosapartirdelaño2004. | K32: 603939 | L32: =MONTH(F32) -> 9 | M32: =YEAR(F32) -> 2025 | N32: CAPACITACION | O32: 45939 | P32: CAPACITACIÓN POLITICAS DE SEGURIDAD VIAL | Q32: NO PAGO | R32: ACTIVO
A33: 1001237255 | B33: AGUIRRE OSORIO JUAN CAMILO | C33: UT MEJIA Y ACEVEDO SYE VOLQUET | D33: TERCEROS | E33: MEDELLIN | F33: 45902 | G33: Bello | H33: H13 | I33: STE056 | J33: =VLOOKUP(H33,VALIDACIONES!$A$2:$B$138,2,0) -> Las demas conductas que constituyan infraccion a las normas de transito y que no se encuentren descritas en este acto administrativo. | K33: 201351 | L33: =MONTH(F33) -> 9 | M33: =YEAR(F33) -> 2025 | N33: CAPACITACION | O33: 45939 | P33: CAPACITACIÓN MANEJO DEFENSIVO | Q33: PAGO | R33: ACTIVO
A34: 75108007 | B34: OSPINA LOPEZ JHON FREDY | C34: CHEC | D34: TERCEROS | E34: MANIZALES | F34: 45906 | G34: Anserma | H34: C02 | I34: GTU941 | J34: =VLOOKUP(H34,VALIDACIONES!$A$2:$B$138,2,0) -> Estacionar un vehículo en los sitios prohibidos por el Código Nacional de Tránsito, reglamentado por la Res.3027. | K34: 603930 | L34: =MONTH(F34) -> 9 | M34: =YEAR(F34) -> 2025 | N34: CAPACITACION | O34: 45939 | P34: CAPACITACIÓN EN NORMAS DE TRANSITO | Q34: NO PAGO | R34: ACTIVO
A35: 8433989 | B35: CORREA GUZMAN JULIO EDUARDO | C35: ADMINISTRATIVO | D35: ADMINISTRATIVOS | E35: MEDELLIN | F35: 45961 | G35: Medellin | H35: C24 | I35: ANV39H | J35: =VLOOKUP(H35,VALIDACIONES!$A$2:$B$138,2,0) -> Conducir motocicleta sin observar las siguientes normas.(verlistadodesituaciones) | K35: 604054 | L35: =MONTH(F35) -> 10 | M35: =YEAR(F35) -> 2025 | N35: CAPACITACION | O35: 45967 | P35: CAPACITACIÓN EN NORMAS DE TRANSITO
A36: 1017154790 | B36: GUZMAN LOTERO CARLOS MARIO | C36: FLOTA PROPIA | D36: FLOTA PROPIA | E36: MEDELLIN | F36: 45946 | G36: Medellin | H36: C02 | I36: LKL764 | J36: =VLOOKUP(H36,VALIDACIONES!$A$2:$B$138,2,0) -> Estacionar un vehículo en los sitios prohibidos por el Código Nacional de Tránsito, reglamentado por la Res.3027. | K36: 604054 | L36: =MONTH(F36) -> 10 | M36: =YEAR(F36) -> 2025 | N36: CAPACITACION
A37: 1152450531 | B37: IZQUIERDO ACEVEDO DANIEL | C37: FLOTA PROPIA | D37: FLOTA PROPIA | E37: MEDELLIN | F37: 45939 | G37: Itaguí | H37: C14 | I37: JLM04H | J37: =VLOOKUP(H37,VALIDACIONES!$A$2:$B$138,2,0) -> Transitar por los siguientes sitios restringidos o en horas prohibidas por laautoridad competente. Además, el vehículo será inmovilizado.(verlistado) | K37: 603930 | L37: =MONTH(F37) -> 10 | M37: =YEAR(F37) -> 2025 | N37: CAPACITACION
A38: 70033808 | B38: LOPEZ ECHEVERRY HECTOR RAMIRO | C38: EPM NUEVO | D38: TERCEROS | E38: MEDELLIN | F38: 45952 | G38: Medellin | H38: D03 | I38: GDW677 | J38: =VLOOKUP(H38,VALIDACIONES!$A$2:$B$138,2,0) -> Transitarensentidocontrarioalestipuladoparalavía,calzadaocarril.Enelcasodemotocicletaseprocederaasuinmovilizaciónhastatantonosepagueelvalordelamultaolaautoridadcompetentedecidasobresuimposicionenlosterminosdelosarticulos135y136delcódigonacionaldetránsito. | K38: 1207762 | L38: =MONTH(F38) -> 10 | M38: =YEAR(F38) -> 2025 | N38: CAPACITACION | O38: 45967 | P38: CAPACITACIÓN EN NORMAS DE TRANSITO
A39: 1017139302 | B39: SANCHEZ AGUDELO DEISY MIRELLA | C39: GRUPO SURA | D39: TERCEROS | E39: MEDELLIN | F39: 45936 | G39: Itaguí | H39: C14 | J39: =VLOOKUP(H39,VALIDACIONES!$A$2:$B$138,2,0) -> Transitar por los siguientes sitios restringidos o en horas prohibidas por laautoridad competente. Además, el vehículo será inmovilizado.(verlistado) | K39: 603930 | L39: =MONTH(F39) -> 10 | M39: =YEAR(F39) -> 2025 | N39: CAPACITACION
A40: 71315786 | B40: TAMAYO PEREZ GUILLERMO LEON | C40: EPM NUEVO | D40: TERCEROS | E40: MEDELLIN | F40: 45950 | G40: Sabaneta | H40: C35 | I40: RAS977 | J40: =VLOOKUP(H40,VALIDACIONES!$A$2:$B$138,2,0) -> No realizar la revisión técnico mecánica y de emisiones en los siguientes plazos o cuando aún portando los certificados correspondientes no cuenta con las siguientes condiciones tecnicomecánica y de emisiones contaminantes, además el vehiculo será inmovilizado.(verlistado) | K40: 603939 | L40: =MONTH(F40) -> 10 | M40: =YEAR(F40) -> 2025 | N40: CAPACITACION | O40: 45967 | P40: CAPACITACIÓN EN NORMAS DE TRANSITO
A41: 71315786 | B41: TAMAYO PEREZ GUILLERMO LEON | C41: EPM NUEVO | D41: TERCEROS | E41: MEDELLIN | F41: 45949 | G41: Itaguí | H41: C35 | I41: RAS977 | J41: =VLOOKUP(H41,VALIDACIONES!$A$2:$B$138,2,0) -> No realizar la revisión técnico mecánica y de emisiones en los siguientes plazos o cuando aún portando los certificados correspondientes no cuenta con las siguientes condiciones tecnicomecánica y de emisiones contaminantes, además el vehiculo será inmovilizado.(verlistado) | K41: 603930 | L41: =MONTH(F41) -> 10 | M41: =YEAR(F41) -> 2025 | N41: CAPACITACION | O41: 45967 | P41: CAPACITACIÓN EN NORMAS DE TRANSITO
A42: 71315786 | B42: TAMAYO PEREZ GUILLERMO LEON | C42: EPM NUEVO | D42: TERCEROS | E42: MEDELLIN | F42: 45953 | G42: Sabaneta | H42: D02 | I42: RAS977 | J42: =VLOOKUP(H42,VALIDACIONES!$A$2:$B$138,2,0) -> ConducirsinportarelSeguroObligatoriodeAccidentesdetránsitoordenadoporlaley.Además,elvehículoseráinmovilizado. | K42: 1207877 | L42: =MONTH(F42) -> 10 | M42: =YEAR(F42) -> 2025 | N42: CAPACITACION | O42: 45967 | P42: CAPACITACIÓN EN NORMAS DE TRANSITO
A43: 98570609 | B43: RODRIGUEZ CASTANO SERGIO | C43: GRUPO SURA | D43: TERCEROS | E43: MEDELLIN | F43: 45950 | G43: Medellin | H43: C02 | J43: =VLOOKUP(H43,VALIDACIONES!$A$2:$B$138,2,0) -> Estacionar un vehículo en los sitios prohibidos por el Código Nacional de Tránsito, reglamentado por la Res.3027. | K43: 604054 | L43: =MONTH(F43) -> 10 | M43: =YEAR(F43) -> 2025 | N43: CAPACITACION
A44: 98529108 | B44: VALENCIA GIRALDO JOHN MARIO | C44: FLOTA PROPIA | D44: FLOTA PROPIA | E44: MEDELLIN | F44: 45945 | G44: Medellin | H44: C02 | J44: =VLOOKUP(H44,VALIDACIONES!$A$2:$B$138,2,0) -> Estacionar un vehículo en los sitios prohibidos por el Código Nacional de Tránsito, reglamentado por la Res.3027. | K44: 604054 | L44: =MONTH(F44) -> 10 | M44: =YEAR(F44) -> 2025 | N44: CAPACITACION | Q44: PAGO | R44: ACTIVO | S44: NO | T44: NO | U44: NO | V44: NO
A45: 8129204 | B45: GALLO MONTOYA JUAN PABLO | C45: ADMINISTRATIVO | D45: ADMINISTRATIVOS | E45: MEDELLIN | F45: 45990 | G45: Guarne | H45: C35 | I45: FCU876 | J45: =VLOOKUP(H45,VALIDACIONES!$A$2:$B$138,2,0) -> No realizar la revisión técnico mecánica y de emisiones en los siguientes plazos o cuando aún portando los certificados correspondientes no cuenta con las siguientes condiciones tecnicomecánica y de emisiones contaminantes, además el vehiculo será inmovilizado.(verlistado) | K45: 603939 | L45: =MONTH(F45) -> 11 | M45: =YEAR(F45) -> 2025 | N45: CAPACITACION | O45: CAPACITACION | P45: CAPACITACIÓN EN NORMAS DE TRANSITO | Q45: NO PAGO | R45: ACTIVO | S45: NO | T45: NO | U45: SI | V45: NO
A46: 98531237 | B46: HOLGUIN LOPEZ HERMIS DE JESUS | C46: JARDIN BOTANICO | D46: TERCEROS | E46: MEDELLIN | F46: 45988 | G46: Medellin | H46: C35 | I46: WCP673 | J46: =VLOOKUP(H46,VALIDACIONES!$A$2:$B$138,2,0) -> No realizar la revisión técnico mecánica y de emisiones en los siguientes plazos o cuando aún portando los certificados correspondientes no cuenta con las siguientes condiciones tecnicomecánica y de emisiones contaminantes, además el vehiculo será inmovilizado.(verlistado) | K46: 604054 | L46: =MONTH(F46) -> 11 | M46: =YEAR(F46) -> 2025 | N46: CAPACITACION | P46: CAPACITACIÓN EN NORMAS DE TRANSITO | Q46: NO PAGO | R46: INACTIVO | S46: NO | T46: NO | U46: SI | V46: NO
A47: 98531237 | B47: HOLGUIN LOPEZ HERMIS DE JESUS | C47: JARDIN BOTANICO | D47: TERCEROS | E47: MEDELLIN | F47: 45971 | G47: Medellin | H47: B15 | I47: WLX424 | J47: =VLOOKUP(H47,VALIDACIONES!$A$2:$B$138,2,0) -> Conducirunvehículodeserviciopúblicoquenolleveelavisodetarifasoficialesencondicionesdefácillecturaparalospasajerosoposeeresteavisodeterioradooadulterado. | K47: 305095 | L47: =MONTH(F47) -> 11 | M47: =YEAR(F47) -> 2025 | N47: CAPACITACION | P47: CAPACITACIÓN EN NORMAS DE TRANSITO | Q47: NO PAGO | R47: INACTIVO | S47: NO | T47: NO | U47: SI | V47: NO
A48: 98482941 | B48: URIBE PULGARIN JOHN HENRY | C48: EPM NUEVO | D48: TERCEROS | E48: MEDELLIN | F48: 45986 | G48: Bello | H48: C02 | J48: =VLOOKUP(H48,VALIDACIONES!$A$2:$B$138,2,0) -> Estacionar un vehículo en los sitios prohibidos por el Código Nacional de Tránsito, reglamentado por la Res.3027. | K48: 604043 | L48: =MONTH(F48) -> 11 | M48: =YEAR(F48) -> 2025 | N48: CAPACITACION | P48: CAPACITACIÓN EN NORMAS DE TRANSITO | Q48: NO PAGO | R48: ACTIVO | S48: NO | T48: NO | U48: SI | V48: NO
A49: 1037663209 | B49: ARENAS GALVIS KEVIN | C49: ADMINISTRATIVO | D49: ADMINISTRATIVOS | E49: MEDELLIN | F49: 45955 | G49: Itagui | H49: C29 | I49: YAL23F | J49: =VLOOKUP(H49,VALIDACIONES!$A$2:$B$138,2,0) -> Conducir un vehículo a velocidad superior a la máxima permitida, la cual deberá estar señalizada en forma sectorizada, no obstante esta no podrá ser superior a (verlistado) | K49: 603939 | L49: =MONTH(F49) -> 10 | M49: =YEAR(F49) -> 2025
A50: 1037663209 | B50: ARENAS GALVIS KEVIN | C50: ADMINISTRATIVO | D50: ADMINISTRATIVOS | E50: MEDELLIN | F50: 46001 | G50: Bello | H50: C24 | I50: YAL23F | J50: =VLOOKUP(H50,VALIDACIONES!$A$2:$B$138,2,0) -> Conducir motocicleta sin observar las siguientes normas.(verlistadodesituaciones) | K50: 603939 | L50: =MONTH(F50) -> 12 | M50: =YEAR(F50) -> 2025 | N50: CAPACITACION | O50: 46095 | P50: CAPACITACIÓN EN NORMAS DE TRANSITO | Q50: NO PAGO | R50: ACTIVO | S50: NO | T50: NO | U50: NO | V50: NO
A51: 1037663209 | B51: ARENAS GALVIS KEVIN | C51: ADMINISTRATIVO | D51: ADMINISTRATIVOS | E51: MEDELLIN | F51: 45909 | G51: Itagui | H51: D04 | I51: YAL23F | J51: =VLOOKUP(H51,VALIDACIONES!$A$2:$B$138,2,0) -> Nodetenerseanteunaluzrojaoamarilladesemáforo,unaseñalde"PARE"ounsemáforointermitenteenrojo.Enelcasodemotocicletaseprocederaasuinmovilizaciónhastatantonosepagueelvalordelamultaolaautoridadcompetentedecidasobresuimposicionenlosterminosdelosarticulos135y136delcódigonacionaldetránsito. | K51: 1207860 | L51: =MONTH(F51) -> 9 | M51: =YEAR(F51) -> 2025
A52: 4415359 | B52: PEREZ GIRALDO RUBIEL | C52: CHEC | D52: TERCEROS | E52: MANIZALES | F52: 46004 | G52: Manizales | H52: D04 | I52: STQ987 | J52: =VLOOKUP(H52,VALIDACIONES!$A$2:$B$138,2,0) -> Nodetenerseanteunaluzrojaoamarilladesemáforo,unaseñalde"PARE"ounsemáforointermitenteenrojo.Enelcasodemotocicletaseprocederaasuinmovilizaciónhastatantonosepagueelvalordelamultaolaautoridadcompetentedecidasobresuimposicionenlosterminosdelosarticulos135y136delcódigonacionaldetránsito. | K52: 1207855 | L52: =MONTH(F52) -> 12 | M52: =YEAR(F52) -> 2025 | N52: CAPACITACION | O52: 46095 | P52: CAPACITACIÓN EN NORMAS DE TRANSITO | Q52: NO PAGO | R52: ACTIVO | S52: NO | T52: NO | U52: NO | V52: NO
A53: 71798982 | B53: SIERRA PEREZ ALEX JAMILTON | C53: UT MEJIA Y ACEVEDO SYE VOLQUET | D53: TERCEROS | E53: MEDELLIN | F53: 45993 | G53: Itaguí | H53: C35 | I53: EQX587 | J53: =VLOOKUP(H53,VALIDACIONES!$A$2:$B$138,2,0) -> No realizar la revisión técnico mecánica y de emisiones en los siguientes plazos o cuando aún portando los certificados correspondientes no cuenta con las siguientes condiciones tecnicomecánica y de emisiones contaminantes, además el vehiculo será inmovilizado.(verlistado) | K53: 603930 | L53: =MONTH(F53) -> 12 | M53: =YEAR(F53) -> 2025 | N53: CAPACITACION | O53: 46095 | P53: CAPACITACIÓN EN NORMAS DE TRANSITO | Q53: NO PAGO | R53: ACTIVO | S53: NO | T53: NO | U53: NO | V53: NO
A54: 1040743363 | B54: PULGARIN CHALARCA JESUS ALBERTO | C54: EPM NUEVO | D54: TERCEROS | E54: MEDELLIN | F54: 46021 | G54: La Estrella | H54: C06 | J54: =VLOOKUP(H54,VALIDACIONES!$A$2:$B$138,2,0) -> Noutilizarelcinturóndeseguridadporpartedelosocupantesdelvehículoyloscinturonesdeseguridadenlosasientostraserosenlosvehículosfabricadosapartirdelaño2004. | K54: 603930 | L54: =MONTH(F54) -> 12 | M54: =YEAR(F54) -> 2025 | N54: CAPACITACION | O54: 46095 | P54: CAPACITACIÓN EN NORMAS DE TRANSITO | Q54: NO PAGO | R54: ACTIVO | S54: NO | T54: NO | U54: NO | V54: NO
A55: 1070603395 | B55: UGHETTI ECHEVERRIA DAVID | C55: EPM NUEVO | D55: TERCEROS | E55: MEDELLIN | F55: 46007 | G55: Sabaneta | H55: C29 | I55: SNX263 | J55: =VLOOKUP(H55,VALIDACIONES!$A$2:$B$138,2,0) -> Conducir un vehículo a velocidad superior a la máxima permitida, la cual deberá estar señalizada en forma sectorizada, no obstante esta no podrá ser superior a (verlistado) | K55: 603939 | L55: =MONTH(F55) -> 12 | M55: =YEAR(F55) -> 2025 | N55: CAPACITACION | O55: 46095 | P55: CAPACITACIÓN EN NORMAS DE TRANSITO | Q55: NO PAGO | R55: ACTIVO | S55: NO | T55: NO | U55: NO | V55: NO
A56: 1033375997 | B56: AVILEZ CRUZ JHAN CARLOS | C56: EPM NUEVO | D56: TERCEROS | E56: MEDELLIN | F56: 46053 | G56: Medellin | H56: C31 | I56: NNL198 | J56: =VLOOKUP(H56,VALIDACIONES!$A$2:$B$138,2,0) -> No acatar las señales o requerimientos impartidos por los agentes de Tránsito. | K56: 633232 | L56: =MONTH(F56) -> 1 | M56: =YEAR(F56) -> 2026 | N56: CAPACITACION | O56: 46099 | P56: CAPACITACIÓN POLITICAS DE SEGURIDAD VIAL | Q56: NO PAGO | R56: ACTIVO | S56: NO | T56: NO | U56: SI | V56: NO
A57: 71693884 | B57: RUIZ GARCIA FABIO LEON | C57: GRUPO SURA | D57: TERCEROS | E57: MEDELLIN | F57: 46045 | G57: Medellin | H57: C02 | I57: EOX592 | J57: =VLOOKUP(H57,VALIDACIONES!$A$2:$B$138,2,0) -> Estacionar un vehículo en los sitios prohibidos por el Código Nacional de Tránsito, reglamentado por la Res.3027. | K57: 633232 | L57: =MONTH(F57) -> 1 | M57: =YEAR(F57) -> 2026 | N57: CAPACITACION | O57: 46099 | P57: CAPACITACIÓN POLITICAS DE SEGURIDAD VIAL | Q57: NO PAGO | R57: ACTIVO | S57: NO | T57: NO | U57: SI | V57: NO
A58: 1036684908 | B58: SANCHEZ CASTANO EMMANUEL | C58: GRUPO SURA | D58: TERCEROS | E58: MEDELLIN | F58: 46039 | G58: Medellin | H58: B10 | I58: WDZ203 | J58: =VLOOKUP(H58,VALIDACIONES!$A$2:$B$138,2,0) -> Conducirunvehículoconvidriospolarizados,entintadosuoscurecidos,sinportarelpermisorespectivo,deacuerdoalareglamentaciónexistenteo,nollevarelvehículodeserviciopúblicocolectivourbanoconlosvidriostransparentes. | K58: 337385 | L58: =MONTH(F58) -> 1 | M58: =YEAR(F58) -> 2026 | N58: CAPACITACION | O58: 46099 | P58: CAPACITACIÓN POLITICAS DE SEGURIDAD VIAL | Q58: NO PAGO | R58: ACTIVO | S58: NO | T58: NO | U58: SI | V58: NO
A59: 71798982 | B59: SIERRA PEREZ ALEX JAMILTON | C59: UT MEJIA Y ACEVEDO SYE VOLQUET | D59: TERCEROS | E59: MEDELLIN | F59: 46031 | G59: Itaguí | H59: C29 | I59: JKB54D | J59: =VLOOKUP(H59,VALIDACIONES!$A$2:$B$138,2,0) -> Conducir un vehículo a velocidad superior a la máxima permitida, la cual deberá estar señalizada en forma sectorizada, no obstante esta no podrá ser superior a (verlistado) | K59: 633105 | L59: =MONTH(F59) -> 1 | M59: =YEAR(F59) -> 2026 | N59: CAPACITACION | O59: 46099 | P59: CAPACITACIÓN POLITICAS DE SEGURIDAD VIAL | Q59: PAGO | R59: ACTIVO | S59: NO | T59: NO | U59: SI | V59: SI
A60: 71530504 | B60: TORRES GOMEZ FABIO ESTEBAN | C60: UT MEJIA Y ACEVEDO SYE VOLQUET | D60: TERCEROS | E60: MEDELLIN | F60: 46041 | G60: Sabaneta | H60: C26 | I60: TKJ132 | J60: =VLOOKUP(H60,VALIDACIONES!$A$2:$B$138,2,0) -> Transitarenvehículosde3.5omástoneladasporelcarrilizquierdodelavíacuandohubieremásdeuncarril. | K60: 633111 | L60: =MONTH(F60) -> 1 | M60: =YEAR(F60) -> 2026 | N60: CAPACITACION | O60: 46099 | P60: CAPACITACIÓN POLITICAS DE SEGURIDAD VIAL | Q60: NO PAGO | R60: ACTIVO | S60: NO | T60: NO | U60: SI | V60: NO
A61: 1022034949 | B61: GIRALDO CHALARCA DANIEL | C61: JARDIN BOTANICO | D61: TERCEROS | E61: MEDELLIN | F61: 46055 | G61: Sabaneta | H61: D02 | J61: =VLOOKUP(H61,VALIDACIONES!$A$2:$B$138,2,0) -> ConducirsinportarelSeguroObligatoriodeAccidentesdetránsitoordenadoporlaley.Además,elvehículoseráinmovilizado. | K61: 1266222 | L61: =MONTH(F61) -> 2 | M61: =YEAR(F61) -> 2026
A62: 1000635424 | B62: JARAMILLO USUGA BRANDON | C62: GRUPO SURA | D62: TERCEROS | E62: MEDELLIN | F62: 46078 | G62: Medellin | H62: C02 | I62: JYX641 | J62: =VLOOKUP(H62,VALIDACIONES!$A$2:$B$138,2,0) -> Estacionar un vehículo en los sitios prohibidos por el Código Nacional de Tránsito, reglamentado por la Res.3027. | K62: 633232 | L62: =MONTH(F62) -> 2 | M62: =YEAR(F62) -> 2026 | N62: CAPACITACION | O62: 46099 | P62: CAPACITACIÓN EN NORMAS DE TRANSITO | R62: ACTIVO | S62: NO | T62: NO | U62: SI | V62: NO
A63: 71613262 | B63: VELEZ VELEZ LUIS ORLANDO | C63: UT MEJIA Y ACEVEDO SYE VOLQUET | D63: TERCEROS | E63: MEDELLIN | F63: 46062 | G63: Sabaneta | H63: C26 | I63: SLP053 | J63: =VLOOKUP(H63,VALIDACIONES!$A$2:$B$138,2,0) -> Transitarenvehículosde3.5omástoneladasporelcarrilizquierdodelavíacuandohubieremásdeuncarril. | K63: 633111 | L63: =MONTH(F63) -> 2 | M63: =YEAR(F63) -> 2026 | N63: CAPACITACION | O63: 46099 | P63: CAPACITACIÓN EN NORMAS DE TRANSITO | R63: ACTIVO | S63: NO | T63: NO | U63: SI | V63: NO
A64: 1128386181 | B64: WILCHES BERRIO MOISES | C64: MEDICARTE | D64: TERCEROS | E64: MEDELLIN | F64: 46077 | G64: Medellin | H64: D17 | I64: CYX116 | J64: =VLOOKUP(H64,VALIDACIONES!$A$2:$B$138,2,0) -> Cuandosedetecteoadviertaunainfracciónalasnormasdeemisióncontaminantesodegeneraciónderuidoporvehículosautomotores | K64: 1266101 | L64: =MONTH(F64) -> 2 | M64: =YEAR(F64) -> 2026 | N64: CAPACITACION | O64: 46099 | P64: CAPACITACIÓN EN NORMAS DE TRANSITO | R64: ACTIVO | S64: NO | T64: NO | U64: SI | V64: NO
A65: 1017249531 | B65: ARBELAEZ SOTO LIZZETH | C65: ADMINISTRATIVO | D65: ADMINISTRATIVOS | E65: MEDELLIN | F65: 46097 | G65: Medellin | H65: C14 | I65: WEO38G | J65: =VLOOKUP(H65,VALIDACIONES!$A$2:$B$138,2,0) -> Transitar por los siguientes sitios restringidos o en horas prohibidas por laautoridad competente. Además, el vehículo será inmovilizado.(verlistado) | K65: 633105 | L65: =MONTH(F65) -> 3 | M65: =YEAR(F65) -> 2026 | N65: CAPACITACION | O65: 46169 | P65: CAPACITACIÓN EN NORMAS DE TRANSITO | R65: ACTIVO | S65: NO | T65: NO | U65: SI | V65: NO
A66: 9977142 | B66: CADAVID GOMEZ FABIO NELSON | C66: EPM NUEVO | D66: TERCEROS | E66: MEDELLIN | F66: 46103 | G66: Titiribi VÍA NACIONA | H66: F | I66: NNN114 | J66: =VLOOKUP(H66,VALIDACIONES!$A$2:$B$138,2,0) -> #N/A | K66: - | L66: =MONTH(F66) -> 3 | M66: =YEAR(F66) -> 2026 | N66: CAPACITACION | O66: 46169 | P66: CAPACITACIÓN EN NORMAS DE TRANSITO | R66: INACTIVO | S66: NO | T66: NO | U66: No | V66: NO
A67: 1152465154 | B67: DAVID BENJUMEA SIMON | C67: ADMINISTRATIVO | D67: ADMINISTRATIVOS | E67: MEDELLIN | F67: 46089 | G67: Medellin | H67: C24 | I67: QJV19G | J67: =VLOOKUP(H67,VALIDACIONES!$A$2:$B$138,2,0) -> Conducir motocicleta sin observar las siguientes normas.(verlistadodesituaciones) | K67: 633232 | L67: =MONTH(F67) -> 3 | M67: =YEAR(F67) -> 2026 | N67: CAPACITACION | O67: 46169 | P67: CAPACITACIÓN EN NORMAS DE TRANSITO | R67: ACTIVO | S67: NO | T67: NO | U67: SI | V67: NO
A68: 15325218 | B68: GAVIRIA ESPINOSA CARLOS ARTURO | C68: EPM NUEVO | D68: TERCEROS | E68: MEDELLIN | F68: 46101 | G68: Medellin | H68: C02 | J68: =VLOOKUP(H68,VALIDACIONES!$A$2:$B$138,2,0) -> Estacionar un vehículo en los sitios prohibidos por el Código Nacional de Tránsito, reglamentado por la Res.3027. | K68: 633232 | L68: =MONTH(F68) -> 3 | M68: =YEAR(F68) -> 2026 | N68: CAPACITACION | P68: CAPACITACIÓN EN NORMAS DE TRANSITO | R68: ACTIVO | S68: NO | T68: NO | U68: SI | V68: NO | W68: Ya se encontraba paga y no quiso enviar comprobante de pago
A69: 10549212 | B69: GOMEZ VIVEROS HENRY MARTIN | C69: CHEC | D69: TERCEROS | E69: MANIZALES | F69: 46108 | G69: Manizales | H69: C03 | J69: =VLOOKUP(H69,VALIDACIONES!$A$2:$B$138,2,0) -> Bloquearunacalzadaointersecciónconunvehículo,salvocuandoelbloqueoobedezcaalaocurrenciadeunaccidente. | K69: 633111 | L69: =MONTH(F69) -> 3 | M69: =YEAR(F69) -> 2026 | N69: CAPACITACION | O69: 46169 | P69: CAPACITACIÓN EN NORMAS DE TRANSITO | R69: ACTIVO | S69: NO | T69: NO | U69: SI | V69: NO | W69: Ya se encontraba paga y no quiso enviar comprobante de pago
A70: 1007562395 | B70: IBARRA MONTALVO DAIVER ENRIQUE | C70: EPM NUEVO | D70: TERCEROS | E70: MEDELLIN | F70: 46091 | G70: Bello | H70: C07 | I70: LKL968 | J70: =VLOOKUP(H70,VALIDACIONES!$A$2:$B$138,2,0) -> Dejardeseñalizar(verlistadodesituaciones) | K70: 633111 | L70: =MONTH(F70) -> 3 | M70: =YEAR(F70) -> 2026 | N70: CAPACITACION | O70: 46169 | P70: CAPACITACIÓN EN NORMAS DE TRANSITO | R70: ACTIVO | S70: NO | T70: NO | U70: SI | V70: NO
A71: 1036684908 | B71: SANCHEZ CASTANO EMMANUEL | C71: GRUPO SURA | D71: TERCEROS | E71: MEDELLIN | F71: 46101 | G71: La Estrella | H71: C14 | I71: SRJ25D | J71: =VLOOKUP(H71,VALIDACIONES!$A$2:$B$138,2,0) -> Transitar por los siguientes sitios restringidos o en horas prohibidas por laautoridad competente. Además, el vehículo será inmovilizado.(verlistado) | K71: 633105 | L71: =MONTH(F71) -> 3 | M71: =YEAR(F71) -> 2026 | N71: CAPACITACION | O71: 46170 | P71: CAPACITACIÓN EN NORMAS DE TRANSITO | R71: ACTIVO | S71: NO | T71: NO | U71: SI | V71: NO
A72: 98631773 | B72: SOLORZANO ARANGO CARLOS ANDRES | C72: EPM NUEVO | D72: TERCEROS | E72: MEDELLIN | F72: 46106 | G72: Marinilla | H72: C31 | I72: NNL532 | J72: =VLOOKUP(H72,VALIDACIONES!$A$2:$B$138,2,0) -> No acatar las señales o requerimientos impartidos por los agentes de Tránsito. | K72: 633111 | L72: =MONTH(F72) -> 3 | M72: =YEAR(F72) -> 2026 | N72: CAPACITACION | O72: 46170 | P72: CAPACITACIÓN EN NORMAS DE TRANSITO | R72: INACTIVO | S72: NO | T72: NO | U72: SI | V72: NO | W72: Ya no labora
A73: 71613262 | B73: VELEZ VELEZ LUIS ORLANDO | C73: UT MEJIA Y ACEVEDO SYE VOLQUET | D73: TERCEROS | E73: MEDELLIN | F73: 46106 | G73: Sabaneta | H73: C26 | J73: =VLOOKUP(H73,VALIDACIONES!$A$2:$B$138,2,0) -> Transitarenvehículosde3.5omástoneladasporelcarrilizquierdodelavíacuandohubieremásdeuncarril. | K73: 633111 | L73: =MONTH(F73) -> 3 | M73: =YEAR(F73) -> 2026 | N73: CAPACITACION | O73: 46170 | P73: CAPACITACIÓN EN NORMAS DE TRANSITO | R73: ACTIVO | S73: NO | T73: NO | U73: SI | V73: NO | W73: Ya se encontraba paga y no quiso enviar comprobante de pago
A74: 71383929 | B74: JARAMILLO JARAMILLO ELKIN MAURICIO | C74: JARDIN BOTANICO | D74: TERCEROS | E74: MEDELLIN | F74: 46135 | G74: Medellin | H74: C35 | I74: WCP673 | J74: =VLOOKUP(H74,VALIDACIONES!$A$2:$B$138,2,0) -> No realizar la revisión técnico mecánica y de emisiones en los siguientes plazos o cuando aún portando los certificados correspondientes no cuenta con las siguientes condiciones tecnicomecánica y de emisiones contaminantes, además el vehiculo será inmovilizado.(verlistado) | K74: 633232 | L74: =MONTH(F74) -> 4 | M74: =YEAR(F74) -> 2026 | N74: CAPACITACION | O74: 46170
A75: 1106739051 | B75: MARTINEZ PALOMO ZABDIEL | C75: ADMINISTRATIVO | D75: ADMINISTRATIVOS | E75: MEDELLIN | F75: 46121 | G75: Envigado | H75: C24 | I75: GOY13F | J75: =VLOOKUP(H75,VALIDACIONES!$A$2:$B$138,2,0) -> Conducir motocicleta sin observar las siguientes normas.(verlistadodesituaciones) | K75: 633111 | L75: =MONTH(F75) -> 4 | M75: =YEAR(F75) -> 2026 | N75: CAPACITACION | O75: 46170

Sheet CORRESPONDENCIA
A1: CEDULA | B1: NOMBRE | C1: MES | D1: AÑO | E1: CODIGO INFRACCIÓN | F1: TEXTO | G1: DESCRIPICIÓN | H1: VALOR LETRAS | I1: VALOR
A2: 98613966 | B2: JHON FREDY CANO GOMEZ | C2: Diciembre | D2: 2024 | E2: C02 | F2: Estacionar un vehículo en los sitios prohibidos por el Código Nacional de Tránsito, reglamentado por la Res.3027. | G2: Estacionar un vehículo en los sitios prohibidos | H2: Quinientos dos mil seiscientos veintiocho pesos moneda legal colombiana | I2: $ 572.628,00
A3: 10271854 | B3: JHON JAIRO GUTIERREZ | C3: Diciembre | D3: 2024 | E3: D04 | F3: Nodetenerseanteunaluzrojaoamarilladesemáforo,unaseñalde"PARE"ounsemáforointermitenteenrojo.Enelcasodemotocicletaseprocederaasuinmovilizaciónhastatantonosepagueelvalordelamultaolaautoridadcompetentedecidasobresuimposicionenlosterminosdelosarticulos135y136delcódigonacionaldetránsito. | G3: No detenerse ante luz roja o PARE | H3: Quinientos dos mil seiscientos veintiocho pesos moneda legal colombiana | I3: $ 1.145.029,00
A4: 98514320 | B4: ALBERTO MUNOZ DIEZ | C4: Diciembre | D4: 2024 | E4: D02 | F4: ConducirsinportarelSeguroObligatoriodeAccidentesdetránsitoordenadoporlaley.Además,elvehículoseráinmovilizado. | G4: No portaba SOAT | H4: Quinientos dos mil seiscientos veintiocho pesos moneda legal colombiana | I4: $ 1.145.040,00
A5: 71947379 | B5: EDISON B SALDARRIAGA GUTIERREZ | C5: Diciembre | D5: 2024 | E5: C29 | F5: Conducir un vehículo a velocidad superior a la máxima permitida, la cual deberá estar señalizada en forma sectorizada, no obstante esta no podrá ser superior a (verlistado) | G5: Excesos de velocidad | H5: Quinientos dos mil seiscientos veintiocho pesos moneda legal colombiana | I5: $ 572.520,00
A6: 98646700 | B6: JAIME ANDRES ZAPATA RUA | C6: Diciembre | D6: 2024 | E6: C02 | F6: Estacionar un vehículo en los sitios prohibidos por el Código Nacional de Tránsito, reglamentado por la Res.3027. | G6: Estacionar un vehículo en los sitios prohibidos | H6: Quinientos dos mil seiscientos veintiocho pesos moneda legal colombiana | I6: $ 572.628,00
A7: 1002643041 | B7: MATEO GIRALDO GUTIERREZ | C7: Diciembre | D7: 2024 | E7: D04 | F7: Nodetenerseanteunaluzrojaoamarilladesemáforo,unaseñalde"PARE"ounsemáforointermitenteenrojo.Enelcasodemotocicletaseprocederaasuinmovilizaciónhastatantonosepagueelvalordelamultaolaautoridadcompetentedecidasobresuimposicionenlosterminosdelosarticulos135y136delcódigonacionaldetránsito. | G7: No detenerse ante luz roja o PARE | H7: Quinientos dos mil seiscientos veintiocho pesos moneda legal colombiana | I7: $ 1.145.040,00
A8: 71601030 | B8: JAIME ALBERTO ESCOBAR POSADA | C8: Diciembre | D8: 2024 | E8: C29 | F8: Conducir un vehículo a velocidad superior a la máxima permitida, la cual deberá estar señalizada en forma sectorizada, no obstante esta no podrá ser superior a (verlistado) | G8: Excesos de velocidad | H8: Quinientos dos mil seiscientos veintiocho pesos moneda legal colombiana | I8: $ 572.498,00

Sheet VALIDACIONES
A1: Código Infracción | B1: Infracción | C1: SMLDV | D1: Columna1 | E1: Moto | F1: Carro | G1: NoAutomotor | I1: Tipo Contrato | J1: Ciudad | K1: Capacitación | L1: Control infracciones | M1: Tipo de Accion | N1: ESTADO | O1: SI/NO
A2: A01 | B2: No transitar por la derecha de la vía. | C2: 4 | D2: $ 91,927 | I2: ADMINISTRATIVOS | J2: ARMENIA | K2: CAPACITACIÓN SEGURIDAD VIAL Y MOVILIDAD | L2: PAGO | M2: CAPACITACION | N2: ACTIVO | O2: SI
A3: A02 | B3: Agarrarse de otro vehículo en movimiento. | C3: 4 | D3: $ 91,927 | I3: FLOTA PROPIA | J3: BOGOTA | K3: CAPACITACIÓN CONTROL DE EXCESOS DE VELOCIDAD | L3: NO PAGO | M3: SUSPENSION | N3: INACTIVO | O3: NO
A4: A03 | B4: Transportar personas o cosas que disminuyen su visibilidad o incomoden la conducción. | C4: 4 | D4: $ 91,927 | I4: TERCEROS | J4: BUGA | K4: CAPACITACIÓN EN NORMAS DE TRANSITO | L4: ACUERDO DE PAGO | M4: RETIRO
A5: A04 | B5: Transitar por andenes,aceras,puentes o demás lugares de uso exclusivo para el tránsito de personas. | C5: 4 | D5: $ 91,927 | J5: CALI | K5: CAPACITACIÓN POLITICAS DE SEGURIDAD VIAL | M5: N/A
A6: A05 | B6: No respetar las señales de tránsito. | C6: 4 | D6: $ 91,927 | J6: IBAGUE | K6: CAPACITACIÓN MANEJO DEFENSIVO
A7: A06 | B7: Transitar sin los dispositivos luminosos requeridos. | C7: 4 | D7: $ 91,927 | J7: MANIZALES
A8: A07 | B8: Transitar sin dispositivos que permitan la parada inmediata o con ellos, pero en estado de fectuoso. | C8: 4 | D8: $ 91,927 | J8: MEDELLIN
A9: A08 | B9: Transitarporzonasprohibidaso,poraquellasvíasendondelasautoridadescompetentesloprohíbano,conducirporvíasdiferentesaaquellasdiseñadasparaello,cuandolashubiere. | C9: 4 | D9: $ 91,927 | J9: PEREIRA
A10: A09 | B10: Adelantar entre dos vehículos automotores que estén en sus respectivos carriles. | C10: 4 | D10: $ 91,927 | J10: POPAYAN
A11: A10 | B11: Conducir por la vía férrea o por zonas de protección y seguridad. | C11: 4 | D11: $ 91,927 | J11: RIONEGRO
A12: A11 | B12: Transitar por zonas restringidas o por vías de alta velocidad como autopistas y arterias. | C12: 4 | D12: $ 91,927 | G12: X | J12: SOGAMOSO
A13: A12 | B13: Prestar servicio público con este tipo de vehículos. Además, el vehículo será inmovilizado por primera vez por 5días, 20 días por segunda vez y 40 días por tercera vez. | C13: 4 | D13: $ 91,927 | G13: X | J13: MIEL
A14: B01 | B14: Conducir un vehículo sin llevar consigo la licencia de conducción. | C14: 8 | D14: $ 183,854 | J14: SAN CARLOS
A15: B02 | B15: Conducir un vehículo con la licencia de conducción vencida. | C15: 8 | D15: $ 183,854 | E15: X | F15: X | J15: JAGUAS
A16: B03 | B16: Conducir un vehículo sin placas, no portar la senel extremo delantero o trasero, portarlas con obstáculos o encondiciones que dificulten su plena identificación, portar en el lugar destinado a las placas, distintivos similares a éstas o que la imiten o que correspondan a placas de otros países o, sin el permiso vigente expedido por autoridad de tránsito. Realizar cambio en las características que identifican un vehículo automotor, cambiar, modificar o adulterar los números de identificación del motor, chasis o serie de un vehículo. | C16: 8 | D16: $ 183,854 | E16: X | F16: X | J16: CALDERAS
A17: B04 | B17: Conducir un vehículo con placas adulteradas, retocadas o alteradas. | C17: 8 | D17: $ 183,854 | E17: X | F17: X | J17: AMOYA
A18: B05 | B18: Conducir un vehículo con una sola placa, o sin el permiso vigente expedido por autoridad de tránsito. | C18: 8 | D18: $ 183,854 | E18: X | F18: X
A19: B06 | B19: Conducir un vehículo con placas falsas. | C19: 8 | D19: $ 183,854 | E19: X | F19: X
A20: B07 | B20: No informar a la autoridad de tránsito competente el cambio de motor o color de un vehículo. En ambos casos, el vehículo será inmovilizado. | C20: 8 | D20: $ 183,854 | E20: X | F20: X
A21: B08 | B21: No pagar el peaje en los sitios establecidos. | C21: 8 | D21: $ 183,854 | E21: X | F21: X
A22: B09 | B22: Utilizar equipos de sonido a volúmenes que incomoden a los pasajeros de un vehículo de servicio público. | C22: 8 | D22: $ 183,854
A23: B10 | B23: Conducirunvehículoconvidriospolarizados,entintadosuoscurecidos,sinportarelpermisorespectivo,deacuerdoalareglamentaciónexistenteo,nollevarelvehículodeserviciopúblicocolectivourbanoconlosvidriostransparentes. | C23: 8 | D23: $ 183,854
A24: B11 | B24: Conducirunvehículoconpropaganda,publicidadoadhesivosensusvidriosqueobstaculicenlavisibilidad. | C24: 8 | D24: $ 183,854
A25: B12 | B25: No respetar las normas establecidas por la autoridad competente para el tránsito de cortejos fúnebres. | C25: 8 | D25: $ 183,854
A26: B13 | B26: Norespetarlasformacionesdetropas,lamarchadedesfiles,procesiones,entierros,filasestudiantilesylasmanifestacionespúblicasyactividadesdeportivas,debidamenteautorizadasporlasautoridadesdetránsito. | C26: 8 | D26: $ 183,854
A27: B14 | B27: RemolcarotrovehículoviolandolodispuestoenelArtículo72delCódigoNacionaldeTránsito. | C27: 8 | D27: $ 183,854
A28: B15 | B28: Conducirunvehículodeserviciopúblicoquenolleveelavisodetarifasoficialesencondicionesdefácillecturaparalospasajerosoposeeresteavisodeterioradooadulterado. | C28: 8 | D28: $ 183,854
A29: B16 | B29: Permitirqueenunvehículodeserviciopúblicoparatransportedepasajerossellevenanimalesuobjetosqueincomodenalospasajeros. | C29: 8 | D29: $ 183,854
A30: B17 | B30: Abandonarunvehículodeserviciopúblicoconpasajeros. | C30: 8 | D30: $ 183,854
A31: B18 | B31: Notransitarporelcarrilderechoelvehículodetransportepúblicoindividualcuandotransitasinpasajerosindicandoladisponibilidadparaprestarelservicio,medianteluzespecialolaseñalluminosadeestarlibre. | C31: 8 | D31: $ 183,854
A32: B19 | B32: Realizarelcargueodescarguedeunvehículoensitiosyhorasprohibidasporlasautoridadescompetentes,deacuerdoconloestablecidoenlasnormascorrespondientes. | C32: 8 | D32: $ 183,854
A33: B20 | B33: Transportarcarne,pescadooalimentosfácilmentecorruptibles,envehículosquenocumplanlascondicionesfijadasporelMinisteriodeTransporte. | C33: 8 | D33: $ 183,854
... A37: C01 | B37: Presentarlicenciadeconducciónadulteradaoajena,locualdarálugaralainmovilizacióndelvehículo. | C37: 15 | D37: $ 344,727
A38: C02 | B38: Estacionar un vehículo en los sitios prohibidos por el Código Nacional de Tránsito, reglamentado por la Res.3027. | C38: 15 | D38: $ 344,727 | E38: X | F38: X
A39: C03 | B39: Bloquearunacalzadaointersecciónconunvehículo,salvocuandoelbloqueoobedezcaalaocurrenciadeunaccidente. | C39: 15 | D39: $ 344,727
A40: C04 | B40: Estacionarunvehículosintomarlassiguientesprecauciones:(verlistado) | C40: 15 | D40: $ 344,727
A41: C05 | B41: Noreducirlavelocidada30kilómetrosporhoraenlossiguientescasos:(Verlistado) | C41: 15 | D41: $ 344,727
A42: C06 | B42: Noutilizarelcinturóndeseguridadporpartedelosocupantesdelvehículoyloscinturonesdeseguridadenlosasientostraserosenlosvehículosfabricadosapartirdelaño2004. | C42: 15 | D42: $ 344,727
A43: C07 | B43: Dejardeseñalizar(verlistadodesituaciones) | C43: 15 | D43: $ 344,727
A44: C08 | B44: Transitar sin los dispositivos luminosos requeridos; no llevarlos vehículos de servicio público y oficial un aviso visible tanto en el interior como en el exterior en el que se señale el número telefónico del centro de llamadas contratado por la Superintendencia de puertos y transporte o los vehículos de servicio público no llevar además, marcado en los costados y en el techo el número de la placa o los demás elementos determinados en el Código. | C44: 15 | D44: $ 344,727
A45: C09 | B45: Norespetarlasseñalesdedetenciónenelcrucedeunalíneaférreaaunadistanciamínimadecinco(5)metrosdelalíneaferrea,oconducirporlavíaférreaoporlaszonasdeprotecciónyseguridaddeella. | C45: 15 | D45: $ 344,727
A46: C10 | B46: Conducir un vehículo con una o varias puertas abiertas. | C46: 15 | D46: $ 344,727
A47: C11 | B47: Noportarcomomínimoelsiguienteequipodeprevenciónyseguridad.(verlistado) | C47: 15 | D47: $ 344,727
A48: C12 | B48: Proveerdecombustibleunvehículoautomotorconelmotorencendido,conpasajerosabordocuandoelvehículoesdeserviciopúblicoderadiodeacciónnacional,transporteespecialyescolaroproveerdecombustibleunvehículoderadiodeacciónmetropolitano,distritalomunicipalmientrasqueesténprestandoelservicio. | C48: 15 | D48: $ 344,727
A49: C13 | B49: Conducirunvehículoautomotorsinlasadaptacionespertinentes,cuandoelconductorpadecedelimitaciónfísica. | C49: 15 | D49: $ 344,727
A50: C14 | B50: Transitar por los siguientes sitios restringidos o en horas prohibidas por laautoridad competente. Además, el vehículo será inmovilizado.(verlistado) | C50: 15 | D50: $ 344,727
A51: C15 | B51: Conducir un vehículo, particular o de servicio público, excediendo la capacidad autorizada en la licencia de tránsito o tarjeta de operación. | C51: 15 | D51: $ 344,727 | E51: X | F51: X
A52: C16 | B52: Conducirunvehículoescolarsinelpermisorespectivoolosdistintivosreglamentarios,estoes,nollevarloscoloresverdey/oblancodistribuidosalolargoyanchodelacarrocería,enlaparteposteriordelacarroceríadelvehículofranjasalternasdediez(10)centímetrosdeanchoencoloresamarilloynegro,coninclinaciónde45gradosyunaalturamínimade60c/tm;enlapartesuperiortraseraydelanteradelacarroceríaencaracteresdestacados,dealturamínimade10c/tm,nollevarlaleyenda"ESCOLAR",ademáselvehiculoseráinmovilizado. | C52: 15 | D52: $ 344,727
A53: C17 | B53: Circularconcombinacionesdevehículosdedos(2)omásunidadesremolcadas,sinautorizaciónespecialdeautoridadcompetente. | C53: 15 | D53: $ 344,727 | E53: X | F53: X
A54: C18 | B54: Conducirunvehículoautorizadoparaprestarserviciopúblicoconeltaxímetrodañado,conlossellosrotosoetiquetasadhesivasconcalibraciónvencidaoadulteradasocuandosecarezcadeél,ocuandoaúnteniéndolo,nocumplaconlasnormasmínimasdecalidadyseguridadexigidosporlaautoridadcompetenteoestenoestéenfuncionamiento. | C54: 15 | D54: $ 344,727
A55: C19 | B55: Dejar o recoger pasajeros en sitios distintos de los demarcados porlasautoridades, al costado derecho de la vía, salvo en paraderos especiales de vías troncales que sean diseñadas y operadas con destinación exclusiva al transporte público masivo. | C55: 15 | D55: $ 344,727 | E55: X | F55: X
A56: C20 | B56: Conducirunvehículodecargaenquesetransportenmaterialesdeconstrucciónoagranelsinlasmedidasdeprotección,higieneyseguridadordenadas;quenoestédebidamenteempacada,rotulada,embaladaycubiertaconformealanormatividadtécnicanacionalcuandoestaaplique,deacuerdoalasexigenciaspropiasdesunaturaleza. | C56: 15 | D56: $ 344,727
A57: C21 | B57: Noasegurarlacargaparaevitarquesecaiganenlavíalascosastransportadas.Además,seinmovilizaráelvehículohastatantoseremedielasituación. | C57: 15 | D57: $ 344,727 | E57: X | F57: X
A58: C22 | B58: Transportarcargadedimensionessuperioresalasautorizadassincumplirconlosrequisitosexigidos.Además,elvehículoseráinmovilizadohastaqueseremediedichasituación. | C58: 15 | D58: $ 344,727 | E58: X | F58: X
A59: C23 | B59: Impartirenvíaspúblicasalpúblicoenseñanzaprácticaparaconducir,sinestarautorizadoparaello. | C59: 15 | D59: $ 344,727 | E59: X | F59: X
A60: C24 | B60: Conducir motocicleta sin observar las siguientes normas.(verlistadodesituaciones) | C60: 15 | D60: $ 344,727
A61: C25 | B61: Transitarsinatenderalgunadelassiguientesreglas.(verlistadodesituaciones) | C61: 15 | D61: $ 344,727
A62: C26 | B62: Transitarenvehículosde3.5omástoneladasporelcarrilizquierdodelavíacuandohubieremásdeuncarril. | C62: 15 | D62: $ 344,727
A63: C27 | B63: Conducirunvehículocuyacargaopasajerosobstruyanlavisibilidaddelconductorhaciaelfrente,atrásocostados,oimpidanelcontrolsobreelsistemadedirección,frenososeguridad.Además,seráinmovilizado. | C63: 15 | D63: $ 344,727
A64: C28 | B64: Hacerusodesirenas,lucesintermitentes,odealtaintensidadyaparatossimilares,loscualesestánreservadosalosvehículosdebomberos,ambulancias,recolectoresdebasura,socorro,emergencia,fuerzasmilitares,policíayautoridadesdetránsitoytransporte;elusodecornetasenelperímetrourban;elusoeinstalación,encualquiervehiculodestinadoalacirculaciónenvíaspúblicas,detodaclasededispositivosoaccesoriosdiseñadosparaproducirruido,talescomoválvulas,resonadoresypitosadaptadosalossistemasdebajoydefrenosdeaire;elusoderesonadoresenelescapedegasesdecualquierfuentemóvilylacirculacióndevehiculosquenocuentenconsistemadesilenciadorencorrectoestadodefuncionamiento. | C64: 15 | D64: $ 344,727 | E64: X | F64: X
A65: C29 | B65: Conducir un vehículo a velocidad superior a la máxima permitida, la cual deberá estar señalizada en forma sectorizada, no obstante esta no podrá ser superior a (verlistado) | C65: 15 | D65: $ 344,727
A66: C30 | B66: No atenderunaseñaldecedaelpaso | C66: 15 | D66: $ 344,727
A67: C31 | B67: No acatar las señales o requerimientos impartidos por los agentes de Tránsito. | C67: 15 | D67: $ 344,727
A68: C32 | B68: Norespetarelpasodepeatonesquecruzanunavíaensitiopermitidoparaellosonodarleslaprelaciónenlasfranjasparaelloestablecidas. | C68: 15 | D68: $ 344,727
A69: C33 | B69: Ponerunvehículoenmarchasinlasprecaucionesparaevitarchoques. | C69: 15 | D69: $ 344,727
A70: C34 | B70: Repararunvehículoenlasvíaspúblicas,parqueoaceraohacerloencasodeemergencia,sinatenderelprocedimientoseñaladoenelCódigo.Orepararvehículosautomotoresenlazonadeseguridadyproteccióndelavíaférrea,enlospatiosdemaniobrasdelasestaciones,losapartaderosydemásanexidadesferroviarias. | C70: 15 | D70: $ 344,727
A71: C35 | B71: No realizar la revisión técnico mecánica y de emisiones en los siguientes plazos o cuando aún portando los certificados correspondientes no cuenta con las siguientes condiciones tecnicomecánica y de emisiones contaminantes, además el vehiculo será inmovilizado.(verlistado) | C71: 15 | D71: $ 344,727
A72: C36 | B72: Transportar carga en contenedores sin los dispositivos especiales de sujeción. El vehículo será inmovilizado. | C72: 15 | D72: $ 344,727
A73: C37 | B73: Transportar pasajeros en el platón de una camioneta picó o en laplataforma de un vehículo de carga, trátese de furgón o plataforma de estacas. | C73: 15 | D73: $ 344,727
A74: C38 | B74: Usar sistemas móviles de comunicación o teléfonos instalados en los vehículos al momento de conducir, exceptuando si éstos son utilizados con accesorios o equipos auxiliares que permitan tener las manos libres. | C74: 15 | D74: $ 344,727 | E74: X | F74: X
A75: C39 | B75: Vulnerar las reglas de estacionamientocontenidasenelarticulo77deestecódigo | C75: 15 | D75: $ 344,727 | E75: X | F75: X
A76: C40 | B76: Losconductoresconmovilidadnormalqueestacionensusvehículosenlugarespúblicosdeestacionamientodemarcadosconelsímbolointernacionaldeaccesibilidadparalosautomotoresquetransportenoseanconducidosporpersonasconmovilidadreducidaovehículosparacentrosdeeducaciónespecialoderehabilitación(multade15salariosmínimos). | C76: 15 | D76: $ 344,727
A77: D01 | B77: Guiarunvehículosinhaberobtenidolalicenciadeconduccióncorrespondiente.Además,elvehículoseráinmovilizadoenellugardeloshechos,hastaqueéstesearetiradoporunapersonaautorizadaporelinfractorconlicenciadeconducción. | C77: 30 | D77: $ 689,454
A78: D02 | B78: ConducirsinportarelSeguroObligatoriodeAccidentesdetránsitoordenadoporlaley.Además,elvehículoseráinmovilizado. | C78: 30 | D78: $ 689,454
A79: D03 | B79: Transitarensentidocontrarioalestipuladoparalavía,calzadaocarril.Enelcasodemotocicletaseprocederaasuinmovilizaciónhastatantonosepagueelvalordelamultaolaautoridadcompetentedecidasobresuimposicionenlosterminosdelosarticulos135y136delcódigonacionaldetránsito. | C79: 30 | D79: $ 689,454 | E79: X | F79: X
A80: D04 | B80: Nodetenerseanteunaluzrojaoamarilladesemáforo,unaseñalde"PARE"ounsemáforointermitenteenrojo.Enelcasodemotocicletaseprocederaasuinmovilizaciónhastatantonosepagueelvalordelamultaolaautoridadcompetentedecidasobresuimposicionenlosterminosdelosarticulos135y136delcódigonacionaldetránsito. | C80: 30 | D80: $ 689,454 | E80: X | F80: X
A81: D05 | B81: Conducirunvehículosobreaceras,plazas,víaspeatonales,separadores,bermas,demarcacionesdecanalización,zonasverdesovíasespecialesparavehículosnomotorizados.Enelcasodemotocicletaseprocederaasuinmovilizaciónhastatantonosepagueelvalordelamultaolaautoridadcompetentedecidasobresuimposicionenlosterminosdelosarticulos135y136delcódigonacionaldetránsito. | C81: 30 | D81: $ 689,454 | E81: X
A82: D06 | B82: Adelantaraotrovehículoenberma,túnel,puente,curva,pasosanivelycrucesnoreguladosoalaproximarsealacimadeunacuestaodondelaseñaldetránsitocorrespondienteloindique.Enelcasodemotocicletaseprocederaasuinmovilizaciónhastatantonosepagueelvalordelamultaolaautoridadcompetentedecidasobresuimposicionenlosterminosdelosarticulos135y136delcódigonacionaldetránsito. | C82: 30 | D82: $ 689,454 | E82: X
A83: D07 | B83: Conducirrealizandomaniobrasaltamentepeligrosaseirresponsablesqueponganenpeligroalaspersonasolascosas.Enelcasodemotocicletaseprocederaasuinmovilizaciónhastatantonosepagueelvalordelamultaolaautoridadcompetentedecidasobresuimposicionenlosterminosdelosarticulos135y136delcódigonacionaldetránsito. | C83: 30 | D83: $ 689,454
A84: D08 | B84: Conducirunvehículosinlucesosinlosdispositivosluminososdeposición,direccionalesodefreno,oconalgunadeellasdañada,enlashorasocircunstanciasseñaladasacontinuación.Además,elvehículoseráinmovilizado,cuandonolefuncionendosomasdeestasluces.(verlistadodesituaciones). | C84: 30 | D84: $ 689,454 | E84: X
A85: D09 | B85: Nopermitirelpasodelosvehículosdeemergencia,estoes,ambulancias,vehículosdecuerpodebomberos,vehículosdesocorrooemergenciaydelapoliciaoejército.Elconductordebeorillarsealcostadoderechodelacalzadaocarrilydetenerelmovimientodelvehiculo,cuandoanunciesupresenciapormediodeluces,sirenas,campanasocualquierseñalópticaoaudible. | C85: 30 | D85: $ 689,454 | E85: X
A86: D10 | B86: Conducirunvehículoparatransporteescolarconexcesodevelocidad.Enlasvíasurbanas,lavelocidadnopodrásersuperiora(60)kilómetrosporhoraysiempreycuandoseencuentredebidamenteseñalizada.Enlascarreterasnacionalesydepartamentalesenningúncasolavelocidadpodrásersuperioraochenta(80)kilómetrosporhoraysiempreycuandoseencuentredebidamenteseñalizada. | C86: 30 | D86: $ 689,454 | E86: X
A87: D11 | B87: Permitirelserviciopúblicodepasajerosquenotengalasalidadeemergenciaencadaunodesuscostadosadicionalmentealapuertadeascensodepasajeros.Enestecaso,lamultaseimpondrásolidariamentealaempresaalacualestéafiliadoyalpropietario.Ysisetrataredeservicioparticular,seimpondrálasanciónsolidariamentealpropietario. | C87: 30 | D87: $ 689,454 | E87: X | F87: X
A88: D12 | B88: Conducirunvehículoque,sinladebidaautorización,sedestineaunserviciodiferentedeaquelparaelcualtienelicenciadetránsito.Además,elvehículoseráinmovilizadoporprimeravez,poreltérminodecincodías,porsegundavezveintedíasyporterceravezcuarentadias. | C88: 30 | D88: $ 689,454
A89: D13 | B89: Encasodetransportarcargaconpesosuperioralautorizadoelvehículoseráinmovilizadoyelexcesodeberásertransbordado. | C89: 30 | D89: $ 689,454
A90: D14 | B90: Lasautoridadesdetránsitoordenaránlainmovilizacióninmediatadelosvehículosqueusenparasumovilizacióncombustiblesnoreguladoscomogaspropanouotrosqueponganenpeligrolavidadelosusuariosodelospeatones. | C90: 30 | D90: $ 689,454
A91: D15 | B91: Cambiodelrecorridootrazadodelarutaparavehículodeserviciodetransportepúblicodepasajeros,autorizadoporelorganismodetránsitocorrespondiente.Enestecaso,lamultaseimpondrásolidariamentealaempresaalacualestéafiliadoelvehículoyalpropietario.ademaselvehiculoserainmovilizado,salvocasosdefuerzamayorqueseandebidamenteautorizadosporelagentedetránsito. | C91: 30 | D91: $ 689,454
A92: D16 | B92: Arrojarresiduossólidosalespaciopúblicodesdeunvehículoautomotorodetracciónanimalohumana,estacionadooenmovimiento. | C92: 30 | D92: $ 689,454
A93: D17 | B93: Cuandosedetecteoadviertaunainfracciónalasnormasdeemisióncontaminantesodegeneraciónderuidoporvehículosautomotores | C93: 30 | D93: $ 689,454
A94: E01 | B94: Proveercombustibleavehículosdeserviciopúblicoconpasajerosabordo. | C94: 45 | D94: $ 1,034,181
A95: E02 | B95: Negarseaprestarelserviciopúblicosincausajustificada,siemprequedichanegativacausealteraciondelordenpúblico. | C95: 45 | D95: $ 1,034,181 | E95: X | F95: X
A96: E03 | B96: Conducirenestadodeembriaguez,obajolosefectosdesustanciasalucinógenas,seatenderaaloestablecidoenelarticulo152deestecódigo.Sisetratadeconductoresdevehiculosdeserviciopublico,detransporteescolarodeinstructordeconducción,lamultapecuniariayelperiododesuspensiondelalicenciaseduplicarán.Entodosloscasosdeembriaguezelvehículoseráinmovilizadoyelestadodeembriaguezoalcoholemiaseestablecerámedianteunapruebaquenocauselesión,lacualserádeterminadaporelInstitutodeMedicinaLegalyCienciasForenses. | C96: 45 | D96: $ 1,034,181
A97: E04 | B97: Transportarenelmismovehículoyalmismotiempopersonasysustanciaspeligrosascomoexplosivos,tóxicos,radiactivos,combustiblesnoautorizadosetc.Enestoscasossesuspenderálalicenciaporun(1)añoypordos(2)añoscadavezquereincida.Elvehículoseráinmovilizadopor(1)añocadavez. | C97: 45 | D97: $ 1,034,181
A98: F01 | B98: Invadirlazonadestinadaaltránsitodevehículos,transitarenéstaenpatines,monopatines,patinetasosimilares. | C98: 1 | D98: $ 22,982 | E98: X | F98: X | G98: X
A99: F02 | B99: Llevar,sinlasdebidasprecauciones,elementosquepuedanobstaculizaroafectareltránsito. | C99: 1 | D99: $ 22,982
A100: F03 | B100: Cruzarporsitiosnopermitidosotransitarsobreel | C100: 1 | D100: $ 22,982
B101: guardavías del ferrocarril.
A102: F04 | B102: Colocarsedelanteodetrásdeunvehículoquetengaelmotorencendido. | C102: 1 | D102: $ 17,853
A103: F05 | B103: Remolcarsedevehículosenmovimiento. | C103: 1 | D103: $ 17,853
...

Sheet INFRACCIONES 2017-2024
A1: Cedula | B1: Nombre completo | C1: Centros de Costos | D1: Tipo de Contrato | E1: Ciudad | F1: Fecha Infracción | G1: Lugar de la Infraccion | H1: Código infracción | I1: Descripción Infracciones | J1: Valor Infracción | K1: Tipo de Acción | L1: Fecha de Notificación | M1: Clase de Capacitación | N1: Mes | O1: Año | P1: Control Infracciones | Q1: ESTADO | R1: DEVOLUCION NOTIFICACION | S1: DEVOLUCION REGISTRO DE FORMACION | T1: CAPACITACION Y EVALUACION | U1: Observaciones
A2: 98534209 | B2: JUAN MANUEL LOPEZ CUESTA | C2: EMTELCO | D2: TERCEROS | E2: MEDELLIN | F2: 42761 | G2: 05088000 Bello | H2: H13 | I2: =VLOOKUP(H2,VALIDACIONES!$A$2:$B$138,2,0) -> Las demas conductas que constituyan infraccion a las normas de transito y que no se encuentren descritas en este acto administrativo. | J2: 0 | K2: CAPACITACION | M2: CAPACITACIÓN SEGURIDAD VIAL Y MOVILIDAD | N2: =MONTH(F2) -> 1 | O2: =YEAR(F2) -> 2017
A3: 10142350 | B3: JULIAN ANDRES NARANJO GARCIA | C3: TELEFONICA DE PEREIRA | D3: TERCEROS | E3: PEREIRA | F3: 42738 | G3: 76147000 Cartago | H3: C29 | I3: =VLOOKUP(H3,VALIDACIONES!$A$2:$B$138,2,0) -> Conducir un vehículo a velocidad superior a la máxima permitida, la cual deberá estar señalizada en forma sectorizada, no obstante esta no podrá ser superior a (verlistado) | J3: 368858 | K3: CAPACITACION | M3: CAPACITACIÓN SEGURIDAD VIAL Y MOVILIDAD | N3: =MONTH(F3) -> 1 | O3: =YEAR(F3) -> 2017
A4: 71607384 | B4: WILFREDO DE JESUS ALARCA MEDINA | C4: EPM | D4: TERCEROS | E4: MEDELLIN | F4: 42752 | G4: 05847000 Urrao | H4: B01 | I4: =VLOOKUP(H4,VALIDACIONES!$A$2:$B$138,2,0) -> Conducir un vehículo sin llevar consigo la licencia de conducción. | J4: 98364 | K4: CAPACITACION | M4: CAPACITACIÓN EN NORMAS DE TRANSITO | N4: =MONTH(F4) -> 1 | O4: =YEAR(F4) -> 2017
A5: 15481162 | B5: RUBEN DARIO HIGUITA DURAN | C5: FLOTA PROPIA | D5: FLOTA PROPIA | E5: MEDELLIN | F5: 42790 | G5: 05360000 Itaguí | H5: B19 | I5: =VLOOKUP(H5,VALIDACIONES!$A$2:$B$138,2,0) -> Realizarelcargueodescarguedeunvehículoensitiosyhorasprohibidasporlasautoridadescompetentes,deacuerdoconloestablecidoenlasnormascorrespondientes. | J5: 196728 | K5: CAPACITACIÓN | N5: =MONTH(F5) -> 2 | O5: =YEAR(F5) -> 2017
A6: 18502611 | B6: ALVARO SALAZAR GOMEZ | C6: TELEFONICA DE PEREIRA | D6: TERCEROS | E6: PEREIRA | F6: 42772 | G6: 66001000 Pereira | H6: C38 | I6: =VLOOKUP(H6,VALIDACIONES!$A$2:$B$138,2,0) -> Usar sistemas móviles de comunicación o teléfonos instalados en los vehículos al momento de conducir, exceptuando si éstos son utilizados con accesorios o equipos auxiliares que permitan tener las manos libres. | J6: 368859 | K6: CAPACITACIÓN | N6: =MONTH(F6) -> 2 | O6: =YEAR(F6) -> 2017
A7: 71294662 | B7: HECTOR MAURICIO BOHORQUEZ CHICA | C7: SERV AMBIENTALES GEOGRAFICOS | D7: TERCEROS | E7: MEDELLIN | F7: 42772 | G7: 05266000 Envigado | H7: C24 | I7: =VLOOKUP(H7,VALIDACIONES!$A$2:$B$138,2,0) -> Conducir motocicleta sin observar las siguientes normas.(verlistadodesituaciones) | J7: 368865 | K7: CAPACITACIÓN | N7: =MONTH(F7) -> 2 | O7: =YEAR(F7) -> 2017
A8: 71741519 | B8: JUAN CARLOS LALINDE CASTRILLON | C8: EMTELCO | D8: TERCEROS | E8: MEDELLIN | F8: 42787 | G8: 05360000 Itaguí | H8: C38 | I8: =VLOOKUP(H8,VALIDACIONES!$A$2:$B$138,2,0) -> Usar sistemas móviles de comunicación o teléfonos instalados en los vehículos al momento de conducir, exceptuando si éstos son utilizados con accesorios o equipos auxiliares que permitan tener las manos libres. | J8: 368865 | K8: CAPACITACIÓN | N8: =MONTH(F8) -> 2 | O8: =YEAR(F8) -> 2017
A9: 98567164 | B9: DIEGO ARMANDO MONTOYA ARANGO | C9: EPM | D9: TERCEROS | E9: MEDELLIN | F9: 42770 | G9: 05001000 Medellin | H9: C06 | I9: =VLOOKUP(H9,VALIDACIONES!$A$2:$B$138,2,0) -> Noutilizarelcinturóndeseguridadporpartedelosocupantesdelvehículoyloscinturonesdeseguridadenlosasientostraserosenlosvehículosfabricadosapartirdelaño2004. | J9: 368865 | K9: CAPACITACIÓN | N9: =MONTH(F9) -> 2 | O9: =YEAR(F9) -> 2017
A10: 1107055509 | B10: FRANKLY MARINO OROZCO | C10: EMTELCO | D10: TERCEROS | E10: CALI | F10: 42776 | G10: 76001000 Cali | H10: D02 | I10: =VLOOKUP(H10,VALIDACIONES!$A$2:$B$138,2,0) -> ConducirsinportarelSeguroObligatoriodeAccidentesdetránsitoordenadoporlaley.Además,elvehículoseráinmovilizado. | J10: 762.33 | K10: CAPACITACIÓN | N10: =MONTH(F10) -> 2 | O10: =YEAR(F10) -> 2017
A11: 1128267059 | B11: JHOVANNY ESNEIDER RAMIREZ RAMIREZ | C11: EPM | D11: TERCEROS | E11: MEDELLIN | F11: 42783 | G11: 05001000 Medellin | H11: C38 | I11: =VLOOKUP(H11,VALIDACIONES!$A$2:$B$138,2,0) -> Usar sistemas móviles de comunicación o teléfonos instalados en los vehículos al momento de conducir, exceptuando si éstos son utilizados con accesorios o equipos auxiliares que permitan tener las manos libres. | J11: 368865 | K11: CAPACITACIÓN | N11: =MONTH(F11) -> 2 | O11: =YEAR(F11) -> 2017
A12: 4403863 | B12: LUIS FERNANDO CARDONA RIVERA | C12: EMTELCO | D12: TERCEROS | E12: ARMENIA | F12: 42822 | G12: 63001000 Armenia | H12: C38 | I12: =VLOOKUP(H12,VALIDACIONES!$A$2:$B$138,2,0) -> Usar sistemas móviles de comunicación o teléfonos instalados en los vehículos al momento de conducir, exceptuando si éstos son utilizados con accesorios o equipos auxiliares que permitan tener las manos libres. | J12: 368865 | K12: CAPACITACIÓN | M12: CAPACITACIÓN SEGURIDAD VIAL Y MOVILIDAD | N12: =MONTH(F12) -> 3 | O12: =YEAR(F12) -> 2017
A13: 10139971 | B13: JAVIER DUQUE VARGAS | C13: TELEFONICA DE PEREIRA | D13: TERCEROS | E13: PEREIRA | F13: 42808 | G13: 76147000 Cartago | H13: C29 | I13: =VLOOKUP(H13,VALIDACIONES!$A$2:$B$138,2,0) -> Conducir un vehículo a velocidad superior a la máxima permitida, la cual deberá estar señalizada en forma sectorizada, no obstante esta no podrá ser superior a (verlistado) | J13: 368858 | K13: CAPACITACIÓN | M13: CAPACITACIÓN SEGURIDAD VIAL Y MOVILIDAD | N13: =MONTH(F13) -> 3 | O13: =YEAR(F13) -> 2017
A14: 10258031 | B14: LUIS MIGUEL GOMEZ CARO | C14: EMTELCO | D14: TERCEROS | E14: MEDELLIN | F14: 42824 | G14: 05380000 La Estrella | H14: C31 | I14: =VLOOKUP(H14,VALIDACIONES!$A$2:$B$138,2,0) -> No acatar las señales o requerimientos impartidos por los agentes de Tránsito. | J14: 368865 | K14: CAPACITACIÓN | M14: CAPACITACIÓN SEGURIDAD VIAL Y MOVILIDAD | N14: =MONTH(F14) -> 3 | O14: =YEAR(F14) -> 2017
A15: 16219255 | B15: ALVARO HERNAN LONDO¿O BETANCURT | C15: TELEFONICA DE PEREIRA | D15: TERCEROS | E15: PEREIRA | F15: 42795 | G15: 68276000 Floridablanca | H15: C02 | I15: =VLOOKUP(H15,VALIDACIONES!$A$2:$B$138,2,0) -> Estacionar un vehículo en los sitios prohibidos por el Código Nacional de Tránsito, reglamentado por la Res.3027. | J15: 368859 | K15: CAPACITACIÓN | M15: CAPACITACIÓN SEGURIDAD VIAL Y MOVILIDAD | N15: =MONTH(F15) -> 3 | O15: =YEAR(F15) -> 2017
A16: 71663939 | B16: ILDEBRANDO GIRALDO GOMEZ | C16: EPM | D16: TERCEROS | E16: MEDELLIN | F16: 42801 | G16: 05887000 Yarumal (Polca) | H16: D06 | I16: =VLOOKUP(H16,VALIDACIONES!$A$2:$B$138,2,0) -> Adelantaraotrovehículoenberma,túnel,puente,curva,pasosanivelycrucesnoreguladosoalaproximarsealacimadeunacuestaodondelaseñaldetránsitocorrespondienteloindique.Enelcasodemotocicletaseprocederaasuinmovilizaciónhastatantonosepagueelvalordelamultaolaautoridadcompetentedecidasobresuimposicionenlosterminosdelosarticulos135y136delcódigonacionaldetránsito. | J16: 737717 | K16: CAPACITACIÓN | M16: CAPACITACIÓN SEGURIDAD VIAL Y MOVILIDAD | N16: =MONTH(F16) -> 3 | O16: =YEAR(F16) -> 2017
A17: 98676634 | B17: RAMIRO FLOREZ NIETO | C17: SERV AMBIENTALES GEOGRAFICOS | D17: TERCEROS | E17: MEDELLIN | F17: 42796 | G17: 05001000 Medellin | H17: C35 | I17: =VLOOKUP(H17,VALIDACIONES!$A$2:$B$138,2,0) -> No realizar la revisión técnico mecánica y de emisiones en los siguientes plazos o cuando aún portando los certificados correspondientes no cuenta con las siguientes condiciones tecnicomecánica y de emisiones contaminantes, además el vehiculo será inmovilizado.(verlistado) | J17: 368865 | K17: CAPACITACIÓN | M17: CAPACITACIÓN SEGURIDAD VIAL Y MOVILIDAD | N17: =MONTH(F17) -> 3 | O17: =YEAR(F17) -> 2017
A18: 18154430 | B18: JHON JAIRO SALAZAR BERRIO | C18: EMPRESA ENERGIA DE PEREIRA | D18: TERCEROS | E18: PEREIRA | F18: 42826 | G18: 66001000 Pereira | H18: C02 | I18: =VLOOKUP(H18,VALIDACIONES!$A$2:$B$138,2,0) -> Estacionar un vehículo en los sitios prohibidos por el Código Nacional de Tránsito, reglamentado por la Res.3027. | J18: 230537 | K18: CAPACITACIÓN | N18: =MONTH(F18) -> 4 | O18: =YEAR(F18) -> 2017
A19: 70117652 | B19: FRANCISCO JAVIER NORE¿A HURTADO | C19: TELEMEDELLIN | D19: TERCEROS | E19: MEDELLIN | F19: 42850 | G19: 05001000 Medellin | H19: B10 | I19: =VLOOKUP(H19,VALIDACIONES!$A$2:$B$138,2,0) -> Conducirunvehículoconvidriospolarizados,entintadosuoscurecidos,sinportarelpermisorespectivo,deacuerdoalareglamentaciónexistenteo,nollevarelvehículodeserviciopúblicocolectivourbanoconlosvidriostransparentes. | J19: 196728 | K19: CAPACITACIÓN | N19: =MONTH(F19) -> 4 | O19: =YEAR(F19) -> 2017
A20: 70555881 | B20: JAIR DE JESUS DIOSA MONCADA | C20: EPM | D20: TERCEROS | E20: MEDELLIN | F20: 42836 | G20: 05380000 La Estrella | H20: D04 | I20: =VLOOKUP(H20,VALIDACIONES!$A$2:$B$138,2,0) -> Nodetenerseanteunaluzrojaoamarilladesemáforo,unaseñalde"PARE"ounsemáforointermitenteenrojo.Enelcasodemotocicletaseprocederaasuinmovilizaciónhastatantonosepagueelvalordelamultaolaautoridadcompetentedecidasobresuimposicionenlosterminosdelosarticulos135y136delcódigonacionaldetránsito. | J20: 737717 | K20: CAPACITACIÓN | N20: =MONTH(F20) -> 4 | O20: =YEAR(F20) -> 2017
A21: 1128405439 | B21: JUAN ESTEBAN AGUDELO | C21: EPM | D21: TERCEROS | E21: MEDELLIN | F21: 42852 | G21: 05079000 Barbosa | H21: C29 | I21: =VLOOKUP(H21,VALIDACIONES!$A$2:$B$138,2,0) -> Conducir un vehículo a velocidad superior a la máxima permitida, la cual deberá estar señalizada en forma sectorizada, no obstante esta no podrá ser superior a (verlistado) | J21: 230537 | K21: CAPACITACIÓN | N21: =MONTH(F21) -> 4 | O21: =YEAR(F21) -> 2017
A22: 1152703369 | B22: JOHAN E HERRERA VARGAS | C22: INMEL | D22: TERCEROS | E22: MEDELLIN | F22: 42844 | G22: 05631000 Sabaneta | H22: D17 | I22: =VLOOKUP(H22,VALIDACIONES!$A$2:$B$138,2,0) -> Cuandosedetecteoadviertaunainfracciónalasnormasdeemisióncontaminantesodegeneraciónderuidoporvehículosautomotores | J22: 73773 | K22: CAPACITACIÓN | N22: =MONTH(F22) -> 4 | O22: =YEAR(F22) -> 2017
A23: 10032356 | B23: JOHN EDWIN HERNANDEZ PUERTA | C23: EMPRESA ENERGIA DE PEREIRA | D23: TERCEROS | E23: PEREIRA | F23: 42870 | G23: 66001000 Pereira | H23: C06 | I23: =VLOOKUP(H23,VALIDACIONES!$A$2:$B$138,2,0) -> Noutilizarelcinturóndeseguridadporpartedelosocupantesdelvehículoyloscinturonesdeseguridadenlosasientostraserosenlosvehículosfabricadosapartirdelaño2004. | J23: 368859 | K23: CAPACITACIÓN | N23: =MONTH(F23) -> 5 | O23: =YEAR(F23) -> 2017
A24: 43907795 | B24: LEIDY VIVIANA PRECIADO ORTEGA | C24: ADMINISTRATIVO | D24: ADMINISTRATIVOS | E24: MEDELLIN | F24: 42873 | G24: 05380000 La Estrella | H24: C24 | I24: =VLOOKUP(H24,VALIDACIONES!$A$2:$B$138,2,0) -> Conducir motocicleta sin observar las siguientes normas.(verlistadodesituaciones) | J24: 368858 | K24: CAPACITACIÓN | N24: =MONTH(F24) -> 5 | O24: =YEAR(F24) -> 2017
A25: 70059512 | B25: WILLIAM DE JESUS RESTREPO SALAZAR | C25: EPM | D25: TERCEROS | E25: MEDELLIN | F25: 42882 | G25: 05001000 Medellin | H25: B02 | I25: =VLOOKUP(H25,VALIDACIONES!$A$2:$B$138,2,0) -> Conducir un vehículo con la licencia de conducción vencida. | J25: 196728 | K25: CAPACITACIÓN | N25: =MONTH(F25) -> 5 | O25: =YEAR(F25) -> 2017
A26: 71333282 | B26: WVLADIMIR RIVERA SUAREZ | C26: EMTELCO | D26: TERCEROS | E26: MEDELLIN | F26: 42873 | G26: 05088000 Bello | H26: C06 | I26: =VLOOKUP(H26,VALIDACIONES!$A$2:$B$138,2,0) -> Noutilizarelcinturóndeseguridadporpartedelosocupantesdelvehículoyloscinturonesdeseguridadenlosasientostraserosenlosvehículosfabricadosapartirdelaño2004. | J26: 368865 | K26: CAPACITACIÓN | N26: =MONTH(F26) -> 5 | O26: =YEAR(F26) -> 2017
A27: 71531701 | B27: LUIS FERNANDO MAYA ORTIZ | C27: COMERCIALIZADORA SYE | D27: TERCEROS | E27: MEDELLIN | F27: 42875 | G27: 05308000 Girardota | H27: C02 | I27: =VLOOKUP(H27,VALIDACIONES!$A$2:$B$138,2,0) -> Estacionar un vehículo en los sitios prohibidos por el Código Nacional de Tránsito, reglamentado por la Res.3027. | J27: 368859 | K27: CAPACITACIÓN | N27: =MONTH(F27) -> 5 | O27: =YEAR(F27) -> 2017
A28: 71727551 | B28: JULIO ZULUAGA PALACIO | C28: EPM | D28: TERCEROS | E28: MEDELLIN | F28: 42860 | G28: 05031000 Amalfi | H28: C11 | I28: =VLOOKUP(H28,VALIDACIONES!$A$2:$B$138,2,0) -> Noportarcomomínimoelsiguienteequipodeprevenciónyseguridad.(verlistado) | J28: 368865 | K28: CAPACITACIÓN | N28: =MONTH(F28) -> 5 | O28: =YEAR(F28) -> 2017
A29: 1107055509 | B29: FRANKLY MARINO OROZCO | C29: EMTELCO | D29: TERCEROS | E29: CALI | F29: 42878 | G29: 76001000 Cali | H29: C06 | I29: =VLOOKUP(H29,VALIDACIONES!$A$2:$B$138,2,0) -> Noutilizarelcinturóndeseguridadporpartedelosocupantesdelvehículoyloscinturonesdeseguridadenlosasientostraserosenlosvehículosfabricadosapartirdelaño2004. | J29: 393465 | K29: CAPACITACIÓN | N29: =MONTH(F29) -> 5 | O29: =YEAR(F29) -> 2017
... A35: 98530767 | B35: JOSE ALBERTO TIRADO MONTOYA | C35: EPM | D35: TERCEROS | E35: MEDELLIN | F35: 42898 | G35: 25875000 Villeta | H35: D06 | I35: =VLOOKUP(H35,VALIDACIONES!$A$2:$B$138,2,0) -> Adelantaraotrovehículoenberma,túnel,puente,curva,pasosanivelycrucesnoreguladosoalaproximarsealacimadeunacuestaodondelaseñaldetránsitocorrespondienteloindique.Enelcasodemotocicletaseprocederaasuinmovilizaciónhastatantonosepagueelvalordelamultaolaautoridadcompetentedecidasobresuimposicionenlosterminosdelosarticulos135y136delcódigonacionaldetránsito. | J35: 737717 | K35: CAPACITACIÓN | N35: =MONTH(F35) -> 6 | O35: =YEAR(F35) -> 2017
A36: 98566893 | B36: ELKIN ANDRES ESPINOSA CALDERON | C36: EMTELCO | D36: TERCEROS | E36: MEDELLIN | F36: 42895 | G36: 08001000 Barranquilla | H36: C29 | I36: =VLOOKUP(H36,VALIDACIONES!$A$2:$B$138,2,0) -> Conducir un vehículo a velocidad superior a la máxima permitida, la cual deberá estar señalizada en forma sectorizada, no obstante esta no podrá ser superior a (verlistado) | J36: 368.87 | K36: CAPACITACIÓN | N36: =MONTH(F36) -> 6 | O36: =YEAR(F36) -> 2017
A37: 1053797412 | B37: HERMES OLMEDO BARRIOS ORDO¿EZ | C37: EMPRESA ENERGIA DE PEREIRA | D37: TERCEROS | E37: PEREIRA | F37: 42896 | G37: 66001000 Pereira | H37: C02 | I37: =VLOOKUP(H37,VALIDACIONES!$A$2:$B$138,2,0) -> Estacionar un vehículo en los sitios prohibidos por el Código Nacional de Tránsito, reglamentado por la Res.3027. | J37: 368859 | K37: CAPACITACIÓN | N37: =MONTH(F37) -> 6 | O37: =YEAR(F37) -> 2017
A38: 1039023563 | B38: DIEGO ANDRES ALVAREZ ALVAREZ | C38: COMERCIALIZADORA SYE | D38: TERCEROS | E38: MEDELLIN | F38: 42929 | G38: 05001000 Medellin | H38: D04 | I38: =VLOOKUP(H38,VALIDACIONES!$A$2:$B$138,2,0) -> Nodetenerseanteunaluzrojaoamarilladesemáforo,unaseñalde"PARE"ounsemáforointermitenteenrojo.Enelcasodemotocicletaseprocederaasuinmovilizaciónhastatantonosepagueelvalordelamultaolaautoridadcompetentedecidasobresuimposicionenlosterminosdelosarticulos135y136delcódigonacionaldetránsito. | J38: 737730 | K38: CAPACITACIÓN | N38: =MONTH(F38) -> 7 | O38: =YEAR(F38) -> 2017
A39: 10125296 | B39: JESUS ALONSO LOAIZA RINCON | C39: EMTELCO | D39: TERCEROS | E39: PEREIRA | F39: 42943 | G39: 66001000 Pereira | H39: C35 | I39: =VLOOKUP(H39,VALIDACIONES!$A$2:$B$138,2,0) -> No realizar la revisión técnico mecánica y de emisiones en los siguientes plazos o cuando aún portando los certificados correspondientes no cuenta con las siguientes condiciones tecnicomecánica y de emisiones contaminantes, además el vehiculo será inmovilizado.(verlistado) | J39: 230537 | K39: CAPACITACIÓN | N39: =MONTH(F39) -> 7 | O39: =YEAR(F39) -> 2017
A40: 8399689 | B40: JAIME ALBEIRO RENDON OCAMPO | C40: FLOTA PROPIA | D40: FLOTA PROPIA | E40: MEDELLIN | F40: 42941 | G40: 05380000 La Estrella | H40: C24 | I40: =VLOOKUP(H40,VALIDACIONES!$A$2:$B$138,2,0) -> Conducir motocicleta sin observar las siguientes normas.(verlistadodesituaciones) | J40: 368858 | K40: CAPACITACIÓN | N40: =MONTH(F40) -> 7 | O40: =YEAR(F40) -> 2017
A41: 4519142 | B41: CESAR VILLA | C41: TELEFONICA DE PEREIRA | D41: TERCEROS | E41: PEREIRA | F41: 42937 | G41: 66001000 Pereira | H41: C02 | I41: =VLOOKUP(H41,VALIDACIONES!$A$2:$B$138,2,0) -> Estacionar un vehículo en los sitios prohibidos por el Código Nacional de Tránsito, reglamentado por la Res.3027. | J41: 368859 | K41: CAPACITACIÓN | N41: =MONTH(F41) -> 7 | O41: =YEAR(F41) -> 2017
A42: 10131845 | B42: CARLOS ALBERTO CARMONA HERNANDEZ | C42: TELEFONICA DE PEREIRA | D42: TERCEROS | E42: PEREIRA | F42: 42950 | G42: 66001000 Pereira | H42: C35 | I42: =VLOOKUP(H42,VALIDACIONES!$A$2:$B$138,2,0) -> No realizar la revisión técnico mecánica y de emisiones en los siguientes plazos o cuando aún portando los certificados correspondientes no cuenta con las siguientes condiciones tecnicomecánica y de emisiones contaminantes, además el vehiculo será inmovilizado.(verlistado) | J42: 368859 | K42: CAPACITACIÓN | N42: =MONTH(F42) -> 8 | O42: =YEAR(F42) -> 2017
A43: 1033679693 | B43: GABRIEL FERNANDO CORREDOR ALDANA | C43: EPM | D43: TERCEROS | E43: BOGOTA | F43: 42958 | G43: 11001000 Bogotá D.C. | H43: B10 | I43: =VLOOKUP(H43,VALIDACIONES!$A$2:$B$138,2,0) -> Conducirunvehículoconvidriospolarizados,entintadosuoscurecidos,sinportarelpermisorespectivo,deacuerdoalareglamentaciónexistenteo,nollevarelvehículodeserviciopúblicocolectivourbanoconlosvidriostransparentes. | J43: 98.3 | K43: CAPACITACIÓN | N43: =MONTH(F43) -> 8 | O43: =YEAR(F43) -> 2017
A44: 10139971 | B44: JAVIER DUQUE VARGAS | C44: TELEFONICA DE PEREIRA | D44: TERCEROS | E44: PEREIRA | F44: 42967 | G44: 76147000 Cartago | H44: C29 | I44: =VLOOKUP(H44,VALIDACIONES!$A$2:$B$138,2,0) -> Conducir un vehículo a velocidad superior a la máxima permitida, la cual deberá estar señalizada en forma sectorizada, no obstante esta no podrá ser superior a (verlistado) | J44: 368858 | K44: CAPACITACIÓN | N44: =MONTH(F44) -> 8 | O44: =YEAR(F44) -> 2017
A45: 1152191464 | B45: JUAN ESTEBAN GIRALDO RODRIGUEZ | C45: EPM | D45: TERCEROS | E45: MEDELLIN | F45: 42957 | G45: 54405000 Los Patios | H45: D04 | I45: =VLOOKUP(H45,VALIDACIONES!$A$2:$B$138,2,0) -> Nodetenerseanteunaluzrojaoamarilladesemáforo,unaseñalde"PARE"ounsemáforointermitenteenrojo.Enelcasodemotocicletaseprocederaasuinmovilizaciónhastatantonosepagueelvalordelamultaolaautoridadcompetentedecidasobresuimposicionenlosterminosdelosarticulos135y136delcódigonacionaldetránsito. | J45: 737717 | K45: CAPACITACIÓN | N45: =MONTH(F45) -> 8 | O45: =YEAR(F45) -> 2017
A46: 9915223 | B46: JOSE ALEXANDER GRAJALES OCAMPO | C46: EMPRESA ENERGIA DE PEREIRA | D46: TERCEROS | E46: PEREIRA | F46: 42958 | G46: 66001000 Pereira | H46: C02 | I46: =VLOOKUP(H46,VALIDACIONES!$A$2:$B$138,2,0) -> Estacionar un vehículo en los sitios prohibidos por el Código Nacional de Tránsito, reglamentado por la Res.3027. | J46: 368859 | K46: CAPACITACIÓN | N46: =MONTH(F46) -> 8 | O46: =YEAR(F46) -> 2017
A47: 10118724 | B47: JUAN DE LA CRUZ LONDOÑO CASTILLO | C47: EMPRESA ENERGIA DE PEREIRA | D47: TERCEROS | E47: PEREIRA | F47: 42966 | G47: 66001000 Pereira | H47: D03 | I47: =VLOOKUP(H47,VALIDACIONES!$A$2:$B$138,2,0) -> Transitarensentidocontrarioalestipuladoparalavía,calzadaocarril.Enelcasodemotocicletaseprocederaasuinmovilizaciónhastatantonosepagueelvalordelamultaolaautoridadcompetentedecidasobresuimposicionenlosterminosdelosarticulos135y136delcódigonacionaldetránsito. | J47: 737717 | K47: CAPACITACIÓN | N47: =MONTH(F47) -> 8 | O47: =YEAR(F47) -> 2017
A48: 8187606 | B48: JULIO ENRIQUE PADILLA MEDINA | C48: EPM | D48: TERCEROS | E48: MEDELLIN | F48: 42961 | G48: 15572000 Puerto Boyacá (Polca) | H48: C31 | I48: =VLOOKUP(H48,VALIDACIONES!$A$2:$B$138,2,0) -> No acatar las señales o requerimientos impartidos por los agentes de Tránsito. | J48: 368859 | K48: CAPACITACIÓN | N48: =MONTH(F48) -> 8 | O48: =YEAR(F48) -> 2017
A49: 3468974 | B49: MOISES JESUS SANCHEZ ARAQUE | C49: EMTELCO | D49: TERCEROS | E49: MEDELLIN | F49: 42955 | G49: 05360000 Itaguí | H49: B01 | I49: =VLOOKUP(H49,VALIDACIONES!$A$2:$B$138,2,0) -> Conducir un vehículo sin llevar consigo la licencia de conducción. | J49: 196728 | K49: CAPACITACIÓN | N49: =MONTH(F49) -> 8 | O49: =YEAR(F49) -> 2017
A50: 71694692 | B50: GUILLERMO LEON VELEZ GONZALEZ | C50: EPM | D50: TERCEROS | E50: MEDELLIN | F50: 42971 | G50: 05001000 Medellin | H50: C02 | I50: =VLOOKUP(H50,VALIDACIONES!$A$2:$B$138,2,0) -> Estacionar un vehículo en los sitios prohibidos por el Código Nacional de Tránsito, reglamentado por la Res.3027. | J50: 368865 | K50: CAPACITACIÓN | N50: =MONTH(F50) -> 8 | O50: =YEAR(F50) -> 2017
A51: 1037593068 | B51: FRANKLIN STIVEN AGUILAR FLOREZ | C51: ARGOS | D51: TERCEROS | E51: MEDELLIN | F51: 42985 | G51: 17380000 La Dorada | H51: C29 | I51: =VLOOKUP(H51,VALIDACIONES!$A$2:$B$138,2,0) -> Conducir un vehículo a velocidad superior a la máxima permitida, la cual deberá estar señalizada en forma sectorizada, no obstante esta no podrá ser superior a (verlistado) | J51: 36887 | K51: CAPACITACIÓN | N51: =MONTH(F51) -> 9 | O51: =YEAR(F51) -> 2017
A52: 71674351 | B52: ARMANDO DE JESUS ARROYAVE HENAO | C52: FLOTA PROPIA | D52: FLOTA PROPIA | E52: MEDELLIN | F52: 42990 | G52: 05380000 La Estrella | H52: C24 | I52: =VLOOKUP(H52,VALIDACIONES!$A$2:$B$138,2,0) -> Conducir motocicleta sin observar las siguientes normas.(verlistadodesituaciones) | J52: 368858 | K52: CAPACITACIÓN | N52: =MONTH(F52) -> 9 | O52: =YEAR(F52) -> 2017
A53: 70509776 | B53: WILSON DE JESUS CORREA USMA | C53: EPM | D53: TERCEROS | E53: MEDELLIN | F53: 42990 | G53: 17380000 La Dorada | H53: C29 | I53: =VLOOKUP(H53,VALIDACIONES!$A$2:$B$138,2,0) -> Conducir un vehículo a velocidad superior a la máxima permitida, la cual deberá estar señalizada en forma sectorizada, no obstante esta no podrá ser superior a (verlistado) | J53: 36887 | K53: CAPACITACIÓN | N53: =MONTH(F53) -> 9 | O53: =YEAR(F53) -> 2017
A54: 15516017 | B54: OSCAR UBEIMAR GOMEZ LEGARDA | C54: COMERCIALIZADORA SYE | D54: TERCEROS | E54: MEDELLIN | F54: 43000 | G54: 05212000 Copacabana | H54: H13 | I54: =VLOOKUP(H54,VALIDACIONES!$A$2:$B$138,2,0) -> Las demas conductas que constituyan infraccion a las normas de transito y que no se encuentren descritas en este acto administrativo. | J54: - | K54: CAPACITACIÓN | N54: =MONTH(F54) -> 9 | O54: =YEAR(F54) -> 2017
A55: 98643488 | B55: JALLER DE JESUS GOMEZ QUINTERO | C55: EPM | D55: TERCEROS | E55: MEDELLIN | F55: 43004 | G55: 05380000 La Estrella | H55: C29 | I55: =VLOOKUP(H55,VALIDACIONES!$A$2:$B$138,2,0) -> Conducir un vehículo a velocidad superior a la máxima permitida, la cual deberá estar señalizada en forma sectorizada, no obstante esta no podrá ser superior a (verlistado) | J55: 368858 | K55: CAPACITACIÓN | N55: =MONTH(F55) -> 9 | O55: =YEAR(F55) -> 2017
A56: 1094902521 | B56: JAIR ANDRES HENAO MARTINEZ | C56: EMTELCO | D56: TERCEROS | E56: ARMENIA | F56: 42982 | G56: 63001000 Armenia | H56: B01 | I56: =VLOOKUP(H56,VALIDACIONES!$A$2:$B$138,2,0) -> Conducir un vehículo sin llevar consigo la licencia de conducción. | J56: 196728 | K56: CAPACITACIÓN | N56: =MONTH(F56) -> 9 | O56: =YEAR(F56) -> 2017
A57: 8294503 | B57: JUAN BAUTISTA JARAMILLO OSORIO | C57: EPM | D57: TERCEROS | E57: MEDELLIN | F57: 42990 | G57: 05360000 Itaguí | H57: C02 | I57: =VLOOKUP(H57,VALIDACIONES!$A$2:$B$138,2,0) -> Estacionar un vehículo en los sitios prohibidos por el Código Nacional de Tránsito, reglamentado por la Res.3027. | J57: 368865 | K57: CAPACITACIÓN | N57: =MONTH(F57) -> 9 | O57: =YEAR(F57) -> 2017
A58: 1088302838 | B58: LUIS FERNANDO MAYA MARIN | C58: TELEFONICA DE PEREIRA | D58: TERCEROS | E58: PEREIRA | F58: 43006 | G58: 76147000 Cartago | H58: D03 | I58: =VLOOKUP(H58,VALIDACIONES!$A$2:$B$138,2,0) -> Transitarensentidocontrarioalestipuladoparalavía,calzadaocarril.Enelcasodemotocicletaseprocederaasuinmovilizaciónhastatantonosepagueelvalordelamultaolaautoridadcompetentedecidasobresuimposicionenlosterminosdelosarticulos135y136delcódigonacionaldetránsito. | J58: 737717 | K58: CAPACITACIÓN | N58: =MONTH(F58) -> 9 | O58: =YEAR(F58) -> 2017
A59: 70093672 | B59: RAUL FARLEY MOLINA MARULANDA | C59: EPM | D59: TERCEROS | E59: MEDELLIN | F59: 42991 | G59: 05380000 La Estrella | H59: C29 | I59: =VLOOKUP(H59,VALIDACIONES!$A$2:$B$138,2,0) -> Conducir un vehículo a velocidad superior a la máxima permitida, la cual deberá estar señalizada en forma sectorizada, no obstante esta no podrá ser superior a (verlistado) | J59: 368858 | K59: CAPACITACIÓN | N59: =MONTH(F59) -> 9 | O59: =YEAR(F59) -> 2017
A60: 1107055509 | B60: FRANKLY MARINO OROZCO | C60: EMTELCO | D60: TERCEROS | E60: CALI | F60: 42980 | G60: 76001000 Cali | H60: B03 | I60: =VLOOKUP(H60,VALIDACIONES!$A$2:$B$138,2,0) -> Conducir un vehículo sin placas, no portar la senel extremo delantero o trasero, portarlas con obstáculos o encondiciones que dificulten su plena identificación, portar en el lugar destinado a las placas, distintivos similares a éstas o que la imiten o que correspondan a placas de otros países o, sin el permiso vigente expedido por autoridad de tránsito. Realizar cambio en las características que identifican un vehículo automotor, cambiar, modificar o adulterar los números de identificación del motor, chasis o serie de un vehículo. | J60: 221328 | K60: CAPACITACIÓN | N60: =MONTH(F60) -> 9 | O60: =YEAR(F60) -> 2017
A61: 70518460 | B61: JUAN CARLOS OSPINA CASTA¿O | C61: EMTELCO | D61: TERCEROS | E61: MEDELLIN | F61: 43005 | G61: 05631000 Sabaneta | H61: C38 | I61: =VLOOKUP(H61,VALIDACIONES!$A$2:$B$138,2,0) -> Usar sistemas móviles de comunicación o teléfonos instalados en los vehículos al momento de conducir, exceptuando si éstos son utilizados con accesorios o equipos auxiliares que permitan tener las manos libres. | J61: 368865 | K61: CAPACITACIÓN | N61: =MONTH(F61) -> 9 | O61: =YEAR(F61) -> 2017
A62: 71691380 | B62: FRANCISCO TOVAR RENDON | C62: EPM | D62: TERCEROS | E62: MEDELLIN | F62: 43007 | G62: 15572000 Puerto Boyacá (Polca) | H62: D06 | I62: =VLOOKUP(H62,VALIDACIONES!$A$2:$B$138,2,0) -> Adelantaraotrovehículoenberma,túnel,puente,curva,pasosanivelycrucesnoreguladosoalaproximarsealacimadeunacuestaodondelaseñaldetránsitocorrespondienteloindique.Enelcasodemotocicletaseprocederaasuinmovilizaciónhastatantonosepagueelvalordelamultaolaautoridadcompetentedecidasobresuimposicionenlosterminosdelosarticulos135y136delcódigonacionaldetránsito. | J62: 737717 | K62: CAPACITACIÓN | N62: =MONTH(F62) -> 9 | O62: =YEAR(F62) -> 2017
A63: 71765988 | B63: JHON ALEXANDER VEGA | C63: COMERCIALIZADORA SYE | D63: TERCEROS | E63: MEDELLIN | F63: 43005 | G63: 05308000 Girardota (Polca) | H63: C35 | I63: =VLOOKUP(H63,VALIDACIONES!$A$2:$B$138,2,0) -> No realizar la revisión técnico mecánica y de emisiones en los siguientes plazos o cuando aún portando los certificados correspondientes no cuenta con las siguientes condiciones tecnicomecánica y de emisiones contaminantes, además el vehiculo será inmovilizado.(verlistado) | J63: 368859 | K63: CAPACITACIÓN | N63: =MONTH(F63) -> 9 | O63: =YEAR(F63) -> 2017
A64: 4390053 | B64: JORGE ELIAS QUICENO GOMEZ | C64: EMTELCO | D64: TERCEROS | E64: PEREIRA | F64: 43025 | G64: 66682000 Santa Rosa de Cabal | H64: C04 | I64: =VLOOKUP(H64,VALIDACIONES!$A$2:$B$138,2,0) -> Estacionarunvehículosintomarlassiguientesprecauciones:(verlistado) | J64: 368850 | K64: CAPACITACIÓN | N64: 10 | O64: =YEAR(F64) -> 2017
A65: 1035521496 | B65: JOHAN ANDRES ROLDAN MISAS | C65: COMERCIALIZADORA SYE | D65: TERCEROS | E65: MEDELLIN | F65: 43027 | G65: 05001000 Medellin | H65: C37 | I65: =VLOOKUP(H65,VALIDACIONES!$A$2:$B$138,2,0) -> Transportar pasajeros en el platón de una camioneta picó o en laplataforma de un vehículo de carga, trátese de furgón o plataforma de estacas. | J65: 368865 | K65: CAPACITACIÓN | N65: 10 | O65: =YEAR(F65) -> 2017
A66: 98657031 | B66: HECTOR GREGORIO VILLA LOPERA | C66: COMERCIALIZADORA SYE | D66: TERCEROS | E66: MEDELLIN | F66: 43029 | G66: 05001000 Medellin | H66: B03 | I66: =VLOOKUP(H66,VALIDACIONES!$A$2:$B$138,2,0) -> Conducir un vehículo sin placas, no portar la senel extremo delantero o trasero, portarlas con obstáculos o encondiciones que dificulten su plena identificación, portar en el lugar destinado a las placas, distintivos similares a éstas o que la imiten o que correspondan a placas de otros países o, sin el permiso vigente expedido por autoridad de tránsito. Realizar cambio en las características que identifican un vehículo automotor, cambiar, modificar o adulterar los números de identificación del motor, chasis o serie de un vehículo. | J66: 196728 | K66: CAPACITACIÓN | N66: 10 | O66: =YEAR(F66) -> 2017
A67: 1110514655 | B67: JUAN CAMILO SALGADO CAMARGO | C67: EMTELCO | D67: TERCEROS | E67: IBAGUE | F67: 43058 | G67: 73026000 Alvarado (Polca) | H67: C35 | I67: =VLOOKUP(H67,VALIDACIONES!$A$2:$B$138,2,0) -> No realizar la revisión técnico mecánica y de emisiones en los siguientes plazos o cuando aún portando los certificados correspondientes no cuenta con las siguientes condiciones tecnicomecánica y de emisiones contaminantes, además el vehiculo será inmovilizado.(verlistado) | J67: 123783 | K67: CAPACITACIÓN | N67: 11 | O67: =YEAR(F67) -> 2017
A68: 70001338 | B68: ARCADIO DE JESUS CANO ZAPATA | C68: FLOTA PROPIA | D68: FLOTA PROPIA | E68: MEDELLIN | F68: 43061 | G68: 05079000 Barbosa (Polca) | H68: D07 | I68: =VLOOKUP(H68,VALIDACIONES!$A$2:$B$138,2,0) -> Conducirrealizandomaniobrasaltamentepeligrosaseirresponsablesqueponganenpeligroalaspersonasolascosas.Enelcasodemotocicletaseprocederaasuinmovilizaciónhastatantonosepagueelvalordelamultaolaautoridadcompetentedecidasobresuimposicionenlosterminosdelosarticulos135y136delcódigonacionaldetránsito. | J68: 737717 | K68: CAPACITACIÓN | N68: 11 | O68: =YEAR(F68) -> 2017
A69: 98522991 | B69: HUGO ALBERTO GALLEGO JARAMILLO | C69: EMTELCO | D69: TERCEROS | E69: MEDELLIN | F69: 43047 | G69: 05360000 Itaguí | H69: C06 | I69: =VLOOKUP(H69,VALIDACIONES!$A$2:$B$138,2,0) -> Noutilizarelcinturóndeseguridadporpartedelosocupantesdelvehículoyloscinturonesdeseguridadenlosasientostraserosenlosvehículosfabricadosapartirdelaño2004. | J69: 368865 | K69: CAPACITACIÓN | N69: 11 | O69: =YEAR(F69) -> 2017
A70: 10019873 | B70: CESAR WILLIAM HENAO CARDONA | C70: TELEFONICA DE PEREIRA | D70: TERCEROS | E70: PEREIRA | F70: 43041 | G70: 66682000 Santa Rosa de Cabal | H70: B01 | I70: =VLOOKUP(H70,VALIDACIONES!$A$2:$B$138,2,0) -> Conducir un vehículo sin llevar consigo la licencia de conducción. | J70: 196720 | K70: CAPACITACIÓN | N70: 11 | O70: =YEAR(F70) -> 2017
A71: 16230156 | B71: FREDY YEFERSON LOPEZ ORREGO | C71: EMTELCO | D71: TERCEROS | E71: PEREIRA | F71: 43049 | G71: 05380000 La Estrella | H71: C14 | I71: =VLOOKUP(H71,VALIDACIONES!$A$2:$B$138,2,0) -> Transitar por los siguientes sitios restringidos o en horas prohibidas por laautoridad competente. Además, el vehículo será inmovilizado.(verlistado) | J71: 368858 | K71: CAPACITACIÓN | N71: 11 | O71: =YEAR(F71) -> 2017
A72: 98658387 | B72: NORMAN PARRA ORTIZ | C72: COMERCIALIZADORA SYE | D72: TERCEROS | E72: MEDELLIN | F72: 43066 | G72: 05088000 Bello | H72: B01 | I72: =VLOOKUP(H72,VALIDACIONES!$A$2:$B$138,2,0) -> Conducir un vehículo sin llevar consigo la licencia de conducción. | J72: 196728 | K72: CAPACITACIÓN | N72: 11 | O72: =YEAR(F72) -> 2017
A73: 71664224 | B73: ERNEY VELASQUEZ GARCIA | C73: COMERCIALIZADORA SYE | D73: TERCEROS | E73: MEDELLIN | F73: 43063 | G73: 05631000 Sabaneta | H73: C38 | I73: =VLOOKUP(H73,VALIDACIONES!$A$2:$B$138,2,0) -> Usar sistemas móviles de comunicación o teléfonos instalados en los vehículos al momento de conducir, exceptuando si éstos son utilizados con accesorios o equipos auxiliares que permitan tener las manos libres. | J73: 368865 | K73: CAPACITACIÓN | N73: 11 | O73: =YEAR(F73) -> 2017
A74: 71638569 | B74: WILLIAN ENRIQUE ESTRADA TAPASCO | C74: EPM | D74: TERCEROS | E74: MEDELLIN | F74: 43080 | G74: 05088000 Bello | H74: C29 | I74: =VLOOKUP(H74,VALIDACIONES!$A$2:$B$138,2,0) -> Conducir un vehículo a velocidad superior a la máxima permitida, la cual deberá estar señalizada en forma sectorizada, no obstante esta no podrá ser superior a (verlistado) | J74: 368865 | K74: CAPACITACIÓN | N74: 12 | O74: =YEAR(F74) -> 2017
A75: 14962421 | B75: JUAN LEMOS SEVILLANO | C75: EMTELCO | D75: TERCEROS | E75: CALI | F75: 43082 | G75: 76001000 Cali | H75: C14 | I75: =VLOOKUP(H75,VALIDACIONES!$A$2:$B$138,2,0) -> Transitar por los siguientes sitios restringidos o en horas prohibidas por laautoridad competente. Además, el vehículo será inmovilizado.(verlistado) | J75: 393465 | K75: CAPACITACIÓN | N75: 12 | O75: =YEAR(F75) -> 2017
... A81: 71372712 | B81: CRISTIAN CAMILO YEPES SERNA | C81: EMTELCO | D81: TERCEROS | E81: MEDELLIN | F81: 43091 | G81: 05360000 Itaguí | H81: H03 | I81: =VLOOKUP(H81,VALIDACIONES!$A$2:$B$138,2,0) -> El conductor, pasajero o peaton, que obstaculice, perjudique o ponga en riesgo a las demas personas o que no cumpla las normas y señales de transito que le sean aplicables o no obedezca las indicaciones que les den las autoridades de tránsito. | J81: 0 | K81: CAPACITACIÓN | N81: 12 | O81: =YEAR(F81) -> 2017
A82: 8306871 | B82: JOHN DARIO BARRERA TABORDA | C82: EMTELCO | D82: TERCEROS | E82: MEDELLIN | F82: 43129 | G82: 05266000 Envigado | H82: D17 | I82: =VLOOKUP(H82,VALIDACIONES!$A$2:$B$138,2,0) -> Cuandosedetecteoadviertaunainfracciónalasnormasdeemisióncontaminantesodegeneraciónderuidoporvehículosautomotores | J82: 781230 | K82: CAPACITACIÓN | M82: CAPACITACIÓN POLITICAS DE SEGURIDAD VIAL | N82: =MONTH(F82) -> 1 | O82: =YEAR(F82) -> 2018
A83: 19084515 | B83: BERNARDO SOLER GONZALEZ | C83: EPM | D83: TERCEROS | E83: MEDELLIN | F83: 43124 | G83: 05001000 Medellin | H83: C29 | I83: =VLOOKUP(H83,VALIDACIONES!$A$2:$B$138,2,0) -> Conducir un vehículo a velocidad superior a la máxima permitida, la cual deberá estar señalizada en forma sectorizada, no obstante esta no podrá ser superior a (verlistado) | J83: 390615 | K83: CAPACITACIÓN | M83: CAPACITACIÓN POLITICAS DE SEGURIDAD VIAL | N83: =MONTH(F83) -> 1 | O83: =YEAR(F83) -> 2018
A84: 94361495 | B84: AGUSTIN VELASQUEZ MURIEL | C84: EMTELCO | D84: TERCEROS | E84: CALI | F84: 43117 | G84: 76001000 Cali | H84: C11 | I84: =VLOOKUP(H84,VALIDACIONES!$A$2:$B$138,2,0) -> Noportarcomomínimoelsiguienteequipodeprevenciónyseguridad.(verlistado) | J84: 416615 | K84: CAPACITACIÓN | M84: CAPACITACIÓN POLITICAS DE SEGURIDAD VIAL | N84: =MONTH(F84) -> 1 | O84: =YEAR(F84) -> 2018
A85: 70085907 | B85: MIGUEL ANGEL ARRUBLA GIL | C85: EPM | D85: TERCEROS | E85: MEDELLIN | F85: 43138 | G85: 25899000 Zipaquira | H85: C29 | I85: =VLOOKUP(H85,VALIDACIONES!$A$2:$B$138,2,0) -> Conducir un vehículo a velocidad superior a la máxima permitida, la cual deberá estar señalizada en forma sectorizada, no obstante esta no podrá ser superior a (verlistado) | J85: 390621 | K85: CAPACITACIÓN | M85: CAPACITACIÓN POLITICAS DE SEGURIDAD VIAL | N85: =MONTH(F85) -> 2 | O85: =YEAR(F85) -> 2018
A86: 98533424 | B86: ELKIN ALBERTO DUQUE | C86: EPM | D86: TERCEROS | E86: MEDELLIN | F86: 43149 | G86: 05001000 Medellin | H86: C29 | I86: =VLOOKUP(H86,VALIDACIONES!$A$2:$B$138,2,0) -> Conducir un vehículo a velocidad superior a la máxima permitida, la cual deberá estar señalizada en forma sectorizada, no obstante esta no podrá ser superior a (verlistado) | J86: 390615 | K86: CAPACITACIÓN | M86: CAPACITACIÓN POLITICAS DE SEGURIDAD VIAL | N86: =MONTH(F86) -> 2 | O86: =YEAR(F86) -> 2018
A87: 8010609 | B87: JHON JAIRO GARCIA | C87: EMTELCO | D87: TERCEROS | E87: MEDELLIN | F87: 43138 | G87: 05266000 Envigado | H87: D17 | I87: =VLOOKUP(H87,VALIDACIONES!$A$2:$B$138,2,0) -> Cuandosedetecteoadviertaunainfracciónalasnormasdeemisióncontaminantesodegeneraciónderuidoporvehículosautomotores | J87: 78123 | K87: CAPACITACIÓN | M87: CAPACITACIÓN POLITICAS DE SEGURIDAD VIAL | N87: =MONTH(F87) -> 2 | O87: =YEAR(F87) -> 2018
A88: 8406965 | B88: LUIS EDUARDO GOEZ CARVAJAL | C88: EPM | D88: TERCEROS | E88: MEDELLIN | F88: 43157 | G88: 05001000 Medellin | H88: C08 | I88: =VLOOKUP(H88,VALIDACIONES!$A$2:$B$138,2,0) -> Transitar sin los dispositivos luminosos requeridos; no llevarlos vehículos de servicio público y oficial un aviso visible tanto en el interior como en el exterior en el que se señale el número telefónico del centro de llamadas contratado por la Superintendencia de puertos y transporte o los vehículos de servicio público no llevar además, marcado en los costados y en el techo el número de la placa o los demás elementos determinados en el Código. | J88: 390615 | K88: CAPACITACIÓN | M88: CAPACITACIÓN POLITICAS DE SEGURIDAD VIAL | N88: =MONTH(F88) -> 2 | O88: =YEAR(F88) -> 2018
A89: 71384501 | B89: ANDRES FELIPE MEJIA QUIROZ | C89: EMTELCO | D89: TERCEROS | E89: PEREIRA | F89: 43143 | G89: 13052000 Arjona | H89: C29 | I89: =VLOOKUP(H89,VALIDACIONES!$A$2:$B$138,2,0) -> Conducir un vehículo a velocidad superior a la máxima permitida, la cual deberá estar señalizada en forma sectorizada, no obstante esta no podrá ser superior a (verlistado) | J89: 390621 | K89: CAPACITACIÓN | M89: CAPACITACIÓN POLITICAS DE SEGURIDAD VIAL | N89: =MONTH(F89) -> 2 | O89: =YEAR(F89) -> 2018
A90: 98512080 | B90: HUMBERTO EDUARDO RIVERA ALVAREZ | C90: EPM | D90: TERCEROS | E90: MEDELLIN | F90: 43159 | G90: 05001000 Medellin | H90: C02 | I90: =VLOOKUP(H90,VALIDACIONES!$A$2:$B$138,2,0) -> Estacionar un vehículo en los sitios prohibidos por el Código Nacional de Tránsito, reglamentado por la Res.3027. | J90: 390615 | K90: CAPACITACIÓN | M90: CAPACITACIÓN POLITICAS DE SEGURIDAD VIAL | N90: =MONTH(F90) -> 2 | O90: =YEAR(F90) -> 2018
A91: 8794135 | B91: EDUARDO RUIZ TORRES | C91: EPM | D91: TERCEROS | E91: MEDELLIN | F91: 43147 | G91: 05308000 Girardota | H91: C02 | I91: =VLOOKUP(H91,VALIDACIONES!$A$2:$B$138,2,0) -> Estacionar un vehículo en los sitios prohibidos por el Código Nacional de Tránsito, reglamentado por la Res.3027. | J91: 390615 | K91: CAPACITACIÓN | M91: CAPACITACIÓN POLITICAS DE SEGURIDAD VIAL | N91: =MONTH(F91) -> 2 | O91: =YEAR(F91) -> 2018
A92: 18509726 | B92: JIMY JAIDER VALENCIA RESTREPO | C92: EMTELCO | D92: TERCEROS | E92: PEREIRA | F92: 43143 | G92: 66001000 Pereira | H92: C02 | I92: =VLOOKUP(H92,VALIDACIONES!$A$2:$B$138,2,0) -> Estacionar un vehículo en los sitios prohibidos por el Código Nacional de Tránsito, reglamentado por la Res.3027. | J92: 390621 | K92: CAPACITACIÓN | M92: CAPACITACIÓN POLITICAS DE SEGURIDAD VIAL | N92: =MONTH(F92) -> 2 | O92: =YEAR(F92) -> 2018
A93: 14799538 | B93: OSCAR MAURICIO CAICEDO BEJARANO | C93: EMTELCO | D93: TERCEROS | E93: CALI | F93: 43136 | G93: 76520000 Palmira | H93: 300 | I93: =VLOOKUP(H93,VALIDACIONES!$A$2:$B$138,2,0) -> Acuerdo de pago incumplido | J93: 229035 | K93: CAPACITACIÓN | M93: CAPACITACIÓN POLITICAS DE SEGURIDAD VIAL | N93: =MONTH(F93) -> 2 | O93: =YEAR(F93) -> 2018
A94: 1088305344 | B94: JOHN DAYNER AGUIRRE ARDILA | C94: EMPRESA ENERGIA DE PEREIRA | D94: TERCEROS | E94: PEREIRA | F94: 43160 | G94: 66001000 Pereira | H94: C02 | I94: =VLOOKUP(H94,VALIDACIONES!$A$2:$B$138,2,0) -> Estacionar un vehículo en los sitios prohibidos por el Código Nacional de Tránsito, reglamentado por la Res.3027. | J94: 390621 | K94: CAPACITACIÓN | M94: CAPACITACIÓN POLITICAS DE SEGURIDAD VIAL | N94: =MONTH(F94) -> 3 | O94: =YEAR(F94) -> 2018
A95: 10533168 | B95: WARNER ORLANDO ALEGRIA ORDO?EZ | C95: EMTELCO | D95: TERCEROS | E95: CALI | F95: 43165 | G95: 76001000 Cali | H95: C02 | I95: =VLOOKUP(H95,VALIDACIONES!$A$2:$B$138,2,0) -> Estacionar un vehículo en los sitios prohibidos por el Código Nacional de Tránsito, reglamentado por la Res.3027. | J95: 390615 | K95: CAPACITACIÓN | M95: CAPACITACIÓN POLITICAS DE SEGURIDAD VIAL | N95: =MONTH(F95) -> 3 | O95: =YEAR(F95) -> 2018
A96: 71780042 | B96: ERIC HUMBERTO BENITEZ POSADA | C96: COMERCIALIZADORA SYE | D96: TERCEROS | E96: MEDELLIN | F96: 43173 | G96: 05001000 Medellin | H96: C26 | I96: =VLOOKUP(H96,VALIDACIONES!$A$2:$B$138,2,0) -> Transitarenvehículosde3.5omástoneladasporelcarrilizquierdodelavíacuandohubieremásdeuncarril. | J96: 390615 | K96: CAPACITACIÓN | M96: CAPACITACIÓN POLITICAS DE SEGURIDAD VIAL | N96: =MONTH(F96) -> 3 | O96: =YEAR(F96) -> 2018
A97: 98551570 | B97: ALEJANDRO BETANCUR ISAZA | C97: FUNDACION EPM | D97: TERCEROS | E97: MEDELLIN | F97: 43179 | G97: 05001000 Medellin | H97: C29 | I97: =VLOOKUP(H97,VALIDACIONES!$A$2:$B$138,2,0) -> Conducir un vehículo a velocidad superior a la máxima permitida, la cual deberá estar señalizada en forma sectorizada, no obstante esta no podrá ser superior a (verlistado) | J97: 390615 | K97: CAPACITACIÓN | M97: CAPACITACIÓN POLITICAS DE SEGURIDAD VIAL | N97: =MONTH(F97) -> 3 | O97: =YEAR(F97) -> 2018
A98: 71293523 | B98: HERNAN DARIO ECHEVERRI VILLA | C98: SANAR | D98: TERCEROS | E98: MEDELLIN | F98: 43167 | G98: 05360000 Itaguí | H98: C14 | I98: =VLOOKUP(H98,VALIDACIONES!$A$2:$B$138,2,0) -> Transitar por los siguientes sitios restringidos o en horas prohibidas por laautoridad competente. Además, el vehículo será inmovilizado.(verlistado) | J98: 390615 | K98: CAPACITACIÓN | M98: CAPACITACIÓN POLITICAS DE SEGURIDAD VIAL | N98: =MONTH(F98) -> 3 | O98: =YEAR(F98) -> 2018
A99: 10103588 | B99: ALFONSO LONDO¿O ARANGO | C99: EMPRESA ENERGIA DE PEREIRA | D99: TERCEROS | E99: PEREIRA | F99: 43182 | G99: 66001000 Pereira | H99: H13 | I99: =VLOOKUP(H99,VALIDACIONES!$A$2:$B$138,2,0) -> Las demas conductas que constituyan infraccion a las normas de transito y que no se encuentren descritas en este acto administrativo. | J99: 0 | K99: CAPACITACIÓN | M99: CAPACITACIÓN POLITICAS DE SEGURIDAD VIAL | N99: =MONTH(F99) -> 3 | O99: =YEAR(F99) -> 2018
A100: 1128466472 | B100: ANDRES FELIPE MUNERA PAREJA | C100: EPM | D100: TERCEROS | E100: MEDELLIN | F100: 43165 | G100: 05088000 Bello | H100: C38 | I100: =VLOOKUP(H100,VALIDACIONES!$A$2:$B$138,2,0) -> Usar sistemas móviles de comunicación o teléfonos instalados en los vehículos al momento de conducir, exceptuando si éstos son utilizados con accesorios o equipos auxiliares que permitan tener las manos libres. | J100: 0 | K100: CAPACITACIÓN | M100: CAPACITACIÓN POLITICAS DE SEGURIDAD VIAL | N100: =MONTH(F100) -> 3 | O100: =YEAR(F100) -> 2018
A101: 10105313 | B101: HECTOR JAIME NARVAEZ MARIN | C101: EMTELCO | D101: TERCEROS | E101: PEREIRA | F101: 43180 | G101: 66170000 Dosquebradas | H101: C06 | I101: =VLOOKUP(H101,VALIDACIONES!$A$2:$B$138,2,0) -> Noutilizarelcinturóndeseguridadporpartedelosocupantesdelvehículoyloscinturonesdeseguridadenlosasientostraserosenlosvehículosfabricadosapartirdelaño2004. | J101: 244134 | K101: CAPACITACIÓN | M101: CAPACITACIÓN POLITICAS DE SEGURIDAD VIAL | N101: =MONTH(F101) -> 3 | O101: =YEAR(F101) -> 2018
A102: 16077743 | B102: CARLOS ANDRES RIVERA QUINTERO | C102: EMTELCO | D102: TERCEROS | E102: MANIZALES | F102: 43181 | G102: 17001000 Manizales | H102: C02 | I102: =VLOOKUP(H102,VALIDACIONES!$A$2:$B$138,2,0) -> Estacionar un vehículo en los sitios prohibidos por el Código Nacional de Tránsito, reglamentado por la Res.3027. | J102: 390615 | K102: CAPACITACIÓN | M102: CAPACITACIÓN POLITICAS DE SEGURIDAD VIAL | N102: =MONTH(F102) -> 3 | O102: =YEAR(F102) -> 2018
A103: 16446130 | B103: GILBERTO JOSE SANCHEZ APOLINAR | C103: EMTELCO | D103: TERCEROS | E103: CALI | F103: 43161 | G103: 76001000 Cali | H103: C02 | I103: =VLOOKUP(H103,VALIDACIONES!$A$2:$B$138,2,0) -> Estacionar un vehículo en los sitios prohibidos por el Código Nacional de Tránsito, reglamentado por la Res.3027. | J103: 390615 | K103: CAPACITACIÓN | M103: CAPACITACIÓN POLITICAS DE SEGURIDAD VIAL | N103: =MONTH(F103) -> 3 | O103: =YEAR(F103) -> 2018
A104: 14585197 | B104: JOSE ARBOLEDA LOPEZ | C104: EMTELCO | D104: TERCEROS | E104: BUGA | F104: 43195 | G104: 76001000 Cali | H104: C29 | I104: =VLOOKUP(H104,VALIDACIONES!$A$2:$B$138,2,0) -> Conducir un vehículo a velocidad superior a la máxima permitida, la cual deberá estar señalizada en forma sectorizada, no obstante esta no podrá ser superior a (verlistado) | J104: 390615 | K104: CAPACITACIÓN | M104: CAPACITACIÓN POLITICAS DE SEGURIDAD VIAL | N104: =MONTH(F104) -> 4 | O104: =YEAR(F104) -> 2018
A105: 70519618 | B105: ORLANDO DE JESUS ARROYAVE GIL | C105: EMTELCO | D105: TERCEROS | E105: MEDELLIN | F105: 43213 | G105: 05360000 Itaguí | H105: F | I105: =VLOOKUP(H105,VALIDACIONES!$A$2:$B$138,2,0) -> #N/A | J105: 0 | K105: CAPACITACIÓN | M105: CAPACITACIÓN POLITICAS DE SEGURIDAD VIAL | N105: =MONTH(F105) -> 4 | O105: =YEAR(F105) -> 2018
... A121: 98764588 | B121: ARLEY GONZALO VARGAS URREGO | C121: MEJIA Y ACEVEDO | D121: TERCEROS | E121: MEDELLIN | F121: 43251 | G121: 05088000 Bello | H121: C03 | I121: =VLOOKUP(H121,VALIDACIONES!$A$2:$B$138,2,0) -> Bloquearunacalzadaointersecciónconunvehículo,salvocuandoelbloqueoobedezcaalaocurrenciadeunaccidente. | J121: 390615 | K121: CAPACITACIÓN | M121: CAPACITACIÓN POLITICAS DE SEGURIDAD VIAL | N121: =MONTH(F121) -> 5 | O121: =YEAR(F121) -> 2018
A122: 16662139 | B122: LUIS ALFREDO VIAFARA VELASCO | C122: EMTELCO | D122: TERCEROS | E122: CALI | F122: 43238 | G122: 76001000 Cali | H122: 300 | I122: =VLOOKUP(H122,VALIDACIONES!$A$2:$B$138,2,0) -> Acuerdo de pago incumplido | J122: 589785 | K122: CAPACITACIÓN | M122: CAPACITACIÓN POLITICAS DE SEGURIDAD VIAL | N122: =MONTH(F122) -> 5 | O122: =YEAR(F122) -> 2018
A123: 3353481 | B123: INDALECIO DE JESUS AGUDELO ATEHORTUA | C123: EPM | D123: TERCEROS | E123: MEDELLIN | F123: 43273 | G123: 05360000 Itaguí | H123: C02 | I123: =VLOOKUP(H123,VALIDACIONES!$A$2:$B$138,2,0) -> Estacionar un vehículo en los sitios prohibidos por el Código Nacional de Tránsito, reglamentado por la Res.3027. | J123: 390615 | K123: CAPACITACIÓN | N123: =MONTH(F123) -> 6 | O123: =YEAR(F123) -> 2018
A124: 15928517 | B124: URIEL ALBERTO ARIAS GIRALDO | C124: COMERCIALIZADORA SYE | D124: TERCEROS | E124: MEDELLIN | F124: 43258 | G124: 05308000 Girardota | H124: D17 | I124: =VLOOKUP(H124,VALIDACIONES!$A$2:$B$138,2,0) -> Cuandosedetecteoadviertaunainfracciónalasnormasdeemisióncontaminantesodegeneraciónderuidoporvehículosautomotores | J124: 781230 | K124: CAPACITACIÓN | N124: =MONTH(F124) -> 6 | O124: =YEAR(F124) -> 2018
A125: 98487377 | B125: DIEGO LEON LOPEZ ZAPATA | C125: JARDIN BOTANICO | D125: TERCEROS | E125: MEDELLIN | F125: 43276 | G125: 05360000 Itaguí | H125: B01 | I125: =VLOOKUP(H125,VALIDACIONES!$A$2:$B$138,2,0) -> Conducir un vehículo sin llevar consigo la licencia de conducción. | J125: 208328 | K125: CAPACITACIÓN | N125: =MONTH(F125) -> 6 | O125: =YEAR(F125) -> 2018
...
